Workbook

Sheet Synopsis of Line Items
B1: Solicitation No. N4008525R2559
B2: INDEFINITE DELIVERY, INDEFINITE QUANTITY CONSTRUCTION CONTRACT FOR CONSTRUCTION MAINTENANCE FOR RIGID PAVING AT THE VARIOUS NAVAL FACILITIES THROUGHOUT HAMPTON ROADS, VIRGINIA
B4: EXHIBIT LINE ITEM NUMBERS
B5: EXHIBIT LINE ITEM NUMBERS DESCRIPTION OF WORK FOR SUPPLIES/SERVICES (Applicable to Exhibits A, B, C, D, E - attached)
B7: Contractor shall verify scope of work for each line item as defined in Section C Descriptions and Specifications, Section C, Contract No. N4008525R2559, Construction Maintenance for Rigid Paving at Various Federal Activities in the Hampton Roads Region
A9: ELIN | B9: Description | C9: Est. Qty | D9: Unit
B11: INDEFINITE QUANTITY (IQ) WORK ITEMS - CLIN 0001
A13: A001 | B13: SITE PREPERATION WORK (UFGS 01 57 19 Temporary Environmental Controls)
B15: Each line item under "Site Preparation Work" shall include all Material, Equipment, Labor, Suprevision, Sub-Contractor cost, Bonding, and Overhead to complete the following tasks: A) Provide the original installation of the required items. B) Maintain the required items in such a maner that they provide the required service, and are neet and sightly. C) At the end of the job all remaining material shall be removed from government property, and the job area returned to its pre work condition.
A17: A00101 | B17: Temparory chain link fencing fencing, 6 ft hight minimum | C17: 500 | D17: LF
A18: A00102 | B18: Dust control for disturbed soil or haul roads | C18: 500 | D18: 1000-SY
A19: A00103 | B19: Temporary diversion dikes | C19: 300 | D19: LF
A20: A00104 | B20: Silt fencing | C20: 10000 | D20: LF
A21: A00105 | B21: Storm drain inlet silt protection | C21: 300 | D21: EA
A22: A00106 | B22: Barricades: Low profile barricades as required to close movement areas to aircraft in order to safely perform work. | C22: 3000 | D22: LF
A23: A00107 | B23: Temporary Runway and Helipad "X" Closure markings. (typically made of yellow plywood) | C23: 25 | D23: EA
A25: A002 | B25: DEMOLITION, REMOVAL, AND DISPOSAL.
B27: Saw cutting (00101): a. Saw cut to up to 4 inch depth per LF when ordered per task order. When cuts are not to full depth of the material, materials can be broken off at the bottom of the saw cut ordered. Where a depth of cut less than 4 inches is all that is required the contractor will be paid as if a full 4 inch depth cut was made but the contractor will assume all risk of damage to material to remain in the event that they choose to use less than the entire 4 inch depth of cut. Where directed by the government to use less than full 4 inch depth cuts the Government will assume the risk of damage to material to remain in place.
B28: b. Includes saw cutting by large machine, or by hand saw where large machines cannot reach, protection of surrounding property, dust containment, proper disposal of debris off of Government property, water if needed where Government fixtures are not accessible, barricades, flagmen, and all safety related equipment to provide saw cutting.
B29: c. A demo plan is required for each task order requiring saw cutting. A demo plan should show the who (operator or person in charge, persons contacted for scheduling, etc., what (equipment to be used, including safety equipment, when (dates, times, and room numbers etc.) and how the job will start and end including all safety precautions.
B30: d. If the material to be cut is more than 4 inches in thickness but less than 12 inches in thickness the contractor will be paid the bid price per inch depth for the cuts made. (i.e. quantity/depth directed); ex. 15 LF * 8 inch depth = 120 LF-in
A32: A00201 | B32: Sawcutting (Per LF per inch depth; 4 inch min. depth to be paid except as noted in d.) (Section 02 41 00) | C32: 55000 | D32: LF-IN
B34: Concrete and Bituminous Pavement Removal (00102-00104): a. Break up and remove, by breaking into manageable pieces, plain or reinforced concrete (portland or asphalt). Load, haul and properly dispose of off of Government property. Includes protection of surrounding property, dust containment, disposal of debris, providing and placing barricades, flagmen, a demo plan, and all safety related equipment to provide concrete (portland or asphalt) removal.
B35: b. In some cases the task may require the contractor to use jackhammers and buggy, or light and heavy equipment to break up and remove materials from areas where normal equipment cannot be operated such as alleyways, and between railroad tracks. Concrete may be plain or reinforced and will be ordered on separate line items.
B36: c. Fabric found during the removal of Portland or asphalt concrete shall be removed as part of the work requirement at no additional cost to the Government.
B37: d. All material shall be removed and disposed at the contractor's expense.
A39: A00202 | B39: Concrete Removal-Plain (Section 02 41 00) | C39: 2500 | D39: CY
A41: A00203 | B41: Concrete Removal-Reinf (Section 02 41 00) | C41: 2500 | D41: CY
A43: A00204 | B43: Bituminous Pavement Removal (Section 02 41 00) | C43: 10000 | D43: CY
B45: Milling of Bituminous Pavement (00105): a. Mill existing bituminous pavement with Government approved milling machine (square yard per inch). Load milled materials into dump trucks, sweep with broom tractor, or by hand. Milling operations in aircraft operating areas must use a vacuum powered sweeper truck to minimize foreign object damage (FOD). Contain and recycle bituminous pavement materials milled off of Government property. Remove and properly dispose of debris caused by milling off of Government property. Includes protection of surrounding property, dust containment, disposal of debris, providing and placing barricades, flagmen, a demo plan, and all safety related equipment to Mill existing bituminous pavement.
B46: b. All material shall be removed and disposed at the contractor's expense.
A48: A00205 | B48: Milling of Bituminous Pavement (Section 32 01 16.17) | C48: 200000 | D48: SY-IN
B50: Rubber and Paint Removal (00106-00110): a. Remove 90 percent of all visible rubber and remove 85 or 100 percent of loose, flaking paint with Government approved high-pressure rubber and paint removal equipment, and properly dispose of debris off of Government property. Contractor shall be responsible for repairing any damage caused by the removal work.
B51: b. All material shall be removed and disposed at the contractor's expense.
A53: A00206 | B53: Rubber Removal 1 To 75,000 SF (Section 32 01 11.51) | C53: 100000 | D53: SF
A55: A00207 | B55: Rubber Removal 75,001 To 200,000 SF (Section 32 01 11.51) | C55: 200000 | D55: SF
A57: A00208 | B57: Rubber Removal 200,001 and Above (Section 32 01 11.51) | C57: 1402000 | D57: SF
A59: A00209 | B59: Paint Removal Contractor Disposal 85% (Section 32 01 11.51) | C59: 82000 | D59: SF
A61: A00210 | B61: Paint Removal Contractor Disposal 100% (Section 32 01 11.51) | C61: 20000 | D61: SF
B63: Aircraft Tiedown Removal (00111): a. Includes protection of surrounding property, dust containment, disposal of debris off of Government property, providing and placing barricades, flagmen, a demo plan, and all safety-related equipment.
A65: A00211 | B65: Remove Aircraft Tiedown (Includes Saw cutting) (Section 02 41 00) | C65: 50 | D65: EA
A67: A003 | B67: EXCAVATION AND GRADING
B69: A003 Excavation, Fill, and Grading (00201 – 00208)
B71: a. Excavate, fill, and grade to elevation and limits indicated on task order, or already established by others. Excavate or fill to achieve proper drainage. Import additional Suitable Material (Section 31 23 00.00 20) as required and compact to required in-place density and provide third party verification of suitable material and in-place density testing. Dispose of surplus excavated material in a RCRA level D licensed Solid Waste Disposal Facility off Government property.
B72: b. Hand excavate when within 2 feet of an underground utility, equipment is not practical, and in confined work areas.
B73: c. Repair, rehabilitation, or replacement of ditches or fills destroyed or damaged by storms, floods, or other discrete events, provided the repair, rehabilitation, or replacement.
B74: d. Remove accumulated sediments and debris in the vicinity of existing structures (e.g., bridges, culverted road crossings, water intake structures, roadways, runways, taxiways, etc.) and/or the placement of new or additional riprap to protect the structure or minimum amount of grading to restore proper site drainage.
B75: e. Includes protection of surrounding property, dust containment, disposal of debris, excess material, demolition plan, work plan, and all required worker safety equipment.
B76: f. Provide and implement traffic control in accordance with the Manual on Uniform Traffic Control Devices (MUTCD).
B77: g. At the Government’s discretion, salvaged material may be retained for future or current use. The Government will notify the Contractor prior to the start of work what materials and equipment shall be salvaged. If the Government decides to salvage material and equipment, the Contractor will be directed to perform the one of the following:
B78: a. Transport and unload the material to any location on the base at no additional cost.
B79: b. Transport and unload the material to a designated location off base. The Government shall pay only for the additional hauling charge under line item “Overhall”.
A82: A00301 | B82: Excavation and Grading (Section 31 00 00) | C82: 1000 | D82: CY
A84: A00302 | B84: Hand Excavation (Section 31 00 00) | C84: 200 | D84: CY
A86: A00303 | B86: Furnish and Install Topsoil (Section 31 00 00) | C86: 100 | D86: CY
A88: A00304 | B88: Overhaul (Section 31 00 00) | C88: 100 | D88: MI
A90: A00305 | B90: Import and Placement of Suitable Soil (Section 31 00 00) | C90: 250 | D90: CY
B91: Contractor should assume Satisfactory Materials are Suitable unless other specific materials are specified.
A92: A00306 | B92: Import and Placement of Select Granular Fill (Section 31 00 00) | C92: 250 | D92: CY
A94: A00307 | B94: Import and Placement of VDOT 21A/B Crushed Stone (Section 31 00 00) | C94: 250 | D94: CY
A96: A00308 | B96: Import and Placement of VDOT 57 Crushed Stone (Section 31 00 00) | C96: 250 | D96: CY
A98: A00309 | B98: Removal of accumulated Sediments and Debris (Section 31 00 00) | C98: 1000 | D98: TON
A100: A00310 | B100: Repair, rehabilitation, or replacement of ditches or fills (Section 31 00 00) | C100: 7260 | D100: SY
A103: A004 | B103: FABRICS
B105: Fabrics (00401-00402): a. Soil and pavement fabric includes fabric, placement, overlaps, folds, and repairs to fabric, measured from perimeter to perimeter. Provide and apply liquid bituminous with pavement fabric.
B106: b. Includes protection of surrounding property, dust containment, providing and placing barricades, flagmen, and all safety-related equipment.
A108: A00401 | B108: Geogrid Soil Reinforcement (Section 31 05 21) | C108: 1000 | D108: SY
A110: A00402 | B110: Geotextile (Section 31 05 19) | C110: 1000 | D110: SY
A112: A005 | B112: AGGREGATE
B114: Aggregate and Fine Aggregate Base Course (00501-00502): a. Aggregate or aggregate base course shall be furnished and applied to elevations shown, or to achieve drainage when elevations are not shown. Apply in maximum of 6" lifts unless otherwise directed by the Government and compact to the density percentage required. Protect work area so that new grade and fine aggregates are not lost. Provide density test and results.
B115: b. Includes protection of surrounding property, dust containment, providing and placing barricades, flagmen, and all safety-related equipment.
A117: A00501 | B117: Coarse Aggragete (Section 31 00 00) | C117: 500 | D117: TN
A119: A00502 | B119: Aggregate Base Course (Section 32 11 23) | C119: 1000 | D119: TN
A121: A006 | B121: CRACK SEALING AND BITUMINOUS
B123: Bituminous (00601-00609): a. Liquid bituminous is ordered as a prime or tack coat for new asphalt paving work. See VDOT manuals (www.vdot.gov) for rate of application and method. Liquid bituminous and placing is included with the installation of pavement fabric (line item 00302).
B124: b. Crack sealing includes cleaning cracks, herbicide, sealant application and clean up.
B125: c. Bituminous concrete (all FAA mixes) includes providing, delivery, placement (80% machine, 20% hand) to grade on prepared surface, compaction, and test. Liquid bituminous prime or tack coat will be ordered on separate line items. Voids filled with bituminous concrete before paving is started are not considered pothole repair.
B126: d. 100% handwork (all FAA mixes) will be ordered as an additional cost when more than 20% of areas to be paved are not accessible to equipment normally used, or when the thickness of paving (Such as skim coating) is only feasible by 100% handwork.
B127: e. Includes protection of surrounding property, dust containment, barricades, flagmen, and all safety-related equipment.
A129: A00601 | B129: Liquid Bituminous (Section 32 12 10) | C129: 1000 | D129: GL
A131: A00602 | B131: Crack Sealing (Section 32 01 17.16) | C131: 100000 | D131: LF
A133: A00603 | B133: Crack Repairs - Across Entire Width of Slab (Section 32 01 17.16) | C133: 500 | D133: LF
A135: A00604 | B135: Crack Repairs - Not Across Entire Width of Slab (Section 32 01 17.16) | C135: 500 | D135: LF
A137: A00605 | B137: Bituminous Concrete BM-25.0, BM-32.5 (Base Mix) (Section 32 12 17) | C137: 2500 | D137: TN
A139: A00606 | B139: Bituminous Concrete IM-19.0 (Intermediate Mix) (Section 32 12 17) | C139: 2500 | D139: TN
A141: A00607 | B141: Bituminous Concrete P-401 (Surface Mix) (Section 32 12 15.13) | C141: 2500 | D141: TN
A143: A00608 | B143: Bituminous Concrete SM-9.5, SM-12.5 (Surface Mix) (Section 32 12 17) | C143: 2500 | D143: TN
A145: A00609 | B145: 100% Handwork | C145: 3000 | D145: SY-IN
A147: A007 | B147: CONCRETE PAVEMENT
B149: Concrete Pavement (00601-00618): a. Concrete aprons, valley gutters, handicap aprons, slabs and misc. shapes placed and installed by various methods and machines, includes forms, vapor barrier, expansion material, concrete placement, curing, backfill, and fine grade of existing earth. Excavation, stone, topsoil, and seed will be ordered on separate line items as needed.
B150: b. High early concrete is added as an additional cost to other concrete line items when they are used. High early shall increase concrete compressive strength to 4,000 psi within 7 days.
B151: c. Minor edge repairs, surface spalls and crack repairs. Remove loose or deleterious material up to one-inch deep and hand patch to blend into existing with a high strength grout. Includes curing.
B152: d. Joint sealing includes cleaning cracks, routing, backer rod, bond breaker tape, herbicide, vegetation removal, sealant application and cleanup.
B153: e. Includes protection of surrounding property, dust containment, barricades, flagmen, and all safety-related equipment.
A155: A00701 | B155: Total Slab Replacement: 8" Thick 0 To 28 CY (Section 32 13 11) | C155: 200 | D155: CY
A157: A00702 | B157: Total Slab Replacement: 8" Thick 28 To 84 CY (Section 32 13 11) | C157: 200 | D157: CY
A159: A00703 | B159: Total Slab Replacement: 8" Thick Over 84 CY (Section 32 13 11) | C159: 200 | D159: CY
A161: A00704 | B161: Total Slab Replacement: 10" Thick 0 To 28 CY (Section 32 13 11) | C161: 200 | D161: CY
A163: A00705 | B163: Total Slab Replacement: 10" Thick 28 To 84 CY (Section 32 13 11) | C163: 200 | D163: CY
A165: A00706 | B165: Total Slab Replacement: 10" Thick Over 84 CY (Section 32 13 11) | C165: 200 | D165: CY
...

Sheet Summary
C3: SUMMARY PAGE
C6: Option | E6: Total
C8: BASE YEAR | E8: =SUM('Base Year '!G249:G250) -> 250000
C10: OPTION ONE | E10: =SUM('Option One '!G248:G249) -> 250000
C12: OPTION TWO | E12: =SUM('Option Two '!G248:G249) -> 250000
C14: OPTION THREE | E14: =SUM('Option Three'!G248:G249) -> 250000
C16: OPTION FOUR | E16: =SUM('Option Four'!G248:G249) -> 250000
C19: TOTAL | E19: =SUM(E8:E16) -> 1250000

Sheet Base Year 
A1: Solicitation No. N4008525R2559
A2: INDEFINITE DELIVERY, INDEFINITE QUANTITY CONSTRUCTION CONTRACT FOR RIGID PAVING REPAIR AND REPLACMENT AT VARIOUS NAVAL FACILITIES THROUGHOUT HAMPTON ROADS, VIRGINIA
A3: EXHIBIT A, EXHIBIT LINE ITEMS
A4: SCHEDULE OF PRICES FOR SUPPLIES/SERVICES
A6: INDEFINITE QUANTITY (IQ) WORK ITEMS - BASE YEAR - CLIN 0001
A8: ELIN | B8: Description | C8: Est. Qty | D8: Unit | F8: Unit Price | G8: Extended Price
A10: A001 | B10: SITE PREPERATION WORK (UFGS 01 57 19 Temporary Environmental Controls)
A12: A00101 | B12: Temparory chain link fencing fencing, 6 ft hight minimum | C12: 500 | D12: LF | G12: =C12*F12 -> 0
A14: A00102 | B14: Dust control for disturbed soil or haul roads | C14: 500 | D14: 1000-SY | G14: =C14*F14 -> 0
A16: A00103 | B16: Temporary diversion dikes | C16: 300 | D16: LF | G16: =C16*F16 -> 0
A18: A00104 | B18: Silt fencing | C18: 10000 | D18: LF | G18: =C18*F18 -> 0
A20: A00105 | B20: Storm drain inlet silt protection | C20: 300 | D20: EA | G20: =C20*F20 -> 0
A22: A00106 | B22: Barricades: Low profile barricades as required to close movement areas to aircraft in order to safely perform work. | C22: 3000 | D22: LF | G22: =C22*F22 -> 0
A24: A00107 | B24: Temporary Runway and Helipad "X" Closure markings. (typically made of yellow plywood) | C24: 25 | D24: EA | G24: =C24*F24 -> 0
A26: A002 | B26: DEMOLITION, REMOVAL, AND DISPOSAL
A28: A00201 | B28: Sawcutting (Per LF up to 4 inches deep) | C28: 55000 | D28: LF-IN | G28: =C28*F28 -> 0
A30: A00202 | B30: Concrete Removal-Plain | C30: 2500 | D30: CY | G30: =C30*F30 -> 0
A32: A00203 | B32: Concrete Removal-Reinf | C32: 2500 | D32: CY | G32: =C32*F32 -> 0
A34: A00204 | B34: Bituminous Pavement Removal | C34: 10000 | D34: CY | G34: =C34*F34 -> 0
A36: A00205 | B36: Milling of Bituminous Pavement | C36: 200000 | D36: SY-IN | G36: =C36*F36 -> 0
A38: A00206 | B38: Rubber Removal 1 To 75,000 SF | C38: 100000 | D38: SF | G38: =C38*F38 -> 0
A40: A00207 | B40: Rubber Removal 75,001 To 200,000 SF | C40: 200000 | D40: SF | G40: =C40*F40 -> 0
A42: A00208 | B42: Rubber Removal 200,001 and Above | C42: 1402000 | D42: SF | G42: =C42*F42 -> 0
A44: A00209 | B44: Paint Removal Contractor Disposal (85%) | C44: 82000 | D44: SF | G44: =C44*F44 -> 0
A46: A00210 | B46: Paint Removal Contractor Disposal (100%) | C46: 20000 | D46: SF | G46: =C46*F46 -> 0
A48: A00211 | B48: Remove Aircraft Tiedown (Includes Saw cutting) | C48: 50 | D48: EA | G48: =C48*F48 -> 0
A50: A003 | B50: EXCAVATION AND GRADING
A52: A00301 | B52: Excavation and Grading | C52: 1000 | D52: CY | G52: =C52*F52 -> 0
A54: A00302 | B54: Hand Excavation | C54: 200 | D54: CY | G54: =C54*F54 -> 0
A56: A00303 | B56: Furnish and Install Topsoil | C56: 100 | D56: CY | G56: =C56*F56 -> 0
A58: A00304 | B58: Overhaul | C58: 100 | D58: MI | G58: =C58*F58 -> 0
A60: A00305 | B60: Import and Placement of Suitable Soil | C60: 250 | D60: CY | G60: =C60*F60 -> 0
A62: A00306 | B62: Import and Placement of Select Granular Fill | C62: 250 | D62: CY | G62: =C62*F62 -> 0
A64: A00307 | B64: Import and Placement of VDOT 21A/B Crushed Stone | C64: 250 | D64: CY | G64: =C64*F64 -> 0
A66: A00308 | B66: Import and Placement of VDOT 57 Crushed Stone | C66: 250 | D66: CY | G66: =C66*F66 -> 0
A68: A00309 | B68: Removal of accumulated Sediments and Debris | C68: 1000 | D68: TON | G68: =C68*F68 -> 0
A70: A00310 | B70: Repair, rehabilitation, or replacement of ditches or fills | C70: 7260 | D70: SY | G70: =C70*F70 -> 0
A72: A004 | B72: FABRICS
A74: A00401 | B74: Soil Reinforcement Fabric | C74: 1000 | D74: SY | G74: =C74*F74 -> 0
A76: A00402 | B76: Geotextile | C76: 1000 | D76: SY | G76: =C76*F76 -> 0
A78: A005 | B78: AGGREGATE
A80: A00501 | B80: Coarse Aggregate | C80: 500 | D80: TN | G80: =C80*F80 -> 0
A82: A00502 | B82: Aggregate Base Course | C82: 1000 | D82: TN | G82: =C82*F82 -> 0
A84: A006 | B84: CRACK SEALING AND BITUMINOUS
A86: A00601 | B86: Liquid Bituminous | C86: 1000 | D86: GL | G86: =C86*F86 -> 0
A88: A00602 | B88: Crack Sealing | C88: 100000 | D88: LF | G88: =C88*F88 -> 0
A90: A00603 | B90: Crack Repairs - Across Entire Width of Slab | C90: 500 | D90: LF | G90: =C90*F90 -> 0
A92: A00604 | B92: Crack Repairs - Not Across Entire Width of Slab | C92: 500 | D92: LF | G92: =C92*F92 -> 0
A94: A00605 | B94: Bituminous Concrete B-2 (Base Mix) | C94: 2500 | D94: TN | G94: =C94*F94 -> 0
A96: A00606 | B96: Bituminous Concrete 1M1B (Intermitted Mix) | C96: 2500 | D96: TN | G96: =C96*F96 -> 0
A98: A00607 | B98: Bituminous Concrete P-401 (Surface Mix) | C98: 2500 | D98: TN | G98: =C98*F98 -> 0
A100: A00608 | B100: Bituminous Concrete SM-9.5, SM-12.5 (Surface Mix) | C100: 2500 | D100: TN | G100: =C100*F100 -> 0
A102: A00609 | B102: 100% Handwork | C102: 3000 | D102: SY-IN | G102: =C102*F102 -> 0
A104: A007 | B104: CONCRETE PAVEMENT
A106: A00701 | B106: Total Slab Replacement: 8" Thick 0 To 28 CY | C106: 200 | D106: CY | G106: =C106*F106 -> 0
A108: A00702 | B108: Total Slab Replacement: 8" Thick 28 To 84 CY | C108: 200 | D108: CY | G108: =C108*F108 -> 0
A110: A00703 | B110: Total Slab Replacement: 8" Thick Over 84 CY | C110: 200 | D110: CY | G110: =C110*F110 -> 0
A112: A00704 | B112: Total Slab Replacement: 10" Thick 0 To 28 CY | C112: 200 | D112: CY | G112: =C112*F112 -> 0
A114: A00705 | B114: Total Slab Replacement: 10" Thick 28 To 84 CY | C114: 200 | D114: CY | G114: =C114*F114 -> 0
A116: A00706 | B116: Total Slab Replacement: 10" Thick Over 84 CY | C116: 200 | D116: CY | G116: =C116*F116 -> 0
A118: A00707 | B118: Total Slab Replacement: 12" Thick 0 To 28 CY | C118: 200 | D118: CY | G118: =C118*F118 -> 0
A120: A00708 | B120: Total Slab Replacement: 12" Thick 28 To 84 CY | C120: 200 | D120: CY | G120: =C120*F120 -> 0
A122: A00709 | B122: Total Slab Replacement: 12" Thick Over 84 CY | C122: 200 | D122: CY | G122: =C122*F122 -> 0
A124: A00710 | B124: Partial Slab Replacement: 8" Thick | C124: 64 | D124: CY | G124: =C124*F124 -> 0
A126: A00711 | B126: Partial Slab Replacement: 10" Thick | C126: 30 | D126: CY | G126: =C126*F126 -> 0
A128: A00712 | B128: Partial Slab Replacement: 12" Thick | C128: 90 | D128: CY | G128: =C128*F128 -> 0
... A140: A00718 | B140: Use of High Early Strength Concrete | C140: 500 | D140: CY | G140: =C140*F140 -> 0
A142: A008 | B142: PAVEMENT MARKINGS
A144: A00801 | B144: Black Out/Black Background | C144: 50000 | D144: SF | G144: =C144*F144 -> 0
A146: A00802 | B146: Glass Spheres (Type III) | C146: 2600 | D146: LBS | G146: =C146*F146 -> 0
A148: A00803 | B148: Center Lines 0 To 1,000 SF | C148: 2500 | D148: SF | G148: =C148*F148 -> 0
A150: A00804 | B150: Center Lines Over 1,000 SF | C150: 25500 | D150: SF | G150: =C150*F150 -> 0
A152: A00805 | B152: Other Than Center Lines 0 To 1,000 SF | C152: 76000 | D152: SF | G152: =C152*F152 -> 0
A154: A00806 | B154: Other Than Center Lines Over 1,000 SF | C154: 76000 | D154: SF | G154: =C154*F154 -> 0
A156: A00807 | B156: Hatched Lines | C156: 135000 | D156: SF | G156: =C156*F156 -> 0
A158: A00808 | B158: Letters and Numbers | C158: 26000 | D158: SF | G158: =C158*F158 -> 0
A160: A00809 | B160: Arrows | C160: 9000 | D160: SF | G160: =C160*F160 -> 0
A162: A009 | B162: MISCELLANEOUS
A164: A00901 | B164: Dowels 1" X 16" - Wet-set (Sections 03 30 53, 32 13 13.03 ) | C164: 400 | D164: EA | G164: =C164*F164 -> 0
A166: A00902 | B166: Dowels 1 1/4" X 20" - Wet-set (Sections 03 30 53, 32 13 13.03 ) | C166: 400 | D166: EA | G166: =C166*F166 -> 0
A168: A00903 | B168: Dowels 1" X 16" - Drilled / epoxy(Sections 03 30 53, 32 13 13.03) | C168: 400 | D168: EA | G168: =C168*F168 -> 0
A170: A00904 | B170: Dowels 1 1/4" X 20" - Drilled / epoxy(Sections 03 30 53, 32 13 13.03) | C170: 400 | D170: EA | G170: =C170*F170 -> 0
A172: A00905 | B172: Welded Wire Fabric | C172: 3000 | D172: LBS | G172: =C172*F172 -> 0
A174: A00906 | B174: Reinforcing Steel | C174: 60000 | D174: LBS | G174: =C174*F174 -> 0
A176: A00907 | B176: Mooring Eye | C176: 10 | D176: EA | G176: =C176*F176 -> 0
A178: A00908 | B178: Mooring Eye in New Concrete | C178: 50 | D178: EA | G178: =C178*F178 -> 0
A180: A00909 | B180: Fine grade Existing Topsoil and seed | C180: 60000 | D180: SF | G180: =C180*F180 -> 0
A182: A009010 | B182: Furnish, Fine grade and Seed Topsoil | C182: 60000 | D182: SF | G182: =C182*F182 -> 0
A184: A009011 | B184: Quick Response: (One Time Additive Cost To A Task Order) | C184: 6 | D184: EA | G184: =C184*F184 -> 0
A186: A00912 | B186: Herbicide | C186: 5400 | D186: SY | G186: =C186*F186 -> 0
... A192: A00915 | B192: Grounding Points in New Concrete | C192: 50 | D192: EA | G192: =C192*F192 -> 0
A194: A010 | B194: LIGHTING
A196: A01001 | B196: Taxi-way Edge Light - In-Pavement Incandescent | C196: 5 | D196: EA | G196: =C196*F196 -> 0
A198: A01002 | B198: Taxi-way Edge Light - Elevated Incandescent | C198: 20 | D198: EA | G198: =C198*F198 -> 0
A200: A01003 | B200: Taxi-way Edge Light - In-Pavement LED | C200: 5 | D200: EA | G200: =C200*F200 -> 0
A202: A01004 | B202: Taxi-way Edge Light - Elevated LED | C202: 20 | D202: EA | G202: =C202*F202 -> 0
A204: A01005 | B204: Runway Edge Light - In-Pavement Incandescent | C204: 5 | D204: EA | G204: =C204*F204 -> 0
A206: A01006 | B206: Runway Edge Light - Elevated Incandescent | C206: 20 | D206: EA | G206: =C206*F206 -> 0
A208: A01007 | B208: Runway Edge Light - In-Pavement LED | C208: 5 | D208: EA | G208: =C208*F208 -> 0
A210: A01008 | B210: Runway Edge Light - Elevated LED | C210: 20 | D210: EA | G210: =C210*F210 -> 0
...

Sheet Option One 
A1: Solicitation No. N4008525R2559
A2: INDEFINITE DELIVERY, INDEFINITE QUANTITY CONSTRUCTION CONTRACT FOR RIGID PAVING REPAIR AND REPLACMENT AT VARIOUS NAVAL FACILITIES THROUGHOUT HAMPTON ROADS, VIRGINIA
A3: EXHIBIT B, EXHIBIT LINE ITEMS
A4: SCHEDULE OF PRICES FOR SUPPLIES/SERVICES
A6: INDEFINITE QUANTITY (IQ) WORK ITEMS - Option One - CLIN 0002
A8: ELIN | B8: Description | C8: Est. Qty | D8: Unit | F8: Unit Price | G8: Extended Price
A10: B001 | B10: SITE PREPERATION WORK (UFGS 01 57 19 Temporary Environmental Controls)
A12: B00101 | B12: Temparory chain link fencing fencing, 6 ft hight minimum | C12: 500 | D12: LF | G12: =C12*F12 -> 0
A14: B00102 | B14: Dust control for disturbed soil or haul roads | C14: 500 | D14: 1000-SY | G14: =C14*F14 -> 0
A16: B00103 | B16: Temporary diversion dikes | C16: 300 | D16: LF | G16: =C16*F16 -> 0
A18: B00104 | B18: Silt fencing | C18: 10000 | D18: LF | G18: =C18*F18 -> 0
A20: B00105 | B20: Storm drain inlet silt protection | C20: 300 | D20: EA | G20: =C20*F20 -> 0
A22: B00106 | B22: Barricades: Low profile barricades as required to close movement areas to aircraft in order to safely perform work. | C22: 3000 | D22: LF | G22: =C22*F22 -> 0
A24: B00107 | B24: Temporary Runway and Helipad "X" Closure markings. (typically made of yellow plywood) | C24: 25 | D24: EA | G24: =C24*F24 -> 0
A26: B002 | B26: DEMOLITION, REMOVAL, AND DISPOSAL
A28: B00201 | B28: Sawcutting (Per LF up to 4 inches deep) | C28: 55000 | D28: LF-IN | G28: =C28*F28 -> 0
A30: B00202 | B30: Concrete Removal-Plain | C30: 2500 | D30: CY | G30: =C30*F30 -> 0
A32: B00203 | B32: Concrete Removal-Reinf | C32: 2500 | D32: CY | G32: =C32*F32 -> 0
A34: B00204 | B34: Bituminous Pavement Removal | C34: 10000 | D34: CY | G34: =C34*F34 -> 0
A36: B00205 | B36: Milling of Bituminous Pavement | C36: 200000 | D36: SY-IN | G36: =C36*F36 -> 0
A38: B00206 | B38: Rubber Removal 1 To 75,000 SF | C38: 100000 | D38: SF | G38: =C38*F38 -> 0
A40: B00207 | B40: Rubber Removal 75,001 To 200,000 SF | C40: 200000 | D40: SF | G40: =C40*F40 -> 0
A42: B00208 | B42: Rubber Removal 200,001 and Above | C42: 1402000 | D42: SF | G42: =C42*F42 -> 0
A44: B00209 | B44: Paint Removal Contractor Disposal (85%) | C44: 82000 | D44: SF | G44: =C44*F44 -> 0
A46: B00210 | B46: Paint Removal Contractor Disposal (100%) | C46: 20000 | D46: SF | G46: =C46*F46 -> 0
A48: B00211 | B48: Remove Aircraft Tiedown (Includes Saw cutting) | C48: 50 | D48: EA | G48: =C48*F48 -> 0
A50: B003 | B50: EXCAVATION AND GRADING
A52: B00301 | B52: Excavation and Grading | C52: 1000 | D52: CY | G52: =C52*F52 -> 0
A54: B00302 | B54: Hand Excavation | C54: 200 | D54: CY | G54: =C54*F54 -> 0
A56: B00303 | B56: Furnish and Install Topsoil | C56: 100 | D56: CY | G56: =C56*F56 -> 0
A58: B00304 | B58: Overhaul | C58: 100 | D58: MI | G58: =C58*F58 -> 0
A60: B00305 | B60: Import and Placement of Suitable Soil | C60: 250 | D60: CY | G60: =C60*F60 -> 0
A62: B00306 | B62: Import and Placement of Select Granular Fill | C62: 250 | D62: CY | G62: =C62*F62 -> 0
A64: B00307 | B64: Import and Placement of VDOT 21A/B Crushed Stone | C64: 250 | D64: CY | G64: =C64*F64 -> 0
A66: B00308 | B66: Import and Placement of VDOT 57 Crushed Stone | C66: 250 | D66: CY | G66: =C66*F66 -> 0
A68: B00309 | B68: Removal of accumulated Sediments and Debris | C68: 1000 | D68: TON | G68: =C68*F68 -> 0
A70: B00310 | B70: Repair, rehabilitation, or replacement of ditches or fills | C70: 7260 | D70: SY | G70: =C70*F70 -> 0
A72: B004 | B72: FABRICS
A74: B00401 | B74: Soil Reinforcement Fabric | C74: 1000 | D74: SY | G74: =C74*F74 -> 0
A76: B00402 | B76: Geotextile | C76: 1000 | D76: SY | G76: =C76*F76 -> 0
A78: B005 | B78: AGGREGATE
A80: B00501 | B80: Coarse Aggregate | C80: 500 | D80: TN | G80: =C80*F80 -> 0
A82: B00502 | B82: Aggregate Base Course | C82: 1000 | D82: TN | G82: =C82*F82 -> 0
A84: B006 | B84: CRACK SEALING AND BITUMINOUS
A86: B00601 | B86: Liquid Bituminous | C86: 1000 | D86: GL | G86: =C86*F86 -> 0
A88: B00602 | B88: Crack Sealing | C88: 100000 | D88: LF | G88: =C88*F88 -> 0
A90: B00603 | B90: Crack Repairs - Across Entire Width of Slab | C90: 500 | D90: LF | G90: =C90*F90 -> 0
A92: B00604 | B92: Crack Repairs - Not Across Entire Width of Slab | C92: 500 | D92: LF | G92: =C92*F92 -> 0
A94: B00605 | B94: Bituminous Concrete B-2 (Base Mix) | C94: 2500 | D94: TN | G94: =C94*F94 -> 0
A96: B00606 | B96: Bituminous Concrete 1M1B (Intermitted Mix) | C96: 2500 | D96: TN | G96: =C96*F96 -> 0
A98: B00607 | B98: Bituminous Concrete P-401 (Surface Mix) | C98: 2500 | D98: TN | G98: =C98*F98 -> 0
A100: B00608 | B100: Bituminous Concrete SM-9.5, SM-12.5 (Surface Mix) | C100: 2500 | D100: TN | G100: =C100*F100 -> 0
A102: B00609 | B102: 100% Handwork | C102: 3000 | D102: SY-IN | G102: =C102*F102 -> 0
A104: B007 | B104: CONCRETE PAVEMENT
A106: B00701 | B106: Total Slab Replacement: 8" Thick 0 To 28 CY | C106: 200 | D106: CY | G106: =C106*F106 -> 0
A108: B00702 | B108: Total Slab Replacement: 8" Thick 28 To 84 CY | C108: 200 | D108: CY | G108: =C108*F108 -> 0
A110: B00703 | B110: Total Slab Replacement: 8" Thick Over 84 CY | C110: 200 | D110: CY | G110: =C110*F110 -> 0
A112: B00704 | B112: Total Slab Replacement: 10" Thick 0 To 28 CY | C112: 200 | D112: CY | G112: =C112*F112 -> 0
A114: B00705 | B114: Total Slab Replacement: 10" Thick 28 To 84 CY | C114: 200 | D114: CY | G114: =C114*F114 -> 0
A116: B00706 | B116: Total Slab Replacement: 10" Thick Over 84 CY | C116: 200 | D116: CY | G116: =C116*F116 -> 0
A118: B00707 | B118: Total Slab Replacement: 12" Thick 0 To 28 CY | C118: 200 | D118: CY | G118: =C118*F118 -> 0
A120: B00708 | B120: Total Slab Replacement: 12" Thick 28 To 84 CY | C120: 200 | D120: CY | G120: =C120*F120 -> 0
A122: B00709 | B122: Total Slab Replacement: 12" Thick Over 84 CY | C122: 200 | D122: CY | G122: =C122*F122 -> 0
A124: B00710 | B124: Partial Slab Replacement: 8" Thick | C124: 64 | D124: CY | G124: =C124*F124 -> 0
A126: B00711 | B126: Partial Slab Replacement: 10" Thick | C126: 30 | D126: CY | G126: =C126*F126 -> 0
A128: B00712 | B128: Partial Slab Replacement: 12" Thick | C128: 90 | D128: CY | G128: =C128*F128 -> 0
... A140: B00718 | B140: Use of High Early Strength Concrete | C140: 500 | D140: CY | G140: =C140*F140 -> 0
A142: B008 | B142: PAVEMENT MARKINGS
A144: B00801 | B144: Black Out/Black Background | C144: 50000 | D144: SF | G144: =C144*F144 -> 0
A146: B00802 | B146: Glass Spheres (Type III) | C146: 2600 | D146: LBS | G146: =C146*F146 -> 0
A148: B00803 | B148: Center Lines 0 To 1,000 SF | C148: 2500 | D148: SF | G148: =C148*F148 -> 0
A150: B00804 | B150: Center Lines Over 1,000 SF | C150: 25500 | D150: SF | G150: =C150*F150 -> 0
A152: B00805 | B152: Other Than Center Lines 0 To 1,000 SF | C152: 76000 | D152: SF | G152: =C152*F152 -> 0
A154: B00806 | B154: Other Than Center Lines Over 1,000 SF | C154: 76000 | D154: SF | G154: =C154*F154 -> 0
A156: B00807 | B156: Hatched Lines | C156: 135000 | D156: SF | G156: =C156*F156 -> 0
A158: B00808 | B158: Letters and Numbers | C158: 26000 | D158: SF | G158: =C158*F158 -> 0
A160: B00809 | B160: Arrows | C160: 9000 | D160: SF | G160: =C160*F160 -> 0
A162: B009 | B162: MISCELLANEOUS
A164: B00901 | B164: Dowels 1" X 16" - Wet-set (Sections 03 30 53, 32 13 13.03 ) | C164: 400 | D164: EA | G164: =C164*F164 -> 0
A166: B00902 | B166: Dowels 1 1/4" X 20" - Wet-set (Sections 03 30 53, 32 13 13.03 ) | C166: 400 | D166: EA | G166: =C166*F166 -> 0
A168: B00903 | B168: Dowels 1" X 16" - Drilled / epoxy(Sections 03 30 53, 32 13 13.03) | C168: 400 | D168: EA | G168: =C168*F168 -> 0
A170: B00904 | B170: Dowels 1 1/4" X 20" - Drilled / epoxy(Sections 03 30 53, 32 13 13.03) | C170: 400 | D170: EA | G170: =C170*F170 -> 0
A172: B00905 | B172: Welded Wire Fabric | C172: 3000 | D172: LBS | G172: =C172*F172 -> 0
A174: B00906 | B174: Reinforcing Steel | C174: 60000 | D174: LBS | G174: =C174*F174 -> 0
A176: B00907 | B176: Mooring Eye | C176: 10 | D176: EA | G176: =C176*F176 -> 0
A178: B00908 | B178: Mooring Eye in New Concrete | C178: 50 | D178: EA | G178: =C178*F178 -> 0
A180: B00909 | B180: Fine grade Existing Topsoil and seed | C180: 60000 | D180: SF | G180: =C180*F180 -> 0
A182: B009010 | B182: Furnish, Fine grade and Seed Topsoil | C182: 60000 | D182: SF | G182: =C182*F182 -> 0
A184: B009011 | B184: Quick Response: (One Time Additive Cost To A Task Order) | C184: 6 | D184: EA | G184: =C184*F184 -> 0
A186: B00912 | B186: Herbicide | C186: 5400 | D186: SY | G186: =C186*F186 -> 0
... A192: B00915 | B192: Grounding Points in New Concrete | C192: 50 | D192: EA | G192: =C192*F192 -> 0
A194: B010 | B194: LIGHTING
A196: B01001 | B196: Taxi-way Edge Light - In-Pavement Incandescent | C196: 5 | D196: EA | G196: =C196*F196 -> 0
A198: B01002 | B198: Taxi-way Edge Light - Elevated Incandescent | C198: 20 | D198: EA | G198: =C198*F198 -> 0
A200: B01003 | B200: Taxi-way Edge Light - In-Pavement LED | C200: 5 | D200: EA | G200: =C200*F200 -> 0
A202: B01004 | B202: Taxi-way Edge Light - Elevated LED | C202: 20 | D202: EA | G202: =C202*F202 -> 0
A204: B01005 | B204: Runway Edge Light - In-Pavement Incandescent | C204: 5 | D204: EA | G204: =C204*F204 -> 0
A206: B01006 | B206: Runway Edge Light - Elevated Incandescent | C206: 20 | D206: EA | G206: =C206*F206 -> 0
A208: B01007 | B208: Runway Edge Light - In-Pavement LED | C208: 5 | D208: EA | G208: =C208*F208 -> 0
A210: B01008 | B210: Runway Edge Light - Elevated LED | C210: 20 | D210: EA | G210: =C210*F210 -> 0
...

Sheet Option Two 
A1: Solicitation No. N4008525R2559
A2: INDEFINITE DELIVERY, INDEFINITE QUANTITY CONSTRUCTION CONTRACT FOR RIGID PAVING REPAIR AND REPLACMENT AT VARIOUS NAVAL FACILITIES THROUGHOUT HAMPTON ROADS, VIRGINIA
A3: EXHIBIT C, EXHIBIT LINE ITEMS
A4: SCHEDULE OF PRICES FOR SUPPLIES/SERVICES
A6: INDEFINITE QUANTITY (IQ) WORK ITEMS - Option Two - CLIN 0003
A8: ELIN | B8: Description | C8: Est. Qty | D8: Unit | F8: Unit Price | G8: Extended Price
A10: C001 | B10: SITE PREPERATION WORK (UFGS 01 57 19 Temporary Environmental Controls)
A12: C00101 | B12: Temparory chain link fencing fencing, 6 ft hight minimum | C12: 500 | D12: LF | G12: =C12*F12 -> 0
A14: C00102 | B14: Dust control for disturbed soil or haul roads | C14: 500 | D14: 1000-SY | G14: =C14*F14 -> 0
A16: C00103 | B16: Temporary diversion dikes | C16: 300 | D16: LF | G16: =C16*F16 -> 0
A18: C00104 | B18: Silt fencing | C18: 10000 | D18: LF | G18: =C18*F18 -> 0
A20: C00105 | B20: Storm drain inlet silt protection | C20: 300 | D20: EA | G20: =C20*F20 -> 0
A22: C00106 | B22: Barricades: Low profile barricades as required to close movement areas to aircraft in order to safely perform work. | C22: 3000 | D22: LF | G22: =C22*F22 -> 0
A24: C00107 | B24: Temporary Runway and Helipad "X" Closure markings. (typically made of yellow plywood) | C24: 25 | D24: EA | G24: =C24*F24 -> 0
A26: C002 | B26: DEMOLITION, REMOVAL, AND DISPOSAL
A28: C00201 | B28: Sawcutting (Per LF up to 4 inches deep) | C28: 55000 | D28: LF-IN | G28: =C28*F28 -> 0
A30: C00202 | B30: Concrete Removal-Plain | C30: 2500 | D30: CY | G30: =C30*F30 -> 0
A32: C00203 | B32: Concrete Removal-Reinf | C32: 2500 | D32: CY | G32: =C32*F32 -> 0
A34: C00204 | B34: Bituminous Pavement Removal | C34: 10000 | D34: CY | G34: =C34*F34 -> 0
A36: C00205 | B36: Milling of Bituminous Pavement | C36: 200000 | D36: SY-IN | G36: =C36*F36 -> 0
A38: C00206 | B38: Rubber Removal 1 To 75,000 SF | C38: 100000 | D38: SF | G38: =C38*F38 -> 0
A40: C00207 | B40: Rubber Removal 75,001 To 200,000 SF | C40: 200000 | D40: SF | G40: =C40*F40 -> 0
A42: C00208 | B42: Rubber Removal 200,001 and Above | C42: 1402000 | D42: SF | G42: =C42*F42 -> 0
A44: C00209 | B44: Paint Removal Contractor Disposal (85%) | C44: 82000 | D44: SF | G44: =C44*F44 -> 0
A46: C00210 | B46: Paint Removal Contractor Disposal (100%) | C46: 20000 | D46: SF | G46: =C46*F46 -> 0
A48: C00211 | B48: Remove Aircraft Tiedown (Includes Saw cutting) | C48: 50 | D48: EA | G48: =C48*F48 -> 0
A50: C003 | B50: EXCAVATION AND GRADING
A52: C00301 | B52: Excavation and Grading | C52: 1000 | D52: CY | G52: =C52*F52 -> 0
A54: C00302 | B54: Hand Excavation | C54: 200 | D54: CY | G54: =C54*F54 -> 0
A56: C00303 | B56: Furnish and Install Topsoil | C56: 100 | D56: CY | G56: =C56*F56 -> 0
A58: C00304 | B58: Overhaul | C58: 100 | D58: MI | G58: =C58*F58 -> 0
A60: C00305 | B60: Import and Placement of Suitable Soil | C60: 250 | D60: CY | G60: =C60*F60 -> 0
A62: C00306 | B62: Import and Placement of Select Granular Fill | C62: 250 | D62: CY | G62: =C62*F62 -> 0
A64: C00307 | B64: Import and Placement of VDOT 21A/B Crushed Stone | C64: 250 | D64: CY | G64: =C64*F64 -> 0
A66: C00308 | B66: Import and Placement of VDOT 57 Crushed Stone | C66: 250 | D66: CY | G66: =C66*F66 -> 0
A68: C00309 | B68: Removal of accumulated Sediments and Debris | C68: 1000 | D68: TON | G68: =C68*F68 -> 0
A70: C00310 | B70: Repair, rehabilitation, or replacement of ditches or fills | C70: 7260 | D70: SY | G70: =C70*F70 -> 0
A72: C004 | B72: FABRICS
A74: C00401 | B74: Soil Reinforcement Fabric | C74: 1000 | D74: SY | G74: =C74*F74 -> 0
A76: C00402 | B76: Geotextile | C76: 1000 | D76: SY | G76: =C76*F76 -> 0
A78: C005 | B78: AGGREGATE
A80: C00501 | B80: Coarse Aggregate | C80: 500 | D80: TN | G80: =C80*F80 -> 0
A82: C00502 | B82: Aggregate Base Course | C82: 1000 | D82: TN | G82: =C82*F82 -> 0
A84: C006 | B84: CRACK SEALING AND BITUMINOUS
A86: C00601 | B86: Liquid Bituminous | C86: 1000 | D86: GL | G86: =C86*F86 -> 0
A88: C00602 | B88: Crack Sealing | C88: 100000 | D88: LF | G88: =C88*F88 -> 0
A90: C00603 | B90: Crack Repairs - Across Entire Width of Slab | C90: 500 | D90: LF | G90: =C90*F90 -> 0
A92: C00604 | B92: Crack Repairs - Not Across Entire Width of Slab | C92: 500 | D92: LF | G92: =C92*F92 -> 0
A94: C00605 | B94: Bituminous Concrete B-2 (Base Mix) | C94: 2500 | D94: TN | G94: =C94*F94 -> 0
A96: C00606 | B96: Bituminous Concrete 1M1B (Intermitted Mix) | C96: 2500 | D96: TN | G96: =C96*F96 -> 0
A98: C00607 | B98: Bituminous Concrete P-401 (Surface Mix) | C98: 2500 | D98: TN | G98: =C98*F98 -> 0
A100: C00608 | B100: Bituminous Concrete SM-9.5, SM-12.5 (Surface Mix) | C100: 2500 | D100: TN | G100: =C100*F100 -> 0
A102: C00609 | B102: 100% Handwork | C102: 3000 | D102: SY-IN | G102: =C102*F102 -> 0
A104: C007 | B104: CONCRETE PAVEMENT
A106: C00701 | B106: Total Slab Replacement: 8" Thick 0 To 28 CY | C106: 200 | D106: CY | G106: =C106*F106 -> 0
A108: C00702 | B108: Total Slab Replacement: 8" Thick 28 To 84 CY | C108: 200 | D108: CY | G108: =C108*F108 -> 0
A110: C00703 | B110: Total Slab Replacement: 8" Thick Over 84 CY | C110: 200 | D110: CY | G110: =C110*F110 -> 0
A112: C00704 | B112: Total Slab Replacement: 10" Thick 0 To 28 CY | C112: 200 | D112: CY | G112: =C112*F112 -> 0
A114: C00705 | B114: Total Slab Replacement: 10" Thick 28 To 84 CY | C114: 200 | D114: CY | G114: =C114*F114 -> 0
A116: C00706 | B116: Total Slab Replacement: 10" Thick Over 84 CY | C116: 200 | D116: CY | G116: =C116*F116 -> 0
A118: C00707 | B118: Total Slab Replacement: 12" Thick 0 To 28 CY | C118: 200 | D118: CY | G118: =C118*F118 -> 0
A120: C00708 | B120: Total Slab Replacement: 12" Thick 28 To 84 CY | C120: 200 | D120: CY | G120: =C120*F120 -> 0
A122: C00709 | B122: Total Slab Replacement: 12" Thick Over 84 CY | C122: 200 | D122: CY | G122: =C122*F122 -> 0
A124: C00710 | B124: Partial Slab Replacement: 8" Thick | C124: 64 | D124: CY | G124: =C124*F124 -> 0
A126: C00711 | B126: Partial Slab Replacement: 10" Thick | C126: 30 | D126: CY | G126: =C126*F126 -> 0
A128: C00712 | B128: Partial Slab Replacement: 12" Thick | C128: 90 | D128: CY | G128: =C128*F128 -> 0
... A140: C00718 | B140: Use of High Early Strength Concrete | C140: 500 | D140: CY | G140: =C140*F140 -> 0
A142: C008 | B142: PAVEMENT MARKINGS
A144: C00801 | B144: Black Out/Black Background | C144: 50000 | D144: SF | G144: =C144*F144 -> 0
A146: C00802 | B146: Glass Spheres (Type III) | C146: 2600 | D146: LBS | G146: =C146*F146 -> 0
A148: C00803 | B148: Center Lines 0 To 1,000 SF | C148: 2500 | D148: SF | G148: =C148*F148 -> 0
A150: C00804 | B150: Center Lines Over 1,000 SF | C150: 25500 | D150: SF | G150: =C150*F150 -> 0
A152: C00805 | B152: Other Than Center Lines 0 To 1,000 SF | C152: 76000 | D152: SF | G152: =C152*F152 -> 0
A154: C00806 | B154: Other Than Center Lines Over 1,000 SF | C154: 76000 | D154: SF | G154: =C154*F154 -> 0
A156: C00807 | B156: Hatched Lines | C156: 135000 | D156: SF | G156: =C156*F156 -> 0
A158: C00808 | B158: Letters and Numbers | C158: 26000 | D158: SF | G158: =C158*F158 -> 0
A160: C00809 | B160: Arrows | C160: 9000 | D160: SF | G160: =C160*F160 -> 0
A162: C009 | B162: MISCELLANEOUS
A164: C00901 | B164: Dowels 1" X 16" - Wet-set (Sections 03 30 53, 32 13 13.03 ) | C164: 400 | D164: EA | G164: =C164*F164 -> 0
A166: C00902 | B166: Dowels 1 1/4" X 20" - Wet-set (Sections 03 30 53, 32 13 13.03 ) | C166: 400 | D166: EA | G166: =C166*F166 -> 0
A168: C00903 | B168: Dowels 1" X 16" - Drilled / epoxy(Sections 03 30 53, 32 13 13.03) | C168: 400 | D168: EA | G168: =C168*F168 -> 0
A170: C00904 | B170: Dowels 1 1/4" X 20" - Drilled / epoxy(Sections 03 30 53, 32 13 13.03) | C170: 400 | D170: EA | G170: =C170*F170 -> 0
A172: C00905 | B172: Welded Wire Fabric | C172: 3000 | D172: LBS | G172: =C172*F172 -> 0
A174: C00906 | B174: Reinforcing Steel | C174: 60000 | D174: LBS | G174: =C174*F174 -> 0
A176: C00907 | B176: Mooring Eye | C176: 10 | D176: EA | G176: =C176*F176 -> 0
A178: C00908 | B178: Mooring Eye in New Concrete | C178: 50 | D178: EA | G178: =C178*F178 -> 0
A180: C00909 | B180: Fine grade Existing Topsoil and seed | C180: 60000 | D180: SF | G180: =C180*F180 -> 0
A182: C009010 | B182: Furnish, Fine grade and Seed Topsoil | C182: 60000 | D182: SF | G182: =C182*F182 -> 0
A184: C009011 | B184: Quick Response: (One Time Additive Cost To A Task Order) | C184: 6 | D184: EA | G184: =C184*F184 -> 0
A186: C00912 | B186: Herbicide | C186: 5400 | D186: SY | G186: =C186*F186 -> 0
... A192: C00915 | B192: Grounding Points in New Concrete | C192: 50 | D192: EA | G192: =C192*F192 -> 0
A194: C010 | B194: LIGHTING
A196: C01001 | B196: Taxi-way Edge Light - In-Pavement Incandescent | C196: 5 | D196: EA | G196: =C196*F196 -> 0
A198: C01002 | B198: Taxi-way Edge Light - Elevated Incandescent | C198: 20 | D198: EA | G198: =C198*F198 -> 0
A200: C01003 | B200: Taxi-way Edge Light - In-Pavement LED | C200: 5 | D200: EA | G200: =C200*F200 -> 0
A202: C01004 | B202: Taxi-way Edge Light - Elevated LED | C202: 20 | D202: EA | G202: =C202*F202 -> 0
A204: C01005 | B204: Runway Edge Light - In-Pavement Incandescent | C204: 5 | D204: EA | G204: =C204*F204 -> 0
A206: C01006 | B206: Runway Edge Light - Elevated Incandescent | C206: 20 | D206: EA | G206: =C206*F206 -> 0
A208: C01007 | B208: Runway Edge Light - In-Pavement LED | C208: 5 | D208: EA | G208: =C208*F208 -> 0
A210: C01008 | B210: Runway Edge Light - Elevated LED | C210: 20 | D210: EA | G210: =C210*F210 -> 0
...

Sheet Option Three
A1: Solicitation No. N4008525R2559
A2: INDEFINITE DELIVERY, INDEFINITE QUANTITY CONSTRUCTION CONTRACT FOR RIGID PAVING REPAIR AND REPLACMENT AT VARIOUS NAVAL FACILITIES THROUGHOUT HAMPTON ROADS, VIRGINIA
A3: EXHIBIT D, EXHIBIT LINE ITEMS
A4: SCHEDULE OF PRICES FOR SUPPLIES/SERVICES
A6: INDEFINITE QUANTITY (IQ) WORK ITEMS - Option Three - CLIN 0004
A8: ELIN | B8: Description | C8: Est. Qty | D8: Unit | F8: Unit Price | G8: Extended Price
A10: D001 | B10: SITE PREPERATION WORK (UFGS 01 57 19 Temporary Environmental Controls)
A12: D00101 | B12: Temparory chain link fencing fencing, 6 ft hight minimum | C12: 500 | D12: LF | G12: =C12*F12 -> 0
A14: D00102 | B14: Dust control for disturbed soil or haul roads | C14: 500 | D14: 1000-SY | G14: =C14*F14 -> 0
A16: D00103 | B16: Temporary diversion dikes | C16: 300 | D16: LF | G16: =C16*F16 -> 0
A18: D00104 | B18: Silt fencing | C18: 10000 | D18: LF | G18: =C18*F18 -> 0
A20: D00105 | B20: Storm drain inlet silt protection | C20: 300 | D20: EA | G20: =C20*F20 -> 0
A22: D00106 | B22: Barricades: Low profile barricades as required to close movement areas to aircraft in order to safely perform work. | C22: 3000 | D22: LF | G22: =C22*F22 -> 0
A24: D00107 | B24: Temporary Runway and Helipad "X" Closure markings. (typically made of yellow plywood) | C24: 25 | D24: EA | G24: =C24*F24 -> 0
A26: D002 | B26: DEMOLITION, REMOVAL, AND DISPOSAL
A28: D00201 | B28: Sawcutting (Per LF up to 4 inches deep) | C28: 55000 | D28: LF-IN | G28: =C28*F28 -> 0
A30: D00202 | B30: Concrete Removal-Plain | C30: 2500 | D30: CY | G30: =C30*F30 -> 0
A32: D00203 | B32: Concrete Removal-Reinf | C32: 2500 | D32: CY | G32: =C32*F32 -> 0
A34: D00204 | B34: Bituminous Pavement Removal | C34: 10000 | D34: CY | G34: =C34*F34 -> 0
A36: D00205 | B36: Milling of Bituminous Pavement | C36: 200000 | D36: SY-IN | G36: =C36*F36 -> 0
A38: D00206 | B38: Rubber Removal 1 To 75,000 SF | C38: 100000 | D38: SF | G38: =C38*F38 -> 0
A40: D00207 | B40: Rubber Removal 75,001 To 200,000 SF | C40: 200000 | D40: SF | G40: =C40*F40 -> 0
A42: D00208 | B42: Rubber Removal 200,001 and Above | C42: 1402000 | D42: SF | G42: =C42*F42 -> 0
A44: D00209 | B44: Paint Removal Contractor Disposal (85%) | C44: 82000 | D44: SF | G44: =C44*F44 -> 0
A46: D00210 | B46: Paint Removal Contractor Disposal (100%) | C46: 20000 | D46: SF | G46: =C46*F46 -> 0
A48: D00211 | B48: Remove Aircraft Tiedown (Includes Saw cutting) | C48: 50 | D48: EA | G48: =C48*F48 -> 0
A50: D003 | B50: EXCAVATION AND GRADING
A52: D00301 | B52: Excavation and Grading | C52: 1000 | D52: CY | G52: =C52*F52 -> 0
A54: D00302 | B54: Hand Excavation | C54: 200 | D54: CY | G54: =C54*F54 -> 0
A56: D00303 | B56: Furnish and Install Topsoil | C56: 100 | D56: CY | G56: =C56*F56 -> 0
A58: D00304 | B58: Overhaul | C58: 100 | D58: MI | G58: =C58*F58 -> 0
A60: D00305 | B60: Import and Placement of Suitable Soil | C60: 250 | D60: CY | G60: =C60*F60 -> 0
A62: D00306 | B62: Import and Placement of Select Granular Fill | C62: 250 | D62: CY | G62: =C62*F62 -> 0
A64: D00307 | B64: Import and Placement of VDOT 21A/B Crushed Stone | C64: 250 | D64: CY | G64: =C64*F64 -> 0
A66: D00308 | B66: Import and Placement of VDOT 57 Crushed Stone | C66: 250 | D66: CY | G66: =C66*F66 -> 0
A68: D00309 | B68: Removal of accumulated Sediments and Debris | C68: 1000 | D68: TON | G68: =C68*F68 -> 0
A70: D00310 | B70: Repair, rehabilitation, or replacement of ditches or fills | C70: 7260 | D70: SY | G70: =C70*F70 -> 0
A72: D004 | B72: FABRICS
A74: D00401 | B74: Soil Reinforcement Fabric | C74: 1000 | D74: SY | G74: =C74*F74 -> 0
A76: D00402 | B76: Geotextile | C76: 1000 | D76: SY | G76: =C76*F76 -> 0
A78: D005 | B78: AGGREGATE
A80: D00501 | B80: Coarse Aggregate | C80: 500 | D80: TN | G80: =C80*F80 -> 0
A82: D00502 | B82: Aggregate Base Course | C82: 1000 | D82: TN | G82: =C82*F82 -> 0
A84: D006 | B84: CRACK SEALING AND BITUMINOUS
A86: D00601 | B86: Liquid Bituminous | C86: 1000 | D86: GL | G86: =C86*F86 -> 0
A88: D00602 | B88: Crack Sealing | C88: 100000 | D88: LF | G88: =C88*F88 -> 0
A90: D00603 | B90: Crack Repairs - Across Entire Width of Slab | C90: 500 | D90: LF | G90: =C90*F90 -> 0
A92: D00604 | B92: Crack Repairs - Not Across Entire Width of Slab | C92: 500 | D92: LF | G92: =C92*F92 -> 0
A94: D00605 | B94: Bituminous Concrete B-2 (Base Mix) | C94: 2500 | D94: TN | G94: =C94*F94 -> 0
A96: D00606 | B96: Bituminous Concrete 1M1B (Intermitted Mix) | C96: 2500 | D96: TN | G96: =C96*F96 -> 0
A98: D00607 | B98: Bituminous Concrete P-401 (Surface Mix) | C98: 2500 | D98: TN | G98: =C98*F98 -> 0
A100: D00608 | B100: Bituminous Concrete SM-9.5, SM-12.5 (Surface Mix) | C100: 2500 | D100: TN | G100: =C100*F100 -> 0
A102: D00609 | B102: 100% Handwork | C102: 3000 | D102: SY-IN | G102: =C102*F102 -> 0
A104: D007 | B104: CONCRETE PAVEMENT
A106: D00701 | B106: Total Slab Replacement: 8" Thick 0 To 28 CY | C106: 200 | D106: CY | G106: =C106*F106 -> 0
A108: D00702 | B108: Total Slab Replacement: 8" Thick 28 To 84 CY | C108: 200 | D108: CY | G108: =C108*F108 -> 0
A110: D00703 | B110: Total Slab Replacement: 8" Thick Over 84 CY | C110: 200 | D110: CY | G110: =C110*F110 -> 0
A112: D00704 | B112: Total Slab Replacement: 10" Thick 0 To 28 CY | C112: 200 | D112: CY | G112: =C112*F112 -> 0
A114: D00705 | B114: Total Slab Replacement: 10" Thick 28 To 84 CY | C114: 200 | D114: CY | G114: =C114*F114 -> 0
A116: D00706 | B116: Total Slab Replacement: 10" Thick Over 84 CY | C116: 200 | D116: CY | G116: =C116*F116 -> 0
A118: D00707 | B118: Total Slab Replacement: 12" Thick 0 To 28 CY | C118: 200 | D118: CY | G118: =C118*F118 -> 0
A120: D00708 | B120: Total Slab Replacement: 12" Thick 28 To 84 CY | C120: 200 | D120: CY | G120: =C120*F120 -> 0
A122: D00709 | B122: Total Slab Replacement: 12" Thick Over 84 CY | C122: 200 | D122: CY | G122: =C122*F122 -> 0
A124: D00710 | B124: Partial Slab Replacement: 8" Thick | C124: 64 | D124: CY | G124: =C124*F124 -> 0
A126: D00711 | B126: Partial Slab Replacement: 10" Thick | C126: 30 | D126: CY | G126: =C126*F126 -> 0
A128: D00712 | B128: Partial Slab Replacement: 12" Thick | C128: 90 | D128: CY | G128: =C128*F128 -> 0
... A140: D00718 | B140: Use of High Early Strength Concrete | C140: 500 | D140: CY | G140: =C140*F140 -> 0
A142: D008 | B142: PAVEMENT MARKINGS
A144: D00801 | B144: Black Out/Black Background | C144: 50000 | D144: SF | G144: =C144*F144 -> 0
A146: D00802 | B146: Glass Spheres (Type III) | C146: 2600 | D146: LBS | G146: =C146*F146 -> 0
A148: D00803 | B148: Center Lines 0 To 1,000 SF | C148: 2500 | D148: SF | G148: =C148*F148 -> 0
A150: D00804 | B150: Center Lines Over 1,000 SF | C150: 25500 | D150: SF | G150: =C150*F150 -> 0
A152: D00805 | B152: Other Than Center Lines 0 To 1,000 SF | C152: 76000 | D152: SF | G152: =C152*F152 -> 0
A154: D00806 | B154: Other Than Center Lines Over 1,000 SF | C154: 76000 | D154: SF | G154: =C154*F154 -> 0
A156: D00807 | B156: Hatched Lines | C156: 135000 | D156: SF | G156: =C156*F156 -> 0
A158: D00808 | B158: Letters and Numbers | C158: 26000 | D158: SF | G158: =C158*F158 -> 0
A160: D00809 | B160: Arrows | C160: 9000 | D160: SF | G160: =C160*F160 -> 0
A162: D009 | B162: MISCELLANEOUS
A164: D00901 | B164: Dowels 1" X 16" - Wet-set (Sections 03 30 53, 32 13 13.03 ) | C164: 400 | D164: EA | G164: =C164*F164 -> 0
A166: D00902 | B166: Dowels 1 1/4" X 20" - Wet-set (Sections 03 30 53, 32 13 13.03 ) | C166: 400 | D166: EA | G166: =C166*F166 -> 0
A168: D00903 | B168: Dowels 1" X 16" - Drilled / epoxy(Sections 03 30 53, 32 13 13.03) | C168: 400 | D168: EA | G168: =C168*F168 -> 0
A170: D00904 | B170: Dowels 1 1/4" X 20" - Drilled / epoxy(Sections 03 30 53, 32 13 13.03) | C170: 400 | D170: EA | G170: =C170*F170 -> 0
A172: D00905 | B172: Welded Wire Fabric | C172: 3000 | D172: LBS | G172: =C172*F172 -> 0
A174: D00906 | B174: Reinforcing Steel | C174: 60000 | D174: LBS | G174: =C174*F174 -> 0
A176: D00907 | B176: Mooring Eye | C176: 10 | D176: EA | G176: =C176*F176 -> 0
A178: D00908 | B178: Mooring Eye in New Concrete | C178: 50 | D178: EA | G178: =C178*F178 -> 0
A180: D00909 | B180: Fine grade Existing Topsoil and seed | C180: 60000 | D180: SF | G180: =C180*F180 -> 0
A182: D009010 | B182: Furnish, Fine grade and Seed Topsoil | C182: 60000 | D182: SF | G182: =C182*F182 -> 0
A184: D009011 | B184: Quick Response: (One Time Additive Cost To A Task Order) | C184: 6 | D184: EA | G184: =C184*F184 -> 0
A186: D00912 | B186: Herbicide | C186: 5400 | D186: SY | G186: =C186*F186 -> 0
... A192: D00915 | B192: Grounding Points in New Concrete | C192: 50 | D192: EA | G192: =C192*F192 -> 0
A194: D010 | B194: LIGHTING
A196: D01001 | B196: Taxi-way Edge Light - In-Pavement Incandescent | C196: 5 | D196: EA | G196: =C196*F196 -> 0
A198: D01002 | B198: Taxi-way Edge Light - Elevated Incandescent | C198: 20 | D198: EA | G198: =C198*F198 -> 0
A200: D01003 | B200: Taxi-way Edge Light - In-Pavement LED | C200: 5 | D200: EA | G200: =C200*F200 -> 0
A202: D01004 | B202: Taxi-way Edge Light - Elevated LED | C202: 20 | D202: EA | G202: =C202*F202 -> 0
A204: D01005 | B204: Runway Edge Light - In-Pavement Incandescent | C204: 5 | D204: EA | G204: =C204*F204 -> 0
A206: D01006 | B206: Runway Edge Light - Elevated Incandescent | C206: 20 | D206: EA | G206: =C206*F206 -> 0
A208: D01007 | B208: Runway Edge Light - In-Pavement LED | C208: 5 | D208: EA | G208: =C208*F208 -> 0
A210: D01008 | B210: Runway Edge Light - Elevated LED | C210: 20 | D210: EA | G210: =C210*F210 -> 0
...

Sheet Option Four
A1: Solicitation No. N4008525R2559
A2: INDEFINITE DELIVERY, INDEFINITE QUANTITY CONSTRUCTION CONTRACT FOR RIGID PAVING REPAIR AND REPLACMENT AT VARIOUS NAVAL FACILITIES THROUGHOUT HAMPTON ROADS, VIRGINIA
A3: EXHIBIT E, EXHIBIT LINE ITEMS
A4: SCHEDULE OF PRICES FOR SUPPLIES/SERVICES
A6: INDEFINITE QUANTITY (IQ) WORK ITEMS - Option Four - CLIN 0005
A8: ELIN | B8: Description | C8: Est. Qty | D8: Unit | F8: Unit Price | G8: Extended Price
A10: E001 | B10: SITE PREPERATION WORK (UFGS 01 57 19 Temporary Environmental Controls)
A12: E00101 | B12: Temparory chain link fencing fencing, 6 ft hight minimum | C12: 500 | D12: LF | G12: =C12*F12 -> 0
A14: E00102 | B14: Dust control for disturbed soil or haul roads | C14: 500 | D14: 1000-SY | G14: =C14*F14 -> 0
A16: E00103 | B16: Temporary diversion dikes | C16: 300 | D16: LF | G16: =C16*F16 -> 0
A18: E00104 | B18: Silt fencing | C18: 10000 | D18: LF | G18: =C18*F18 -> 0
A20: E00105 | B20: Storm drain inlet silt protection | C20: 300 | D20: EA | G20: =C20*F20 -> 0
A22: E00106 | B22: Barricades: Low profile barricades as required to close movement areas to aircraft in order to safely perform work. | C22: 3000 | D22: LF | G22: =C22*F22 -> 0
A24: E00107 | B24: Temporary Runway and Helipad "X" Closure markings. (typically made of yellow plywood) | C24: 25 | D24: EA | G24: =C24*F24 -> 0
A26: E002 | B26: DEMOLITION, REMOVAL, AND DISPOSAL
A28: E00201 | B28: Sawcutting (Per LF up to 4 inches deep) | C28: 55000 | D28: LF-IN | G28: =C28*F28 -> 0
A30: E00202 | B30: Concrete Removal-Plain | C30: 2500 | D30: CY | G30: =C30*F30 -> 0
A32: E00203 | B32: Concrete Removal-Reinf | C32: 2500 | D32: CY | G32: =C32*F32 -> 0
A34: E00204 | B34: Bituminous Pavement Removal | C34: 10000 | D34: CY | G34: =C34*F34 -> 0
A36: E00205 | B36: Milling of Bituminous Pavement | C36: 200000 | D36: SY-IN | G36: =C36*F36 -> 0
A38: E00206 | B38: Rubber Removal 1 To 75,000 SF | C38: 100000 | D38: SF | G38: =C38*F38 -> 0
A40: E00207 | B40: Rubber Removal 75,001 To 200,000 SF | C40: 200000 | D40: SF | G40: =C40*F40 -> 0
A42: E00208 | B42: Rubber Removal 200,001 and Above | C42: 1402000 | D42: SF | G42: =C42*F42 -> 0
A44: E00209 | B44: Paint Removal Contractor Disposal (85%) | C44: 82000 | D44: SF | G44: =C44*F44 -> 0
A46: E00210 | B46: Paint Removal Contractor Disposal (100%) | C46: 20000 | D46: SF | G46: =C46*F46 -> 0
A48: E00211 | B48: Remove Aircraft Tiedown (Includes Saw cutting) | C48: 50 | D48: EA | G48: =C48*F48 -> 0
A50: E003 | B50: EXCAVATION AND GRADING
A52: E00301 | B52: Excavation and Grading | C52: 1000 | D52: CY | G52: =C52*F52 -> 0
A54: E00302 | B54: Hand Excavation | C54: 200 | D54: CY | G54: =C54*F54 -> 0
A56: E00303 | B56: Furnish and Install Topsoil | C56: 100 | D56: CY | G56: =C56*F56 -> 0
A58: E00304 | B58: Overhaul | C58: 100 | D58: MI | G58: =C58*F58 -> 0
A60: E00305 | B60: Import and Placement of Suitable Soil | C60: 250 | D60: CY | G60: =C60*F60 -> 0
A62: E00306 | B62: Import and Placement of Select Granular Fill | C62: 250 | D62: CY | G62: =C62*F62 -> 0
A64: E00307 | B64: Import and Placement of VDOT 21A/B Crushed Stone | C64: 250 | D64: CY | G64: =C64*F64 -> 0
A66: E00308 | B66: Import and Placement of VDOT 57 Crushed Stone | C66: 250 | D66: CY | G66: =C66*F66 -> 0
A68: E00309 | B68: Removal of accumulated Sediments and Debris | C68: 1000 | D68: TON | G68: =C68*F68 -> 0
A70: E00310 | B70: Repair, rehabilitation, or replacement of ditches or fills | C70: 7260 | D70: SY | G70: =C70*F70 -> 0
A72: E004 | B72: FABRICS
A74: E00401 | B74: Soil Reinforcement Fabric | C74: 1000 | D74: SY | G74: =C74*F74 -> 0
A76: E00402 | B76: Geotextile | C76: 1000 | D76: SY | G76: =C76*F76 -> 0
A78: E005 | B78: AGGREGATE
A80: E00501 | B80: Coarse Aggregate | C80: 500 | D80: TN | G80: =C80*F80 -> 0
A82: E00502 | B82: Aggregate Base Course | C82: 1000 | D82: TN | G82: =C82*F82 -> 0
A84: E006 | B84: CRACK SEALING AND BITUMINOUS
A86: E00601 | B86: Liquid Bituminous | C86: 1000 | D86: GL | G86: =C86*F86 -> 0
A88: E00602 | B88: Crack Sealing | C88: 100000 | D88: LF | G88: =C88*F88 -> 0
A90: E00603 | B90: Crack Repairs - Across Entire Width of Slab | C90: 500 | D90: LF | G90: =C90*F90 -> 0
A92: E00604 | B92: Crack Repairs - Not Across Entire Width of Slab | C92: 500 | D92: LF | G92: =C92*F92 -> 0
A94: E00605 | B94: Bituminous Concrete B-2 (Base Mix) | C94: 2500 | D94: TN | G94: =C94*F94 -> 0
A96: E00606 | B96: Bituminous Concrete 1M1B (Intermitted Mix) | C96: 2500 | D96: TN | G96: =C96*F96 -> 0
A98: E00607 | B98: Bituminous Concrete P-401 (Surface Mix) | C98: 2500 | D98: TN | G98: =C98*F98 -> 0
A100: E00608 | B100: Bituminous Concrete SM-9.5, SM-12.5 (Surface Mix) | C100: 2500 | D100: TN | G100: =C100*F100 -> 0
A102: E00609 | B102: 100% Handwork | C102: 3000 | D102: SY-IN | G102: =C102*F102 -> 0
A104: E007 | B104: CONCRETE PAVEMENT
A106: E00701 | B106: Total Slab Replacement: 8" Thick 0 To 28 CY | C106: 200 | D106: CY | G106: =C106*F106 -> 0
A108: E00702 | B108: Total Slab Replacement: 8" Thick 28 To 84 CY | C108: 200 | D108: CY | G108: =C108*F108 -> 0
A110: E00703 | B110: Total Slab Replacement: 8" Thick Over 84 CY | C110: 200 | D110: CY | G110: =C110*F110 -> 0
A112: E00704 | B112: Total Slab Replacement: 10" Thick 0 To 28 CY | C112: 200 | D112: CY | G112: =C112*F112 -> 0
A114: E00705 | B114: Total Slab Replacement: 10" Thick 28 To 84 CY | C114: 200 | D114: CY | G114: =C114*F114 -> 0
A116: E00706 | B116: Total Slab Replacement: 10" Thick Over 84 CY | C116: 200 | D116: CY | G116: =C116*F116 -> 0
A118: E00707 | B118: Total Slab Replacement: 12" Thick 0 To 28 CY | C118: 200 | D118: CY | G118: =C118*F118 -> 0
A120: E00708 | B120: Total Slab Replacement: 12" Thick 28 To 84 CY | C120: 200 | D120: CY | G120: =C120*F120 -> 0
A122: E00709 | B122: Total Slab Replacement: 12" Thick Over 84 CY | C122: 200 | D122: CY | G122: =C122*F122 -> 0
A124: E00710 | B124: Partial Slab Replacement: 8" Thick | C124: 64 | D124: CY | G124: =C124*F124 -> 0
A126: E00711 | B126: Partial Slab Replacement: 10" Thick | C126: 30 | D126: CY | G126: =C126*F126 -> 0
A128: E00712 | B128: Partial Slab Replacement: 12" Thick | C128: 90 | D128: CY | G128: =C128*F128 -> 0
... A140: E00718 | B140: Use of High Early Strength Concrete | C140: 500 | D140: CY | G140: =C140*F140 -> 0
A142: E008 | B142: PAVEMENT MARKINGS
A144: E00801 | B144: Black Out/Black Background | C144: 50000 | D144: SF | G144: =C144*F144 -> 0
A146: E00802 | B146: Glass Spheres (Type III) | C146: 2600 | D146: LBS | G146: =C146*F146 -> 0
A148: E00803 | B148: Center Lines 0 To 1,000 SF | C148: 2500 | D148: SF | G148: =C148*F148 -> 0
A150: E00804 | B150: Center Lines Over 1,000 SF | C150: 25500 | D150: SF | G150: =C150*F150 -> 0
A152: E00805 | B152: Other Than Center Lines 0 To 1,000 SF | C152: 76000 | D152: SF | G152: =C152*F152 -> 0
A154: E00806 | B154: Other Than Center Lines Over 1,000 SF | C154: 76000 | D154: SF | G154: =C154*F154 -> 0
A156: E00807 | B156: Hatched Lines | C156: 135000 | D156: SF | G156: =C156*F156 -> 0
A158: E00808 | B158: Letters and Numbers | C158: 26000 | D158: SF | G158: =C158*F158 -> 0
A160: E00809 | B160: Arrows | C160: 9000 | D160: SF | G160: =C160*F160 -> 0
A162: E009 | B162: MISCELLANEOUS
A164: E00901 | B164: Dowels 1" X 16" - Wet-set (Sections 03 30 53, 32 13 13.03 ) | C164: 400 | D164: EA | G164: =C164*F164 -> 0
A166: E00902 | B166: Dowels 1 1/4" X 20" - Wet-set (Sections 03 30 53, 32 13 13.03 ) | C166: 400 | D166: EA | G166: =C166*F166 -> 0
A168: E00903 | B168: Dowels 1" X 16" - Drilled / epoxy(Sections 03 30 53, 32 13 13.03) | C168: 400 | D168: EA | G168: =C168*F168 -> 0
A170: E00904 | B170: Dowels 1 1/4" X 20" - Drilled / epoxy(Sections 03 30 53, 32 13 13.03) | C170: 400 | D170: EA | G170: =C170*F170 -> 0
A172: E00905 | B172: Welded Wire Fabric | C172: 3000 | D172: LBS | G172: =C172*F172 -> 0
A174: E00906 | B174: Reinforcing Steel | C174: 60000 | D174: LBS | G174: =C174*F174 -> 0
A176: E00907 | B176: Mooring Eye | C176: 10 | D176: EA | G176: =C176*F176 -> 0
A178: E00908 | B178: Mooring Eye in New Concrete | C178: 50 | D178: EA | G178: =C178*F178 -> 0
A180: E00909 | B180: Fine grade Existing Topsoil and seed | C180: 60000 | D180: SF | G180: =C180*F180 -> 0
A182: E009010 | B182: Furnish, Fine grade and Seed Topsoil | C182: 60000 | D182: SF | G182: =C182*F182 -> 0
A184: E009011 | B184: Quick Response: (One Time Additive Cost To A Task Order) | C184: 6 | D184: EA | G184: =C184*F184 -> 0
A186: E00912 | B186: Herbicide | C186: 5400 | D186: SY | G186: =C186*F186 -> 0
... A192: E00915 | B192: Grounding Points in New Concrete | C192: 50 | D192: EA | G192: =C192*F192 -> 0
A194: E010 | B194: LIGHTING
A196: E01001 | B196: Taxi-way Edge Light - In-Pavement Incandescent | C196: 5 | D196: EA | G196: =C196*F196 -> 0
A198: E01002 | B198: Taxi-way Edge Light - Elevated Incandescent | C198: 20 | D198: EA | G198: =C198*F198 -> 0
A200: E01003 | B200: Taxi-way Edge Light - In-Pavement LED | C200: 5 | D200: EA | G200: =C200*F200 -> 0
A202: E01004 | B202: Taxi-way Edge Light - Elevated LED | C202: 20 | D202: EA | G202: =C202*F202 -> 0
A204: E01005 | B204: Runway Edge Light - In-Pavement Incandescent | C204: 5 | D204: EA | G204: =C204*F204 -> 0
A206: E01006 | B206: Runway Edge Light - Elevated Incandescent | C206: 20 | D206: EA | G206: =C206*F206 -> 0
A208: E01007 | B208: Runway Edge Light - In-Pavement LED | C208: 5 | D208: EA | G208: =C208*F208 -> 0
A210: E01008 | B210: Runway Edge Light - Elevated LED | C210: 20 | D210: EA | G210: =C210*F210 -> 0
...
