Workbook
Name _BasePeriod: 'SIR Section B Input'!$K$2
Name _OP1: 'SIR Section B Input'!$K$3
Name _OP2: 'SIR Section B Input'!$K$4
Name _OP3: 'SIR Section B Input'!$K$5
Name _OP4: 'SIR Section B Input'!$K$6
Name A: #REF!
Name abb: #REF!
Name accr: #REF!
Name acpu: #REF!
Name acss: #REF!
Name act: #REF!
Name acur: #REF!
Name adac: #REF!
Name adry: #REF!
Name afsn: #REF!
Name ah: #REF!
Name airc: #REF!
Name aiu: #REF!
Name apge: #REF!
Name aprpt: #REF!
Name aqs: #REF!
Name arv: #REF!
Name atos: #REF!
Name ats: #REF!
Name autdr: #REF!
Name avc: #REF!
Name avm: #REF!
Name Base: 'SIR Section B Input'!#REF!
Name batch: #REF!
Name bbht: #REF!
Name bflgt: #REF!
Name bfnc: #REF!
Name bfp: #REF!
Name blr: #REF!
Name boocl: #REF!
Name bov: #REF!
Name brdg: #REF!
Name bs: #REF!
Name bsps: #REF!
Name btum: #REF!
Name butvl: #REF!
Name bv: #REF!
Name cath: #REF!
Name cbr: #REF!
Name chem: #REF!
Name chgdet: #REF!
Name chllr: #REF!
Name chlor: #REF!
Name chnhst: #REF!
Name closer: #REF!
Name comp: #REF!
Name compch: #REF!
Name condu: #REF!
Name cont: #REF!
Name contp: #REF!
Name contrly: #REF!
Name contv: #REF!
Name Conv.: #REF!
Name coolt: #REF!
Name crac: #REF!

Sheet CLIN Pricing Information
A1: CENTRAL SERVICES AREA
A3: B.1 GENERAL
A5: This is an Indefinite Delivery Indefinite Quantity contract with Firm Fixed Price (FFP) and Labor Hours (LH) line items. The contract consists of one Base Year and four (4) Option Years for a total of five (5) years if all options are exercised. All orders for services under this contract will be procured by Task Order (TO). The minimum guarantee order will be FFP Base Year Basic Services for 17 sites.
A7: Escalation of labor, Health and Welfare rates, and any other indirect costs/rates embedded in the fully burdened hourly rates is not permitted.
A9: B.2 PRICES
A11: Prices are established for each FAA facility as shown below. Contract Line-Item Numbers (CLIN) are structured with five characters, “ABCDE” and defined as follows:
A13: A = Year of Contract (0xxxx=Base, 1xxxx=Option Year 1, etc.)
A14: BCD = FAA Facility (x001x=C90 TRACON, x002x=D10 TRACON, etc.)
A15: E = Service Type (xxxx1=Basic Service, xxxx2=Temporary Additional Services, etc.)
A17: NOTE: The price for each item is set forth below. Items will only be purchased as authorized by a TO in accordance with (IAW) the Ordering clause (3.2.4-16).
A19: B.2.1 CLIN PRICING INFORMATION
A21: CLINs XXXX1 FFP per month - Basic Services
... A41: IAW SOW C.4.2.2, the Contractor may be required to conduct a period of roving patrols at select facilities, for eight (8) hours/day for five (5) days per week, Monday through Friday, on an as needed basis. To facilitate this effort, an additional one (1) CSO will be present at the facility.

Sheet SIR Section B Input
A1: BASE PERIOD
A2: CLIN | B2: Description | C2: Loc ID / Fac Type | D2: Pricing | E2: # Units FFP = Months LH = Hours | F2: LH Price | G2: Monthly Price | H2: Period Price | J2: Base Period | K2: 9/30/2026-9/29/2027
A3: 00011 | B3: Basic Service | C3: C90 / TRACON (x001x) | D3: FFP | E3: 12 | F3: N/A | G3: ='C90 Rate Build Up'!H67 -> #DIV/0! | H3: =E3*G3 -> #DIV/0! | J3: Option Period 1 | K3: 9/30/2027-9/29/2028
A4: 00012 | B4: Temporary Additional Service (TAS) | D4: LH | E4: 80 | F4: ='C90 Rate Build Up'!$H$68 -> #DIV/0! | G4: N/A | H4: =E4*F4 -> #DIV/0! | J4: Option Period 2 | K4: 9/30/2028-9/29/2029
A5: 00013 | B5: Emergency Security Service (ESS) | D5: LH | E5: 16 | F5: ='C90 Rate Build Up'!$K$68 -> #DIV/0! | G5: N/A | H5: =E5*F5 -> #DIV/0! | J5: Option Period 3 | K5: 9/30/2029-9/29/2030
A6: 00014 | B6: Other Services (Time not Worked) | D6: LH | E6: 16 | F6: ='C90 Rate Build Up'!$H$68 -> #DIV/0! | G6: N/A | H6: =E6*F6 -> #DIV/0! | J6: OptionPeriod 4 | K6: 9/30/2030-9/29/2031
A7: 00015 | B7: Training | D7: LH | E7: 80 | F7: ='C90 Rate Build Up'!$H$68 -> #DIV/0! | G7: N/A | H7: =E7*F7 -> #DIV/0!
A8: 00016 | B8: Random Screening | D8: LH | E8: 48 | F8: ='C90 Rate Build Up'!$H$68 -> #DIV/0! | G8: N/A | H8: =E8*F8 -> #DIV/0!
A9: 00017 | B9: Roving Patrol | D9: LH | E9: 1040 | F9: ='C90 Rate Build Up'!$H$68 -> #DIV/0! | G9: N/A | H9: =E9*F9 -> #DIV/0!
B10: Total Period Price | H10: =SUM(H3:H9) -> #DIV/0!
A11: 00021 | B11: Basic Service | C11: D10 / TRACON (x002x) | D11: FFP | E11: 12 | F11: N/A | G11: ='D10 Rate Build Up'!H67 -> #DIV/0! | H11: =E11*G11 -> #DIV/0!
A12: 00022 | B12: Temporary Additional Service (TAS) | D12: LH | E12: 80 | F12: ='D10 Rate Build Up'!H68 -> #DIV/0! | G12: N/A | H12: =E12*F12 -> #DIV/0!
A13: 00023 | B13: Emergency Security Service (ESS) | D13: LH | E13: 16 | F13: ='D10 Rate Build Up'!K68 -> #DIV/0! | G13: N/A | H13: =E13*F13 -> #DIV/0!
A14: 00024 | B14: Other Services (Time not Worked) | D14: LH | E14: 16 | F14: ='D10 Rate Build Up'!H68 -> #DIV/0! | G14: N/A | H14: =E14*F14 -> #DIV/0!
A15: 00025 | B15: Training | D15: LH | E15: 80 | F15: ='D10 Rate Build Up'!H68 -> #DIV/0! | G15: N/A | H15: =E15*F15 -> #DIV/0!
A16: 00026 | B16: Random Screening | D16: LH | E16: 48 | F16: ='D10 Rate Build Up'!H68 -> #DIV/0! | G16: N/A | H16: =E16*F16 -> #DIV/0!
A17: 00027 | B17: Roving Patrol | D17: LH | E17: 1040 | F17: ='D10 Rate Build Up'!H68 -> #DIV/0! | G17: N/A | H17: =E17*F17 -> #DIV/0!
B18: Total Period Price | H18: =SUM(H11:H17) -> #DIV/0!
A19: 00031 | B19: Basic Service | C19: DFW / ATCT-E (x003x) | D19: FFP | E19: 12 | F19: N/A | G19: ='DFW ATCT-E Rate Build Up'!H67 -> #DIV/0! | H19: =E19*G19 -> #DIV/0!
A20: 00032 | B20: Temporary Additional Service (TAS) | D20: LH | E20: 80 | F20: ='DFW ATCT-E Rate Build Up'!H68 -> #DIV/0! | G20: N/A | H20: =E20*F20 -> #DIV/0!
A21: 00033 | B21: Emergency Security Service (ESS) | D21: LH | E21: 16 | F21: ='DFW ATCT-E Rate Build Up'!K68 -> #DIV/0! | G21: N/A | H21: =E21*F21 -> #DIV/0!
A22: 00034 | B22: Other Services (Time not Worked) | D22: LH | E22: 16 | F22: ='DFW ATCT-E Rate Build Up'!H68 -> #DIV/0! | G22: N/A | H22: =E22*F22 -> #DIV/0!
A23: 00035 | B23: Training | D23: LH | E23: 80 | F23: ='DFW ATCT-E Rate Build Up'!H68 -> #DIV/0! | G23: N/A | H23: =E23*F23 -> #DIV/0!
A24: 00036 | B24: Random Screening | D24: LH | E24: 48 | F24: ='DFW ATCT-E Rate Build Up'!H68 -> #DIV/0! | G24: N/A | H24: =E24*F24 -> #DIV/0!
A25: 00037 | B25: Roving Patrol | D25: LH | E25: 1040 | F25: ='DFW ATCT-E Rate Build Up'!H68 -> #DIV/0! | G25: N/A | H25: =E25*F25 -> #DIV/0!
B26: Total Period Price | H26: =SUM(H19:H25) -> #DIV/0!
A27: 00041 | B27: Basic Service | C27: DFW / ATCT-W (x004x) | D27: FFP | E27: 12 | F27: N/A | G27: ='DFW ATCT-W Rate Build Up'!H67 -> #DIV/0! | H27: =E27*G27 -> #DIV/0!
A28: 00042 | B28: Temporary Additional Service (TAS) | D28: LH | E28: 80 | F28: ='DFW ATCT-W Rate Build Up'!H68 -> #DIV/0! | G28: N/A | H28: =E28*F28 -> #DIV/0!
A29: 00043 | B29: Emergency Security Service (ESS) | D29: LH | E29: 16 | F29: ='DFW ATCT-W Rate Build Up'!K68 -> #DIV/0! | G29: N/A | H29: =E29*F29 -> #DIV/0!
A30: 00044 | B30: Other Services (Time not Worked) | D30: LH | E30: 16 | F30: ='DFW ATCT-W Rate Build Up'!H68 -> #DIV/0! | G30: N/A | H30: =E30*F30 -> #DIV/0!
A31: 00045 | B31: Training | D31: LH | E31: 80 | F31: ='DFW ATCT-W Rate Build Up'!H68 -> #DIV/0! | G31: N/A | H31: =E31*F31 -> #DIV/0!
A32: 00046 | B32: Random Screening | D32: LH | E32: 48 | F32: ='DFW ATCT-W Rate Build Up'!H68 -> #DIV/0! | G32: N/A | H32: =E32*F32 -> #DIV/0!
A33: 00047 | B33: Roving Patrol | D33: LH | E33: 1040 | F33: ='DFW ATCT-W Rate Build Up'!H68 -> #DIV/0! | G33: N/A | H33: =E33*F33 -> #DIV/0!
B34: Total Period Price | H34: =SUM(H27:H33) -> #DIV/0!
A35: 00051 | B35: Basic Service | C35: DTW / ATCT (x005x) | D35: FFP | E35: 12 | F35: N/A | G35: ='DTW Rate Build Up'!H67 -> #DIV/0! | H35: =E35*G35 -> #DIV/0!
A36: 00052 | B36: Temporary Additional Service (TAS) | D36: LH | E36: 80 | F36: ='DTW Rate Build Up'!H68 -> #DIV/0! | G36: N/A | H36: =E36*F36 -> #DIV/0!
A37: 00053 | B37: Emergency Security Service (ESS) | D37: LH | E37: 16 | F37: ='DTW Rate Build Up'!K68 -> #DIV/0! | G37: N/A | H37: =E37*F37 -> #DIV/0!
A38: 00054 | B38: Other Services (Time not Worked) | D38: LH | E38: 16 | F38: ='DTW Rate Build Up'!H68 -> #DIV/0! | G38: N/A | H38: =E38*F38 -> #DIV/0!
A39: 00055 | B39: Training | D39: LH | E39: 80 | F39: ='DTW Rate Build Up'!H68 -> #DIV/0! | G39: N/A | H39: =E39*F39 -> #DIV/0!
A40: 00056 | B40: Random Screening | D40: LH | E40: 48 | F40: ='DTW Rate Build Up'!H68 -> #DIV/0! | G40: N/A | H40: =E40*F40 -> #DIV/0!
A41: 00057 | B41: Roving Patrol | D41: LH | E41: 1040 | F41: ='DTW Rate Build Up'!H68 -> #DIV/0! | G41: N/A | H41: =E41*F41 -> #DIV/0!
B42: Total Period Price | H42: =SUM(H35:H41) -> #DIV/0!
A43: 00061 | B43: Basic Service | C43: I90 / TRACON (x006x) | D43: FFP | E43: 12 | F43: N/A | G43: ='I90 TRACON Rate Build Up'!H67 -> #DIV/0! | H43: =E43*G43 -> #DIV/0!
A44: 00062 | B44: Temporary Additional Service (TAS) | D44: LH | E44: 80 | F44: ='I90 TRACON Rate Build Up'!H68 -> #DIV/0! | G44: N/A | H44: =E44*F44 -> #DIV/0!
A45: 00063 | B45: Emergency Security Service (ESS) | D45: LH | E45: 16 | F45: ='I90 TRACON Rate Build Up'!K68 -> #DIV/0! | G45: N/A | H45: =E45*F45 -> #DIV/0!
A46: 00064 | B46: Other Services (Time not Worked) | D46: LH | E46: 16 | F46: ='I90 TRACON Rate Build Up'!H68 -> #DIV/0! | G46: N/A | H46: =E46*F46 -> #DIV/0!
A47: 00065 | B47: Training | D47: LH | E47: 80 | F47: ='I90 TRACON Rate Build Up'!H68 -> #DIV/0! | G47: N/A | H47: =E47*F47 -> #DIV/0!
A48: 00066 | B48: Random Screening | D48: LH | E48: 48 | F48: ='I90 TRACON Rate Build Up'!H68 -> #DIV/0! | G48: N/A | H48: =E48*F48 -> #DIV/0!
A49: 00067 | B49: Roving Patrol | D49: LH | E49: 1040 | F49: ='I90 TRACON Rate Build Up'!H68 -> #DIV/0! | G49: N/A | H49: =E49*F49 -> #DIV/0!
B50: Total Period Price | H50: =SUM(H43:H49) -> #DIV/0!
A52: BASE PERIOD
A53: CLIN | B53: Description | C53: Loc ID / Fac Type | D53: Pricing | E53: # Units FFP = Months LH = Hours | F53: LH Price | G53: Monthly Price | H53: Period Price
A54: 00071 | B54: Basic Service | C54: IAH / ATCT (x007x) | D54: FFP | E54: 12 | F54: N/A | G54: ='IAH ATCT Rate Build Up'!H67 -> #DIV/0! | H54: =E54*G54 -> #DIV/0!
A55: 00072 | B55: Temporary Additional Service (TAS) | D55: LH | E55: 80 | F55: ='IAH ATCT Rate Build Up'!H68 -> #DIV/0! | G55: N/A | H55: =E55*F55 -> #DIV/0!
A56: 00073 | B56: Emergency Security Service (ESS) | D56: LH | E56: 16 | F56: ='IAH ATCT Rate Build Up'!K68 -> #DIV/0! | G56: N/A | H56: =E56*F56 -> #DIV/0!
A57: 00074 | B57: Other Services (Time not Worked) | D57: LH | E57: 16 | F57: ='IAH ATCT Rate Build Up'!H68 -> #DIV/0! | G57: N/A | H57: =E57*F57 -> #DIV/0!
A58: 00075 | B58: Training | D58: LH | E58: 80 | F58: ='IAH ATCT Rate Build Up'!H68 -> #DIV/0! | G58: N/A | H58: =E58*F58 -> #DIV/0!
A59: 00076 | B59: Random Screening | D59: LH | E59: 48 | F59: ='IAH ATCT Rate Build Up'!H68 -> #DIV/0! | G59: N/A | H59: =E59*F59 -> #DIV/0!
A60: 00077 | B60: Roving Patrol | D60: LH | E60: 1040 | F60: ='IAH ATCT Rate Build Up'!H68 -> #DIV/0! | G60: N/A | H60: =E60*F60 -> #DIV/0!
B61: Total Period Price | H61: =SUM(H54:H60) -> #DIV/0!
A62: 00081 | B62: Basic Service | C62: MSP / ATCT (x008x) | D62: FFP | E62: 12 | F62: N/A | G62: ='MSP ATCT Rate Build Up'!H67 -> #DIV/0! | H62: =E62*G62 -> #DIV/0!
A63: 00082 | B63: Temporary Additional Service (TAS) | D63: LH | E63: 80 | F63: ='MSP ATCT Rate Build Up'!H68 -> #DIV/0! | G63: N/A | H63: =E63*F63 -> #DIV/0!
A64: 00083 | B64: Emergency Security Service (ESS) | D64: LH | E64: 16 | F64: ='MSP ATCT Rate Build Up'!K68 -> #DIV/0! | G64: N/A | H64: =E64*F64 -> #DIV/0!
A65: 00084 | B65: Other Services (Time not Worked) | D65: LH | E65: 16 | F65: ='MSP ATCT Rate Build Up'!H68 -> #DIV/0! | G65: N/A | H65: =E65*F65 -> #DIV/0!
A66: 00085 | B66: Training | D66: LH | E66: 80 | F66: ='MSP ATCT Rate Build Up'!H68 -> #DIV/0! | G66: N/A | H66: =E66*F66 -> #DIV/0!
A67: 00086 | B67: Random Screening | D67: LH | E67: 48 | F67: ='MSP ATCT Rate Build Up'!H68 -> #DIV/0! | G67: N/A | H67: =E67*F67 -> #DIV/0!
A68: 00087 | B68: Roving Patrol | D68: LH | E68: 1040 | F68: ='MSP ATCT Rate Build Up'!H68 -> #DIV/0! | G68: N/A | H68: =E68*F68 -> #DIV/0!
B69: Total Period Price | H69: =SUM(H62:H68) -> #DIV/0!
A70: 00091 | B70: Basic Service | C70: ORD / ATCT (x009x) | D70: FFP | E70: 12 | F70: N/A | G70: ='ORD ATCT Rate Build Up'!H67 -> #DIV/0! | H70: =E70*G70 -> #DIV/0!
A71: 00092 | B71: Temporary Additional Service (TAS) | D71: LH | E71: 80 | F71: ='ORD ATCT Rate Build Up'!H68 -> #DIV/0! | G71: N/A | H71: =E71*F71 -> #DIV/0!
A72: 00093 | B72: Emergency Security Service (ESS) | D72: LH | E72: 16 | F72: ='ORD ATCT Rate Build Up'!K68 -> #DIV/0! | G72: N/A | H72: =E72*F72 -> #DIV/0!
A73: 00094 | B73: Other Services (Time not Worked) | D73: LH | E73: 16 | F73: ='ORD ATCT Rate Build Up'!H68 -> #DIV/0! | G73: N/A | H73: =E73*F73 -> #DIV/0!
A74: 00095 | B74: Training | D74: LH | E74: 80 | F74: ='ORD ATCT Rate Build Up'!H68 -> #DIV/0! | G74: N/A | H74: =E74*F74 -> #DIV/0!
A75: 00096 | B75: Random Screening | D75: LH | E75: 48 | F75: ='ORD ATCT Rate Build Up'!H68 -> #DIV/0! | G75: N/A | H75: =E75*F75 -> #DIV/0!
A76: 00097 | B76: Roving Patrol | D76: LH | E76: 1040 | F76: ='ORD ATCT Rate Build Up'!H68 -> #DIV/0! | G76: N/A | H76: =E76*F76 -> #DIV/0!
B77: Total Period Price | H77: =SUM(H70:H76) -> #DIV/0!
A78: 00101 | B78: Basic Service | C78: ZAB / ARTCC (x010x) | D78: FFP | E78: 12 | F78: N/A | G78: ='ZAB ARTCC Rate Build Up'!H67 -> #DIV/0! | H78: =E78*G78 -> #DIV/0!
A79: 00102 | B79: Temporary Additional Service (TAS) | D79: LH | E79: 80 | F79: ='ZAB ARTCC Rate Build Up'!H68 -> #DIV/0! | G79: N/A | H79: =E79*F79 -> #DIV/0!
A80: 00103 | B80: Emergency Security Service (ESS) | D80: LH | E80: 16 | F80: ='ZAB ARTCC Rate Build Up'!K68 -> #DIV/0! | G80: N/A | H80: =E80*F80 -> #DIV/0!
A81: 00104 | B81: Other Services (Time not Worked) | D81: LH | E81: 16 | F81: ='ZAB ARTCC Rate Build Up'!H68 -> #DIV/0! | G81: N/A | H81: =E81*F81 -> #DIV/0!
A82: 00105 | B82: Training | D82: LH | E82: 80 | F82: ='ZAB ARTCC Rate Build Up'!H68 -> #DIV/0! | G82: N/A | H82: =E82*F82 -> #DIV/0!
A83: 00106 | B83: Random Screening | D83: LH | E83: 48 | F83: ='ZAB ARTCC Rate Build Up'!H68 -> #DIV/0! | G83: N/A | H83: =E83*F83 -> #DIV/0!
A84: 00107 | B84: Roving Patrol | D84: LH | E84: 1040 | F84: ='ZAB ARTCC Rate Build Up'!H68 -> #DIV/0! | G84: N/A | H84: =E84*F84 -> #DIV/0!
B85: Total Period Price | H85: =SUM(H78:H84) -> #DIV/0!
A86: 00111 | B86: Basic Service | C86: ZAU / ARTCC (x011x) | D86: FFP | E86: 12 | F86: N/A | G86: ='ZAU Rate Build Up'!H67 -> #DIV/0! | H86: =E86*G86 -> #DIV/0!
A87: 00112 | B87: Temporary Additional Service (TAS) | D87: LH | E87: 80 | F87: ='ZAU Rate Build Up'!H68 -> #DIV/0! | G87: N/A | H87: =E87*F87 -> #DIV/0!
A88: 00113 | B88: Emergency Security Service (ESS) | D88: LH | E88: 16 | F88: ='ZAU Rate Build Up'!K68 -> #DIV/0! | G88: N/A | H88: =E88*F88 -> #DIV/0!
A89: 00114 | B89: Other Services (Time not Worked) | D89: LH | E89: 16 | F89: ='ZAU Rate Build Up'!H68 -> #DIV/0! | G89: N/A | H89: =E89*F89 -> #DIV/0!
A90: 00115 | B90: Training | D90: LH | E90: 80 | F90: ='ZAU Rate Build Up'!H68 -> #DIV/0! | G90: N/A | H90: =E90*F90 -> #DIV/0!
A91: 00116 | B91: Random Screening | D91: LH | E91: 48 | F91: ='ZAU Rate Build Up'!H68 -> #DIV/0! | G91: N/A | H91: =E91*F91 -> #DIV/0!
A92: 00117 | B92: Roving Patrol | D92: LH | E92: 1040 | F92: ='ZAU Rate Build Up'!H68 -> #DIV/0! | G92: N/A | H92: =E92*F92 -> #DIV/0!
B93: Total Period Price | H93: =SUM(H86:H92) -> #DIV/0!
A94: 00121 | B94: Basic Service | C94: ZFW / ARTCC (x012x) | D94: FFP | E94: 12 | F94: N/A | G94: ='ZFW Rate Build Up'!H67 -> #DIV/0! | H94: =E94*G94 -> #DIV/0!
A95: 00122 | B95: Temporary Additional Service (TAS) | D95: LH | E95: 80 | F95: ='ZFW Rate Build Up'!H68 -> #DIV/0! | G95: N/A | H95: =E95*F95 -> #DIV/0!
A96: 00123 | B96: Emergency Security Service (ESS) | D96: LH | E96: 16 | F96: ='ZFW Rate Build Up'!K68 -> #DIV/0! | G96: N/A | H96: =E96*F96 -> #DIV/0!
A97: 00124 | B97: Other Services (Time not Worked) | D97: LH | E97: 16 | F97: ='ZFW Rate Build Up'!H68 -> #DIV/0! | G97: N/A | H97: =E97*F97 -> #DIV/0!
A98: 00125 | B98: Training | D98: LH | E98: 80 | F98: ='ZFW Rate Build Up'!H68 -> #DIV/0! | G98: N/A | H98: =E98*F98 -> #DIV/0!
A99: 00126 | B99: Random Screening | D99: LH | E99: 48 | F99: ='ZFW Rate Build Up'!H68 -> #DIV/0! | G99: N/A | H99: =E99*F99 -> #DIV/0!
A100: 00127 | B100: Roving Patrol | D100: LH | E100: 1040 | F100: ='ZFW Rate Build Up'!H68 -> #DIV/0! | G100: N/A | H100: =E100*F100 -> #DIV/0!
B101: Total Period Price | H101: =SUM(H94:H100) -> #DIV/0!
...

Sheet Summary Prices By Site
A1: Facility | G1: Base Period 06/30/2022 - 09/29/2023 | I1: Option Period 1 | K1: Option Period 2 | M1: Option Period 3 | O1: Option Period 4 | Q1: Total Site Price
A2: Service Area | B2: Region | C2: Location ID (LID) | D2: Facility Type (FAC) | E2: City | F2: State | G2: Monthly Price | H2: Period Price | I2: Monthly Price | J2: Period Price | K2: Monthly Price | L2: Period Price | M2: Monthly Price | N2: Period Price | O2: Monthly Price | P2: Period Price
A3: Western Service Area
A4: WSA | B4: AAL | C4: AAL | D4: 1 | E4: Anchorage | F4: AK | G4: Reserved | H4: Reserved | I4: Reserved | J4: Reserved | K4: Reserved | L4: Reserved | M4: Reserved | N4: Reserved | O4: Reserved | P4: Reserved | Q4: Reserved
A5: CSA | B5: AGL | C5: C90 | D5: TRACON | E5: Elgin | F5: IL | G5: =H5/12 -> #DIV/0! | H5: ='SIR Section B Input'!H10 -> #DIV/0! | I5: =J5/12 -> #DIV/0! | J5: ='SIR Section B Input'!H165 -> #DIV/0! | K5: =L5/12 -> #DIV/0! | L5: ='SIR Section B Input'!H320 -> #DIV/0! | M5: =N5/12 -> #DIV/0! | N5: ='SIR Section B Input'!H475 -> #DIV/0! | O5: =P5/12 -> #DIV/0! | P5: ='SIR Section B Input'!H630 -> #DIV/0! | Q5: =SUM(H5,J5,L5,N5,P5) -> #DIV/0!
A6: CSA | B6: ASW | C6: D10 | D6: TRACON | E6: Dallas/Fort Worth | F6: TX | G6: =H6/12 -> #DIV/0! | H6: ='SIR Section B Input'!H18 -> #DIV/0! | I6: =J6/12 -> #DIV/0! | J6: ='SIR Section B Input'!H173 -> #DIV/0! | K6: =L6/12 -> #DIV/0! | L6: ='SIR Section B Input'!H328 -> #DIV/0! | M6: =N6/12 -> #DIV/0! | N6: ='SIR Section B Input'!H483 -> #DIV/0! | O6: =P6/12 -> #DIV/0! | P6: ='SIR Section B Input'!H638 -> #DIV/0! | Q6: =SUM(H6,J6,L6,N6,P6) -> #DIV/0!
A7: CSA | B7: ASW | C7: DFW | D7: ATCT-E | E7: Dallas/Fort Worth | F7: TX | G7: =H7/12 -> #DIV/0! | H7: ='SIR Section B Input'!H26 -> #DIV/0! | I7: =J7/12 -> #DIV/0! | J7: ='SIR Section B Input'!H181 -> #DIV/0! | K7: =L7/12 -> #DIV/0! | L7: ='SIR Section B Input'!H336 -> #DIV/0! | M7: =N7/12 -> #DIV/0! | N7: ='SIR Section B Input'!H491 -> #DIV/0! | O7: =P7/12 -> #DIV/0! | P7: ='SIR Section B Input'!H646 -> #DIV/0! | Q7: =SUM(H7,J7,L7,N7,P7) -> #DIV/0!
A8: CSA | B8: ASW | C8: DFW | D8: ATCT-W | E8: Dallas/Fort Worth | F8: TX | G8: =H8/12 -> #DIV/0! | H8: ='SIR Section B Input'!H34 -> #DIV/0! | I8: =J8/12 -> #DIV/0! | J8: ='SIR Section B Input'!H189 -> #DIV/0! | K8: =L8/12 -> #DIV/0! | L8: ='SIR Section B Input'!H344 -> #DIV/0! | M8: =N8/12 -> #DIV/0! | N8: ='SIR Section B Input'!H499 -> #DIV/0! | O8: =P8/12 -> #DIV/0! | P8: ='SIR Section B Input'!H654 -> #DIV/0! | Q8: =SUM(H8,J8,L8,N8,P8) -> #DIV/0!
A9: CSA | B9: AGL | C9: DTW | D9: ATCT | E9: Detroit | F9: MI | G9: =H9/12 -> #DIV/0! | H9: ='SIR Section B Input'!H42 -> #DIV/0! | I9: =J9/12 -> #DIV/0! | J9: ='SIR Section B Input'!H197 -> #DIV/0! | K9: =L9/12 -> #DIV/0! | L9: ='SIR Section B Input'!H352 -> #DIV/0! | M9: =N9/12 -> #DIV/0! | N9: ='SIR Section B Input'!H507 -> #DIV/0! | O9: =P9/12 -> #DIV/0! | P9: ='SIR Section B Input'!H662 -> #DIV/0! | Q9: =SUM(H9,J9,L9,N9,P9) -> #DIV/0!
A10: CSA | C10: OAK | D10: ATCT | E10: Oakland | F10: CA
A11: CSA | B11: ASW | C11: I90 | D11: TRACON | E11: Houston | F11: TX | G11: =H11/12 -> #DIV/0! | H11: ='SIR Section B Input'!H50 -> #DIV/0! | I11: =J11/12 -> #DIV/0! | J11: ='SIR Section B Input'!H205 -> #DIV/0! | K11: =L11/12 -> #DIV/0! | L11: ='SIR Section B Input'!H360 -> #DIV/0! | M11: =N11/12 -> #DIV/0! | N11: ='SIR Section B Input'!H515 -> #DIV/0! | O11: =P11/12 -> #DIV/0! | P11: ='SIR Section B Input'!H670 -> #DIV/0! | Q11: =SUM(H11,J11,L11,N11,P11) -> #DIV/0!
A12: CSA | B12: ASW | C12: IAH | D12: ATCT | E12: Houston | F12: TX | G12: =H12/12 -> #DIV/0! | H12: ='SIR Section B Input'!H61 -> #DIV/0! | I12: =J12/12 -> #DIV/0! | J12: ='SIR Section B Input'!H216 -> #DIV/0! | K12: =L12/12 -> #DIV/0! | L12: ='SIR Section B Input'!H371 -> #DIV/0! | M12: =N12/12 -> #DIV/0! | N12: ='SIR Section B Input'!H526 -> #DIV/0! | O12: =P12/12 -> #DIV/0! | P12: ='SIR Section B Input'!H681 -> #DIV/0! | Q12: =SUM(H12,J12,L12,N12,P12) -> #DIV/0!
A13: CSA | B13: AGL | C13: MSP | D13: ATCT | E13: Minneapolis | F13: MN | G13: =H13/12 -> #DIV/0! | H13: ='SIR Section B Input'!H69 -> #DIV/0! | I13: =J13/12 -> #DIV/0! | J13: ='SIR Section B Input'!H224 -> #DIV/0! | K13: =L13/12 -> #DIV/0! | L13: ='SIR Section B Input'!H379 -> #DIV/0! | M13: =N13/12 -> #DIV/0! | N13: ='SIR Section B Input'!H534 -> #DIV/0! | O13: =P13/12 -> #DIV/0! | P13: ='SIR Section B Input'!H689 -> #DIV/0! | Q13: =SUM(H13,J13,L13,N13,P13) -> #DIV/0!
A14: CSA | B14: AGL | C14: ORD | D14: ATCT | E14: Chicago | F14: IL | G14: =H14/12 -> #DIV/0! | H14: ='SIR Section B Input'!H77 -> #DIV/0! | I14: =J14/12 -> #DIV/0! | J14: ='SIR Section B Input'!H232 -> #DIV/0! | K14: =L14/12 -> #DIV/0! | L14: ='SIR Section B Input'!H387 -> #DIV/0! | M14: =N14/12 -> #DIV/0! | N14: ='SIR Section B Input'!H542 -> #DIV/0! | O14: =P14/12 -> #DIV/0! | P14: ='SIR Section B Input'!H697 -> #DIV/0! | Q14: =SUM(H14,J14,L14,N14,P14) -> #DIV/0!
A15: CSA | B15: ASW | C15: ZAB | D15: ARTCC | E15: Albuquerque | F15: NM | G15: =H15/12 -> #DIV/0! | H15: ='SIR Section B Input'!H85 -> #DIV/0! | I15: =J15/12 -> #DIV/0! | J15: ='SIR Section B Input'!H240 -> #DIV/0! | K15: =L15/12 -> #DIV/0! | L15: ='SIR Section B Input'!H395 -> #DIV/0! | M15: =N15/12 -> #DIV/0! | N15: ='SIR Section B Input'!H550 -> #DIV/0! | O15: =P15/12 -> #DIV/0! | P15: ='SIR Section B Input'!H705 -> #DIV/0! | Q15: =SUM(H15,J15,L15,N15,P15) -> #DIV/0!
A16: CSA | B16: AGL | C16: ZAU | D16: ARTCC | E16: Aurora | F16: IL | G16: =H16/12 -> #DIV/0! | H16: ='SIR Section B Input'!H93 -> #DIV/0! | I16: =J16/12 -> #DIV/0! | J16: ='SIR Section B Input'!H248 -> #DIV/0! | K16: =L16/12 -> #DIV/0! | L16: ='SIR Section B Input'!H403 -> #DIV/0! | M16: =N16/12 -> #DIV/0! | N16: ='SIR Section B Input'!H558 -> #DIV/0! | O16: =P16/12 -> #DIV/0! | P16: ='SIR Section B Input'!H713 -> #DIV/0! | Q16: =SUM(H16,J16,L16,N16,P16) -> #DIV/0!
A17: CSA | B17: ASW | C17: ZFW | D17: ARTCC | E17: Fort Worth | F17: TX | G17: =H17/12 -> #DIV/0! | H17: ='SIR Section B Input'!H101 -> #DIV/0! | I17: =J17/12 -> #DIV/0! | J17: ='SIR Section B Input'!H256 -> #DIV/0! | K17: =L17/12 -> #DIV/0! | L17: ='SIR Section B Input'!H411 -> #DIV/0! | M17: =N17/12 -> #DIV/0! | N17: ='SIR Section B Input'!H566 -> #DIV/0! | O17: =P17/12 -> #DIV/0! | P17: ='SIR Section B Input'!H721 -> #DIV/0! | Q17: =SUM(H17,J17,L17,N17,P17) -> #DIV/0!
A18: CSA | B18: ASW | C18: ZHU | D18: ARTCC | E18: Houston | F18: TX | G18: =H18/12 -> #DIV/0! | H18: ='SIR Section B Input'!H109 -> #DIV/0! | I18: =J18/12 -> #DIV/0! | J18: ='SIR Section B Input'!H264 -> #DIV/0! | K18: =L18/12 -> #DIV/0! | L18: ='SIR Section B Input'!H419 -> #DIV/0! | M18: =N18/12 -> #DIV/0! | N18: ='SIR Section B Input'!H574 -> #DIV/0! | O18: =P18/12 -> #DIV/0! | P18: ='SIR Section B Input'!H729 -> #DIV/0! | Q18: =SUM(H18,J18,L18,N18,P18) -> #DIV/0!
A19: CSA | B19: AGL | C19: ZID | D19: ARTCC | E19: Indianapolis | F19: IN | G19: =H19/12 -> #DIV/0! | H19: ='SIR Section B Input'!H120 -> #DIV/0! | I19: =J19/12 -> #DIV/0! | J19: ='SIR Section B Input'!H275 -> #DIV/0! | K19: =L19/12 -> #DIV/0! | L19: ='SIR Section B Input'!H430 -> #DIV/0! | M19: =N19/12 -> #DIV/0! | N19: ='SIR Section B Input'!H585 -> #DIV/0! | O19: =P19/12 -> #DIV/0! | P19: ='SIR Section B Input'!H740 -> #DIV/0! | Q19: =SUM(H19,J19,L19,N19,P19) -> #DIV/0!
A20: CSA | B20: ACE | C20: ZKC | D20: ARTCC | E20: Olathe | F20: KS | G20: =H20/12 -> #DIV/0! | H20: ='SIR Section B Input'!H128 -> #DIV/0! | I20: =J20/12 -> #DIV/0! | J20: ='SIR Section B Input'!H283 -> #DIV/0! | K20: =L20/12 -> #DIV/0! | L20: ='SIR Section B Input'!H438 -> #DIV/0! | M20: =N20/12 -> #DIV/0! | N20: ='SIR Section B Input'!H593 -> #DIV/0! | O20: =P20/12 -> #DIV/0! | P20: ='SIR Section B Input'!H748 -> #DIV/0! | Q20: =SUM(H20,J20,L20,N20,P20) -> #DIV/0!
A21: CSA | B21: ASW | C21: ZMP | D21: ARTCC | E21: Farmington | F21: MN | G21: =H21/12 -> #DIV/0! | H21: ='SIR Section B Input'!H136 -> #DIV/0! | I21: =J21/12 -> #DIV/0! | J21: ='SIR Section B Input'!H291 -> #DIV/0! | K21: =L21/12 -> #DIV/0! | L21: ='SIR Section B Input'!H446 -> #DIV/0! | M21: =N21/12 -> #DIV/0! | N21: ='SIR Section B Input'!H601 -> #DIV/0! | O21: =P21/12 -> #DIV/0! | P21: ='SIR Section B Input'!H756 -> #DIV/0! | Q21: =SUM(H21,J21,L21,N21,P21) -> #DIV/0!
A22: CSA | B22: AGL | C22: ZOB | D22: ARTCC | E22: Oberlin | F22: OH | G22: =H22/12 -> #DIV/0! | H22: ='SIR Section B Input'!H144 -> #DIV/0! | I22: =J22/12 -> #DIV/0! | J22: ='SIR Section B Input'!H299 -> #DIV/0! | K22: =L22/12 -> #DIV/0! | L22: ='SIR Section B Input'!H454 -> #DIV/0! | M22: =N22/12 -> #DIV/0! | N22: ='SIR Section B Input'!H609 -> #DIV/0! | O22: =P22/12 -> #DIV/0! | P22: ='SIR Section B Input'!H764 -> #DIV/0! | Q22: =SUM(H22,J22,L22,N22,P22) -> #DIV/0!
A23: Central Service Area Totals: | G23: =H23/12 -> #DIV/0! | H23: =SUM(H5:H22) -> #DIV/0! | I23: =J23/12 -> #DIV/0! | J23: =SUM(J4:J22) -> #DIV/0! | K23: =L23/12 -> #DIV/0! | L23: =SUM(L4:L22) -> #DIV/0! | M23: =N23/12 -> #DIV/0! | N23: =SUM(N4:N22) -> #DIV/0! | O23: =P23/12 -> #DIV/0! | P23: =SUM(P4:P22) -> #DIV/0! | Q23: =SUM(H23,J23,L23,N23,P23) -> #DIV/0!
K24: Total CSA Contract Price: | Q24: =Q23 -> #DIV/0!

Sheet SCA WD
A1: Verification of Wage Determination (WD) Minimums:
A3: Offeror Name:
A4: Proposal Title and Date:
A5: Proposal Number:
A7: Proposed Labor Category: | B7: Occupational Code | C7: SCA WD Number | D7: Location | E7: Direct Labor Rates: 1 | J7: Health & Welfare (H&W) Rate 2 (in dollars per hour worked)
E8: Base | F8: Option 1 | G8: Option 2 | H8: Option 3 | I8: Option 4
A10: Guard II | B10: 27102
A41: INSTRUCTIONS:
A42: (1) Identify the direct, unburdened labor rate for each labor category for each period of contract performance.
A44: (2) Each offeror shall identify its rate of contribution to Health & Welfare (H&W) for each labor category, expressed as dollars per hour.

Sheet CBA WD 
A1: Verification of Collective Bargaining Agreement (CBA) Minimums: 1
A3: Offeror Name:
A4: Proposal Title and Date:
A5: Proposal Number:
A8: Proposed Labor Category: | B8: CBA Labor Category/Identifier 1 | D8: Location | E8: Direct Labor Rates: 2 | J8: Health & Welfare (H&W) Rate 3 (in dollars per hour worked)
C9: CBA
E10: Base | F10: Option 1 | G10: Option 2 | H10: Option 3 | I10: Option 4
A11: Guard II
A43: INSTRUCTIONS:
A44: (1) Correlate each proposed labor category / position to its respective position / identifier in the CBA.
A45: (2) Identify the direct, unburdened labor rate for each labor category for each period of contract performance.
A46: (3) Each offeror shall identify its rate of contribution to Health & Welfare (H&W) for each labor category, expressed as dolars per hour.

Sheet C90 Rate Build Up
A2: {=MID(CELL("filename", A1), FIND("]", CELL("filename", A1)) + 1, LEN(CELL("filename", A1)) - FIND("]", CELL("filename", A1)))} -> C90 Rate Build Up | F2: Base Period | K2: ESS
F3: CBA
A4: =_BasePeriod -> 9/30/2026-9/29/2027
A5: DIRECT LABOR (DL): | E5: HOURS | F5: Rate | H5: TOTAL
A6: 1 | B6: Captain | E6: 0 | F6: 0 | H6: =+E6*F6 -> 0
A7: 2 | B7: Guard II | E7: 0 | F7: 0 | H7: =+E7*F7 -> 0
A8: 3 | B8: Guard II | E8: 0 | F8: 0 | H8: =+E8*F8 -> 0
A9: 4 | B9: Guard II | E9: 0 | F9: 0 | H9: =+E9*F9 -> 0
A10: 5 | B10: Guard II | E10: 0 | F10: 0 | H10: =+E10*F10 -> 0
A11: 6 | B11: Guard II | E11: 0 | F11: 0 | H11: =+E11*F11 -> 0
A12: 7 | B12: Guard II | E12: 0 | F12: 0 | H12: =+E12*F12 -> 0
A13: 8 | B13: Guard II | E13: 0 | F13: 0 | H13: =+E13*F13 -> 0
A14: 9 | B14: Guard II | E14: 0 | F14: 0 | H14: =+E14*F14 -> 0
A15: 10 | B15: Guard II | E15: 0 | F15: 0 | H15: =+E15*F15 -> 0
A16: 11 | B16: Guard II | E16: 0 | F16: 0 | H16: =+E16*F16 -> 0
A17: 12 | B17: Guard II | E17: 0 | F17: 0 | H17: =+E17*F17 -> 0
B18: Total | E18: =SUM(E6:E17) -> 0 | H18: =SUM(H6:H17) -> 0 | I18: =+H18/E18 -> #DIV/0! | K18: =+I18*1.5 -> #DIV/0!
B20: Health and Welfare | F20: 0 | H20: =+E18*F20 -> 0
H21: =+H18+H20 -> 0
A23: EMPLOYEE BENEFIT: | E23: FRINGE RATE
B25: Social Security | E25: 0.062 | G25: =+$E25*$H21 -> 0
B26: Medicare | E26: 0.0145 | G26: =+$E26*$H21 -> 0
B27: SUTA | E27: 0 | G27: =+$E27*$H21 -> 0
B28: FUTA | E28: 0 | G28: =+$E28*$H21 -> 0 | H28: Sum of Payroll Taxes | I28: W/ Payroll Taxes
B29: Workman's Comp /General Liability Insurance | E29: 0 | G29: =+$E29*$H21 -> 0 | H29: =SUM(E25:E29) -> 0.0765 | I29: =+H29*I18+I18 -> #DIV/0!
A30: CBA | B30: Sick Leave (Full Time) | C30: 0 | D30: 0 | E30: =+D30*C30 -> 0 | G30: =+E30*I29 -> #DIV/0!
A31: CBA | B31: Sick Leave (Part Time) | C31: 0 | D31: 0 | E31: =+D31*C31 -> 0 | G31: =+E31*I29 -> #DIV/0!
A32: CBA | B32: Holiday (Based on 11 Days) | C32: 0 | D32: 0 | E32: =+C32*D32 -> 0 | G32: =+E32*I29 -> #DIV/0!
A33: CBA | B33: Vacation (Based on 10 Days) | C33: 0 | D33: 0 | E33: =+C33*D33 -> 0 | G33: =+E33*I29 -> #DIV/0!
A34: CBA | B34: Vacation (Based on 17.5 Days) | C34: 0 | D34: 0 | E34: =+D34*C34 -> 0 | G34: =+E34*I29 -> #DIV/0!
A35: CBA | B35: Vacation (Based on 22.5 Days) | C35: 0 | D35: 0 | E35: =+D35*C35 -> 0 | G35: =+E35*I29 -> #DIV/0!
B36: Health and Welfare for Sick/Holiday/Vacation Hours | E36: =SUM(E30:E35) -> 0 | F36: 0 | G36: =E36*F36 -> 0 | H36: =SUM(G25:G36) -> #DIV/0! | I36: =(H36+H20)/H18 -> #DIV/0! | K36: =K18*I36 -> #DIV/0!
H37: =+H36+H21 -> #DIV/0!
A41: OVERHEAD EXPENSE | D41: 0 | H41: =+H37*D41 -> #DIV/0! | I41: =+H41/H37 -> #DIV/0! | K41: =+(K18+K36)*I41 -> #DIV/0!
A43: OTHER DIRECT COSTS (ODC):
B44: Uniforms @ | C44: 0 | D44: 0 | E44: 0 | G44: =+(C44*D44*E44) -> 0
B45: Boot Allowance | C45: 0 | D45: 0 | E45: 0 | G45: =+(C45*D45*E45) -> 0
B46: Ammo | C46: 0 | D46: 0 | E46: 0 | G46: =+(C46*D46*E46) -> 0
B47: Duty Gear | C47: 0 | D47: 0 | E47: 0 | G47: =+(C47*D47*E47) -> 0
B48: Weapons | C48: 0 | D48: 0 | E48: 0 | G48: =+(C48*D48*E48) -> 0
B49: Medical /Drug Screening / Physicals | C49: 0 | D49: 0 | E49: 0 | G49: =+(C49*D49*E49) -> 0
B50: Professional Licenses | C50: 0 | D50: 0 | E50: 0 | G50: =+(C50*D50*E50) -> 0
B51: Training - Nonrecurring | C51: 0 | D51: 0 | E51: 0 | G51: =+(C51*D51*E51) -> 0
B52: Training - Recurring Annual | C52: 0 | D52: 0 | E52: 0 | G52: =+(C52*D52*E52) -> 0
B53: Shooting Range Qualification / Requal | C53: 0 | D53: 0 | E53: 0 | G53: =+(C53*D53*E53) -> 0
B54: Travel | C54: 0 | D54: 0 | E54: 0 | G54: =+(C54*D54*E54) -> 0 | H54: =SUM(G44:G54) -> 0 | K54: =SUM(K18:K53) -> #DIV/0!
C55: SUBTOTAL | H55: =SUM(H37:H54) -> #DIV/0!
A57: G&A EXPENSE | D57: 0 | H57: =+H55*D57 -> #DIV/0! | I57: =D57 -> 0 | K57: =+K54*I57 -> #DIV/0!
D58: SUBTOTAL G&A/WC/DL | K58: =SUM(K54:K57) -> #DIV/0!
A60: PROFIT | D60: 0 | H60: =(H55+H57)*D60 -> #DIV/0!
D61: SUBTOTAL COST AND PROFIT | H61: =SUM(H55:H60) -> #DIV/0! | I61: =D60 -> 0 | K61: =+K58*I61 -> #DIV/0!
A64: STATE TAXES | D64: 0 | H64: =+H61*D64 -> #DIV/0!
F66: ANNUAL TOTAL | H66: =SUM(H61:H64) -> #DIV/0!
F67: MONTHLY RATE | H67: =+H66/12 -> #DIV/0!
B68: TAS/OTHER SERVICES/TRAINING/RANDOM SCREENING/ROVING PATROL | F68: HOURLY PRICE | H68: =+H66/(E18) -> #DIV/0! | K68: =SUM(K58:K67) -> #DIV/0!
A70: =$A$2 -> C90 Rate Build Up | F70: Option Period 1 | K70: ESS
F71: CBA
A72: =_OP1 -> 9/30/2027-9/29/2028
A73: DIRECT LABOR (DL): | E73: HOURS | F73: Rate | H73: TOTAL
A74: 1 | B74: Captain | E74: 0 | F74: 0 | H74: =+E74*F74 -> 0
A75: 2 | B75: Guard II | E75: 0 | F75: 0 | H75: =+E75*F75 -> 0
A76: 3 | B76: Guard II | E76: 0 | F76: 0 | H76: =+E76*F76 -> 0
A77: 4 | B77: Guard II | E77: 0 | F77: 0 | H77: =+E77*F77 -> 0
A78: 5 | B78: Guard II | E78: 0 | F78: 0 | H78: =+E78*F78 -> 0
A79: 6 | B79: Guard II | E79: 0 | F79: 0 | H79: =+E79*F79 -> 0
A80: 7 | B80: Guard II | E80: 0 | F80: 0 | H80: =+E80*F80 -> 0
A81: 8 | B81: Guard II | E81: 0 | F81: 0 | H81: =+E81*F81 -> 0
A82: 9 | B82: Guard II | E82: 0 | F82: 0 | H82: =+E82*F82 -> 0
A83: 10 | B83: Guard II | E83: 0 | F83: 0 | H83: =+E83*F83 -> 0
A84: 11 | B84: Guard II | E84: 0 | F84: 0 | H84: =+E84*F84 -> 0
A85: 12 | B85: Guard II | E85: 0 | F85: 0 | H85: =+E85*F85 -> 0
B86: Total | E86: =SUM(E74:E85) -> 0 | H86: =SUM(H74:H85) -> 0 | I86: =+H86/E86 -> #DIV/0! | K86: =+I86*1.5 -> #DIV/0!
B88: Health and Welfare | F88: 0 | H88: =+E86*F88 -> 0
H89: =+H86+H88 -> 0
A91: EMPLOYEE BENEFIT: | E91: FRINGE RATE
B93: Social Security | E93: 0.062 | G93: =+$E93*$H89 -> 0
B94: Medicare | E94: 0.0145 | G94: =+$E94*$H89 -> 0
B95: SUTA | E95: 0 | G95: =+$E95*$H89 -> 0
B96: FUTA | E96: 0 | G96: =+$E96*$H89 -> 0 | H96: Sum of Payroll Taxes | I96: W/ Payroll Taxes
B97: Workman's Comp /General Liability Insurance | E97: 0 | G97: =+$E97*$H89 -> 0 | H97: =SUM(E93:E97) -> 0.0765 | I97: =+H97*I86+I86 -> #DIV/0!
A98: CBA | B98: Sick Leave (Full Time) | C98: 0 | D98: 0 | E98: =+D98*C98 -> 0 | G98: =+E98*I97 -> #DIV/0!
A99: CBA | B99: Sick Leave (Part Time) | C99: 0 | D99: 0 | E99: =+D99*C99 -> 0 | G99: =+E99*I97 -> #DIV/0!
A100: CBA | B100: Holiday (Based on 11 Days) | C100: 0 | D100: 0 | E100: =+C100*D100 -> 0 | G100: =+E100*I97 -> #DIV/0!
A101: CBA | B101: Vacation (Based on 10 Days) | C101: 0 | D101: 0 | E101: =+C101*D101 -> 0 | G101: =+E101*I97 -> #DIV/0!
A102: CBA | B102: Vacation (Based on 17.5 Days) | C102: 0 | D102: 0 | E102: =+D102*C102 -> 0 | G102: =+E102*I97 -> #DIV/0!
A103: CBA | B103: Vacation (Based on 22.5 Days) | C103: 0 | D103: 0 | E103: =+D103*C103 -> 0 | G103: =+E103*I97 -> #DIV/0!
B104: Health and Welfare for Sick/Holiday/Vacation Hours | E104: =SUM(E98:E103) -> 0 | F104: 0 | G104: =E104*F104 -> 0 | H104: =SUM(G93:G104) -> #DIV/0! | I104: =(H104+H88)/H86 -> #DIV/0! | K104: =K86*I104 -> #DIV/0!
H105: =+H104+H89 -> #DIV/0!
A109: OVERHEAD EXPENSE | D109: 0 | H109: =+H105*D109 -> #DIV/0! | I109: =+H109/H105 -> #DIV/0! | K109: =+(K86+K104)*I109 -> #DIV/0!
A111: OTHER DIRECT COSTS (ODC):
B112: Uniforms @ | C112: 0 | D112: 0 | E112: 0 | G112: =+(C112*D112*E112) -> 0
B113: Boot Allowance | C113: 0 | D113: 0 | E113: 0 | G113: =+(C113*D113*E113) -> 0
B114: Ammo | C114: 0 | D114: 0 | E114: 0 | G114: =+(C114*D114*E114) -> 0
B115: Duty Gear | C115: 0 | D115: 0 | E115: 0 | G115: =+(C115*D115*E115) -> 0
B116: Weapons | C116: 0 | D116: 0 | E116: 0 | G116: =+(C116*D116*E116) -> 0
B117: Medical /Drug Screening / Physicals | C117: 0 | D117: 0 | E117: 0 | G117: =+(C117*D117*E117) -> 0
B118: Professional Licenses | C118: 0 | D118: 0 | E118: 0 | G118: =+(C118*D118*E118) -> 0
B119: Training - Nonrecurring | C119: 0 | D119: 0 | E119: 0 | G119: =+(C119*D119*E119) -> 0
B120: Training - Recurring Annual | C120: 0 | D120: 0 | E120: 0 | G120: =+(C120*D120*E120) -> 0
B121: Shooting Range Qualification / Requal | C121: 0 | D121: 0 | E121: 0 | G121: =+(C121*D121*E121) -> 0
...

Sheet D10 Rate Build Up
A2: {=MID(CELL("filename", A1), FIND("]", CELL("filename", A1)) + 1, LEN(CELL("filename", A1)) - FIND("]", CELL("filename", A1)))} -> D10 Rate Build Up | F2: Base Period | K2: ESS
F3: CBA
A4: =_BasePeriod -> 9/30/2026-9/29/2027
A5: DIRECT LABOR (DL): | E5: HOURS | F5: Rate | H5: TOTAL
A6: 1 | B6: Captain | E6: 0 | F6: 0 | H6: =+E6*F6 -> 0
A7: 2 | B7: Guard II | E7: 0 | F7: 0 | H7: =+E7*F7 -> 0
A8: 3 | B8: Guard II | E8: 0 | F8: 0 | H8: =+E8*F8 -> 0
A9: 4 | B9: Guard II | E9: 0 | F9: 0 | H9: =+E9*F9 -> 0
A10: 5 | B10: Guard II | E10: 0 | F10: 0 | H10: =+E10*F10 -> 0
A11: 6 | B11: Guard II | E11: 0 | F11: 0 | H11: =+E11*F11 -> 0
A12: 7 | B12: Guard II | E12: 0 | F12: 0 | H12: =+E12*F12 -> 0
A13: 8 | B13: Guard II | E13: 0 | F13: 0 | H13: =+E13*F13 -> 0
A14: 9 | B14: Guard II | E14: 0 | F14: 0 | H14: =+E14*F14 -> 0
A15: 10 | B15: Guard II | E15: 0 | F15: 0 | H15: =+E15*F15 -> 0
A16: 11 | B16: Guard II | E16: 0 | F16: 0 | H16: =+E16*F16 -> 0
A17: 12 | B17: Guard II | E17: 0 | F17: 0 | H17: =+E17*F17 -> 0
B18: Total | E18: =SUM(E6:E17) -> 0 | H18: =SUM(H6:H17) -> 0 | I18: =+H18/E18 -> #DIV/0! | K18: =+I18*1.5 -> #DIV/0!
B20: Health and Welfare | F20: 0 | H20: =+E18*F20 -> 0
H21: =+H18+H20 -> 0
A23: EMPLOYEE BENEFIT: | E23: FRINGE RATE
B25: Social Security | E25: 0.062 | G25: =+$E25*$H21 -> 0
B26: Medicare | E26: 0.0145 | G26: =+$E26*$H21 -> 0
B27: SUTA | E27: 0 | G27: =+$E27*$H21 -> 0
B28: FUTA | E28: 0 | G28: =+$E28*$H21 -> 0 | H28: Sum of Payroll Taxes | I28: W/ Payroll Taxes
B29: Workman's Comp /General Liability Insurance | E29: 0 | G29: =+$E29*$H21 -> 0 | H29: =SUM(E25:E29) -> 0.0765 | I29: =+H29*I18+I18 -> #DIV/0!
A30: CBA | B30: Sick Leave (Full Time) | C30: 0 | D30: 0 | E30: =+D30*C30 -> 0 | G30: =+E30*I29 -> #DIV/0!
A31: CBA | B31: Sick Leave (Part Time) | C31: 0 | D31: 0 | E31: =+D31*C31 -> 0 | G31: =+E31*I29 -> #DIV/0!
A32: CBA | B32: Holiday (Based on 11 Days) | C32: 0 | D32: 0 | E32: =+C32*D32 -> 0 | G32: =+E32*I29 -> #DIV/0!
A33: CBA | B33: Vacation (Based on 10 Days) | C33: 0 | D33: 0 | E33: =+C33*D33 -> 0 | G33: =+E33*I29 -> #DIV/0!
A34: CBA | B34: Vacation (Based on 17.5 Days) | C34: 0 | D34: 0 | E34: =+D34*C34 -> 0 | G34: =+E34*I29 -> #DIV/0!
A35: CBA | B35: Vacation (Based on 22.5 Days) | C35: 0 | D35: 0 | E35: =+D35*C35 -> 0 | G35: =+E35*I29 -> #DIV/0!
B36: Health and Welfare for Sick/Holiday/Vacation Hours | E36: =SUM(E30:E35) -> 0 | F36: 5 | G36: =E36*F36 -> 0 | H36: =SUM(G25:G36) -> #DIV/0! | I36: =(H36+H20)/H18 -> #DIV/0! | K36: =K18*I36 -> #DIV/0!
H37: =+H36+H21 -> #DIV/0!
A41: OVERHEAD EXPENSE | D41: 0 | H41: =+H37*D41 -> #DIV/0! | I41: =+H41/H37 -> #DIV/0! | K41: =+(K18+K36)*I41 -> #DIV/0!
A43: OTHER DIRECT COSTS (ODC):
B44: Uniforms @ | C44: 0 | D44: 0 | E44: 0 | G44: =+(C44*D44*E44) -> 0
B45: Boot Allowance | C45: 0 | D45: 0 | E45: 0 | G45: =+(C45*D45*E45) -> 0
B46: Ammo | C46: 0 | D46: 0 | E46: 0 | G46: =+(C46*D46*E46) -> 0
B47: Duty Gear | C47: 0 | D47: 0 | E47: 0 | G47: =+(C47*D47*E47) -> 0
B48: Weapons | C48: 0 | D48: 0 | E48: 0 | G48: =+(C48*D48*E48) -> 0
B49: Medical /Drug Screening / Physicals | C49: 0 | D49: 0 | E49: 0 | G49: =+(C49*D49*E49) -> 0
B50: Professional Licenses | C50: 0 | D50: 0 | E50: 0 | G50: =+(C50*D50*E50) -> 0
B51: Training - Nonrecurring | C51: 0 | D51: 0 | E51: 0 | G51: =+(C51*D51*E51) -> 0
B52: Training - Recurring Annual | C52: 0 | D52: 0 | E52: 0 | G52: =+(C52*D52*E52) -> 0
B53: Shooting Range Qualification / Requal | C53: 0 | D53: 0 | E53: 0 | G53: =+(C53*D53*E53) -> 0
B54: Travel | C54: 0 | D54: 0 | E54: 0 | G54: =+(C54*D54*E54) -> 0 | H54: =SUM(G44:G54) -> 0 | K54: =SUM(K18:K53) -> #DIV/0!
C55: SUBTOTAL | H55: =SUM(H37:H54) -> #DIV/0!
A57: G&A EXPENSE | D57: 0 | H57: =+H55*D57 -> #DIV/0! | I57: =D57 -> 0 | K57: =+K54*I57 -> #DIV/0!
D58: SUBTOTAL G&A/WC/DL | K58: =SUM(K54:K57) -> #DIV/0!
A60: PROFIT | D60: 0 | H60: =(H55+H57)*D60 -> #DIV/0!
D61: SUBTOTAL COST AND PROFIT | H61: =SUM(H55:H60) -> #DIV/0! | I61: =D60 -> 0 | K61: =+K58*I61 -> #DIV/0!
A64: STATE TAXES | D64: 0 | H64: =+H61*D64 -> #DIV/0!
F66: ANNUAL TOTAL | H66: =SUM(H61:H64) -> #DIV/0!
F67: MONTHLY RATE | H67: =+H66/12 -> #DIV/0!
B68: TAS/OTHER SERVICES/TRAINING/RANDOM SCREENING/ROVING PATROL | F68: HOURLY PRICE | H68: =+H66/(E18) -> #DIV/0! | K68: =SUM(K58:K67) -> #DIV/0!
A70: =$A$2 -> D10 Rate Build Up | F70: Option Period 1 | K70: ESS
F71: CBA
A72: =_OP1 -> 9/30/2027-9/29/2028
A73: DIRECT LABOR (DL): | E73: HOURS | F73: Rate | H73: TOTAL
A74: 1 | B74: Captain | E74: 0 | F74: 0 | H74: =+E74*F74 -> 0
A75: 2 | B75: Guard II | E75: 0 | F75: 0 | H75: =+E75*F75 -> 0
A76: 3 | B76: Guard II | E76: 0 | F76: 0 | H76: =+E76*F76 -> 0
A77: 4 | B77: Guard II | E77: 0 | F77: 0 | H77: =+E77*F77 -> 0
A78: 5 | B78: Guard II | E78: 0 | F78: 0 | H78: =+E78*F78 -> 0
A79: 6 | B79: Guard II | E79: 0 | F79: 0 | H79: =+E79*F79 -> 0
A80: 7 | B80: Guard II | E80: 0 | F80: 0 | H80: =+E80*F80 -> 0
A81: 8 | B81: Guard II | E81: 0 | F81: 0 | H81: =+E81*F81 -> 0
A82: 9 | B82: Guard II | E82: 0 | F82: 0 | H82: =+E82*F82 -> 0
A83: 10 | B83: Guard II | E83: 0 | F83: 0 | H83: =+E83*F83 -> 0
A84: 11 | B84: Guard II | E84: 0 | F84: 0 | H84: =+E84*F84 -> 0
A85: 12 | B85: Guard II | E85: 0 | F85: 0 | H85: =+E85*F85 -> 0
B86: Total | E86: =SUM(E74:E85) -> 0 | H86: =SUM(H74:H85) -> 0 | I86: =+H86/E86 -> #DIV/0! | K86: =+I86*1.5 -> #DIV/0!
B88: Health and Welfare | F88: 0 | H88: =+E86*F88 -> 0
H89: =+H86+H88 -> 0
A91: EMPLOYEE BENEFIT: | E91: FRINGE RATE
B93: Social Security | E93: 0.062 | G93: =+$E93*$H89 -> 0
B94: Medicare | E94: 0.0145 | G94: =+$E94*$H89 -> 0
B95: SUTA | E95: 0 | G95: =+$E95*$H89 -> 0
B96: FUTA | E96: 0 | G96: =+$E96*$H89 -> 0 | H96: Sum of Payroll Taxes | I96: W/ Payroll Taxes
B97: Workman's Comp /General Liability Insurance | E97: 0 | G97: =+$E97*$H89 -> 0 | H97: =SUM(E93:E97) -> 0.0765 | I97: =+H97*I86+I86 -> #DIV/0!
A98: CBA | B98: Sick Leave (Full Time) | C98: 0 | D98: 0 | E98: =+D98*C98 -> 0 | G98: =+E98*I97 -> #DIV/0!
A99: CBA | B99: Sick Leave (Part Time) | C99: 0 | D99: 0 | E99: =+D99*C99 -> 0 | G99: =+E99*I97 -> #DIV/0!
A100: CBA | B100: Holiday (Based on 11 Days) | C100: 0 | D100: 0 | E100: =+C100*D100 -> 0 | G100: =+E100*I97 -> #DIV/0!
A101: CBA | B101: Vacation (Based on 10 Days) | C101: 0 | D101: 0 | E101: =+C101*D101 -> 0 | G101: =+E101*I97 -> #DIV/0!
A102: CBA | B102: Vacation (Based on 17.5 Days) | C102: 0 | D102: 0 | E102: =+D102*C102 -> 0 | G102: =+E102*I97 -> #DIV/0!
A103: CBA | B103: Vacation (Based on 22.5 Days) | C103: 0 | D103: 0 | E103: =+D103*C103 -> 0 | G103: =+E103*I97 -> #DIV/0!
B104: Health and Welfare for Sick/Holiday/Vacation Hours | E104: =SUM(E98:E103) -> 0 | F104: 0 | G104: =E104*F104 -> 0 | H104: =SUM(G93:G104) -> #DIV/0! | I104: =(H104+H88)/H86 -> #DIV/0! | K104: =K86*I104 -> #DIV/0!
H105: =+H104+H89 -> #DIV/0!
A109: OVERHEAD EXPENSE | D109: 0 | H109: =+H105*D109 -> #DIV/0! | I109: =+H109/H105 -> #DIV/0! | K109: =+(K86+K104)*I109 -> #DIV/0!
A111: OTHER DIRECT COSTS (ODC):
B112: Uniforms @ | C112: 0 | D112: 0 | E112: 0 | G112: =+(C112*D112*E112) -> 0
B113: Boot Allowance | C113: 0 | D113: 0 | E113: 0 | G113: =+(C113*D113*E113) -> 0
B114: Ammo | C114: 0 | D114: 0 | E114: 0 | G114: =+(C114*D114*E114) -> 0
B115: Duty Gear | C115: 0 | D115: 0 | E115: 0 | G115: =+(C115*D115*E115) -> 0
B116: Weapons | C116: 0 | D116: 0 | E116: 0 | G116: =+(C116*D116*E116) -> 0
B117: Medical /Drug Screening / Physicals | C117: 0 | D117: 0 | E117: 0 | G117: =+(C117*D117*E117) -> 0
B118: Professional Licenses | C118: 0 | D118: 0 | E118: 0 | G118: =+(C118*D118*E118) -> 0
B119: Training - Nonrecurring | C119: 0 | D119: 0 | E119: 0 | G119: =+(C119*D119*E119) -> 0
B120: Training - Recurring Annual | C120: 0 | D120: 0 | E120: 0 | G120: =+(C120*D120*E120) -> 0
B121: Shooting Range Qualification / Requal | C121: 0 | D121: 0 | E121: 0 | G121: =+(C121*D121*E121) -> 0
...

Sheet DFW ATCT-E Rate Build Up
A2: {=MID(CELL("filename", A1), FIND("]", CELL("filename", A1)) + 1, LEN(CELL("filename", A1)) - FIND("]", CELL("filename", A1)))} -> DFW ATCT-E Rate Build Up | F2: Base Period | K2: ESS
F3: CBA
A4: =_BasePeriod -> 9/30/2026-9/29/2027
A5: DIRECT LABOR (DL): | E5: HOURS | F5: Rate | H5: TOTAL
A6: 1 | B6: Captain | E6: 0 | F6: 0 | H6: =+E6*F6 -> 0
A7: 2 | B7: Guard II | E7: 0 | F7: 0 | H7: =+E7*F7 -> 0
A8: 3 | B8: Guard II | E8: 0 | F8: 0 | H8: =+E8*F8 -> 0
A9: 4 | B9: Guard II | E9: 0 | F9: 0 | H9: =+E9*F9 -> 0
A10: 5 | B10: Guard II | E10: 0 | F10: 0 | H10: =+E10*F10 -> 0
A11: 6 | B11: Guard II | E11: 0 | F11: 0 | H11: =+E11*F11 -> 0
A12: 7 | B12: Guard II | E12: 0 | F12: 0 | H12: =+E12*F12 -> 0
A13: 8 | B13: Guard II | E13: 0 | F13: 0 | H13: =+E13*F13 -> 0
A14: 9 | B14: Guard II | E14: 0 | F14: 0 | H14: =+E14*F14 -> 0
A15: 10 | B15: Guard II | E15: 0 | F15: 0 | H15: =+E15*F15 -> 0
A16: 11 | B16: Guard II | E16: 0 | F16: 0 | H16: =+E16*F16 -> 0
A17: 12 | B17: Guard II | E17: 0 | F17: 0 | H17: =+E17*F17 -> 0
B18: Total | E18: =SUM(E6:E17) -> 0 | H18: =SUM(H6:H17) -> 0 | I18: =+H18/E18 -> #DIV/0! | K18: =+I18*1.5 -> #DIV/0!
B20: Health and Welfare | F20: 0 | H20: =+E18*F20 -> 0
H21: =+H18+H20 -> 0
A23: EMPLOYEE BENEFIT: | E23: FRINGE RATE
B25: Social Security | E25: 0.062 | G25: =+$E25*$H21 -> 0
B26: Medicare | E26: 0.0145 | G26: =+$E26*$H21 -> 0
B27: SUTA | E27: 0 | G27: =+$E27*$H21 -> 0
B28: FUTA | E28: 0 | G28: =+$E28*$H21 -> 0 | H28: Sum of Payroll Taxes | I28: W/ Payroll Taxes
B29: Workman's Comp /General Liability Insurance | E29: 0 | G29: =+$E29*$H21 -> 0 | H29: =SUM(E25:E29) -> 0.0765 | I29: =+H29*I18+I18 -> #DIV/0!
A30: CBA | B30: Sick Leave (Full Time) | C30: 0 | D30: 0 | E30: =+D30*C30 -> 0 | G30: =+E30*I29 -> #DIV/0!
A31: CBA | B31: Sick Leave (Part Time) | C31: 0 | D31: 0 | E31: =+D31*C31 -> 0 | G31: =+E31*I29 -> #DIV/0!
A32: CBA | B32: Holiday (Based on 11 Days) | C32: 0 | D32: 0 | E32: =+C32*D32 -> 0 | G32: =+E32*I29 -> #DIV/0!
A33: CBA | B33: Vacation (Based on 10 Days) | C33: 0 | D33: 0 | E33: =+C33*D33 -> 0 | G33: =+E33*I29 -> #DIV/0!
A34: CBA | B34: Vacation (Based on 17.5 Days) | C34: 0 | D34: 0 | E34: =+D34*C34 -> 0 | G34: =+E34*I29 -> #DIV/0!
A35: CBA | B35: Vacation (Based on 22.5 Days) | C35: 0 | D35: 0 | E35: =+D35*C35 -> 0 | G35: =+E35*I29 -> #DIV/0!
B36: Health and Welfare for Sick/Holiday/Vacation Hours | E36: =SUM(E30:E35) -> 0 | F36: 5 | G36: =E36*F36 -> 0 | H36: =SUM(G25:G36) -> #DIV/0! | I36: =(H36+H20)/H18 -> #DIV/0! | K36: =K18*I36 -> #DIV/0!
H37: =+H36+H21 -> #DIV/0!
A41: OVERHEAD EXPENSE | D41: 0 | H41: =+H37*D41 -> #DIV/0! | I41: =+H41/H37 -> #DIV/0! | K41: =+(K18+K36)*I41 -> #DIV/0!
A43: OTHER DIRECT COSTS (ODC):
B44: Uniforms @ | C44: 0 | D44: 0 | E44: 0 | G44: =+(C44*D44*E44) -> 0
B45: Boot Allowance | C45: 0 | D45: 0 | E45: 0 | G45: =+(C45*D45*E45) -> 0
B46: Ammo | C46: 0 | D46: 0 | E46: 0 | G46: =+(C46*D46*E46) -> 0
B47: Duty Gear | C47: 0 | D47: 0 | E47: 0 | G47: =+(C47*D47*E47) -> 0
B48: Weapons | C48: 0 | D48: 0 | E48: 0 | G48: =+(C48*D48*E48) -> 0
B49: Medical /Drug Screening / Physicals | C49: 0 | D49: 0 | E49: 0 | G49: =+(C49*D49*E49) -> 0
B50: Professional Licenses | C50: 0 | D50: 0 | E50: 0 | G50: =+(C50*D50*E50) -> 0
B51: Training - Nonrecurring | C51: 0 | D51: 0 | E51: 0 | G51: =+(C51*D51*E51) -> 0
B52: Training - Recurring Annual | C52: 0 | D52: 0 | E52: 0 | G52: =+(C52*D52*E52) -> 0
B53: Shooting Range Qualification / Requal | C53: 0 | D53: 0 | E53: 0 | G53: =+(C53*D53*E53) -> 0
B54: Travel | C54: 0 | D54: 0 | E54: 0 | G54: =+(C54*D54*E54) -> 0 | H54: =SUM(G44:G54) -> 0 | K54: =SUM(K18:K53) -> #DIV/0!
C55: SUBTOTAL | H55: =SUM(H37:H54) -> #DIV/0!
A57: G&A EXPENSE | D57: 0 | H57: =+H55*D57 -> #DIV/0! | I57: =D57 -> 0 | K57: =+K54*I57 -> #DIV/0!
D58: SUBTOTAL G&A/WC/DL | K58: =SUM(K54:K57) -> #DIV/0!
A60: PROFIT | D60: 0 | H60: =(H55+H57)*D60 -> #DIV/0!
D61: SUBTOTAL COST AND PROFIT | H61: =SUM(H55:H60) -> #DIV/0! | I61: =D60 -> 0 | K61: =+K58*I61 -> #DIV/0!
A64: STATE TAXES | D64: 0 | H64: =+H61*D64 -> #DIV/0!
F66: ANNUAL TOTAL | H66: =SUM(H61:H64) -> #DIV/0!
F67: MONTHLY RATE | H67: =+H66/12 -> #DIV/0!
B68: TAS/OTHER SERVICES/TRAINING/RANDOM SCREENING/ROVING PATROL | F68: HOURLY PRICE | H68: =+H66/(E18) -> #DIV/0! | K68: =SUM(K58:K67) -> #DIV/0!
A70: =$A$2 -> DFW ATCT-E Rate Build Up | F70: Option Period 1 | K70: ESS
F71: CBA
A72: =_OP1 -> 9/30/2027-9/29/2028
A73: DIRECT LABOR (DL): | E73: HOURS | F73: Rate | H73: TOTAL
A74: 1 | B74: Captain | E74: 0 | F74: 0 | H74: =+E74*F74 -> 0
A75: 2 | B75: Guard II | E75: 0 | F75: 0 | H75: =+E75*F75 -> 0
A76: 3 | B76: Guard II | E76: 0 | F76: 0 | H76: =+E76*F76 -> 0
A77: 4 | B77: Guard II | E77: 0 | F77: 0 | H77: =+E77*F77 -> 0
A78: 5 | B78: Guard II | E78: 0 | F78: 0 | H78: =+E78*F78 -> 0
A79: 6 | B79: Guard II | E79: 0 | F79: 0 | H79: =+E79*F79 -> 0
A80: 7 | B80: Guard II | E80: 0 | F80: 0 | H80: =+E80*F80 -> 0
A81: 8 | B81: Guard II | E81: 0 | F81: 0 | H81: =+E81*F81 -> 0
A82: 9 | B82: Guard II | E82: 0 | F82: 0 | H82: =+E82*F82 -> 0
A83: 10 | B83: Guard II | E83: 0 | F83: 0 | H83: =+E83*F83 -> 0
A84: 11 | B84: Guard II | E84: 0 | F84: 0 | H84: =+E84*F84 -> 0
A85: 12 | B85: Guard II | E85: 0 | F85: 0 | H85: =+E85*F85 -> 0
B86: Total | E86: =SUM(E74:E85) -> 0 | H86: =SUM(H74:H85) -> 0 | I86: =+H86/E86 -> #DIV/0! | K86: =+I86*1.5 -> #DIV/0!
B88: Health and Welfare | F88: 0 | H88: =+E86*F88 -> 0
H89: =+H86+H88 -> 0
A91: EMPLOYEE BENEFIT: | E91: FRINGE RATE
B93: Social Security | E93: 0.062 | G93: =+$E93*$H89 -> 0
B94: Medicare | E94: 0.0145 | G94: =+$E94*$H89 -> 0
B95: SUTA | E95: 0 | G95: =+$E95*$H89 -> 0
B96: FUTA | E96: 0 | G96: =+$E96*$H89 -> 0 | H96: Sum of Payroll Taxes | I96: W/ Payroll Taxes
B97: Workman's Comp /General Liability Insurance | E97: 0 | G97: =+$E97*$H89 -> 0 | H97: =SUM(E93:E97) -> 0.0765 | I97: =+H97*I86+I86 -> #DIV/0!
A98: CBA | B98: Sick Leave (Full Time) | C98: 0 | D98: 0 | E98: =+D98*C98 -> 0 | G98: =+E98*I97 -> #DIV/0!
A99: CBA | B99: Sick Leave (Part Time) | C99: 0 | D99: 0 | E99: =+D99*C99 -> 0 | G99: =+E99*I97 -> #DIV/0!
A100: CBA | B100: Holiday (Based on 11 Days) | C100: 0 | D100: 0 | E100: =+C100*D100 -> 0 | G100: =+E100*I97 -> #DIV/0!
A101: CBA | B101: Vacation (Based on 10 Days) | C101: 0 | D101: 0 | E101: =+C101*D101 -> 0 | G101: =+E101*I97 -> #DIV/0!
A102: CBA | B102: Vacation (Based on 17.5 Days) | C102: 0 | D102: 0 | E102: =+D102*C102 -> 0 | G102: =+E102*I97 -> #DIV/0!
A103: CBA | B103: Vacation (Based on 22.5 Days) | C103: 0 | D103: 0 | E103: =+D103*C103 -> 0 | G103: =+E103*I97 -> #DIV/0!
B104: Health and Welfare for Sick/Holiday/Vacation Hours | E104: =SUM(E98:E103) -> 0 | F104: 0 | G104: =E104*F104 -> 0 | H104: =SUM(G93:G104) -> #DIV/0! | I104: =(H104+H88)/H86 -> #DIV/0! | K104: =K86*I104 -> #DIV/0!
H105: =+H104+H89 -> #DIV/0!
A109: OVERHEAD EXPENSE | D109: 0 | H109: =+H105*D109 -> #DIV/0! | I109: =+H109/H105 -> #DIV/0! | K109: =+(K86+K104)*I109 -> #DIV/0!
A111: OTHER DIRECT COSTS (ODC):
B112: Uniforms @ | C112: 0 | D112: 0 | E112: 0 | G112: =+(C112*D112*E112) -> 0
B113: Boot Allowance | C113: 0 | D113: 0 | E113: 0 | G113: =+(C113*D113*E113) -> 0
B114: Ammo | C114: 0 | D114: 0 | E114: 0 | G114: =+(C114*D114*E114) -> 0
B115: Duty Gear | C115: 0 | D115: 0 | E115: 0 | G115: =+(C115*D115*E115) -> 0
B116: Weapons | C116: 0 | D116: 0 | E116: 0 | G116: =+(C116*D116*E116) -> 0
B117: Medical /Drug Screening / Physicals | C117: 0 | D117: 0 | E117: 0 | G117: =+(C117*D117*E117) -> 0
B118: Professional Licenses | C118: 0 | D118: 0 | E118: 0 | G118: =+(C118*D118*E118) -> 0
B119: Training - Nonrecurring | C119: 0 | D119: 0 | E119: 0 | G119: =+(C119*D119*E119) -> 0
B120: Training - Recurring Annual | C120: 0 | D120: 0 | E120: 0 | G120: =+(C120*D120*E120) -> 0
B121: Shooting Range Qualification / Requal | C121: 0 | D121: 0 | E121: 0 | G121: =+(C121*D121*E121) -> 0
...

Sheet DFW ATCT-W Rate Build Up
A2: {=MID(CELL("filename", A1), FIND("]", CELL("filename", A1)) + 1, LEN(CELL("filename", A1)) - FIND("]", CELL("filename", A1)))} -> DFW ATCT-W Rate Build Up | F2: Base Period | K2: ESS
F3: CBA
A4: =_BasePeriod -> 9/30/2026-9/29/2027
A5: DIRECT LABOR (DL): | E5: HOURS | F5: Rate | H5: TOTAL
A6: 1 | B6: Captain | E6: 0 | F6: 0 | H6: =+E6*F6 -> 0
A7: 2 | B7: Guard II | E7: 0 | F7: 0 | H7: =+E7*F7 -> 0
A8: 3 | B8: Guard II | E8: 0 | F8: 0 | H8: =+E8*F8 -> 0
A9: 4 | B9: Guard II | E9: 0 | F9: 0 | H9: =+E9*F9 -> 0
A10: 5 | B10: Guard II | E10: 0 | F10: 0 | H10: =+E10*F10 -> 0
A11: 6 | B11: Guard II | E11: 0 | F11: 0 | H11: =+E11*F11 -> 0
A12: 7 | B12: Guard II | E12: 0 | F12: 0 | H12: =+E12*F12 -> 0
A13: 8 | B13: Guard II | E13: 0 | F13: 0 | H13: =+E13*F13 -> 0
A14: 9 | B14: Guard II | E14: 0 | F14: 0 | H14: =+E14*F14 -> 0
A15: 10 | B15: Guard II | E15: 0 | F15: 0 | H15: =+E15*F15 -> 0
A16: 11 | B16: Guard II | E16: 0 | F16: 0 | H16: =+E16*F16 -> 0
A17: 12 | B17: Guard II | E17: 0 | F17: 0 | H17: =+E17*F17 -> 0
B18: Total | E18: =SUM(E6:E17) -> 0 | H18: =SUM(H6:H17) -> 0 | I18: =+H18/E18 -> #DIV/0! | K18: =+I18*1.5 -> #DIV/0!
B20: Health and Welfare | F20: 0 | H20: =+E18*F20 -> 0
H21: =+H18+H20 -> 0
A23: EMPLOYEE BENEFIT: | E23: FRINGE RATE
B25: Social Security | E25: 0.062 | G25: =+$E25*$H21 -> 0
B26: Medicare | E26: 0.0145 | G26: =+$E26*$H21 -> 0
B27: SUTA | E27: 0 | G27: =+$E27*$H21 -> 0
B28: FUTA | E28: 0 | G28: =+$E28*$H21 -> 0 | H28: Sum of Payroll Taxes | I28: W/ Payroll Taxes
B29: Workman's Comp /General Liability Insurance | E29: 0 | G29: =+$E29*$H21 -> 0 | H29: =SUM(E25:E29) -> 0.0765 | I29: =+H29*I18+I18 -> #DIV/0!
A30: CBA | B30: Sick Leave (Full Time) | C30: 0 | D30: 0 | E30: =+D30*C30 -> 0 | G30: =+E30*I29 -> #DIV/0!
A31: CBA | B31: Sick Leave (Part Time) | C31: 0 | D31: 0 | E31: =+D31*C31 -> 0 | G31: =+E31*I29 -> #DIV/0!
A32: CBA | B32: Holiday (Based on 11 Days) | C32: 0 | D32: 0 | E32: =+C32*D32 -> 0 | G32: =+E32*I29 -> #DIV/0!
A33: CBA | B33: Vacation (Based on 10 Days) | C33: 0 | D33: 0 | E33: =+C33*D33 -> 0 | G33: =+E33*I29 -> #DIV/0!
A34: CBA | B34: Vacation (Based on 17.5 Days) | C34: 0 | D34: 0 | E34: =+D34*C34 -> 0 | G34: =+E34*I29 -> #DIV/0!
A35: CBA | B35: Vacation (Based on 22.5 Days) | C35: 0 | D35: 0 | E35: =+D35*C35 -> 0 | G35: =+E35*I29 -> #DIV/0!
B36: Health and Welfare for Sick/Holiday/Vacation Hours | E36: =SUM(E30:E35) -> 0 | F36: 0 | G36: =E36*F36 -> 0 | H36: =SUM(G25:G36) -> #DIV/0! | I36: =(H36+H20)/H18 -> #DIV/0! | K36: =K18*I36 -> #DIV/0!
H37: =+H36+H21 -> #DIV/0!
A41: OVERHEAD EXPENSE | D41: 0 | H41: =+H37*D41 -> #DIV/0! | I41: =+H41/H37 -> #DIV/0! | K41: =+(K18+K36)*I41 -> #DIV/0!
A43: OTHER DIRECT COSTS (ODC):
B44: Uniforms @ | C44: 0 | D44: 0 | E44: 0 | G44: =+(C44*D44*E44) -> 0
B45: Boot Allowance | C45: 0 | D45: 0 | E45: 0 | G45: =+(C45*D45*E45) -> 0
B46: Ammo | C46: 0 | D46: 0 | E46: 0 | G46: =+(C46*D46*E46) -> 0
B47: Duty Gear | C47: 0 | D47: 0 | E47: 0 | G47: =+(C47*D47*E47) -> 0
B48: Weapons | C48: 0 | D48: 0 | E48: 0 | G48: =+(C48*D48*E48) -> 0
B49: Medical /Drug Screening / Physicals | C49: 0 | D49: 0 | E49: 0 | G49: =+(C49*D49*E49) -> 0
B50: Professional Licenses | C50: 0 | D50: 0 | E50: 0 | G50: =+(C50*D50*E50) -> 0
B51: Training - Nonrecurring | C51: 0 | D51: 0 | E51: 0 | G51: =+(C51*D51*E51) -> 0
B52: Training - Recurring Annual | C52: 0 | D52: 0 | E52: 0 | G52: =+(C52*D52*E52) -> 0
B53: Shooting Range Qualification / Requal | C53: 0 | D53: 0 | E53: 0 | G53: =+(C53*D53*E53) -> 0
B54: Travel | C54: 0 | D54: 0 | E54: 0 | G54: =+(C54*D54*E54) -> 0 | H54: =SUM(G44:G54) -> 0 | K54: =SUM(K18:K53) -> #DIV/0!
C55: SUBTOTAL | H55: =SUM(H37:H54) -> #DIV/0!
A57: G&A EXPENSE | D57: 0 | H57: =+H55*D57 -> #DIV/0! | I57: =D57 -> 0 | K57: =+K54*I57 -> #DIV/0!
D58: SUBTOTAL G&A/WC/DL | K58: =SUM(K54:K57) -> #DIV/0!
A60: PROFIT | D60: 0 | H60: =(H55+H57)*D60 -> #DIV/0!
D61: SUBTOTAL COST AND PROFIT | H61: =SUM(H55:H60) -> #DIV/0! | I61: =D60 -> 0 | K61: =+K58*I61 -> #DIV/0!
A64: STATE TAXES | D64: 0 | H64: =+H61*D64 -> #DIV/0!
F66: ANNUAL TOTAL | H66: =SUM(H61:H64) -> #DIV/0!
F67: MONTHLY RATE | H67: =+H66/12 -> #DIV/0!
B68: TAS/OTHER SERVICES/TRAINING/RANDOM SCREENING/ROVING PATROL | F68: HOURLY PRICE | H68: =+H66/(E18) -> #DIV/0! | K68: =SUM(K58:K67) -> #DIV/0!
A70: =$A$2 -> DFW ATCT-W Rate Build Up | F70: Option Period 1 | K70: ESS
F71: CBA
A72: =_OP1 -> 9/30/2027-9/29/2028
A73: DIRECT LABOR (DL): | E73: HOURS | F73: Rate | H73: TOTAL
A74: 1 | B74: Captain | E74: 0 | F74: 0 | H74: =+E74*F74 -> 0
A75: 2 | B75: Guard II | E75: 0 | F75: 0 | H75: =+E75*F75 -> 0
A76: 3 | B76: Guard II | E76: 0 | F76: 0 | H76: =+E76*F76 -> 0
A77: 4 | B77: Guard II | E77: 0 | F77: 0 | H77: =+E77*F77 -> 0
A78: 5 | B78: Guard II | E78: 0 | F78: 0 | H78: =+E78*F78 -> 0
A79: 6 | B79: Guard II | E79: 0 | F79: 0 | H79: =+E79*F79 -> 0
A80: 7 | B80: Guard II | E80: 0 | F80: 0 | H80: =+E80*F80 -> 0
A81: 8 | B81: Guard II | E81: 0 | F81: 0 | H81: =+E81*F81 -> 0
A82: 9 | B82: Guard II | E82: 0 | F82: 0 | H82: =+E82*F82 -> 0
A83: 10 | B83: Guard II | E83: 0 | F83: 0 | H83: =+E83*F83 -> 0
A84: 11 | B84: Guard II | E84: 0 | F84: 0 | H84: =+E84*F84 -> 0
A85: 12 | B85: Guard II | E85: 0 | F85: 0 | H85: =+E85*F85 -> 0
B86: Total | E86: =SUM(E74:E85) -> 0 | H86: =SUM(H74:H85) -> 0 | I86: =+H86/E86 -> #DIV/0! | K86: =+I86*1.5 -> #DIV/0!
B88: Health and Welfare | F88: 0 | H88: =+E86*F88 -> 0
H89: =+H86+H88 -> 0
A91: EMPLOYEE BENEFIT: | E91: FRINGE RATE
B93: Social Security | E93: 0.062 | G93: =+$E93*$H89 -> 0
B94: Medicare | E94: 0.0145 | G94: =+$E94*$H89 -> 0
B95: SUTA | E95: 0 | G95: =+$E95*$H89 -> 0
B96: FUTA | E96: 0 | G96: =+$E96*$H89 -> 0 | H96: Sum of Payroll Taxes | I96: W/ Payroll Taxes
B97: Workman's Comp /General Liability Insurance | E97: 0 | G97: =+$E97*$H89 -> 0 | H97: =SUM(E93:E97) -> 0.0765 | I97: =+H97*I86+I86 -> #DIV/0!
A98: CBA | B98: Sick Leave (Full Time) | C98: 0 | D98: 0 | E98: =+D98*C98 -> 0 | G98: =+E98*I97 -> #DIV/0!
A99: CBA | B99: Sick Leave (Part Time) | C99: 0 | D99: 0 | E99: =+D99*C99 -> 0 | G99: =+E99*I97 -> #DIV/0!
A100: CBA | B100: Holiday (Based on 11 Days) | C100: 0 | D100: 0 | E100: =+C100*D100 -> 0 | G100: =+E100*I97 -> #DIV/0!
A101: CBA | B101: Vacation (Based on 10 Days) | C101: 0 | D101: 0 | E101: =+C101*D101 -> 0 | G101: =+E101*I97 -> #DIV/0!
A102: CBA | B102: Vacation (Based on 17.5 Days) | C102: 0 | D102: 0 | E102: =+D102*C102 -> 0 | G102: =+E102*I97 -> #DIV/0!
A103: CBA | B103: Vacation (Based on 22.5 Days) | C103: 0 | D103: 0 | E103: =+D103*C103 -> 0 | G103: =+E103*I97 -> #DIV/0!
B104: Health and Welfare for Sick/Holiday/Vacation Hours | E104: =SUM(E98:E103) -> 0 | F104: 0 | G104: =E104*F104 -> 0 | H104: =SUM(G93:G104) -> #DIV/0! | I104: =(H104+H88)/H86 -> #DIV/0! | K104: =K86*I104 -> #DIV/0!
H105: =+H104+H89 -> #DIV/0!
A109: OVERHEAD EXPENSE | D109: 0 | H109: =+H105*D109 -> #DIV/0! | I109: =+H109/H105 -> #DIV/0! | K109: =+(K86+K104)*I109 -> #DIV/0!
A111: OTHER DIRECT COSTS (ODC):
B112: Uniforms @ | C112: 0 | D112: 0 | E112: 0 | G112: =+(C112*D112*E112) -> 0
B113: Boot Allowance | C113: 0 | D113: 0 | E113: 0 | G113: =+(C113*D113*E113) -> 0
B114: Ammo | C114: 0 | D114: 0 | E114: 0 | G114: =+(C114*D114*E114) -> 0
B115: Duty Gear | C115: 0 | D115: 0 | E115: 0 | G115: =+(C115*D115*E115) -> 0
B116: Weapons | C116: 0 | D116: 0 | E116: 0 | G116: =+(C116*D116*E116) -> 0
B117: Medical /Drug Screening / Physicals | C117: 0 | D117: 0 | E117: 0 | G117: =+(C117*D117*E117) -> 0
B118: Professional Licenses | C118: 0 | D118: 0 | E118: 0 | G118: =+(C118*D118*E118) -> 0
B119: Training - Nonrecurring | C119: 0 | D119: 0 | E119: 0 | G119: =+(C119*D119*E119) -> 0
B120: Training - Recurring Annual | C120: 0 | D120: 0 | E120: 0 | G120: =+(C120*D120*E120) -> 0
B121: Shooting Range Qualification / Requal | C121: 0 | D121: 0 | E121: 0 | G121: =+(C121*D121*E121) -> 0
...

Sheet DTW Rate Build Up
A2: {=MID(CELL("filename", A1), FIND("]", CELL("filename", A1)) + 1, LEN(CELL("filename", A1)) - FIND("]", CELL("filename", A1)))} -> DTW Rate Build Up | F2: Base Period | K2: ESS
F3: CBA
A4: =_BasePeriod -> 9/30/2026-9/29/2027
A5: DIRECT LABOR (DL): | E5: HOURS | F5: Rate | H5: TOTAL
A6: 1 | B6: Captain | E6: 0 | F6: 0 | H6: =+E6*F6 -> 0
A7: 2 | B7: Guard II | E7: 0 | F7: 0 | H7: =+E7*F7 -> 0
A8: 3 | B8: Guard II | E8: 0 | F8: 0 | H8: =+E8*F8 -> 0
A9: 4 | B9: Guard II | E9: 0 | F9: 0 | H9: =+E9*F9 -> 0
A10: 5 | B10: Guard II | E10: 0 | F10: 0 | H10: =+E10*F10 -> 0
A11: 6 | B11: Guard II | E11: 0 | F11: 0 | H11: =+E11*F11 -> 0
A12: 7 | B12: Guard II | E12: 0 | F12: 0 | H12: =+E12*F12 -> 0
A13: 8 | B13: Guard II | E13: 0 | F13: 0 | H13: =+E13*F13 -> 0
A14: 9 | B14: Guard II | E14: 0 | F14: 0 | H14: =+E14*F14 -> 0
A15: 10 | B15: Guard II | E15: 0 | F15: 0 | H15: =+E15*F15 -> 0
A16: 11 | B16: Guard II | E16: 0 | F16: 0 | H16: =+E16*F16 -> 0
A17: 12 | B17: Guard II | E17: 0 | F17: 0 | H17: =+E17*F17 -> 0
B18: Total | E18: =SUM(E6:E17) -> 0 | H18: =SUM(H6:H17) -> 0 | I18: =+H18/E18 -> #DIV/0! | K18: =+I18*1.5 -> #DIV/0!
B20: Health and Welfare | F20: 0 | H20: =+E18*F20 -> 0
H21: =+H18+H20 -> 0
A23: EMPLOYEE BENEFIT: | E23: FRINGE RATE
B25: Social Security | E25: 0.062 | G25: =+$E25*$H21 -> 0
B26: Medicare | E26: 0.0145 | G26: =+$E26*$H21 -> 0
B27: SUTA | E27: 0 | G27: =+$E27*$H21 -> 0
B28: FUTA | E28: 0 | G28: =+$E28*$H21 -> 0 | H28: Sum of Payroll Taxes | I28: W/ Payroll Taxes
B29: Workman's Comp /General Liability Insurance | E29: 0 | G29: =+$E29*$H21 -> 0 | H29: =SUM(E25:E29) -> 0.0765 | I29: =+H29*I18+I18 -> #DIV/0!
A30: CBA | B30: Sick Leave (Full Time) | C30: 0 | D30: 0 | E30: =+D30*C30 -> 0 | G30: =+E30*I29 -> #DIV/0!
A31: CBA | B31: Sick Leave (Part Time) | C31: 0 | D31: 0 | E31: =+D31*C31 -> 0 | G31: =+E31*I29 -> #DIV/0!
A32: CBA | B32: Holiday (Based on 11 Days) | C32: 0 | D32: 0 | E32: =+C32*D32 -> 0 | G32: =+E32*I29 -> #DIV/0!
A33: CBA | B33: Vacation (Based on 10 Days) | C33: 0 | D33: 0 | E33: =+C33*D33 -> 0 | G33: =+E33*I29 -> #DIV/0!
A34: CBA | B34: Vacation (Based on 17.5 Days) | C34: 0 | D34: 0 | E34: =+D34*C34 -> 0 | G34: =+E34*I29 -> #DIV/0!
A35: CBA | B35: Vacation (Based on 22.5 Days) | C35: 0 | D35: 0 | E35: =+D35*C35 -> 0 | G35: =+E35*I29 -> #DIV/0!
B36: Health and Welfare for Sick/Holiday/Vacation Hours | E36: =SUM(E30:E35) -> 0 | F36: 0 | G36: =E36*F36 -> 0 | H36: =SUM(G25:G36) -> #DIV/0! | I36: =(H36+H20)/H18 -> #DIV/0! | K36: =K18*I36 -> #DIV/0!
H37: =+H36+H21 -> #DIV/0!
A41: OVERHEAD EXPENSE | D41: 0 | H41: =+H37*D41 -> #DIV/0! | I41: =+H41/H37 -> #DIV/0! | K41: =+(K18+K36)*I41 -> #DIV/0!
A43: OTHER DIRECT COSTS (ODC):
B44: Uniforms @ | C44: 0 | D44: 0 | E44: 0 | G44: =+(C44*D44*E44) -> 0
B45: Boot Allowance | C45: 0 | D45: 0 | E45: 0 | G45: =+(C45*D45*E45) -> 0
B46: Ammo | C46: 0 | D46: 0 | E46: 0 | G46: =+(C46*D46*E46) -> 0
B47: Duty Gear | C47: 0 | D47: 0 | E47: 0 | G47: =+(C47*D47*E47) -> 0
B48: Weapons | C48: 0 | D48: 0 | E48: 0 | G48: =+(C48*D48*E48) -> 0
B49: Medical /Drug Screening / Physicals | C49: 0 | D49: 0 | E49: 0 | G49: =+(C49*D49*E49) -> 0
B50: Professional Licenses | C50: 0 | D50: 0 | E50: 0 | G50: =+(C50*D50*E50) -> 0
B51: Training - Nonrecurring | C51: 0 | D51: 0 | E51: 0 | G51: =+(C51*D51*E51) -> 0
B52: Training - Recurring Annual | C52: 0 | D52: 0 | E52: 0 | G52: =+(C52*D52*E52) -> 0
B53: Shooting Range Qualification / Requal | C53: 0 | D53: 0 | E53: 0 | G53: =+(C53*D53*E53) -> 0
B54: Travel | C54: 0 | D54: 0 | E54: 0 | G54: =+(C54*D54*E54) -> 0 | H54: =SUM(G44:G54) -> 0 | K54: =SUM(K18:K53) -> #DIV/0!
C55: SUBTOTAL | H55: =SUM(H37:H54) -> #DIV/0!
A57: G&A EXPENSE | D57: 0 | H57: =+H55*D57 -> #DIV/0! | I57: =D57 -> 0 | K57: =+K54*I57 -> #DIV/0!
D58: SUBTOTAL G&A/WC/DL | K58: =SUM(K54:K57) -> #DIV/0!
A60: PROFIT | D60: 0 | H60: =(H55+H57)*D60 -> #DIV/0!
D61: SUBTOTAL COST AND PROFIT | H61: =SUM(H55:H60) -> #DIV/0! | I61: =D60 -> 0 | K61: =+K58*I61 -> #DIV/0!
A64: STATE TAXES | D64: 0 | H64: =+H61*D64 -> #DIV/0!
F66: ANNUAL TOTAL | H66: =SUM(H61:H64) -> #DIV/0!
F67: MONTHLY RATE | H67: =+H66/12 -> #DIV/0!
B68: TAS/OTHER SERVICES/TRAINING/RANDOM SCREENING/ROVING PATROL | F68: HOURLY PRICE | H68: =+H66/(E18) -> #DIV/0! | K68: =SUM(K58:K67) -> #DIV/0!
A70: =$A$2 -> DTW Rate Build Up | F70: Option Period 1 | K70: ESS
F71: CBA
A72: =_OP1 -> 9/30/2027-9/29/2028
A73: DIRECT LABOR (DL): | E73: HOURS | F73: Rate | H73: TOTAL
A74: 1 | B74: Captain | E74: 0 | F74: 0 | H74: =+E74*F74 -> 0
A75: 2 | B75: Guard II | E75: 0 | F75: 0 | H75: =+E75*F75 -> 0
A76: 3 | B76: Guard II | E76: 0 | F76: 0 | H76: =+E76*F76 -> 0
A77: 4 | B77: Guard II | E77: 0 | F77: 0 | H77: =+E77*F77 -> 0
A78: 5 | B78: Guard II | E78: 0 | F78: 0 | H78: =+E78*F78 -> 0
A79: 6 | B79: Guard II | E79: 0 | F79: 0 | H79: =+E79*F79 -> 0
A80: 7 | B80: Guard II | E80: 0 | F80: 0 | H80: =+E80*F80 -> 0
A81: 8 | B81: Guard II | E81: 0 | F81: 0 | H81: =+E81*F81 -> 0
A82: 9 | B82: Guard II | E82: 0 | F82: 0 | H82: =+E82*F82 -> 0
A83: 10 | B83: Guard II | E83: 0 | F83: 0 | H83: =+E83*F83 -> 0
A84: 11 | B84: Guard II | E84: 0 | F84: 0 | H84: =+E84*F84 -> 0
A85: 12 | B85: Guard II | E85: 0 | F85: 0 | H85: =+E85*F85 -> 0
B86: Total | E86: =SUM(E74:E85) -> 0 | H86: =SUM(H74:H85) -> 0 | I86: =+H86/E86 -> #DIV/0! | K86: =+I86*1.5 -> #DIV/0!
B88: Health and Welfare | F88: 0 | H88: =+E86*F88 -> 0
H89: =+H86+H88 -> 0
A91: EMPLOYEE BENEFIT: | E91: FRINGE RATE
B93: Social Security | E93: 0.062 | G93: =+$E93*$H89 -> 0
B94: Medicare | E94: 0.0145 | G94: =+$E94*$H89 -> 0
B95: SUTA | E95: 0 | G95: =+$E95*$H89 -> 0
B96: FUTA | E96: 0 | G96: =+$E96*$H89 -> 0 | H96: Sum of Payroll Taxes | I96: W/ Payroll Taxes
B97: Workman's Comp /General Liability Insurance | E97: 0 | G97: =+$E97*$H89 -> 0 | H97: =SUM(E93:E97) -> 0.0765 | I97: =+H97*I86+I86 -> #DIV/0!
A98: CBA | B98: Sick Leave (Full Time) | C98: 0 | D98: 0 | E98: =+D98*C98 -> 0 | G98: =+E98*I97 -> #DIV/0!
A99: CBA | B99: Sick Leave (Part Time) | C99: 0 | D99: 0 | E99: =+D99*C99 -> 0 | G99: =+E99*I97 -> #DIV/0!
A100: CBA | B100: Holiday (Based on 11 Days) | C100: 0 | D100: 0 | E100: =+C100*D100 -> 0 | G100: =+E100*I97 -> #DIV/0!
A101: CBA | B101: Vacation (Based on 10 Days) | C101: 0 | D101: 0 | E101: =+C101*D101 -> 0 | G101: =+E101*I97 -> #DIV/0!
A102: CBA | B102: Vacation (Based on 17.5 Days) | C102: 0 | D102: 0 | E102: =+D102*C102 -> 0 | G102: =+E102*I97 -> #DIV/0!
A103: CBA | B103: Vacation (Based on 22.5 Days) | C103: 0 | D103: 0 | E103: =+D103*C103 -> 0 | G103: =+E103*I97 -> #DIV/0!
B104: Health and Welfare for Sick/Holiday/Vacation Hours | E104: =SUM(E98:E103) -> 0 | F104: 0 | G104: =E104*F104 -> 0 | H104: =SUM(G93:G104) -> #DIV/0! | I104: =(H104+H88)/H86 -> #DIV/0! | K104: =K86*I104 -> #DIV/0!
H105: =+H104+H89 -> #DIV/0!
A109: OVERHEAD EXPENSE | D109: 0 | H109: =+H105*D109 -> #DIV/0! | I109: =+H109/H105 -> #DIV/0! | K109: =+(K86+K104)*I109 -> #DIV/0!
A111: OTHER DIRECT COSTS (ODC):
B112: Uniforms @ | C112: 0 | D112: 0 | E112: 0 | G112: =+(C112*D112*E112) -> 0
B113: Boot Allowance | C113: 0 | D113: 0 | E113: 0 | G113: =+(C113*D113*E113) -> 0
B114: Ammo | C114: 0 | D114: 0 | E114: 0 | G114: =+(C114*D114*E114) -> 0
B115: Duty Gear | C115: 0 | D115: 0 | E115: 0 | G115: =+(C115*D115*E115) -> 0
B116: Weapons | C116: 0 | D116: 0 | E116: 0 | G116: =+(C116*D116*E116) -> 0
B117: Medical /Drug Screening / Physicals | C117: 0 | D117: 0 | E117: 0 | G117: =+(C117*D117*E117) -> 0
B118: Professional Licenses | C118: 0 | D118: 0 | E118: 0 | G118: =+(C118*D118*E118) -> 0
B119: Training - Nonrecurring | C119: 0 | D119: 0 | E119: 0 | G119: =+(C119*D119*E119) -> 0
B120: Training - Recurring Annual | C120: 0 | D120: 0 | E120: 0 | G120: =+(C120*D120*E120) -> 0
B121: Shooting Range Qualification / Requal | C121: 0 | D121: 0 | E121: 0 | G121: =+(C121*D121*E121) -> 0
...

Sheet I90 TRACON Rate Build Up
A2: {=MID(CELL("filename", A1), FIND("]", CELL("filename", A1)) + 1, LEN(CELL("filename", A1)) - FIND("]", CELL("filename", A1)))} -> I90 TRACON Rate Build Up | F2: Base Period | K2: ESS
F3: CBA
A4: =_BasePeriod -> 9/30/2026-9/29/2027
A5: DIRECT LABOR (DL): | E5: HOURS | F5: Rate | H5: TOTAL
A6: 1 | B6: Captain | E6: 0 | F6: 0 | H6: =+E6*F6 -> 0
A7: 2 | B7: Guard II | E7: 0 | F7: 0 | H7: =+E7*F7 -> 0
A8: 3 | B8: Guard II | E8: 0 | F8: 0 | H8: =+E8*F8 -> 0
A9: 4 | B9: Guard II | E9: 0 | F9: 0 | H9: =+E9*F9 -> 0
A10: 5 | B10: Guard II | E10: 0 | F10: 0 | H10: =+E10*F10 -> 0
A11: 6 | B11: Guard II | E11: 0 | F11: 0 | H11: =+E11*F11 -> 0
A12: 7 | B12: Guard II | E12: 0 | F12: 0 | H12: =+E12*F12 -> 0
A13: 8 | B13: Guard II | E13: 0 | F13: 0 | H13: =+E13*F13 -> 0
A14: 9 | B14: Guard II | E14: 0 | F14: 0 | H14: =+E14*F14 -> 0
A15: 10 | B15: Guard II | E15: 0 | F15: 0 | H15: =+E15*F15 -> 0
A16: 11 | B16: Guard II | E16: 0 | F16: 0 | H16: =+E16*F16 -> 0
A17: 12 | B17: Guard II | E17: 0 | F17: 0 | H17: =+E17*F17 -> 0
B18: Total | E18: =SUM(E6:E17) -> 0 | H18: =SUM(H6:H17) -> 0 | I18: =+H18/E18 -> #DIV/0! | K18: =+I18*1.5 -> #DIV/0!
B20: Health and Welfare | F20: 0 | H20: =+E18*F20 -> 0
H21: =+H18+H20 -> 0
A23: EMPLOYEE BENEFIT: | E23: FRINGE RATE
B25: Social Security | E25: 0.062 | G25: =+$E25*$H21 -> 0
B26: Medicare | E26: 0.0145 | G26: =+$E26*$H21 -> 0
B27: SUTA | E27: 0 | G27: =+$E27*$H21 -> 0
B28: FUTA | E28: 0 | G28: =+$E28*$H21 -> 0 | H28: Sum of Payroll Taxes | I28: W/ Payroll Taxes
B29: Workman's Comp /General Liability Insurance | E29: 0 | G29: =+$E29*$H21 -> 0 | H29: =SUM(E25:E29) -> 0.0765 | I29: =+H29*I18+I18 -> #DIV/0!
A30: CBA | B30: Sick Leave (Full Time) | C30: 0 | D30: 0 | E30: =+D30*C30 -> 0 | G30: =+E30*I29 -> #DIV/0!
A31: CBA | B31: Sick Leave (Part Time) | C31: 0 | D31: 0 | E31: =+D31*C31 -> 0 | G31: =+E31*I29 -> #DIV/0!
A32: CBA | B32: Holiday (Based on 11 Days) | C32: 0 | D32: 0 | E32: =+C32*D32 -> 0 | G32: =+E32*I29 -> #DIV/0!
A33: CBA | B33: Vacation (Based on 10 Days) | C33: 0 | D33: 0 | E33: =+C33*D33 -> 0 | G33: =+E33*I29 -> #DIV/0!
A34: CBA | B34: Vacation (Based on 17.5 Days) | C34: 0 | D34: 0 | E34: =+D34*C34 -> 0 | G34: =+E34*I29 -> #DIV/0!
A35: CBA | B35: Vacation (Based on 22.5 Days) | C35: 0 | D35: 0 | E35: =+D35*C35 -> 0 | G35: =+E35*I29 -> #DIV/0!
B36: Health and Welfare for Sick/Holiday/Vacation Hours | E36: =SUM(E30:E35) -> 0 | F36: 0 | G36: =E36*F36 -> 0 | H36: =SUM(G25:G36) -> #DIV/0! | I36: =(H36+H20)/H18 -> #DIV/0! | K36: =K18*I36 -> #DIV/0!
H37: =+H36+H21 -> #DIV/0!
A41: OVERHEAD EXPENSE | D41: 0 | H41: =+H37*D41 -> #DIV/0! | I41: =+H41/H37 -> #DIV/0! | K41: =+(K18+K36)*I41 -> #DIV/0!
A43: OTHER DIRECT COSTS (ODC):
B44: Uniforms @ | C44: 0 | D44: 0 | E44: 0 | G44: =+(C44*D44*E44) -> 0
B45: Boot Allowance | C45: 0 | D45: 0 | E45: 0 | G45: =+(C45*D45*E45) -> 0
B46: Ammo | C46: 0 | D46: 0 | E46: 0 | G46: =+(C46*D46*E46) -> 0
B47: Duty Gear | C47: 0 | D47: 0 | E47: 0 | G47: =+(C47*D47*E47) -> 0
B48: Weapons | C48: 0 | D48: 0 | E48: 0 | G48: =+(C48*D48*E48) -> 0
B49: Medical /Drug Screening / Physicals | C49: 0 | D49: 0 | E49: 0 | G49: =+(C49*D49*E49) -> 0
B50: Professional Licenses | C50: 0 | D50: 0 | E50: 0 | G50: =+(C50*D50*E50) -> 0
B51: Training - Nonrecurring | C51: 0 | D51: 0 | E51: 0 | G51: =+(C51*D51*E51) -> 0
B52: Training - Recurring Annual | C52: 0 | D52: 0 | E52: 0 | G52: =+(C52*D52*E52) -> 0
B53: Shooting Range Qualification / Requal | C53: 0 | D53: 0 | E53: 0 | G53: =+(C53*D53*E53) -> 0
B54: Travel | C54: 0 | D54: 0 | E54: 0 | G54: =+(C54*D54*E54) -> 0 | H54: =SUM(G44:G54) -> 0 | K54: =SUM(K18:K53) -> #DIV/0!
C55: SUBTOTAL | H55: =SUM(H37:H54) -> #DIV/0!
A57: G&A EXPENSE | D57: 0 | H57: =+H55*D57 -> #DIV/0! | I57: =D57 -> 0 | K57: =+K54*I57 -> #DIV/0!
D58: SUBTOTAL G&A/WC/DL | K58: =SUM(K54:K57) -> #DIV/0!
A60: PROFIT | D60: 0 | H60: =(H55+H57)*D60 -> #DIV/0!
D61: SUBTOTAL COST AND PROFIT | H61: =SUM(H55:H60) -> #DIV/0! | I61: =D60 -> 0 | K61: =+K58*I61 -> #DIV/0!
A64: STATE TAXES | D64: 0 | H64: =+H61*D64 -> #DIV/0!
F66: ANNUAL TOTAL | H66: =SUM(H61:H64) -> #DIV/0!
F67: MONTHLY RATE | H67: =+H66/12 -> #DIV/0!
B68: TAS/OTHER SERVICES/TRAINING/RANDOM SCREENING/ROVING PATROL | F68: HOURLY PRICE | H68: =+H66/(E18) -> #DIV/0! | K68: =SUM(K58:K67) -> #DIV/0!
A70: =$A$2 -> I90 TRACON Rate Build Up | F70: Option Period 1 | K70: ESS
F71: CBA
A72: =_OP1 -> 9/30/2027-9/29/2028
A73: DIRECT LABOR (DL): | E73: HOURS | F73: Rate | H73: TOTAL
A74: 1 | B74: Captain | E74: 0 | F74: 0 | H74: =+E74*F74 -> 0
A75: 2 | B75: Guard II | E75: 0 | F75: 0 | H75: =+E75*F75 -> 0
A76: 3 | B76: Guard II | E76: 0 | F76: 0 | H76: =+E76*F76 -> 0
A77: 4 | B77: Guard II | E77: 0 | F77: 0 | H77: =+E77*F77 -> 0
A78: 5 | B78: Guard II | E78: 0 | F78: 0 | H78: =+E78*F78 -> 0
A79: 6 | B79: Guard II | E79: 0 | F79: 0 | H79: =+E79*F79 -> 0
A80: 7 | B80: Guard II | E80: 0 | F80: 0 | H80: =+E80*F80 -> 0
A81: 8 | B81: Guard II | E81: 0 | F81: 0 | H81: =+E81*F81 -> 0
A82: 9 | B82: Guard II | E82: 0 | F82: 0 | H82: =+E82*F82 -> 0
A83: 10 | B83: Guard II | E83: 0 | F83: 0 | H83: =+E83*F83 -> 0
A84: 11 | B84: Guard II | E84: 0 | F84: 0 | H84: =+E84*F84 -> 0
A85: 12 | B85: Guard II | E85: 0 | F85: 0 | H85: =+E85*F85 -> 0
B86: Total | E86: =SUM(E74:E85) -> 0 | H86: =SUM(H74:H85) -> 0 | I86: =+H86/E86 -> #DIV/0! | K86: =+I86*1.5 -> #DIV/0!
B88: Health and Welfare | F88: 0 | H88: =+E86*F88 -> 0
H89: =+H86+H88 -> 0
A91: EMPLOYEE BENEFIT: | E91: FRINGE RATE
B93: Social Security | E93: 0.062 | G93: =+$E93*$H89 -> 0
B94: Medicare | E94: 0.0145 | G94: =+$E94*$H89 -> 0
B95: SUTA | E95: 0 | G95: =+$E95*$H89 -> 0
B96: FUTA | E96: 0 | G96: =+$E96*$H89 -> 0 | H96: Sum of Payroll Taxes | I96: W/ Payroll Taxes
B97: Workman's Comp /General Liability Insurance | E97: 0 | G97: =+$E97*$H89 -> 0 | H97: =SUM(E93:E97) -> 0.0765 | I97: =+H97*I86+I86 -> #DIV/0!
A98: CBA | B98: Sick Leave (Full Time) | C98: 0 | D98: 0 | E98: =+D98*C98 -> 0 | G98: =+E98*I97 -> #DIV/0!
A99: CBA | B99: Sick Leave (Part Time) | C99: 0 | D99: 0 | E99: =+D99*C99 -> 0 | G99: =+E99*I97 -> #DIV/0!
A100: CBA | B100: Holiday (Based on 11 Days) | C100: 0 | D100: 0 | E100: =+C100*D100 -> 0 | G100: =+E100*I97 -> #DIV/0!
A101: CBA | B101: Vacation (Based on 10 Days) | C101: 0 | D101: 0 | E101: =+C101*D101 -> 0 | G101: =+E101*I97 -> #DIV/0!
A102: CBA | B102: Vacation (Based on 17.5 Days) | C102: 0 | D102: 0 | E102: =+D102*C102 -> 0 | G102: =+E102*I97 -> #DIV/0!
A103: CBA | B103: Vacation (Based on 22.5 Days) | C103: 0 | D103: 0 | E103: =+D103*C103 -> 0 | G103: =+E103*I97 -> #DIV/0!
B104: Health and Welfare for Sick/Holiday/Vacation Hours | E104: =SUM(E98:E103) -> 0 | F104: 0 | G104: =E104*F104 -> 0 | H104: =SUM(G93:G104) -> #DIV/0! | I104: =(H104+H88)/H86 -> #DIV/0! | K104: =K86*I104 -> #DIV/0!
H105: =+H104+H89 -> #DIV/0!
A109: OVERHEAD EXPENSE | D109: 0 | H109: =+H105*D109 -> #DIV/0! | I109: =+H109/H105 -> #DIV/0! | K109: =+(K86+K104)*I109 -> #DIV/0!
A111: OTHER DIRECT COSTS (ODC):
B112: Uniforms @ | C112: 0 | D112: 0 | E112: 0 | G112: =+(C112*D112*E112) -> 0
B113: Boot Allowance | C113: 0 | D113: 0 | E113: 0 | G113: =+(C113*D113*E113) -> 0
B114: Ammo | C114: 0 | D114: 0 | E114: 0 | G114: =+(C114*D114*E114) -> 0
B115: Duty Gear | C115: 0 | D115: 0 | E115: 0 | G115: =+(C115*D115*E115) -> 0
B116: Weapons | C116: 0 | D116: 0 | E116: 0 | G116: =+(C116*D116*E116) -> 0
B117: Medical /Drug Screening / Physicals | C117: 0 | D117: 0 | E117: 0 | G117: =+(C117*D117*E117) -> 0
B118: Professional Licenses | C118: 0 | D118: 0 | E118: 0 | G118: =+(C118*D118*E118) -> 0
B119: Training - Nonrecurring | C119: 0 | D119: 0 | E119: 0 | G119: =+(C119*D119*E119) -> 0
B120: Training - Recurring Annual | C120: 0 | D120: 0 | E120: 0 | G120: =+(C120*D120*E120) -> 0
B121: Shooting Range Qualification / Requal | C121: 0 | D121: 0 | E121: 0 | G121: =+(C121*D121*E121) -> 0
...

Sheet IAH ATCT Rate Build Up
A2: {=MID(CELL("filename", A1), FIND("]", CELL("filename", A1)) + 1, LEN(CELL("filename", A1)) - FIND("]", CELL("filename", A1)))} -> IAH ATCT Rate Build Up | F2: Base Period | K2: ESS
F3: CBA
A4: =_BasePeriod -> 9/30/2026-9/29/2027
A5: DIRECT LABOR (DL): | E5: HOURS | F5: Rate | H5: TOTAL
A6: 1 | B6: Captain | E6: 0 | F6: 0 | H6: =+E6*F6 -> 0
A7: 2 | B7: Guard II | E7: 0 | F7: 0 | H7: =+E7*F7 -> 0
A8: 3 | B8: Guard II | E8: 0 | F8: 0 | H8: =+E8*F8 -> 0
A9: 4 | B9: Guard II | E9: 0 | F9: 0 | H9: =+E9*F9 -> 0
A10: 5 | B10: Guard II | E10: 0 | F10: 0 | H10: =+E10*F10 -> 0
A11: 6 | B11: Guard II | E11: 0 | F11: 0 | H11: =+E11*F11 -> 0
A12: 7 | B12: Guard II | E12: 0 | F12: 0 | H12: =+E12*F12 -> 0
A13: 8 | B13: Guard II | E13: 0 | F13: 0 | H13: =+E13*F13 -> 0
A14: 9 | B14: Guard II | E14: 0 | F14: 0 | H14: =+E14*F14 -> 0
A15: 10 | B15: Guard II | E15: 0 | F15: 0 | H15: =+E15*F15 -> 0
A16: 11 | B16: Guard II | E16: 0 | F16: 0 | H16: =+E16*F16 -> 0
A17: 12 | B17: Guard II | E17: 0 | F17: 0 | H17: =+E17*F17 -> 0
B18: Total | E18: =SUM(E6:E17) -> 0 | H18: =SUM(H6:H17) -> 0 | I18: =+H18/E18 -> #DIV/0! | K18: =+I18*1.5 -> #DIV/0!
B20: Health and Welfare | F20: 0 | H20: =+E18*F20 -> 0
H21: =+H18+H20 -> 0
A23: EMPLOYEE BENEFIT: | E23: FRINGE RATE
B25: Social Security | E25: 0.062 | G25: =+$E25*$H21 -> 0
B26: Medicare | E26: 0.0145 | G26: =+$E26*$H21 -> 0
B27: SUTA | E27: 0 | G27: =+$E27*$H21 -> 0
B28: FUTA | E28: 0 | G28: =+$E28*$H21 -> 0 | H28: Sum of Payroll Taxes | I28: W/ Payroll Taxes
B29: Workman's Comp /General Liability Insurance | E29: 0 | G29: =+$E29*$H21 -> 0 | H29: =SUM(E25:E29) -> 0.0765 | I29: =+H29*I18+I18 -> #DIV/0!
A30: CBA | B30: Sick Leave (Full Time) | C30: 0 | D30: 0 | E30: =+D30*C30 -> 0 | G30: =+E30*I29 -> #DIV/0!
A31: CBA | B31: Sick Leave (Part Time) | C31: 0 | D31: 0 | E31: =+D31*C31 -> 0 | G31: =+E31*I29 -> #DIV/0!
A32: CBA | B32: Holiday (Based on 11 Days) | C32: 0 | D32: 0 | E32: =+C32*D32 -> 0 | G32: =+E32*I29 -> #DIV/0!
A33: CBA | B33: Vacation (Based on 10 Days) | C33: 0 | D33: 0 | E33: =+C33*D33 -> 0 | G33: =+E33*I29 -> #DIV/0!
A34: CBA | B34: Vacation (Based on 17.5 Days) | C34: 0 | D34: 0 | E34: =+D34*C34 -> 0 | G34: =+E34*I29 -> #DIV/0!
A35: CBA | B35: Vacation (Based on 22.5 Days) | C35: 0 | D35: 0 | E35: =+D35*C35 -> 0 | G35: =+E35*I29 -> #DIV/0!
B36: Health and Welfare for Sick/Holiday/Vacation Hours | E36: =SUM(E30:E35) -> 0 | F36: 0 | G36: =E36*F36 -> 0 | H36: =SUM(G25:G36) -> #DIV/0! | I36: =(H36+H20)/H18 -> #DIV/0! | K36: =K18*I36 -> #DIV/0!
H37: =+H36+H21 -> #DIV/0!
A41: OVERHEAD EXPENSE | D41: 0 | H41: =+H37*D41 -> #DIV/0! | I41: =+H41/H37 -> #DIV/0! | K41: =+(K18+K36)*I41 -> #DIV/0!
A43: OTHER DIRECT COSTS (ODC):
B44: Uniforms @ | C44: 0 | D44: 0 | E44: 0 | G44: =+(C44*D44*E44) -> 0
B45: Boot Allowance | C45: 0 | D45: 0 | E45: 0 | G45: =+(C45*D45*E45) -> 0
B46: Ammo | C46: 0 | D46: 0 | E46: 0 | G46: =+(C46*D46*E46) -> 0
B47: Duty Gear | C47: 0 | D47: 0 | E47: 0 | G47: =+(C47*D47*E47) -> 0
B48: Weapons | C48: 0 | D48: 0 | E48: 0 | G48: =+(C48*D48*E48) -> 0
B49: Medical /Drug Screening / Physicals | C49: 0 | D49: 0 | E49: 0 | G49: =+(C49*D49*E49) -> 0
B50: Professional Licenses | C50: 0 | D50: 0 | E50: 0 | G50: =+(C50*D50*E50) -> 0
B51: Training - Nonrecurring | C51: 0 | D51: 0 | E51: 0 | G51: =+(C51*D51*E51) -> 0
B52: Training - Recurring Annual | C52: 0 | D52: 0 | E52: 0 | G52: =+(C52*D52*E52) -> 0
B53: Shooting Range Qualification / Requal | C53: 0 | D53: 0 | E53: 0 | G53: =+(C53*D53*E53) -> 0
B54: Travel | C54: 0 | D54: 0 | E54: 0 | G54: =+(C54*D54*E54) -> 0 | H54: =SUM(G44:G54) -> 0 | K54: =SUM(K18:K53) -> #DIV/0!
C55: SUBTOTAL | H55: =SUM(H37:H54) -> #DIV/0!
A57: G&A EXPENSE | D57: 0 | H57: =+H55*D57 -> #DIV/0! | I57: =D57 -> 0 | K57: =+K54*I57 -> #DIV/0!
D58: SUBTOTAL G&A/WC/DL | K58: =SUM(K54:K57) -> #DIV/0!
A60: PROFIT | D60: 0 | H60: =(H55+H57)*D60 -> #DIV/0!
D61: SUBTOTAL COST AND PROFIT | H61: =SUM(H55:H60) -> #DIV/0! | I61: =D60 -> 0 | K61: =+K58*I61 -> #DIV/0!
A64: STATE TAXES | D64: 0 | H64: =+H61*D64 -> #DIV/0!
F66: ANNUAL TOTAL | H66: =SUM(H61:H64) -> #DIV/0!
F67: MONTHLY RATE | H67: =+H66/12 -> #DIV/0!
B68: TAS/OTHER SERVICES/TRAINING/RANDOM SCREENING/ROVING PATROL | F68: HOURLY PRICE | H68: =+H66/(E18) -> #DIV/0! | K68: =SUM(K58:K67) -> #DIV/0!
A70: =$A$2 -> IAH ATCT Rate Build Up | F70: Option Period 1 | K70: ESS
F71: CBA
A72: =_OP1 -> 9/30/2027-9/29/2028
A73: DIRECT LABOR (DL): | E73: HOURS | F73: Rate | H73: TOTAL
A74: 1 | B74: Captain | E74: 0 | F74: 0 | H74: =+E74*F74 -> 0
A75: 2 | B75: Guard II | E75: 0 | F75: 0 | H75: =+E75*F75 -> 0
A76: 3 | B76: Guard II | E76: 0 | F76: 0 | H76: =+E76*F76 -> 0
A77: 4 | B77: Guard II | E77: 0 | F77: 0 | H77: =+E77*F77 -> 0
A78: 5 | B78: Guard II | E78: 0 | F78: 0 | H78: =+E78*F78 -> 0
A79: 6 | B79: Guard II | E79: 0 | F79: 0 | H79: =+E79*F79 -> 0
A80: 7 | B80: Guard II | E80: 0 | F80: 0 | H80: =+E80*F80 -> 0
A81: 8 | B81: Guard II | E81: 0 | F81: 0 | H81: =+E81*F81 -> 0
A82: 9 | B82: Guard II | E82: 0 | F82: 0 | H82: =+E82*F82 -> 0
A83: 10 | B83: Guard II | E83: 0 | F83: 0 | H83: =+E83*F83 -> 0
A84: 11 | B84: Guard II | E84: 0 | F84: 0 | H84: =+E84*F84 -> 0
A85: 12 | B85: Guard II | E85: 0 | F85: 0 | H85: =+E85*F85 -> 0
B86: Total | E86: =SUM(E74:E85) -> 0 | H86: =SUM(H74:H85) -> 0 | I86: =+H86/E86 -> #DIV/0! | K86: =+I86*1.5 -> #DIV/0!
B88: Health and Welfare | F88: 0 | H88: =+E86*F88 -> 0
H89: =+H86+H88 -> 0
A91: EMPLOYEE BENEFIT: | E91: FRINGE RATE
B93: Social Security | E93: 0.062 | G93: =+$E93*$H89 -> 0
B94: Medicare | E94: 0.0145 | G94: =+$E94*$H89 -> 0
B95: SUTA | E95: 0 | G95: =+$E95*$H89 -> 0
B96: FUTA | E96: 0 | G96: =+$E96*$H89 -> 0 | H96: Sum of Payroll Taxes | I96: W/ Payroll Taxes
B97: Workman's Comp /General Liability Insurance | E97: 0 | G97: =+$E97*$H89 -> 0 | H97: =SUM(E93:E97) -> 0.0765 | I97: =+H97*I86+I86 -> #DIV/0!
A98: CBA | B98: Sick Leave (Full Time) | C98: 0 | D98: 0 | E98: =+D98*C98 -> 0 | G98: =+E98*I97 -> #DIV/0!
A99: CBA | B99: Sick Leave (Part Time) | C99: 0 | D99: 0 | E99: =+D99*C99 -> 0 | G99: =+E99*I97 -> #DIV/0!
A100: CBA | B100: Holiday (Based on 11 Days) | C100: 0 | D100: 0 | E100: =+C100*D100 -> 0 | G100: =+E100*I97 -> #DIV/0!
A101: CBA | B101: Vacation (Based on 10 Days) | C101: 0 | D101: 0 | E101: =+C101*D101 -> 0 | G101: =+E101*I97 -> #DIV/0!
A102: CBA | B102: Vacation (Based on 17.5 Days) | C102: 0 | D102: 0 | E102: =+D102*C102 -> 0 | G102: =+E102*I97 -> #DIV/0!
A103: CBA | B103: Vacation (Based on 22.5 Days) | C103: 0 | D103: 0 | E103: =+D103*C103 -> 0 | G103: =+E103*I97 -> #DIV/0!
B104: Health and Welfare for Sick/Holiday/Vacation Hours | E104: =SUM(E98:E103) -> 0 | F104: 0 | G104: =E104*F104 -> 0 | H104: =SUM(G93:G104) -> #DIV/0! | I104: =(H104+H88)/H86 -> #DIV/0! | K104: =K86*I104 -> #DIV/0!
H105: =+H104+H89 -> #DIV/0!
A109: OVERHEAD EXPENSE | D109: 0 | H109: =+H105*D109 -> #DIV/0! | I109: =+H109/H105 -> #DIV/0! | K109: =+(K86+K104)*I109 -> #DIV/0!
A111: OTHER DIRECT COSTS (ODC):
B112: Uniforms @ | C112: 0 | D112: 0 | E112: 0 | G112: =+(C112*D112*E112) -> 0
B113: Boot Allowance | C113: 0 | D113: 0 | E113: 0 | G113: =+(C113*D113*E113) -> 0
B114: Ammo | C114: 0 | D114: 0 | E114: 0 | G114: =+(C114*D114*E114) -> 0
B115: Duty Gear | C115: 0 | D115: 0 | E115: 0 | G115: =+(C115*D115*E115) -> 0
B116: Weapons | C116: 0 | D116: 0 | E116: 0 | G116: =+(C116*D116*E116) -> 0
B117: Medical /Drug Screening / Physicals | C117: 0 | D117: 0 | E117: 0 | G117: =+(C117*D117*E117) -> 0
B118: Professional Licenses | C118: 0 | D118: 0 | E118: 0 | G118: =+(C118*D118*E118) -> 0
B119: Training - Nonrecurring | C119: 0 | D119: 0 | E119: 0 | G119: =+(C119*D119*E119) -> 0
B120: Training - Recurring Annual | C120: 0 | D120: 0 | E120: 0 | G120: =+(C120*D120*E120) -> 0
B121: Shooting Range Qualification / Requal | C121: 0 | D121: 0 | E121: 0 | G121: =+(C121*D121*E121) -> 0
...

Sheet MSP ATCT Rate Build Up
A2: {=MID(CELL("filename", A1), FIND("]", CELL("filename", A1)) + 1, LEN(CELL("filename", A1)) - FIND("]", CELL("filename", A1)))} -> MSP ATCT Rate Build Up | F2: Base Period | K2: ESS
F3: CBA
A4: =_BasePeriod -> 9/30/2026-9/29/2027
A5: DIRECT LABOR (DL): | E5: HOURS | F5: Rate | H5: TOTAL
A6: 1 | B6: Captain | E6: 0 | F6: 0 | H6: =+E6*F6 -> 0
A7: 2 | B7: Guard II | E7: 0 | F7: 0 | H7: =+E7*F7 -> 0
A8: 3 | B8: Guard II | E8: 0 | F8: 0 | H8: =+E8*F8 -> 0
A9: 4 | B9: Guard II | E9: 0 | F9: 0 | H9: =+E9*F9 -> 0
A10: 5 | B10: Guard II | E10: 0 | F10: 0 | H10: =+E10*F10 -> 0
A11: 6 | B11: Guard II | E11: 0 | F11: 0 | H11: =+E11*F11 -> 0
A12: 7 | B12: Guard II | E12: 0 | F12: 0 | H12: =+E12*F12 -> 0
A13: 8 | B13: Guard II | E13: 0 | F13: 0 | H13: =+E13*F13 -> 0
A14: 9 | B14: Guard II | E14: 0 | F14: 0 | H14: =+E14*F14 -> 0
A15: 10 | B15: Guard II | E15: 0 | F15: 0 | H15: =+E15*F15 -> 0
A16: 11 | B16: Guard II | E16: 0 | F16: 0 | H16: =+E16*F16 -> 0
A17: 12 | B17: Guard II | E17: 0 | F17: 0 | H17: =+E17*F17 -> 0
B18: Total | E18: =SUM(E6:E17) -> 0 | H18: =SUM(H6:H17) -> 0 | I18: =+H18/E18 -> #DIV/0! | K18: =+I18*1.5 -> #DIV/0!
B20: Health and Welfare | F20: 0 | H20: =+E18*F20 -> 0
H21: =+H18+H20 -> 0
A23: EMPLOYEE BENEFIT: | E23: FRINGE RATE
B25: Social Security | E25: 0.062 | G25: =+$E25*$H21 -> 0
B26: Medicare | E26: 0.0145 | G26: =+$E26*$H21 -> 0
B27: SUTA | E27: 0 | G27: =+$E27*$H21 -> 0
B28: FUTA | E28: 0 | G28: =+$E28*$H21 -> 0 | H28: Sum of Payroll Taxes | I28: W/ Payroll Taxes
B29: Workman's Comp /General Liability Insurance | E29: 0 | G29: =+$E29*$H21 -> 0 | H29: =SUM(E25:E29) -> 0.0765 | I29: =+H29*I18+I18 -> #DIV/0!
A30: CBA | B30: Sick Leave (Full Time) | C30: 0 | D30: 0 | E30: =+D30*C30 -> 0 | G30: =+E30*I29 -> #DIV/0!
A31: CBA | B31: Sick Leave (Part Time) | C31: 0 | D31: 0 | E31: =+D31*C31 -> 0 | G31: =+E31*I29 -> #DIV/0!
A32: CBA | B32: Holiday (Based on 11 Days) | C32: 0 | D32: 0 | E32: =+C32*D32 -> 0 | G32: =+E32*I29 -> #DIV/0!
A33: CBA | B33: Vacation (Based on 10 Days) | C33: 0 | D33: 0 | E33: =+C33*D33 -> 0 | G33: =+E33*I29 -> #DIV/0!
A34: CBA | B34: Vacation (Based on 17.5 Days) | C34: 0 | D34: 0 | E34: =+D34*C34 -> 0 | G34: =+E34*I29 -> #DIV/0!
A35: CBA | B35: Vacation (Based on 22.5 Days) | C35: 0 | D35: 0 | E35: =+D35*C35 -> 0 | G35: =+E35*I29 -> #DIV/0!
B36: Health and Welfare for Sick/Holiday/Vacation Hours | E36: =SUM(E30:E35) -> 0 | F36: 0 | G36: =E36*F36 -> 0 | H36: =SUM(G25:G36) -> #DIV/0! | I36: =(H36+H20)/H18 -> #DIV/0! | K36: =K18*I36 -> #DIV/0!
H37: =+H36+H21 -> #DIV/0!
A41: OVERHEAD EXPENSE | D41: 0 | H41: =+H37*D41 -> #DIV/0! | I41: =+H41/H37 -> #DIV/0! | K41: =+(K18+K36)*I41 -> #DIV/0!
A43: OTHER DIRECT COSTS (ODC):
B44: Uniforms @ | C44: 0 | D44: 0 | E44: 0 | G44: =+(C44*D44*E44) -> 0
B45: Boot Allowance | C45: 0 | D45: 0 | E45: 0 | G45: =+(C45*D45*E45) -> 0
B46: Ammo | C46: 0 | D46: 0 | E46: 0 | G46: =+(C46*D46*E46) -> 0
B47: Duty Gear | C47: 0 | D47: 0 | E47: 0 | G47: =+(C47*D47*E47) -> 0
B48: Weapons | C48: 0 | D48: 0 | E48: 0 | G48: =+(C48*D48*E48) -> 0
B49: Medical /Drug Screening / Physicals | C49: 0 | D49: 0 | E49: 0 | G49: =+(C49*D49*E49) -> 0
B50: Professional Licenses | C50: 0 | D50: 0 | E50: 0 | G50: =+(C50*D50*E50) -> 0
B51: Training - Nonrecurring | C51: 0 | D51: 0 | E51: 0 | G51: =+(C51*D51*E51) -> 0
B52: Training - Recurring Annual | C52: 0 | D52: 0 | E52: 0 | G52: =+(C52*D52*E52) -> 0
B53: Shooting Range Qualification / Requal | C53: 0 | D53: 0 | E53: 0 | G53: =+(C53*D53*E53) -> 0
B54: Travel | C54: 0 | D54: 0 | E54: 0 | G54: =+(C54*D54*E54) -> 0 | H54: =SUM(G44:G54) -> 0 | K54: =SUM(K18:K53) -> #DIV/0!
C55: SUBTOTAL | H55: =SUM(H37:H54) -> #DIV/0!
A57: G&A EXPENSE | D57: 0 | H57: =+H55*D57 -> #DIV/0! | I57: =D57 -> 0 | K57: =+K54*I57 -> #DIV/0!
D58: SUBTOTAL G&A/WC/DL | K58: =SUM(K54:K57) -> #DIV/0!
A60: PROFIT | D60: 0 | H60: =(H55+H57)*D60 -> #DIV/0!
D61: SUBTOTAL COST AND PROFIT | H61: =SUM(H55:H60) -> #DIV/0! | I61: =D60 -> 0 | K61: =+K58*I61 -> #DIV/0!
A64: STATE TAXES | D64: 0 | H64: =+H61*D64 -> #DIV/0!
F66: ANNUAL TOTAL | H66: =SUM(H61:H64) -> #DIV/0!
F67: MONTHLY RATE | H67: =+H66/12 -> #DIV/0!
B68: TAS/OTHER SERVICES/TRAINING/RANDOM SCREENING/ROVING PATROL | F68: HOURLY PRICE | H68: =+H66/(E18) -> #DIV/0! | K68: =SUM(K58:K67) -> #DIV/0!
A70: =$A$2 -> MSP ATCT Rate Build Up | F70: Option Period 1 | K70: ESS
F71: CBA
A72: =_OP1 -> 9/30/2027-9/29/2028
A73: DIRECT LABOR (DL): | E73: HOURS | F73: Rate | H73: TOTAL
A74: 1 | B74: Captain | E74: 0 | F74: 0 | H74: =+E74*F74 -> 0
A75: 2 | B75: Guard II | E75: 0 | F75: 0 | H75: =+E75*F75 -> 0
A76: 3 | B76: Guard II | E76: 0 | F76: 0 | H76: =+E76*F76 -> 0
A77: 4 | B77: Guard II | E77: 0 | F77: 0 | H77: =+E77*F77 -> 0
A78: 5 | B78: Guard II | E78: 0 | F78: 0 | H78: =+E78*F78 -> 0
A79: 6 | B79: Guard II | E79: 0 | F79: 0 | H79: =+E79*F79 -> 0
A80: 7 | B80: Guard II | E80: 0 | F80: 0 | H80: =+E80*F80 -> 0
A81: 8 | B81: Guard II | E81: 0 | F81: 0 | H81: =+E81*F81 -> 0
A82: 9 | B82: Guard II | E82: 0 | F82: 0 | H82: =+E82*F82 -> 0
A83: 10 | B83: Guard II | E83: 0 | F83: 0 | H83: =+E83*F83 -> 0
A84: 11 | B84: Guard II | E84: 0 | F84: 0 | H84: =+E84*F84 -> 0
A85: 12 | B85: Guard II | E85: 0 | F85: 0 | H85: =+E85*F85 -> 0
B86: Total | E86: =SUM(E74:E85) -> 0 | H86: =SUM(H74:H85) -> 0 | I86: =+H86/E86 -> #DIV/0! | K86: =+I86*1.5 -> #DIV/0!
B88: Health and Welfare | F88: 0 | H88: =+E86*F88 -> 0
H89: =+H86+H88 -> 0
A91: EMPLOYEE BENEFIT: | E91: FRINGE RATE
B93: Social Security | E93: 0.062 | G93: =+$E93*$H89 -> 0
B94: Medicare | E94: 0.0145 | G94: =+$E94*$H89 -> 0
B95: SUTA | E95: 0 | G95: =+$E95*$H89 -> 0
B96: FUTA | E96: 0 | G96: =+$E96*$H89 -> 0 | H96: Sum of Payroll Taxes | I96: W/ Payroll Taxes
B97: Workman's Comp /General Liability Insurance | E97: 0 | G97: =+$E97*$H89 -> 0 | H97: =SUM(E93:E97) -> 0.0765 | I97: =+H97*I86+I86 -> #DIV/0!
A98: CBA | B98: Sick Leave (Full Time) | C98: 0 | D98: 0 | E98: =+D98*C98 -> 0 | G98: =+E98*I97 -> #DIV/0!
A99: CBA | B99: Sick Leave (Part Time) | C99: 0 | D99: 0 | E99: =+D99*C99 -> 0 | G99: =+E99*I97 -> #DIV/0!
A100: CBA | B100: Holiday (Based on 11 Days) | C100: 0 | D100: 0 | E100: =+C100*D100 -> 0 | G100: =+E100*I97 -> #DIV/0!
A101: CBA | B101: Vacation (Based on 10 Days) | C101: 0 | D101: 0 | E101: =+C101*D101 -> 0 | G101: =+E101*I97 -> #DIV/0!
A102: CBA | B102: Vacation (Based on 17.5 Days) | C102: 0 | D102: 0 | E102: =+D102*C102 -> 0 | G102: =+E102*I97 -> #DIV/0!
A103: CBA | B103: Vacation (Based on 22.5 Days) | C103: 0 | D103: 0 | E103: =+D103*C103 -> 0 | G103: =+E103*I97 -> #DIV/0!
B104: Health and Welfare for Sick/Holiday/Vacation Hours | E104: =SUM(E98:E103) -> 0 | F104: 0 | G104: =E104*F104 -> 0 | H104: =SUM(G93:G104) -> #DIV/0! | I104: =(H104+H88)/H86 -> #DIV/0! | K104: =K86*I104 -> #DIV/0!
H105: =+H104+H89 -> #DIV/0!
A109: OVERHEAD EXPENSE | D109: 0 | H109: =+H105*D109 -> #DIV/0! | I109: =+H109/H105 -> #DIV/0! | K109: =+(K86+K104)*I109 -> #DIV/0!
A111: OTHER DIRECT COSTS (ODC):
B112: Uniforms @ | C112: 0 | D112: 0 | E112: 0 | G112: =+(C112*D112*E112) -> 0
B113: Boot Allowance | C113: 0 | D113: 0 | E113: 0 | G113: =+(C113*D113*E113) -> 0
B114: Ammo | C114: 0 | D114: 0 | E114: 0 | G114: =+(C114*D114*E114) -> 0
B115: Duty Gear | C115: 0 | D115: 0 | E115: 0 | G115: =+(C115*D115*E115) -> 0
B116: Weapons | C116: 0 | D116: 0 | E116: 0 | G116: =+(C116*D116*E116) -> 0
B117: Medical /Drug Screening / Physicals | C117: 0 | D117: 0 | E117: 0 | G117: =+(C117*D117*E117) -> 0
B118: Professional Licenses | C118: 0 | D118: 0 | E118: 0 | G118: =+(C118*D118*E118) -> 0
B119: Training - Nonrecurring | C119: 0 | D119: 0 | E119: 0 | G119: =+(C119*D119*E119) -> 0
B120: Training - Recurring Annual | C120: 0 | D120: 0 | E120: 0 | G120: =+(C120*D120*E120) -> 0
B121: Shooting Range Qualification / Requal | C121: 0 | D121: 0 | E121: 0 | G121: =+(C121*D121*E121) -> 0
...

Sheet ORD ATCT Rate Build Up
A2: {=MID(CELL("filename", A1), FIND("]", CELL("filename", A1)) + 1, LEN(CELL("filename", A1)) - FIND("]", CELL("filename", A1)))} -> ORD ATCT Rate Build Up | F2: Base Period | K2: ESS
F3: CBA
A4: =_BasePeriod -> 9/30/2026-9/29/2027
A5: DIRECT LABOR (DL): | E5: HOURS | F5: Rate | H5: TOTAL
A6: 1 | B6: Captain | E6: 0 | F6: 0 | H6: =+E6*F6 -> 0
A7: 2 | B7: Guard II | E7: 0 | F7: 0 | H7: =+E7*F7 -> 0
A8: 3 | B8: Guard II | E8: 0 | F8: 0 | H8: =+E8*F8 -> 0
A9: 4 | B9: Guard II | E9: 0 | F9: 0 | H9: =+E9*F9 -> 0
A10: 5 | B10: Guard II | E10: 0 | F10: 0 | H10: =+E10*F10 -> 0
A11: 6 | B11: Guard II | E11: 0 | F11: 0 | H11: =+E11*F11 -> 0
A12: 7 | B12: Guard II | E12: 0 | F12: 0 | H12: =+E12*F12 -> 0
A13: 8 | B13: Guard II | E13: 0 | F13: 0 | H13: =+E13*F13 -> 0
A14: 9 | B14: Guard II | E14: 0 | F14: 0 | H14: =+E14*F14 -> 0
A15: 10 | B15: Guard II | E15: 0 | F15: 0 | H15: =+E15*F15 -> 0
A16: 11 | B16: Guard II | E16: 0 | F16: 0 | H16: =+E16*F16 -> 0
A17: 12 | B17: Guard II | E17: 0 | F17: 0 | H17: =+E17*F17 -> 0
B18: Total | E18: =SUM(E6:E17) -> 0 | H18: =SUM(H6:H17) -> 0 | I18: =+H18/E18 -> #DIV/0! | K18: =+I18*1.5 -> #DIV/0!
B20: Health and Welfare | F20: 0 | H20: =+E18*F20 -> 0
H21: =+H18+H20 -> 0
A23: EMPLOYEE BENEFIT: | E23: FRINGE RATE
B25: Social Security | E25: 0.062 | G25: =+$E25*$H21 -> 0
B26: Medicare | E26: 0.0145 | G26: =+$E26*$H21 -> 0
B27: SUTA | E27: 0 | G27: =+$E27*$H21 -> 0
B28: FUTA | E28: 0 | G28: =+$E28*$H21 -> 0 | H28: Sum of Payroll Taxes | I28: W/ Payroll Taxes
B29: Workman's Comp /General Liability Insurance | E29: 0 | G29: =+$E29*$H21 -> 0 | H29: =SUM(E25:E29) -> 0.0765 | I29: =+H29*I18+I18 -> #DIV/0!
A30: CBA | B30: Sick Leave (Full Time) | C30: 0 | D30: 0 | E30: =+D30*C30 -> 0 | G30: =+E30*I29 -> #DIV/0!
A31: CBA | B31: Sick Leave (Part Time) | C31: 0 | D31: 0 | E31: =+D31*C31 -> 0 | G31: =+E31*I29 -> #DIV/0!
A32: CBA | B32: Holiday (Based on 11 Days) | C32: 0 | D32: 0 | E32: =+C32*D32 -> 0 | G32: =+E32*I29 -> #DIV/0!
A33: CBA | B33: Vacation (Based on 10 Days) | C33: 0 | D33: 0 | E33: =+C33*D33 -> 0 | G33: =+E33*I29 -> #DIV/0!
A34: CBA | B34: Vacation (Based on 17.5 Days) | C34: 0 | D34: 0 | E34: =+D34*C34 -> 0 | G34: =+E34*I29 -> #DIV/0!
A35: CBA | B35: Vacation (Based on 22.5 Days) | C35: 0 | D35: 0 | E35: =+D35*C35 -> 0 | G35: =+E35*I29 -> #DIV/0!
B36: Health and Welfare for Sick/Holiday/Vacation Hours | E36: =SUM(E30:E35) -> 0 | F36: 0 | G36: =E36*F36 -> 0 | H36: =SUM(G25:G36) -> #DIV/0! | I36: =(H36+H20)/H18 -> #DIV/0! | K36: =K18*I36 -> #DIV/0!
H37: =+H36+H21 -> #DIV/0!
A41: OVERHEAD EXPENSE | D41: 0 | H41: =+H37*D41 -> #DIV/0! | I41: =+H41/H37 -> #DIV/0! | K41: =+(K18+K36)*I41 -> #DIV/0!
A43: OTHER DIRECT COSTS (ODC):
B44: Uniforms @ | C44: 0 | D44: 0 | E44: 0 | G44: =+(C44*D44*E44) -> 0
B45: Boot Allowance | C45: 0 | D45: 0 | E45: 0 | G45: =+(C45*D45*E45) -> 0
B46: Ammo | C46: 0 | D46: 0 | E46: 0 | G46: =+(C46*D46*E46) -> 0
B47: Duty Gear | C47: 0 | D47: 0 | E47: 0 | G47: =+(C47*D47*E47) -> 0
B48: Weapons | C48: 0 | D48: 0 | E48: 0 | G48: =+(C48*D48*E48) -> 0
B49: Medical /Drug Screening / Physicals | C49: 0 | D49: 0 | E49: 0 | G49: =+(C49*D49*E49) -> 0
B50: Professional Licenses | C50: 0 | D50: 0 | E50: 0 | G50: =+(C50*D50*E50) -> 0
B51: Training - Nonrecurring | C51: 0 | D51: 0 | E51: 0 | G51: =+(C51*D51*E51) -> 0
B52: Training - Recurring Annual | C52: 0 | D52: 0 | E52: 0 | G52: =+(C52*D52*E52) -> 0
B53: Shooting Range Qualification / Requal | C53: 0 | D53: 0 | E53: 0 | G53: =+(C53*D53*E53) -> 0
B54: Travel | C54: 0 | D54: 0 | E54: 0 | G54: =+(C54*D54*E54) -> 0 | H54: =SUM(G44:G54) -> 0 | K54: =SUM(K18:K53) -> #DIV/0!
C55: SUBTOTAL | H55: =SUM(H37:H54) -> #DIV/0!
A57: G&A EXPENSE | D57: 0 | H57: =+H55*D57 -> #DIV/0! | I57: =D57 -> 0 | K57: =+K54*I57 -> #DIV/0!
D58: SUBTOTAL G&A/WC/DL | K58: =SUM(K54:K57) -> #DIV/0!
A60: PROFIT | D60: 0 | H60: =(H55+H57)*D60 -> #DIV/0!
D61: SUBTOTAL COST AND PROFIT | H61: =SUM(H55:H60) -> #DIV/0! | I61: =D60 -> 0 | K61: =+K58*I61 -> #DIV/0!
A64: STATE TAXES | D64: 0 | H64: =+H61*D64 -> #DIV/0!
F66: ANNUAL TOTAL | H66: =SUM(H61:H64) -> #DIV/0!
F67: MONTHLY RATE | H67: =+H66/12 -> #DIV/0!
B68: TAS/OTHER SERVICES/TRAINING/RANDOM SCREENING/ROVING PATROL | F68: HOURLY PRICE | H68: =+H66/(E18) -> #DIV/0! | K68: =SUM(K58:K67) -> #DIV/0!
A70: =$A$2 -> ORD ATCT Rate Build Up | F70: Option Period 1 | K70: ESS
F71: CBA
A72: =_OP1 -> 9/30/2027-9/29/2028
A73: DIRECT LABOR (DL): | E73: HOURS | F73: Rate | H73: TOTAL
A74: 1 | B74: Captain | E74: 0 | F74: 0 | H74: =+E74*F74 -> 0
A75: 2 | B75: Guard II | E75: 0 | F75: 0 | H75: =+E75*F75 -> 0
A76: 3 | B76: Guard II | E76: 0 | F76: 0 | H76: =+E76*F76 -> 0
A77: 4 | B77: Guard II | E77: 0 | F77: 0 | H77: =+E77*F77 -> 0
A78: 5 | B78: Guard II | E78: 0 | F78: 0 | H78: =+E78*F78 -> 0
A79: 6 | B79: Guard II | E79: 0 | F79: 0 | H79: =+E79*F79 -> 0
A80: 7 | B80: Guard II | E80: 0 | F80: 0 | H80: =+E80*F80 -> 0
A81: 8 | B81: Guard II | E81: 0 | F81: 0 | H81: =+E81*F81 -> 0
A82: 9 | B82: Guard II | E82: 0 | F82: 0 | H82: =+E82*F82 -> 0
A83: 10 | B83: Guard II | E83: 0 | F83: 0 | H83: =+E83*F83 -> 0
A84: 11 | B84: Guard II | E84: 0 | F84: 0 | H84: =+E84*F84 -> 0
A85: 12 | B85: Guard II | E85: 0 | F85: 0 | H85: =+E85*F85 -> 0
B86: Total | E86: =SUM(E74:E85) -> 0 | H86: =SUM(H74:H85) -> 0 | I86: =+H86/E86 -> #DIV/0! | K86: =+I86*1.5 -> #DIV/0!
B88: Health and Welfare | F88: 0 | H88: =+E86*F88 -> 0
H89: =+H86+H88 -> 0
A91: EMPLOYEE BENEFIT: | E91: FRINGE RATE
B93: Social Security | E93: 0.062 | G93: =+$E93*$H89 -> 0
B94: Medicare | E94: 0.0145 | G94: =+$E94*$H89 -> 0
B95: SUTA | E95: 0 | G95: =+$E95*$H89 -> 0
B96: FUTA | E96: 0 | G96: =+$E96*$H89 -> 0 | H96: Sum of Payroll Taxes | I96: W/ Payroll Taxes
B97: Workman's Comp /General Liability Insurance | E97: 0 | G97: =+$E97*$H89 -> 0 | H97: =SUM(E93:E97) -> 0.0765 | I97: =+H97*I86+I86 -> #DIV/0!
A98: CBA | B98: Sick Leave (Full Time) | C98: 0 | D98: 0 | E98: =+D98*C98 -> 0 | G98: =+E98*I97 -> #DIV/0!
A99: CBA | B99: Sick Leave (Part Time) | C99: 0 | D99: 0 | E99: =+D99*C99 -> 0 | G99: =+E99*I97 -> #DIV/0!
A100: CBA | B100: Holiday (Based on 11 Days) | C100: 0 | D100: 0 | E100: =+C100*D100 -> 0 | G100: =+E100*I97 -> #DIV/0!
A101: CBA | B101: Vacation (Based on 10 Days) | C101: 0 | D101: 0 | E101: =+C101*D101 -> 0 | G101: =+E101*I97 -> #DIV/0!
A102: CBA | B102: Vacation (Based on 17.5 Days) | C102: 0 | D102: 0 | E102: =+D102*C102 -> 0 | G102: =+E102*I97 -> #DIV/0!
A103: CBA | B103: Vacation (Based on 22.5 Days) | C103: 0 | D103: 0 | E103: =+D103*C103 -> 0 | G103: =+E103*I97 -> #DIV/0!
B104: Health and Welfare for Sick/Holiday/Vacation Hours | E104: =SUM(E98:E103) -> 0 | F104: 0 | G104: =E104*F104 -> 0 | H104: =SUM(G93:G104) -> #DIV/0! | I104: =(H104+H88)/H86 -> #DIV/0! | K104: =K86*I104 -> #DIV/0!
H105: =+H104+H89 -> #DIV/0!
A109: OVERHEAD EXPENSE | D109: 0 | H109: =+H105*D109 -> #DIV/0! | I109: =+H109/H105 -> #DIV/0! | K109: =+(K86+K104)*I109 -> #DIV/0!
A111: OTHER DIRECT COSTS (ODC):
B112: Uniforms @ | C112: 0 | D112: 0 | E112: 0 | G112: =+(C112*D112*E112) -> 0
B113: Boot Allowance | C113: 0 | D113: 0 | E113: 0 | G113: =+(C113*D113*E113) -> 0
B114: Ammo | C114: 0 | D114: 0 | E114: 0 | G114: =+(C114*D114*E114) -> 0
B115: Duty Gear | C115: 0 | D115: 0 | E115: 0 | G115: =+(C115*D115*E115) -> 0
B116: Weapons | C116: 0 | D116: 0 | E116: 0 | G116: =+(C116*D116*E116) -> 0
B117: Medical /Drug Screening / Physicals | C117: 0 | D117: 0 | E117: 0 | G117: =+(C117*D117*E117) -> 0
B118: Professional Licenses | C118: 0 | D118: 0 | E118: 0 | G118: =+(C118*D118*E118) -> 0
B119: Training - Nonrecurring | C119: 0 | D119: 0 | E119: 0 | G119: =+(C119*D119*E119) -> 0
B120: Training - Recurring Annual | C120: 0 | D120: 0 | E120: 0 | G120: =+(C120*D120*E120) -> 0
B121: Shooting Range Qualification / Requal | C121: 0 | D121: 0 | E121: 0 | G121: =+(C121*D121*E121) -> 0
...

Sheet ZAB ARTCC Rate Build Up
A2: {=MID(CELL("filename", A1), FIND("]", CELL("filename", A1)) + 1, LEN(CELL("filename", A1)) - FIND("]", CELL("filename", A1)))} -> ZAB ARTCC Rate Build Up | F2: Base Period | K2: ESS
F3: CBA
A4: =_BasePeriod -> 9/30/2026-9/29/2027
A5: DIRECT LABOR (DL): | E5: HOURS | F5: Rate | H5: TOTAL
A6: 1 | B6: Captain | E6: 0 | F6: 0 | H6: =+E6*F6 -> 0
A7: 2 | B7: Guard II | E7: 0 | F7: 0 | H7: =+E7*F7 -> 0
A8: 3 | B8: Guard II | E8: 0 | F8: 0 | H8: =+E8*F8 -> 0
A9: 4 | B9: Guard II | E9: 0 | F9: 0 | H9: =+E9*F9 -> 0
A10: 5 | B10: Guard II | E10: 0 | F10: 0 | H10: =+E10*F10 -> 0
A11: 6 | B11: Guard II | E11: 0 | F11: 0 | H11: =+E11*F11 -> 0
A12: 7 | B12: Guard II | E12: 0 | F12: 0 | H12: =+E12*F12 -> 0
A13: 8 | B13: Guard II | E13: 0 | F13: 0 | H13: =+E13*F13 -> 0
A14: 9 | B14: Guard II | E14: 0 | F14: 0 | H14: =+E14*F14 -> 0
A15: 10 | B15: Guard II | E15: 0 | F15: 0 | H15: =+E15*F15 -> 0
A16: 11 | B16: Guard II | E16: 0 | F16: 0 | H16: =+E16*F16 -> 0
A17: 12 | B17: Guard II | E17: 0 | F17: 0 | H17: =+E17*F17 -> 0
B18: Total | E18: =SUM(E6:E17) -> 0 | H18: =SUM(H6:H17) -> 0 | I18: =+H18/E18 -> #DIV/0! | K18: =+I18*1.5 -> #DIV/0!
B20: Health and Welfare | F20: 0 | H20: =+E18*F20 -> 0
H21: =+H18+H20 -> 0
A23: EMPLOYEE BENEFIT: | E23: FRINGE RATE
B25: Social Security | E25: 0.062 | G25: =+$E25*$H21 -> 0
B26: Medicare | E26: 0.0145 | G26: =+$E26*$H21 -> 0
B27: SUTA | E27: 0 | G27: =+$E27*$H21 -> 0
B28: FUTA | E28: 0 | G28: =+$E28*$H21 -> 0 | H28: Sum of Payroll Taxes | I28: W/ Payroll Taxes
B29: Workman's Comp /General Liability Insurance | E29: 0 | G29: =+$E29*$H21 -> 0 | H29: =SUM(E25:E29) -> 0.0765 | I29: =+H29*I18+I18 -> #DIV/0!
A30: CBA | B30: Sick Leave (Full Time) | C30: 0 | D30: 0 | E30: =+D30*C30 -> 0 | G30: =+E30*I29 -> #DIV/0!
A31: CBA | B31: Sick Leave (Part Time) | C31: 0 | D31: 0 | E31: =+D31*C31 -> 0 | G31: =+E31*I29 -> #DIV/0!
A32: CBA | B32: Holiday (Based on 11 Days) | C32: 0 | D32: 0 | E32: =+C32*D32 -> 0 | G32: =+E32*I29 -> #DIV/0!
A33: CBA | B33: Vacation (Based on 10 Days) | C33: 0 | D33: 0 | E33: =+C33*D33 -> 0 | G33: =+E33*I29 -> #DIV/0!
A34: CBA | B34: Vacation (Based on 17.5 Days) | C34: 0 | D34: 0 | E34: =+D34*C34 -> 0 | G34: =+E34*I29 -> #DIV/0!
A35: CBA | B35: Vacation (Based on 22.5 Days) | C35: 0 | D35: 0 | E35: =+D35*C35 -> 0 | G35: =+E35*I29 -> #DIV/0!
B36: Health and Welfare for Sick/Holiday/Vacation Hours | E36: =SUM(E30:E35) -> 0 | F36: 0 | G36: =E36*F36 -> 0 | H36: =SUM(G25:G36) -> #DIV/0! | I36: =(H36+H20)/H18 -> #DIV/0! | K36: =K18*I36 -> #DIV/0!
H37: =+H36+H21 -> #DIV/0!
A41: OVERHEAD EXPENSE | D41: 0 | H41: =+H37*D41 -> #DIV/0! | I41: =+H41/H37 -> #DIV/0! | K41: =+(K18+K36)*I41 -> #DIV/0!
A43: OTHER DIRECT COSTS (ODC):
B44: Uniforms @ | C44: 0 | D44: 0 | E44: 0 | G44: =+(C44*D44*E44) -> 0
B45: Boot Allowance | C45: 0 | D45: 0 | E45: 0 | G45: =+(C45*D45*E45) -> 0
B46: Ammo | C46: 0 | D46: 0 | E46: 0 | G46: =+(C46*D46*E46) -> 0
B47: Duty Gear | C47: 0 | D47: 0 | E47: 0 | G47: =+(C47*D47*E47) -> 0
B48: Weapons | C48: 0 | D48: 0 | E48: 0 | G48: =+(C48*D48*E48) -> 0
B49: Medical /Drug Screening / Physicals | C49: 0 | D49: 0 | E49: 0 | G49: =+(C49*D49*E49) -> 0
B50: Professional Licenses | C50: 0 | D50: 0 | E50: 0 | G50: =+(C50*D50*E50) -> 0
B51: Training - Nonrecurring | C51: 0 | D51: 0 | E51: 0 | G51: =+(C51*D51*E51) -> 0
B52: Training - Recurring Annual | C52: 0 | D52: 0 | E52: 0 | G52: =+(C52*D52*E52) -> 0
B53: Shooting Range Qualification / Requal | C53: 0 | D53: 0 | E53: 0 | G53: =+(C53*D53*E53) -> 0
B54: Travel | C54: 0 | D54: 0 | E54: 0 | G54: =+(C54*D54*E54) -> 0 | H54: =SUM(G44:G54) -> 0 | K54: =SUM(K18:K53) -> #DIV/0!
C55: SUBTOTAL | H55: =SUM(H37:H54) -> #DIV/0!
A57: G&A EXPENSE | D57: 0 | H57: =+H55*D57 -> #DIV/0! | I57: =D57 -> 0 | K57: =+K54*I57 -> #DIV/0!
D58: SUBTOTAL G&A/WC/DL | K58: =SUM(K54:K57) -> #DIV/0!
A60: PROFIT | D60: 0 | H60: =(H55+H57)*D60 -> #DIV/0!
D61: SUBTOTAL COST AND PROFIT | H61: =SUM(H55:H60) -> #DIV/0! | I61: =D60 -> 0 | K61: =+K58*I61 -> #DIV/0!
A64: STATE TAXES | D64: 0 | H64: =+H61*D64 -> #DIV/0!
F66: ANNUAL TOTAL | H66: =SUM(H61:H64) -> #DIV/0!
F67: MONTHLY RATE | H67: =+H66/12 -> #DIV/0!
B68: TAS/OTHER SERVICES/TRAINING/RANDOM SCREENING/ROVING PATROL | F68: HOURLY PRICE | H68: =+H66/(E18) -> #DIV/0! | K68: =SUM(K58:K67) -> #DIV/0!
A70: =$A$2 -> ZAB ARTCC Rate Build Up | F70: Option Period 1 | K70: ESS
F71: CBA
A72: =_OP1 -> 9/30/2027-9/29/2028
A73: DIRECT LABOR (DL): | E73: HOURS | F73: Rate | H73: TOTAL
A74: 1 | B74: Captain | E74: 0 | F74: 0 | H74: =+E74*F74 -> 0
A75: 2 | B75: Guard II | E75: 0 | F75: 0 | H75: =+E75*F75 -> 0
A76: 3 | B76: Guard II | E76: 0 | F76: 0 | H76: =+E76*F76 -> 0
A77: 4 | B77: Guard II | E77: 0 | F77: 0 | H77: =+E77*F77 -> 0
A78: 5 | B78: Guard II | E78: 0 | F78: 0 | H78: =+E78*F78 -> 0
A79: 6 | B79: Guard II | E79: 0 | F79: 0 | H79: =+E79*F79 -> 0
A80: 7 | B80: Guard II | E80: 0 | F80: 0 | H80: =+E80*F80 -> 0
A81: 8 | B81: Guard II | E81: 0 | F81: 0 | H81: =+E81*F81 -> 0
A82: 9 | B82: Guard II | E82: 0 | F82: 0 | H82: =+E82*F82 -> 0
A83: 10 | B83: Guard II | E83: 0 | F83: 0 | H83: =+E83*F83 -> 0
A84: 11 | B84: Guard II | E84: 0 | F84: 0 | H84: =+E84*F84 -> 0
A85: 12 | B85: Guard II | E85: 0 | F85: 0 | H85: =+E85*F85 -> 0
B86: Total | E86: =SUM(E74:E85) -> 0 | H86: =SUM(H74:H85) -> 0 | I86: =+H86/E86 -> #DIV/0! | K86: =+I86*1.5 -> #DIV/0!
B88: Health and Welfare | F88: 0 | H88: =+E86*F88 -> 0
H89: =+H86+H88 -> 0
A91: EMPLOYEE BENEFIT: | E91: FRINGE RATE
B93: Social Security | E93: 0.062 | G93: =+$E93*$H89 -> 0
B94: Medicare | E94: 0.0145 | G94: =+$E94*$H89 -> 0
B95: SUTA | E95: 0 | G95: =+$E95*$H89 -> 0
B96: FUTA | E96: 0 | G96: =+$E96*$H89 -> 0 | H96: Sum of Payroll Taxes | I96: W/ Payroll Taxes
B97: Workman's Comp /General Liability Insurance | E97: 0 | G97: =+$E97*$H89 -> 0 | H97: =SUM(E93:E97) -> 0.0765 | I97: =+H97*I86+I86 -> #DIV/0!
A98: CBA | B98: Sick Leave (Full Time) | C98: 0 | D98: 0 | E98: =+D98*C98 -> 0 | G98: =+E98*I97 -> #DIV/0!
A99: CBA | B99: Sick Leave (Part Time) | C99: 0 | D99: 0 | E99: =+D99*C99 -> 0 | G99: =+E99*I97 -> #DIV/0!
A100: CBA | B100: Holiday (Based on 11 Days) | C100: 0 | D100: 0 | E100: =+C100*D100 -> 0 | G100: =+E100*I97 -> #DIV/0!
A101: CBA | B101: Vacation (Based on 10 Days) | C101: 0 | D101: 0 | E101: =+C101*D101 -> 0 | G101: =+E101*I97 -> #DIV/0!
A102: CBA | B102: Vacation (Based on 17.5 Days) | C102: 0 | D102: 0 | E102: =+D102*C102 -> 0 | G102: =+E102*I97 -> #DIV/0!
A103: CBA | B103: Vacation (Based on 22.5 Days) | C103: 0 | D103: 0 | E103: =+D103*C103 -> 0 | G103: =+E103*I97 -> #DIV/0!
B104: Health and Welfare for Sick/Holiday/Vacation Hours | E104: =SUM(E98:E103) -> 0 | F104: 0 | G104: =E104*F104 -> 0 | H104: =SUM(G93:G104) -> #DIV/0! | I104: =(H104+H88)/H86 -> #DIV/0! | K104: =K86*I104 -> #DIV/0!
H105: =+H104+H89 -> #DIV/0!
A109: OVERHEAD EXPENSE | D109: 0 | H109: =+H105*D109 -> #DIV/0! | I109: =+H109/H105 -> #DIV/0! | K109: =+(K86+K104)*I109 -> #DIV/0!
A111: OTHER DIRECT COSTS (ODC):
B112: Uniforms @ | C112: 0 | D112: 0 | E112: 0 | G112: =+(C112*D112*E112) -> 0
B113: Boot Allowance | C113: 0 | D113: 0 | E113: 0 | G113: =+(C113*D113*E113) -> 0
B114: Ammo | C114: 0 | D114: 0 | E114: 0 | G114: =+(C114*D114*E114) -> 0
B115: Duty Gear | C115: 0 | D115: 0 | E115: 0 | G115: =+(C115*D115*E115) -> 0
B116: Weapons | C116: 0 | D116: 0 | E116: 0 | G116: =+(C116*D116*E116) -> 0
B117: Medical /Drug Screening / Physicals | C117: 0 | D117: 0 | E117: 0 | G117: =+(C117*D117*E117) -> 0
B118: Professional Licenses | C118: 0 | D118: 0 | E118: 0 | G118: =+(C118*D118*E118) -> 0
B119: Training - Nonrecurring | C119: 0 | D119: 0 | E119: 0 | G119: =+(C119*D119*E119) -> 0
B120: Training - Recurring Annual | C120: 0 | D120: 0 | E120: 0 | G120: =+(C120*D120*E120) -> 0
B121: Shooting Range Qualification / Requal | C121: 0 | D121: 0 | E121: 0 | G121: =+(C121*D121*E121) -> 0
...

Sheet ZAU Rate Build Up
A2: {=MID(CELL("filename", A1), FIND("]", CELL("filename", A1)) + 1, LEN(CELL("filename", A1)) - FIND("]", CELL("filename", A1)))} -> ZAU Rate Build Up | F2: Base Period | K2: ESS
F3: CBA
A4: =_BasePeriod -> 9/30/2026-9/29/2027
A5: DIRECT LABOR (DL): | E5: HOURS | F5: Rate | H5: TOTAL
A6: 1 | B6: Captain | E6: 0 | F6: 0 | H6: =+E6*F6 -> 0
A7: 2 | B7: Guard II | E7: 0 | F7: 0 | H7: =+E7*F7 -> 0
A8: 3 | B8: Guard II | E8: 0 | F8: 0 | H8: =+E8*F8 -> 0
A9: 4 | B9: Guard II | E9: 0 | F9: 0 | H9: =+E9*F9 -> 0
A10: 5 | B10: Guard II | E10: 0 | F10: 0 | H10: =+E10*F10 -> 0
A11: 6 | B11: Guard II | E11: 0 | F11: 0 | H11: =+E11*F11 -> 0
A12: 7 | B12: Guard II | E12: 0 | F12: 0 | H12: =+E12*F12 -> 0
A13: 8 | B13: Guard II | E13: 0 | F13: 0 | H13: =+E13*F13 -> 0
A14: 9 | B14: Guard II | E14: 0 | F14: 0 | H14: =+E14*F14 -> 0
A15: 10 | B15: Guard II | E15: 0 | F15: 0 | H15: =+E15*F15 -> 0
A16: 11 | B16: Guard II | E16: 0 | F16: 0 | H16: =+E16*F16 -> 0
A17: 12 | B17: Guard II | E17: 0 | F17: 0 | H17: =+E17*F17 -> 0
B18: Total | E18: =SUM(E6:E17) -> 0 | H18: =SUM(H6:H17) -> 0 | I18: =+H18/E18 -> #DIV/0! | K18: =+I18*1.5 -> #DIV/0!
B20: Health and Welfare | F20: 0 | H20: =+E18*F20 -> 0
H21: =+H18+H20 -> 0
A23: EMPLOYEE BENEFIT: | E23: FRINGE RATE
B25: Social Security | E25: 0.062 | G25: =+$E25*$H21 -> 0
B26: Medicare | E26: 0.0145 | G26: =+$E26*$H21 -> 0
B27: SUTA | E27: 0 | G27: =+$E27*$H21 -> 0
B28: FUTA | E28: 0 | G28: =+$E28*$H21 -> 0 | H28: Sum of Payroll Taxes | I28: W/ Payroll Taxes
B29: Workman's Comp /General Liability Insurance | E29: 0 | G29: =+$E29*$H21 -> 0 | H29: =SUM(E25:E29) -> 0.0765 | I29: =+H29*I18+I18 -> #DIV/0!
A30: CBA | B30: Sick Leave (Full Time) | C30: 0 | D30: 0 | E30: =+D30*C30 -> 0 | G30: =+E30*I29 -> #DIV/0!
A31: CBA | B31: Sick Leave (Part Time) | C31: 0 | D31: 0 | E31: =+D31*C31 -> 0 | G31: =+E31*I29 -> #DIV/0!
A32: CBA | B32: Holiday (Based on 11 Days) | C32: 0 | D32: 0 | E32: =+C32*D32 -> 0 | G32: =+E32*I29 -> #DIV/0!
A33: CBA | B33: Vacation (Based on 10 Days) | C33: 0 | D33: 0 | E33: =+C33*D33 -> 0 | G33: =+E33*I29 -> #DIV/0!
A34: CBA | B34: Vacation (Based on 17.5 Days) | C34: 0 | D34: 0 | E34: =+D34*C34 -> 0 | G34: =+E34*I29 -> #DIV/0!
A35: CBA | B35: Vacation (Based on 22.5 Days) | C35: 0 | D35: 0 | E35: =+D35*C35 -> 0 | G35: =+E35*I29 -> #DIV/0!
B36: Health and Welfare for Sick/Holiday/Vacation Hours | E36: =SUM(E30:E35) -> 0 | F36: 0 | G36: =E36*F36 -> 0 | H36: =SUM(G25:G36) -> #DIV/0! | I36: =(H36+H20)/H18 -> #DIV/0! | K36: =K18*I36 -> #DIV/0!
H37: =+H36+H21 -> #DIV/0!
A41: OVERHEAD EXPENSE | D41: 0 | H41: =+H37*D41 -> #DIV/0! | I41: =+H41/H37 -> #DIV/0! | K41: =+(K18+K36)*I41 -> #DIV/0!
A43: OTHER DIRECT COSTS (ODC):
B44: Uniforms @ | C44: 0 | D44: 0 | E44: 0 | G44: =+(C44*D44*E44) -> 0
B45: Boot Allowance | C45: 0 | D45: 0 | E45: 0 | G45: =+(C45*D45*E45) -> 0
B46: Ammo | C46: 0 | D46: 0 | E46: 0 | G46: =+(C46*D46*E46) -> 0
B47: Duty Gear | C47: 0 | D47: 0 | E47: 0 | G47: =+(C47*D47*E47) -> 0
B48: Weapons | C48: 0 | D48: 0 | E48: 0 | G48: =+(C48*D48*E48) -> 0
B49: Medical /Drug Screening / Physicals | C49: 0 | D49: 0 | E49: 0 | G49: =+(C49*D49*E49) -> 0
B50: Professional Licenses | C50: 0 | D50: 0 | E50: 0 | G50: =+(C50*D50*E50) -> 0
B51: Training - Nonrecurring | C51: 0 | D51: 0 | E51: 0 | G51: =+(C51*D51*E51) -> 0
B52: Training - Recurring Annual | C52: 0 | D52: 0 | E52: 0 | G52: =+(C52*D52*E52) -> 0
B53: Shooting Range Qualification / Requal | C53: 0 | D53: 0 | E53: 0 | G53: =+(C53*D53*E53) -> 0
B54: Travel | C54: 0 | D54: 0 | E54: 0 | G54: =+(C54*D54*E54) -> 0 | H54: =SUM(G44:G54) -> 0 | K54: =SUM(K18:K53) -> #DIV/0!
C55: SUBTOTAL | H55: =SUM(H37:H54) -> #DIV/0!
A57: G&A EXPENSE | D57: 0 | H57: =+H55*D57 -> #DIV/0! | I57: =D57 -> 0 | K57: =+K54*I57 -> #DIV/0!
D58: SUBTOTAL G&A/WC/DL | K58: =SUM(K54:K57) -> #DIV/0!
A60: PROFIT | D60: 0 | H60: =(H55+H57)*D60 -> #DIV/0!
D61: SUBTOTAL COST AND PROFIT | H61: =SUM(H55:H60) -> #DIV/0! | I61: =D60 -> 0 | K61: =+K58*I61 -> #DIV/0!
A64: STATE TAXES | D64: 0 | H64: =+H61*D64 -> #DIV/0!
F66: ANNUAL TOTAL | H66: =SUM(H61:H64) -> #DIV/0!
F67: MONTHLY RATE | H67: =+H66/12 -> #DIV/0!
B68: TAS/OTHER SERVICES/TRAINING/RANDOM SCREENING/ROVING PATROL | F68: HOURLY PRICE | H68: =+H66/(E18) -> #DIV/0! | K68: =SUM(K58:K67) -> #DIV/0!
A70: =$A$2 -> ZAU Rate Build Up | F70: Option Period 1 | K70: ESS
F71: CBA
A72: =_OP1 -> 9/30/2027-9/29/2028
A73: DIRECT LABOR (DL): | E73: HOURS | F73: Rate | H73: TOTAL
A74: 1 | B74: Captain | E74: 0 | F74: 0 | H74: =+E74*F74 -> 0
A75: 2 | B75: Guard II | E75: 0 | F75: 0 | H75: =+E75*F75 -> 0
A76: 3 | B76: Guard II | E76: 0 | F76: 0 | H76: =+E76*F76 -> 0
A77: 4 | B77: Guard II | E77: 0 | F77: 0 | H77: =+E77*F77 -> 0
A78: 5 | B78: Guard II | E78: 0 | F78: 0 | H78: =+E78*F78 -> 0
A79: 6 | B79: Guard II | E79: 0 | F79: 0 | H79: =+E79*F79 -> 0
A80: 7 | B80: Guard II | E80: 0 | F80: 0 | H80: =+E80*F80 -> 0
A81: 8 | B81: Guard II | E81: 0 | F81: 0 | H81: =+E81*F81 -> 0
A82: 9 | B82: Guard II | E82: 0 | F82: 0 | H82: =+E82*F82 -> 0
A83: 10 | B83: Guard II | E83: 0 | F83: 0 | H83: =+E83*F83 -> 0
A84: 11 | B84: Guard II | E84: 0 | F84: 0 | H84: =+E84*F84 -> 0
A85: 12 | B85: Guard II | E85: 0 | F85: 0 | H85: =+E85*F85 -> 0
B86: Total | E86: =SUM(E74:E85) -> 0 | H86: =SUM(H74:H85) -> 0 | I86: =+H86/E86 -> #DIV/0! | K86: =+I86*1.5 -> #DIV/0!
B88: Health and Welfare | F88: 0 | H88: =+E86*F88 -> 0
H89: =+H86+H88 -> 0
A91: EMPLOYEE BENEFIT: | E91: FRINGE RATE
B93: Social Security | E93: 0.062 | G93: =+$E93*$H89 -> 0
B94: Medicare | E94: 0.0145 | G94: =+$E94*$H89 -> 0
B95: SUTA | E95: 0 | G95: =+$E95*$H89 -> 0
B96: FUTA | E96: 0 | G96: =+$E96*$H89 -> 0 | H96: Sum of Payroll Taxes | I96: W/ Payroll Taxes
B97: Workman's Comp /General Liability Insurance | E97: 0 | G97: =+$E97*$H89 -> 0 | H97: =SUM(E93:E97) -> 0.0765 | I97: =+H97*I86+I86 -> #DIV/0!
A98: CBA | B98: Sick Leave (Full Time) | C98: 0 | D98: 0 | E98: =+D98*C98 -> 0 | G98: =+E98*I97 -> #DIV/0!
A99: CBA | B99: Sick Leave (Part Time) | C99: 0 | D99: 0 | E99: =+D99*C99 -> 0 | G99: =+E99*I97 -> #DIV/0!
A100: CBA | B100: Holiday (Based on 11 Days) | C100: 0 | D100: 0 | E100: =+C100*D100 -> 0 | G100: =+E100*I97 -> #DIV/0!
A101: CBA | B101: Vacation (Based on 10 Days) | C101: 0 | D101: 0 | E101: =+C101*D101 -> 0 | G101: =+E101*I97 -> #DIV/0!
A102: CBA | B102: Vacation (Based on 17.5 Days) | C102: 0 | D102: 0 | E102: =+D102*C102 -> 0 | G102: =+E102*I97 -> #DIV/0!
A103: CBA | B103: Vacation (Based on 22.5 Days) | C103: 0 | D103: 0 | E103: =+D103*C103 -> 0 | G103: =+E103*I97 -> #DIV/0!
B104: Health and Welfare for Sick/Holiday/Vacation Hours | E104: =SUM(E98:E103) -> 0 | F104: 0 | G104: =E104*F104 -> 0 | H104: =SUM(G93:G104) -> #DIV/0! | I104: =(H104+H88)/H86 -> #DIV/0! | K104: =K86*I104 -> #DIV/0!
H105: =+H104+H89 -> #DIV/0!
A109: OVERHEAD EXPENSE | D109: 0 | H109: =+H105*D109 -> #DIV/0! | I109: =+H109/H105 -> #DIV/0! | K109: =+(K86+K104)*I109 -> #DIV/0!
A111: OTHER DIRECT COSTS (ODC):
B112: Uniforms @ | C112: 0 | D112: 0 | E112: 0 | G112: =+(C112*D112*E112) -> 0
B113: Boot Allowance | C113: 0 | D113: 0 | E113: 0 | G113: =+(C113*D113*E113) -> 0
B114: Ammo | C114: 0 | D114: 0 | E114: 0 | G114: =+(C114*D114*E114) -> 0
B115: Duty Gear | C115: 0 | D115: 0 | E115: 0 | G115: =+(C115*D115*E115) -> 0
B116: Weapons | C116: 0 | D116: 0 | E116: 0 | G116: =+(C116*D116*E116) -> 0
B117: Medical /Drug Screening / Physicals | C117: 0 | D117: 0 | E117: 0 | G117: =+(C117*D117*E117) -> 0
B118: Professional Licenses | C118: 0 | D118: 0 | E118: 0 | G118: =+(C118*D118*E118) -> 0
B119: Training - Nonrecurring | C119: 0 | D119: 0 | E119: 0 | G119: =+(C119*D119*E119) -> 0
B120: Training - Recurring Annual | C120: 0 | D120: 0 | E120: 0 | G120: =+(C120*D120*E120) -> 0
B121: Shooting Range Qualification / Requal | C121: 0 | D121: 0 | E121: 0 | G121: =+(C121*D121*E121) -> 0
...

Sheet ZFW Rate Build Up
A2: {=MID(CELL("filename", A1), FIND("]", CELL("filename", A1)) + 1, LEN(CELL("filename", A1)) - FIND("]", CELL("filename", A1)))} -> ZFW Rate Build Up | F2: Base Period | K2: ESS
F3: CBA
A4: =_BasePeriod -> 9/30/2026-9/29/2027
A5: DIRECT LABOR (DL): | E5: HOURS | F5: Rate | H5: TOTAL
A6: 1 | B6: Captain | E6: 0 | F6: 0 | H6: =+E6*F6 -> 0
A7: 2 | B7: Guard II | E7: 0 | F7: 0 | H7: =+E7*F7 -> 0
A8: 3 | B8: Guard II | E8: 0 | F8: 0 | H8: =+E8*F8 -> 0
A9: 4 | B9: Guard II | E9: 0 | F9: 0 | H9: =+E9*F9 -> 0
A10: 5 | B10: Guard II | E10: 0 | F10: 0 | H10: =+E10*F10 -> 0
A11: 6 | B11: Guard II | E11: 0 | F11: 0 | H11: =+E11*F11 -> 0
A12: 7 | B12: Guard II | E12: 0 | F12: 0 | H12: =+E12*F12 -> 0
A13: 8 | B13: Guard II | E13: 0 | F13: 0 | H13: =+E13*F13 -> 0
A14: 9 | B14: Guard II | E14: 0 | F14: 0 | H14: =+E14*F14 -> 0
A15: 10 | B15: Guard II | E15: 0 | F15: 0 | H15: =+E15*F15 -> 0
A16: 11 | B16: Guard II | E16: 0 | F16: 0 | H16: =+E16*F16 -> 0
A17: 12 | B17: Guard II | E17: 0 | F17: 0 | H17: =+E17*F17 -> 0
B18: Total | E18: =SUM(E6:E17) -> 0 | H18: =SUM(H6:H17) -> 0 | I18: =+H18/E18 -> #DIV/0! | K18: =+I18*1.5 -> #DIV/0!
B20: Health and Welfare | F20: 0 | H20: =+E18*F20 -> 0
H21: =+H18+H20 -> 0
A23: EMPLOYEE BENEFIT: | E23: FRINGE RATE
B25: Social Security | E25: 0.062 | G25: =+$E25*$H21 -> 0
B26: Medicare | E26: 0.0145 | G26: =+$E26*$H21 -> 0
B27: SUTA | E27: 0 | G27: =+$E27*$H21 -> 0
B28: FUTA | E28: 0 | G28: =+$E28*$H21 -> 0 | H28: Sum of Payroll Taxes | I28: W/ Payroll Taxes
B29: Workman's Comp /General Liability Insurance | E29: 0 | G29: =+$E29*$H21 -> 0 | H29: =SUM(E25:E29) -> 0.0765 | I29: =+H29*I18+I18 -> #DIV/0!
A30: CBA | B30: Sick Leave (Full Time) | C30: 0 | D30: 0 | E30: =+D30*C30 -> 0 | G30: =+E30*I29 -> #DIV/0!
A31: CBA | B31: Sick Leave (Part Time) | C31: 0 | D31: 0 | E31: =+D31*C31 -> 0 | G31: =+E31*I29 -> #DIV/0!
A32: CBA | B32: Holiday (Based on 11 Days) | C32: 0 | D32: 0 | E32: =+C32*D32 -> 0 | G32: =+E32*I29 -> #DIV/0!
A33: CBA | B33: Vacation (Based on 10 Days) | C33: 0 | D33: 0 | E33: =+C33*D33 -> 0 | G33: =+E33*I29 -> #DIV/0!
A34: CBA | B34: Vacation (Based on 17.5 Days) | C34: 0 | D34: 0 | E34: =+D34*C34 -> 0 | G34: =+E34*I29 -> #DIV/0!
A35: CBA | B35: Vacation (Based on 22.5 Days) | C35: 0 | D35: 0 | E35: =+D35*C35 -> 0 | G35: =+E35*I29 -> #DIV/0!
B36: Health and Welfare for Sick/Holiday/Vacation Hours | E36: =SUM(E30:E35) -> 0 | F36: 0 | G36: =E36*F36 -> 0 | H36: =SUM(G25:G36) -> #DIV/0! | I36: =(H36+H20)/H18 -> #DIV/0! | K36: =K18*I36 -> #DIV/0!
H37: =+H36+H21 -> #DIV/0!
A41: OVERHEAD EXPENSE | D41: 0 | H41: =+H37*D41 -> #DIV/0! | I41: =+H41/H37 -> #DIV/0! | K41: =+(K18+K36)*I41 -> #DIV/0!
A43: OTHER DIRECT COSTS (ODC):
B44: Uniforms @ | C44: 0 | D44: 0 | E44: 0 | G44: =+(C44*D44*E44) -> 0
B45: Boot Allowance | C45: 0 | D45: 0 | E45: 0 | G45: =+(C45*D45*E45) -> 0
B46: Ammo | C46: 0 | D46: 0 | E46: 0 | G46: =+(C46*D46*E46) -> 0
B47: Duty Gear | C47: 0 | D47: 0 | E47: 0 | G47: =+(C47*D47*E47) -> 0
B48: Weapons | C48: 0 | D48: 0 | E48: 0 | G48: =+(C48*D48*E48) -> 0
B49: Medical /Drug Screening / Physicals | C49: 0 | D49: 0 | E49: 0 | G49: =+(C49*D49*E49) -> 0
B50: Professional Licenses | C50: 0 | D50: 0 | E50: 0 | G50: =+(C50*D50*E50) -> 0
B51: Training - Nonrecurring | C51: 0 | D51: 0 | E51: 0 | G51: =+(C51*D51*E51) -> 0
B52: Training - Recurring Annual | C52: 0 | D52: 0 | E52: 0 | G52: =+(C52*D52*E52) -> 0
B53: Shooting Range Qualification / Requal | C53: 0 | D53: 0 | E53: 0 | G53: =+(C53*D53*E53) -> 0
B54: Travel | C54: 0 | D54: 0 | E54: 0 | G54: =+(C54*D54*E54) -> 0 | H54: =SUM(G44:G54) -> 0 | K54: =SUM(K18:K53) -> #DIV/0!
C55: SUBTOTAL | H55: =SUM(H37:H54) -> #DIV/0!
A57: G&A EXPENSE | D57: 0 | H57: =+H55*D57 -> #DIV/0! | I57: =D57 -> 0 | K57: =+K54*I57 -> #DIV/0!
D58: SUBTOTAL G&A/WC/DL | K58: =SUM(K54:K57) -> #DIV/0!
A60: PROFIT | D60: 0 | H60: =(H55+H57)*D60 -> #DIV/0!
D61: SUBTOTAL COST AND PROFIT | H61: =SUM(H55:H60) -> #DIV/0! | I61: =D60 -> 0 | K61: =+K58*I61 -> #DIV/0!
A64: STATE TAXES | D64: 0 | H64: =+H61*D64 -> #DIV/0!
F66: ANNUAL TOTAL | H66: =SUM(H61:H64) -> #DIV/0!
F67: MONTHLY RATE | H67: =+H66/12 -> #DIV/0!
B68: TAS/OTHER SERVICES/TRAINING/RANDOM SCREENING/ROVING PATROL | F68: HOURLY PRICE | H68: =+H66/(E18) -> #DIV/0! | K68: =SUM(K58:K67) -> #DIV/0!
A70: =$A$2 -> ZFW Rate Build Up | F70: Option Period 1 | K70: ESS
F71: CBA
A72: =_OP1 -> 9/30/2027-9/29/2028
A73: DIRECT LABOR (DL): | E73: HOURS | F73: Rate | H73: TOTAL
A74: 1 | B74: Captain | E74: 0 | F74: 0 | H74: =+E74*F74 -> 0
A75: 2 | B75: Guard II | E75: 0 | F75: 0 | H75: =+E75*F75 -> 0
A76: 3 | B76: Guard II | E76: 0 | F76: 0 | H76: =+E76*F76 -> 0
A77: 4 | B77: Guard II | E77: 0 | F77: 0 | H77: =+E77*F77 -> 0
A78: 5 | B78: Guard II | E78: 0 | F78: 0 | H78: =+E78*F78 -> 0
A79: 6 | B79: Guard II | E79: 0 | F79: 0 | H79: =+E79*F79 -> 0
A80: 7 | B80: Guard II | E80: 0 | F80: 0 | H80: =+E80*F80 -> 0
A81: 8 | B81: Guard II | E81: 0 | F81: 0 | H81: =+E81*F81 -> 0
A82: 9 | B82: Guard II | E82: 0 | F82: 0 | H82: =+E82*F82 -> 0
A83: 10 | B83: Guard II | E83: 0 | F83: 0 | H83: =+E83*F83 -> 0
A84: 11 | B84: Guard II | E84: 0 | F84: 0 | H84: =+E84*F84 -> 0
A85: 12 | B85: Guard II | E85: 0 | F85: 0 | H85: =+E85*F85 -> 0
B86: Total | E86: =SUM(E74:E85) -> 0 | H86: =SUM(H74:H85) -> 0 | I86: =+H86/E86 -> #DIV/0! | K86: =+I86*1.5 -> #DIV/0!
B88: Health and Welfare | F88: 5 | H88: =+E86*F88 -> 0
H89: =+H86+H88 -> 0
A91: EMPLOYEE BENEFIT: | E91: FRINGE RATE
B93: Social Security | E93: 0.062 | G93: =+$E93*$H89 -> 0
B94: Medicare | E94: 0.0145 | G94: =+$E94*$H89 -> 0
B95: SUTA | E95: 0 | G95: =+$E95*$H89 -> 0
B96: FUTA | E96: 0 | G96: =+$E96*$H89 -> 0 | H96: Sum of Payroll Taxes | I96: W/ Payroll Taxes
B97: Workman's Comp /General Liability Insurance | E97: 0 | G97: =+$E97*$H89 -> 0 | H97: =SUM(E93:E97) -> 0.0765 | I97: =+H97*I86+I86 -> #DIV/0!
A98: CBA | B98: Sick Leave (Full Time) | C98: 0 | D98: 0 | E98: =+D98*C98 -> 0 | G98: =+E98*I97 -> #DIV/0!
A99: CBA | B99: Sick Leave (Part Time) | C99: 0 | D99: 0 | E99: =+D99*C99 -> 0 | G99: =+E99*I97 -> #DIV/0!
A100: CBA | B100: Holiday (Based on 11 Days) | C100: 0 | D100: 0 | E100: =+C100*D100 -> 0 | G100: =+E100*I97 -> #DIV/0!
A101: CBA | B101: Vacation (Based on 10 Days) | C101: 0 | D101: 0 | E101: =+C101*D101 -> 0 | G101: =+E101*I97 -> #DIV/0!
A102: CBA | B102: Vacation (Based on 17.5 Days) | C102: 0 | D102: 0 | E102: =+D102*C102 -> 0 | G102: =+E102*I97 -> #DIV/0!
A103: CBA | B103: Vacation (Based on 22.5 Days) | C103: 0 | D103: 0 | E103: =+D103*C103 -> 0 | G103: =+E103*I97 -> #DIV/0!
B104: Health and Welfare for Sick/Holiday/Vacation Hours | E104: =SUM(E98:E103) -> 0 | F104: 0 | G104: =E104*F104 -> 0 | H104: =SUM(G93:G104) -> #DIV/0! | I104: =(H104+H88)/H86 -> #DIV/0! | K104: =K86*I104 -> #DIV/0!
H105: =+H104+H89 -> #DIV/0!
A109: OVERHEAD EXPENSE | D109: 0 | H109: =+H105*D109 -> #DIV/0! | I109: =+H109/H105 -> #DIV/0! | K109: =+(K86+K104)*I109 -> #DIV/0!
A111: OTHER DIRECT COSTS (ODC):
B112: Uniforms @ | C112: 0 | D112: 0 | E112: 0 | G112: =+(C112*D112*E112) -> 0
B113: Boot Allowance | C113: 0 | D113: 0 | E113: 0 | G113: =+(C113*D113*E113) -> 0
B114: Ammo | C114: 0 | D114: 0 | E114: 0 | G114: =+(C114*D114*E114) -> 0
B115: Duty Gear | C115: 0 | D115: 0 | E115: 0 | G115: =+(C115*D115*E115) -> 0
B116: Weapons | C116: 0 | D116: 0 | E116: 0 | G116: =+(C116*D116*E116) -> 0
B117: Medical /Drug Screening / Physicals | C117: 0 | D117: 0 | E117: 0 | G117: =+(C117*D117*E117) -> 0
B118: Professional Licenses | C118: 0 | D118: 0 | E118: 0 | G118: =+(C118*D118*E118) -> 0
B119: Training - Nonrecurring | C119: 0 | D119: 0 | E119: 0 | G119: =+(C119*D119*E119) -> 0
B120: Training - Recurring Annual | C120: 0 | D120: 0 | E120: 0 | G120: =+(C120*D120*E120) -> 0
B121: Shooting Range Qualification / Requal | C121: 0 | D121: 0 | E121: 0 | G121: =+(C121*D121*E121) -> 0
...

Sheet ZHU Rate Build Up
A2: {=MID(CELL("filename", A1), FIND("]", CELL("filename", A1)) + 1, LEN(CELL("filename", A1)) - FIND("]", CELL("filename", A1)))} -> ZHU Rate Build Up | F2: Base Period | K2: ESS
F3: CBA
A4: =_BasePeriod -> 9/30/2026-9/29/2027
A5: DIRECT LABOR (DL): | E5: HOURS | F5: Rate | H5: TOTAL
A6: 1 | B6: Captain | E6: 0 | F6: 0 | H6: =+E6*F6 -> 0
A7: 2 | B7: Guard II | E7: 0 | F7: 0 | H7: =+E7*F7 -> 0
A8: 3 | B8: Guard II | E8: 0 | F8: 0 | H8: =+E8*F8 -> 0
A9: 4 | B9: Guard II | E9: 0 | F9: 0 | H9: =+E9*F9 -> 0
A10: 5 | B10: Guard II | E10: 0 | F10: 0 | H10: =+E10*F10 -> 0
A11: 6 | B11: Guard II | E11: 0 | F11: 0 | H11: =+E11*F11 -> 0
A12: 7 | B12: Guard II | E12: 0 | F12: 0 | H12: =+E12*F12 -> 0
A13: 8 | B13: Guard II | E13: 0 | F13: 0 | H13: =+E13*F13 -> 0
A14: 9 | B14: Guard II | E14: 0 | F14: 0 | H14: =+E14*F14 -> 0
A15: 10 | B15: Guard II | E15: 0 | F15: 0 | H15: =+E15*F15 -> 0
A16: 11 | B16: Guard II | E16: 0 | F16: 0 | H16: =+E16*F16 -> 0
A17: 12 | B17: Guard II | E17: 0 | F17: 0 | H17: =+E17*F17 -> 0
B18: Total | E18: =SUM(E6:E17) -> 0 | H18: =SUM(H6:H17) -> 0 | I18: =+H18/E18 -> #DIV/0! | K18: =+I18*1.5 -> #DIV/0!
B20: Health and Welfare | F20: 0 | H20: =+E18*F20 -> 0
H21: =+H18+H20 -> 0
A23: EMPLOYEE BENEFIT: | E23: FRINGE RATE
B25: Social Security | E25: 0.062 | G25: =+$E25*$H21 -> 0
B26: Medicare | E26: 0.0145 | G26: =+$E26*$H21 -> 0
B27: SUTA | E27: 0 | G27: =+$E27*$H21 -> 0
B28: FUTA | E28: 0 | G28: =+$E28*$H21 -> 0 | H28: Sum of Payroll Taxes | I28: W/ Payroll Taxes
B29: Workman's Comp /General Liability Insurance | E29: 0 | G29: =+$E29*$H21 -> 0 | H29: =SUM(E25:E29) -> 0.0765 | I29: =+H29*I18+I18 -> #DIV/0!
A30: CBA | B30: Sick Leave (Full Time) | C30: 0 | D30: 0 | E30: =+D30*C30 -> 0 | G30: =+E30*I29 -> #DIV/0!
A31: CBA | B31: Sick Leave (Part Time) | C31: 0 | D31: 0 | E31: =+D31*C31 -> 0 | G31: =+E31*I29 -> #DIV/0!
A32: CBA | B32: Holiday (Based on 11 Days) | C32: 0 | D32: 0 | E32: =+C32*D32 -> 0 | G32: =+E32*I29 -> #DIV/0!
A33: CBA | B33: Vacation (Based on 10 Days) | C33: 0 | D33: 0 | E33: =+C33*D33 -> 0 | G33: =+E33*I29 -> #DIV/0!
A34: CBA | B34: Vacation (Based on 17.5 Days) | C34: 0 | D34: 0 | E34: =+D34*C34 -> 0 | G34: =+E34*I29 -> #DIV/0!
A35: CBA | B35: Vacation (Based on 22.5 Days) | C35: 0 | D35: 0 | E35: =+D35*C35 -> 0 | G35: =+E35*I29 -> #DIV/0!
B36: Health and Welfare for Sick/Holiday/Vacation Hours | E36: =SUM(E30:E35) -> 0 | F36: 0 | G36: =E36*F36 -> 0 | H36: =SUM(G25:G36) -> #DIV/0! | I36: =(H36+H20)/H18 -> #DIV/0! | K36: =K18*I36 -> #DIV/0!
H37: =+H36+H21 -> #DIV/0!
A41: OVERHEAD EXPENSE | D41: 0 | H41: =+H37*D41 -> #DIV/0! | I41: =+H41/H37 -> #DIV/0! | K41: =+(K18+K36)*I41 -> #DIV/0!
A43: OTHER DIRECT COSTS (ODC):
B44: Uniforms @ | C44: 0 | D44: 0 | E44: 0 | G44: =+(C44*D44*E44) -> 0
B45: Boot Allowance | C45: 0 | D45: 0 | E45: 0 | G45: =+(C45*D45*E45) -> 0
B46: Ammo | C46: 0 | D46: 0 | E46: 0 | G46: =+(C46*D46*E46) -> 0
B47: Duty Gear | C47: 0 | D47: 0 | E47: 0 | G47: =+(C47*D47*E47) -> 0
B48: Weapons | C48: 0 | D48: 0 | E48: 0 | G48: =+(C48*D48*E48) -> 0
B49: Medical /Drug Screening / Physicals | C49: 0 | D49: 0 | E49: 0 | G49: =+(C49*D49*E49) -> 0
B50: Professional Licenses | C50: 0 | D50: 0 | E50: 0 | G50: =+(C50*D50*E50) -> 0
B51: Training - Nonrecurring | C51: 0 | D51: 0 | E51: 0 | G51: =+(C51*D51*E51) -> 0
B52: Training - Recurring Annual | C52: 0 | D52: 0 | E52: 0 | G52: =+(C52*D52*E52) -> 0
B53: Shooting Range Qualification / Requal | C53: 0 | D53: 0 | E53: 0 | G53: =+(C53*D53*E53) -> 0
B54: Travel | C54: 0 | D54: 0 | E54: 0 | G54: =+(C54*D54*E54) -> 0 | H54: =SUM(G44:G54) -> 0 | K54: =SUM(K18:K53) -> #DIV/0!
C55: SUBTOTAL | H55: =SUM(H37:H54) -> #DIV/0!
A57: G&A EXPENSE | D57: 0 | H57: =+H55*D57 -> #DIV/0! | I57: =D57 -> 0 | K57: =+K54*I57 -> #DIV/0!
D58: SUBTOTAL G&A/WC/DL | K58: =SUM(K54:K57) -> #DIV/0!
A60: PROFIT | D60: 0 | H60: =(H55+H57)*D60 -> #DIV/0!
D61: SUBTOTAL COST AND PROFIT | H61: =SUM(H55:H60) -> #DIV/0! | I61: =D60 -> 0 | K61: =+K58*I61 -> #DIV/0!
A64: STATE TAXES | D64: 0 | H64: =+H61*D64 -> #DIV/0!
F66: ANNUAL TOTAL | H66: =SUM(H61:H64) -> #DIV/0!
F67: MONTHLY RATE | H67: =+H66/12 -> #DIV/0!
B68: TAS/OTHER SERVICES/TRAINING/RANDOM SCREENING/ROVING PATROL | F68: HOURLY PRICE | H68: =+H66/(E18) -> #DIV/0! | K68: =SUM(K58:K67) -> #DIV/0!
A70: =$A$2 -> ZHU Rate Build Up | F70: Option Period 1 | K70: ESS
F71: CBA
A72: =_OP1 -> 9/30/2027-9/29/2028
A73: DIRECT LABOR (DL): | E73: HOURS | F73: Rate | H73: TOTAL
A74: 1 | B74: Captain | E74: 0 | F74: 0 | H74: =+E74*F74 -> 0
A75: 2 | B75: Guard II | E75: 0 | F75: 0 | H75: =+E75*F75 -> 0
A76: 3 | B76: Guard II | E76: 0 | F76: 0 | H76: =+E76*F76 -> 0
A77: 4 | B77: Guard II | E77: 0 | F77: 0 | H77: =+E77*F77 -> 0
A78: 5 | B78: Guard II | E78: 0 | F78: 0 | H78: =+E78*F78 -> 0
A79: 6 | B79: Guard II | E79: 0 | F79: 0 | H79: =+E79*F79 -> 0
A80: 7 | B80: Guard II | E80: 0 | F80: 0 | H80: =+E80*F80 -> 0
A81: 8 | B81: Guard II | E81: 0 | F81: 0 | H81: =+E81*F81 -> 0
A82: 9 | B82: Guard II | E82: 0 | F82: 0 | H82: =+E82*F82 -> 0
A83: 10 | B83: Guard II | E83: 0 | F83: 0 | H83: =+E83*F83 -> 0
A84: 11 | B84: Guard II | E84: 0 | F84: 0 | H84: =+E84*F84 -> 0
A85: 12 | B85: Guard II | E85: 0 | F85: 0 | H85: =+E85*F85 -> 0
B86: Total | E86: =SUM(E74:E85) -> 0 | H86: =SUM(H74:H85) -> 0 | I86: =+H86/E86 -> #DIV/0! | K86: =+I86*1.5 -> #DIV/0!
B88: Health and Welfare | F88: 5 | H88: =+E86*F88 -> 0
H89: =+H86+H88 -> 0
A91: EMPLOYEE BENEFIT: | E91: FRINGE RATE
B93: Social Security | E93: 0.062 | G93: =+$E93*$H89 -> 0
B94: Medicare | E94: 0.0145 | G94: =+$E94*$H89 -> 0
B95: SUTA | E95: 0 | G95: =+$E95*$H89 -> 0
B96: FUTA | E96: 0 | G96: =+$E96*$H89 -> 0 | H96: Sum of Payroll Taxes | I96: W/ Payroll Taxes
B97: Workman's Comp /General Liability Insurance | E97: 0 | G97: =+$E97*$H89 -> 0 | H97: =SUM(E93:E97) -> 0.0765 | I97: =+H97*I86+I86 -> #DIV/0!
A98: CBA | B98: Sick Leave (Full Time) | C98: 0 | D98: 0 | E98: =+D98*C98 -> 0 | G98: =+E98*I97 -> #DIV/0!
A99: CBA | B99: Sick Leave (Part Time) | C99: 0 | D99: 0 | E99: =+D99*C99 -> 0 | G99: =+E99*I97 -> #DIV/0!
A100: CBA | B100: Holiday (Based on 11 Days) | C100: 0 | D100: 0 | E100: =+C100*D100 -> 0 | G100: =+E100*I97 -> #DIV/0!
A101: CBA | B101: Vacation (Based on 10 Days) | C101: 0 | D101: 0 | E101: =+C101*D101 -> 0 | G101: =+E101*I97 -> #DIV/0!
A102: CBA | B102: Vacation (Based on 17.5 Days) | C102: 0 | D102: 0 | E102: =+D102*C102 -> 0 | G102: =+E102*I97 -> #DIV/0!
A103: CBA | B103: Vacation (Based on 22.5 Days) | C103: 0 | D103: 0 | E103: =+D103*C103 -> 0 | G103: =+E103*I97 -> #DIV/0!
B104: Health and Welfare for Sick/Holiday/Vacation Hours | E104: =SUM(E98:E103) -> 0 | F104: 0 | G104: =E104*F104 -> 0 | H104: =SUM(G93:G104) -> #DIV/0! | I104: =(H104+H88)/H86 -> #DIV/0! | K104: =K86*I104 -> #DIV/0!
H105: =+H104+H89 -> #DIV/0!
A109: OVERHEAD EXPENSE | D109: 0 | H109: =+H105*D109 -> #DIV/0! | I109: =+H109/H105 -> #DIV/0! | K109: =+(K86+K104)*I109 -> #DIV/0!
A111: OTHER DIRECT COSTS (ODC):
B112: Uniforms @ | C112: 0 | D112: 0 | E112: 0 | G112: =+(C112*D112*E112) -> 0
B113: Boot Allowance | C113: 0 | D113: 0 | E113: 0 | G113: =+(C113*D113*E113) -> 0
B114: Ammo | C114: 0 | D114: 0 | E114: 0 | G114: =+(C114*D114*E114) -> 0
B115: Duty Gear | C115: 0 | D115: 0 | E115: 0 | G115: =+(C115*D115*E115) -> 0
B116: Weapons | C116: 0 | D116: 0 | E116: 0 | G116: =+(C116*D116*E116) -> 0
B117: Medical /Drug Screening / Physicals | C117: 0 | D117: 0 | E117: 0 | G117: =+(C117*D117*E117) -> 0
B118: Professional Licenses | C118: 0 | D118: 0 | E118: 0 | G118: =+(C118*D118*E118) -> 0
B119: Training - Nonrecurring | C119: 0 | D119: 0 | E119: 0 | G119: =+(C119*D119*E119) -> 0
B120: Training - Recurring Annual | C120: 0 | D120: 0 | E120: 0 | G120: =+(C120*D120*E120) -> 0
B121: Shooting Range Qualification / Requal | C121: 0 | D121: 0 | E121: 0 | G121: =+(C121*D121*E121) -> 0
...

Sheet ZID Rate Build Up
A2: {=MID(CELL("filename", A1), FIND("]", CELL("filename", A1)) + 1, LEN(CELL("filename", A1)) - FIND("]", CELL("filename", A1)))} -> ZID Rate Build Up | F2: Base Period | K2: ESS
F3: CBA
A4: =_BasePeriod -> 9/30/2026-9/29/2027
A5: DIRECT LABOR (DL): | E5: HOURS | F5: Rate | H5: TOTAL
A6: 1 | B6: Captain | E6: 0 | F6: 0 | H6: =+E6*F6 -> 0
A7: 2 | B7: Guard II | E7: 0 | F7: 0 | H7: =+E7*F7 -> 0
A8: 3 | B8: Guard II | E8: 0 | F8: 0 | H8: =+E8*F8 -> 0
A9: 4 | B9: Guard II | E9: 0 | F9: 0 | H9: =+E9*F9 -> 0
A10: 5 | B10: Guard II | E10: 0 | F10: 0 | H10: =+E10*F10 -> 0
A11: 6 | B11: Guard II | E11: 0 | F11: 0 | H11: =+E11*F11 -> 0
A12: 7 | B12: Guard II | E12: 0 | F12: 0 | H12: =+E12*F12 -> 0
A13: 8 | B13: Guard II | E13: 0 | F13: 0 | H13: =+E13*F13 -> 0
A14: 9 | B14: Guard II | E14: 0 | F14: 0 | H14: =+E14*F14 -> 0
A15: 10 | B15: Guard II | E15: 0 | F15: 0 | H15: =+E15*F15 -> 0
A16: 11 | B16: Guard II | E16: 0 | F16: 0 | H16: =+E16*F16 -> 0
A17: 12 | B17: Guard II | E17: 0 | F17: 0 | H17: =+E17*F17 -> 0
B18: Total | E18: =SUM(E6:E17) -> 0 | H18: =SUM(H6:H17) -> 0 | I18: =+H18/E18 -> #DIV/0! | K18: =+I18*1.5 -> #DIV/0!
B20: Health and Welfare | F20: 0 | H20: =+E18*F20 -> 0
H21: =+H18+H20 -> 0
A23: EMPLOYEE BENEFIT: | E23: FRINGE RATE
B25: Social Security | E25: 0.062 | G25: =+$E25*$H21 -> 0
B26: Medicare | E26: 0.0145 | G26: =+$E26*$H21 -> 0
B27: SUTA | E27: 0 | G27: =+$E27*$H21 -> 0
B28: FUTA | E28: 0 | G28: =+$E28*$H21 -> 0 | H28: Sum of Payroll Taxes | I28: W/ Payroll Taxes
B29: Workman's Comp /General Liability Insurance | E29: 0 | G29: =+$E29*$H21 -> 0 | H29: =SUM(E25:E29) -> 0.0765 | I29: =+H29*I18+I18 -> #DIV/0!
A30: CBA | B30: Sick Leave (Full Time) | C30: 0 | D30: 0 | E30: =+D30*C30 -> 0 | G30: =+E30*I29 -> #DIV/0!
A31: CBA | B31: Sick Leave (Part Time) | C31: 0 | D31: 0 | E31: =+D31*C31 -> 0 | G31: =+E31*I29 -> #DIV/0!
A32: CBA | B32: Holiday (Based on 11 Days) | C32: 0 | D32: 0 | E32: =+C32*D32 -> 0 | G32: =+E32*I29 -> #DIV/0!
A33: CBA | B33: Vacation (Based on 10 Days) | C33: 0 | D33: 0 | E33: =+C33*D33 -> 0 | G33: =+E33*I29 -> #DIV/0!
A34: CBA | B34: Vacation (Based on 17.5 Days) | C34: 0 | D34: 0 | E34: =+D34*C34 -> 0 | G34: =+E34*I29 -> #DIV/0!
A35: CBA | B35: Vacation (Based on 22.5 Days) | C35: 0 | D35: 0 | E35: =+D35*C35 -> 0 | G35: =+E35*I29 -> #DIV/0!
B36: Health and Welfare for Sick/Holiday/Vacation Hours | E36: =SUM(E30:E35) -> 0 | F36: 0 | G36: =E36*F36 -> 0 | H36: =SUM(G25:G36) -> #DIV/0! | I36: =(H36+H20)/H18 -> #DIV/0! | K36: =K18*I36 -> #DIV/0!
H37: =+H36+H21 -> #DIV/0!
A41: OVERHEAD EXPENSE | D41: 0 | H41: =+H37*D41 -> #DIV/0! | I41: =+H41/H37 -> #DIV/0! | K41: =+(K18+K36)*I41 -> #DIV/0!
A43: OTHER DIRECT COSTS (ODC):
B44: Uniforms @ | C44: 0 | D44: 0 | E44: 0 | G44: =+(C44*D44*E44) -> 0
B45: Boot Allowance | C45: 0 | D45: 0 | E45: 0 | G45: =+(C45*D45*E45) -> 0
B46: Ammo | C46: 0 | D46: 0 | E46: 0 | G46: =+(C46*D46*E46) -> 0
B47: Duty Gear | C47: 0 | D47: 0 | E47: 0 | G47: =+(C47*D47*E47) -> 0
B48: Weapons | C48: 0 | D48: 0 | E48: 0 | G48: =+(C48*D48*E48) -> 0
B49: Medical /Drug Screening / Physicals | C49: 0 | D49: 0 | E49: 0 | G49: =+(C49*D49*E49) -> 0
B50: Professional Licenses | C50: 0 | D50: 0 | E50: 0 | G50: =+(C50*D50*E50) -> 0
B51: Training - Nonrecurring | C51: 0 | D51: 0 | E51: 0 | G51: =+(C51*D51*E51) -> 0
B52: Training - Recurring Annual | C52: 0 | D52: 0 | E52: 0 | G52: =+(C52*D52*E52) -> 0
B53: Shooting Range Qualification / Requal | C53: 0 | D53: 0 | E53: 0 | G53: =+(C53*D53*E53) -> 0
B54: Travel | C54: 0 | D54: 0 | E54: 0 | G54: =+(C54*D54*E54) -> 0 | H54: =SUM(G44:G54) -> 0 | K54: =SUM(K18:K53) -> #DIV/0!
C55: SUBTOTAL | H55: =SUM(H37:H54) -> #DIV/0!
A57: G&A EXPENSE | D57: 0 | H57: =+H55*D57 -> #DIV/0! | I57: =D57 -> 0 | K57: =+K54*I57 -> #DIV/0!
D58: SUBTOTAL G&A/WC/DL | K58: =SUM(K54:K57) -> #DIV/0!
A60: PROFIT | D60: 0 | H60: =(H55+H57)*D60 -> #DIV/0!
D61: SUBTOTAL COST AND PROFIT | H61: =SUM(H55:H60) -> #DIV/0! | I61: =D60 -> 0 | K61: =+K58*I61 -> #DIV/0!
A64: STATE TAXES | D64: 0 | H64: =+H61*D64 -> #DIV/0!
F66: ANNUAL TOTAL | H66: =SUM(H61:H64) -> #DIV/0!
F67: MONTHLY RATE | H67: =+H66/12 -> #DIV/0!
B68: TAS/OTHER SERVICES/TRAINING/RANDOM SCREENING/ROVING PATROL | F68: HOURLY PRICE | H68: =+H66/(E18) -> #DIV/0! | K68: =SUM(K58:K67) -> #DIV/0!
A70: =$A$2 -> ZID Rate Build Up | F70: Option Period 1 | K70: ESS
F71: CBA
A72: =_OP1 -> 9/30/2027-9/29/2028
A73: DIRECT LABOR (DL): | E73: HOURS | F73: Rate | H73: TOTAL
A74: 1 | B74: Captain | E74: 0 | F74: 0 | H74: =+E74*F74 -> 0
A75: 2 | B75: Guard II | E75: 0 | F75: 0 | H75: =+E75*F75 -> 0
A76: 3 | B76: Guard II | E76: 0 | F76: 0 | H76: =+E76*F76 -> 0
A77: 4 | B77: Guard II | E77: 0 | F77: 0 | H77: =+E77*F77 -> 0
A78: 5 | B78: Guard II | E78: 0 | F78: 0 | H78: =+E78*F78 -> 0
A79: 6 | B79: Guard II | E79: 0 | F79: 0 | H79: =+E79*F79 -> 0
A80: 7 | B80: Guard II | E80: 0 | F80: 0 | H80: =+E80*F80 -> 0
A81: 8 | B81: Guard II | E81: 0 | F81: 0 | H81: =+E81*F81 -> 0
A82: 9 | B82: Guard II | E82: 0 | F82: 0 | H82: =+E82*F82 -> 0
A83: 10 | B83: Guard II | E83: 0 | F83: 0 | H83: =+E83*F83 -> 0
A84: 11 | B84: Guard II | E84: 0 | F84: 0 | H84: =+E84*F84 -> 0
A85: 12 | B85: Guard II | E85: 0 | F85: 0 | H85: =+E85*F85 -> 0
B86: Total | E86: =SUM(E74:E85) -> 0 | H86: =SUM(H74:H85) -> 0 | I86: =+H86/E86 -> #DIV/0! | K86: =+I86*1.5 -> #DIV/0!
B88: Health and Welfare | F88: 5 | H88: =+E86*F88 -> 0
H89: =+H86+H88 -> 0
A91: EMPLOYEE BENEFIT: | E91: FRINGE RATE
B93: Social Security | E93: 0.062 | G93: =+$E93*$H89 -> 0
B94: Medicare | E94: 0.0145 | G94: =+$E94*$H89 -> 0
B95: SUTA | E95: 0 | G95: =+$E95*$H89 -> 0
B96: FUTA | E96: 0 | G96: =+$E96*$H89 -> 0 | H96: Sum of Payroll Taxes | I96: W/ Payroll Taxes
B97: Workman's Comp /General Liability Insurance | E97: 0 | G97: =+$E97*$H89 -> 0 | H97: =SUM(E93:E97) -> 0.0765 | I97: =+H97*I86+I86 -> #DIV/0!
A98: CBA | B98: Sick Leave (Full Time) | C98: 0 | D98: 0 | E98: =+D98*C98 -> 0 | G98: =+E98*I97 -> #DIV/0!
A99: CBA | B99: Sick Leave (Part Time) | C99: 0 | D99: 0 | E99: =+D99*C99 -> 0 | G99: =+E99*I97 -> #DIV/0!
A100: CBA | B100: Holiday (Based on 11 Days) | C100: 0 | D100: 0 | E100: =+C100*D100 -> 0 | G100: =+E100*I97 -> #DIV/0!
A101: CBA | B101: Vacation (Based on 10 Days) | C101: 0 | D101: 0 | E101: =+C101*D101 -> 0 | G101: =+E101*I97 -> #DIV/0!
A102: CBA | B102: Vacation (Based on 17.5 Days) | C102: 0 | D102: 0 | E102: =+D102*C102 -> 0 | G102: =+E102*I97 -> #DIV/0!
A103: CBA | B103: Vacation (Based on 22.5 Days) | C103: 0 | D103: 0 | E103: =+D103*C103 -> 0 | G103: =+E103*I97 -> #DIV/0!
B104: Health and Welfare for Sick/Holiday/Vacation Hours | E104: =SUM(E98:E103) -> 0 | F104: 0 | G104: =E104*F104 -> 0 | H104: =SUM(G93:G104) -> #DIV/0! | I104: =(H104+H88)/H86 -> #DIV/0! | K104: =K86*I104 -> #DIV/0!
H105: =+H104+H89 -> #DIV/0!
A109: OVERHEAD EXPENSE | D109: 0 | H109: =+H105*D109 -> #DIV/0! | I109: =+H109/H105 -> #DIV/0! | K109: =+(K86+K104)*I109 -> #DIV/0!
A111: OTHER DIRECT COSTS (ODC):
B112: Uniforms @ | C112: 0 | D112: 0 | E112: 0 | G112: =+(C112*D112*E112) -> 0
B113: Boot Allowance | C113: 0 | D113: 0 | E113: 0 | G113: =+(C113*D113*E113) -> 0
B114: Ammo | C114: 0 | D114: 0 | E114: 0 | G114: =+(C114*D114*E114) -> 0
B115: Duty Gear | C115: 0 | D115: 0 | E115: 0 | G115: =+(C115*D115*E115) -> 0
B116: Weapons | C116: 0 | D116: 0 | E116: 0 | G116: =+(C116*D116*E116) -> 0
B117: Medical /Drug Screening / Physicals | C117: 0 | D117: 0 | E117: 0 | G117: =+(C117*D117*E117) -> 0
B118: Professional Licenses | C118: 0 | D118: 0 | E118: 0 | G118: =+(C118*D118*E118) -> 0
B119: Training - Nonrecurring | C119: 0 | D119: 0 | E119: 0 | G119: =+(C119*D119*E119) -> 0
B120: Training - Recurring Annual | C120: 0 | D120: 0 | E120: 0 | G120: =+(C120*D120*E120) -> 0
B121: Shooting Range Qualification / Requal | C121: 0 | D121: 0 | E121: 0 | G121: =+(C121*D121*E121) -> 0
...

Sheet ZKC Rate Build Up
A2: {=MID(CELL("filename", A1), FIND("]", CELL("filename", A1)) + 1, LEN(CELL("filename", A1)) - FIND("]", CELL("filename", A1)))} -> ZKC Rate Build Up | F2: Base Period | K2: ESS
F3: CBA
A4: =_BasePeriod -> 9/30/2026-9/29/2027
A5: DIRECT LABOR (DL): | E5: HOURS | F5: Rate | H5: TOTAL
A6: 1 | B6: Captain | E6: 0 | F6: 0 | H6: =+E6*F6 -> 0
A7: 2 | B7: Guard II | E7: 0 | F7: 0 | H7: =+E7*F7 -> 0
A8: 3 | B8: Guard II | E8: 0 | F8: 0 | H8: =+E8*F8 -> 0
A9: 4 | B9: Guard II | E9: 0 | F9: 0 | H9: =+E9*F9 -> 0
A10: 5 | B10: Guard II | E10: 0 | F10: 0 | H10: =+E10*F10 -> 0
A11: 6 | B11: Guard II | E11: 0 | F11: 0 | H11: =+E11*F11 -> 0
A12: 7 | B12: Guard II | E12: 0 | F12: 0 | H12: =+E12*F12 -> 0
A13: 8 | B13: Guard II | E13: 0 | F13: 0 | H13: =+E13*F13 -> 0
A14: 9 | B14: Guard II | E14: 0 | F14: 0 | H14: =+E14*F14 -> 0
A15: 10 | B15: Guard II | E15: 0 | F15: 0 | H15: =+E15*F15 -> 0
A16: 11 | B16: Guard II | E16: 0 | F16: 0 | H16: =+E16*F16 -> 0
A17: 12 | B17: Guard II | E17: 0 | F17: 0 | H17: =+E17*F17 -> 0
B18: Total | E18: =SUM(E6:E17) -> 0 | H18: =SUM(H6:H17) -> 0 | I18: =+H18/E18 -> #DIV/0! | K18: =+I18*1.5 -> #DIV/0!
B20: Health and Welfare | F20: 0 | H20: =+E18*F20 -> 0
H21: =+H18+H20 -> 0
A23: EMPLOYEE BENEFIT: | E23: FRINGE RATE
B25: Social Security | E25: 0.062 | G25: =+$E25*$H21 -> 0
B26: Medicare | E26: 0.0145 | G26: =+$E26*$H21 -> 0
B27: SUTA | E27: 0 | G27: =+$E27*$H21 -> 0
B28: FUTA | E28: 0 | G28: =+$E28*$H21 -> 0 | H28: Sum of Payroll Taxes | I28: W/ Payroll Taxes
B29: Workman's Comp /General Liability Insurance | E29: 0 | G29: =+$E29*$H21 -> 0 | H29: =SUM(E25:E29) -> 0.0765 | I29: =+H29*I18+I18 -> #DIV/0!
A30: CBA | B30: Sick Leave (Full Time) | C30: 0 | D30: 0 | E30: =+D30*C30 -> 0 | G30: =+E30*I29 -> #DIV/0!
A31: CBA | B31: Sick Leave (Part Time) | C31: 0 | D31: 0 | E31: =+D31*C31 -> 0 | G31: =+E31*I29 -> #DIV/0!
A32: CBA | B32: Holiday (Based on 11 Days) | C32: 0 | D32: 0 | E32: =+C32*D32 -> 0 | G32: =+E32*I29 -> #DIV/0!
A33: CBA | B33: Vacation (Based on 10 Days) | C33: 0 | D33: 0 | E33: =+C33*D33 -> 0 | G33: =+E33*I29 -> #DIV/0!
A34: CBA | B34: Vacation (Based on 17.5 Days) | C34: 0 | D34: 0 | E34: =+D34*C34 -> 0 | G34: =+E34*I29 -> #DIV/0!
A35: CBA | B35: Vacation (Based on 22.5 Days) | C35: 0 | D35: 0 | E35: =+D35*C35 -> 0 | G35: =+E35*I29 -> #DIV/0!
B36: Health and Welfare for Sick/Holiday/Vacation Hours | E36: =SUM(E30:E35) -> 0 | F36: 0 | G36: =E36*F36 -> 0 | H36: =SUM(G25:G36) -> #DIV/0! | I36: =(H36+H20)/H18 -> #DIV/0! | K36: =K18*I36 -> #DIV/0!
H37: =+H36+H21 -> #DIV/0!
A41: OVERHEAD EXPENSE | D41: 0 | H41: =+H37*D41 -> #DIV/0! | I41: =+H41/H37 -> #DIV/0! | K41: =+(K18+K36)*I41 -> #DIV/0!
A43: OTHER DIRECT COSTS (ODC):
B44: Uniforms @ | C44: 0 | D44: 0 | E44: 0 | G44: =+(C44*D44*E44) -> 0
B45: Boot Allowance | C45: 0 | D45: 0 | E45: 0 | G45: =+(C45*D45*E45) -> 0
B46: Ammo | C46: 0 | D46: 0 | E46: 0 | G46: =+(C46*D46*E46) -> 0
B47: Duty Gear | C47: 0 | D47: 0 | E47: 0 | G47: =+(C47*D47*E47) -> 0
B48: Weapons | C48: 0 | D48: 0 | E48: 0 | G48: =+(C48*D48*E48) -> 0
B49: Medical /Drug Screening / Physicals | C49: 0 | D49: 0 | E49: 0 | G49: =+(C49*D49*E49) -> 0
B50: Professional Licenses | C50: 0 | D50: 0 | E50: 0 | G50: =+(C50*D50*E50) -> 0
B51: Training - Nonrecurring | C51: 0 | D51: 0 | E51: 0 | G51: =+(C51*D51*E51) -> 0
B52: Training - Recurring Annual | C52: 0 | D52: 0 | E52: 0 | G52: =+(C52*D52*E52) -> 0
B53: Shooting Range Qualification / Requal | C53: 0 | D53: 0 | E53: 0 | G53: =+(C53*D53*E53) -> 0
B54: Travel | C54: 0 | D54: 0 | E54: 0 | G54: =+(C54*D54*E54) -> 0 | H54: =SUM(G44:G54) -> 0 | K54: =SUM(K18:K53) -> #DIV/0!
C55: SUBTOTAL | H55: =SUM(H37:H54) -> #DIV/0!
A57: G&A EXPENSE | D57: 0 | H57: =+H55*D57 -> #DIV/0! | I57: =D57 -> 0 | K57: =+K54*I57 -> #DIV/0!
D58: SUBTOTAL G&A/WC/DL | K58: =SUM(K54:K57) -> #DIV/0!
A60: PROFIT | D60: 0 | H60: =(H55+H57)*D60 -> #DIV/0!
D61: SUBTOTAL COST AND PROFIT | H61: =SUM(H55:H60) -> #DIV/0! | I61: =D60 -> 0 | K61: =+K58*I61 -> #DIV/0!
A64: STATE TAXES | D64: 0 | H64: =+H61*D64 -> #DIV/0!
F66: ANNUAL TOTAL | H66: =SUM(H61:H64) -> #DIV/0!
F67: MONTHLY RATE | H67: =+H66/12 -> #DIV/0!
B68: TAS/OTHER SERVICES/TRAINING/RANDOM SCREENING/ROVING PATROL | F68: HOURLY PRICE | H68: =+H66/(E18) -> #DIV/0! | K68: =SUM(K58:K67) -> #DIV/0!
A70: =$A$2 -> ZKC Rate Build Up | F70: Option Period 1 | K70: ESS
F71: CBA
A72: =_OP1 -> 9/30/2027-9/29/2028
A73: DIRECT LABOR (DL): | E73: HOURS | F73: Rate | H73: TOTAL
A74: 1 | B74: Captain | E74: 0 | F74: 0 | H74: =+E74*F74 -> 0
A75: 2 | B75: Guard II | E75: 0 | F75: 0 | H75: =+E75*F75 -> 0
A76: 3 | B76: Guard II | E76: 0 | F76: 0 | H76: =+E76*F76 -> 0
A77: 4 | B77: Guard II | E77: 0 | F77: 0 | H77: =+E77*F77 -> 0
A78: 5 | B78: Guard II | E78: 0 | F78: 0 | H78: =+E78*F78 -> 0
A79: 6 | B79: Guard II | E79: 0 | F79: 0 | H79: =+E79*F79 -> 0
A80: 7 | B80: Guard II | E80: 0 | F80: 0 | H80: =+E80*F80 -> 0
A81: 8 | B81: Guard II | E81: 0 | F81: 0 | H81: =+E81*F81 -> 0
A82: 9 | B82: Guard II | E82: 0 | F82: 0 | H82: =+E82*F82 -> 0
A83: 10 | B83: Guard II | E83: 0 | F83: 0 | H83: =+E83*F83 -> 0
A84: 11 | B84: Guard II | E84: 0 | F84: 0 | H84: =+E84*F84 -> 0
A85: 12 | B85: Guard II | E85: 0 | F85: 0 | H85: =+E85*F85 -> 0
B86: Total | E86: =SUM(E74:E85) -> 0 | H86: =SUM(H74:H85) -> 0 | I86: =+H86/E86 -> #DIV/0! | K86: =+I86*1.5 -> #DIV/0!
B88: Health and Welfare | F88: 5 | H88: =+E86*F88 -> 0
H89: =+H86+H88 -> 0
A91: EMPLOYEE BENEFIT: | E91: FRINGE RATE
B93: Social Security | E93: 0.062 | G93: =+$E93*$H89 -> 0
B94: Medicare | E94: 0.0145 | G94: =+$E94*$H89 -> 0
B95: SUTA | E95: 0 | G95: =+$E95*$H89 -> 0
B96: FUTA | E96: 0 | G96: =+$E96*$H89 -> 0 | H96: Sum of Payroll Taxes | I96: W/ Payroll Taxes
B97: Workman's Comp /General Liability Insurance | E97: 0 | G97: =+$E97*$H89 -> 0 | H97: =SUM(E93:E97) -> 0.0765 | I97: =+H97*I86+I86 -> #DIV/0!
A98: CBA | B98: Sick Leave (Full Time) | C98: 0 | D98: 0 | E98: =+D98*C98 -> 0 | G98: =+E98*I97 -> #DIV/0!
A99: CBA | B99: Sick Leave (Part Time) | C99: 0 | D99: 0 | E99: =+D99*C99 -> 0 | G99: =+E99*I97 -> #DIV/0!
A100: CBA | B100: Holiday (Based on 11 Days) | C100: 0 | D100: 0 | E100: =+C100*D100 -> 0 | G100: =+E100*I97 -> #DIV/0!
A101: CBA | B101: Vacation (Based on 10 Days) | C101: 0 | D101: 0 | E101: =+C101*D101 -> 0 | G101: =+E101*I97 -> #DIV/0!
A102: CBA | B102: Vacation (Based on 17.5 Days) | C102: 0 | D102: 0 | E102: =+D102*C102 -> 0 | G102: =+E102*I97 -> #DIV/0!
A103: CBA | B103: Vacation (Based on 22.5 Days) | C103: 0 | D103: 0 | E103: =+D103*C103 -> 0 | G103: =+E103*I97 -> #DIV/0!
B104: Health and Welfare for Sick/Holiday/Vacation Hours | E104: =SUM(E98:E103) -> 0 | F104: 0 | G104: =E104*F104 -> 0 | H104: =SUM(G93:G104) -> #DIV/0! | I104: =(H104+H88)/H86 -> #DIV/0! | K104: =K86*I104 -> #DIV/0!
H105: =+H104+H89 -> #DIV/0!
A109: OVERHEAD EXPENSE | D109: 0 | H109: =+H105*D109 -> #DIV/0! | I109: =+H109/H105 -> #DIV/0! | K109: =+(K86+K104)*I109 -> #DIV/0!
A111: OTHER DIRECT COSTS (ODC):
B112: Uniforms @ | C112: 0 | D112: 0 | E112: 0 | G112: =+(C112*D112*E112) -> 0
B113: Boot Allowance | C113: 0 | D113: 0 | E113: 0 | G113: =+(C113*D113*E113) -> 0
B114: Ammo | C114: 0 | D114: 0 | E114: 0 | G114: =+(C114*D114*E114) -> 0
B115: Duty Gear | C115: 0 | D115: 0 | E115: 0 | G115: =+(C115*D115*E115) -> 0
B116: Weapons | C116: 0 | D116: 0 | E116: 0 | G116: =+(C116*D116*E116) -> 0
B117: Medical /Drug Screening / Physicals | C117: 0 | D117: 0 | E117: 0 | G117: =+(C117*D117*E117) -> 0
B118: Professional Licenses | C118: 0 | D118: 0 | E118: 0 | G118: =+(C118*D118*E118) -> 0
B119: Training - Nonrecurring | C119: 0 | D119: 0 | E119: 0 | G119: =+(C119*D119*E119) -> 0
B120: Training - Recurring Annual | C120: 0 | D120: 0 | E120: 0 | G120: =+(C120*D120*E120) -> 0
B121: Shooting Range Qualification / Requal | C121: 0 | D121: 0 | E121: 0 | G121: =+(C121*D121*E121) -> 0
...

Sheet ZMP Rate Build Up
A2: {=MID(CELL("filename", A1), FIND("]", CELL("filename", A1)) + 1, LEN(CELL("filename", A1)) - FIND("]", CELL("filename", A1)))} -> ZMP Rate Build Up | F2: Base Period | K2: ESS
F3: CBA
A4: =_BasePeriod -> 9/30/2026-9/29/2027
A5: DIRECT LABOR (DL): | E5: HOURS | F5: Rate | H5: TOTAL
A6: 1 | B6: Captain | E6: 0 | F6: 0 | H6: =+E6*F6 -> 0
A7: 2 | B7: Guard II | E7: 0 | F7: 0 | H7: =+E7*F7 -> 0
A8: 3 | B8: Guard II | E8: 0 | F8: 0 | H8: =+E8*F8 -> 0
A9: 4 | B9: Guard II | E9: 0 | F9: 0 | H9: =+E9*F9 -> 0
A10: 5 | B10: Guard II | E10: 0 | F10: 0 | H10: =+E10*F10 -> 0
A11: 6 | B11: Guard II | E11: 0 | F11: 0 | H11: =+E11*F11 -> 0
A12: 7 | B12: Guard II | E12: 0 | F12: 0 | H12: =+E12*F12 -> 0
A13: 8 | B13: Guard II | E13: 0 | F13: 0 | H13: =+E13*F13 -> 0
A14: 9 | B14: Guard II | E14: 0 | F14: 0 | H14: =+E14*F14 -> 0
A15: 10 | B15: Guard II | E15: 0 | F15: 0 | H15: =+E15*F15 -> 0
A16: 11 | B16: Guard II | E16: 0 | F16: 0 | H16: =+E16*F16 -> 0
A17: 12 | B17: Guard II | E17: 0 | F17: 0 | H17: =+E17*F17 -> 0
B18: Total | E18: =SUM(E6:E17) -> 0 | H18: =SUM(H6:H17) -> 0 | I18: =+H18/E18 -> #DIV/0! | K18: =+I18*1.5 -> #DIV/0!
B20: Health and Welfare | F20: 0 | H20: =+E18*F20 -> 0
H21: =+H18+H20 -> 0
A23: EMPLOYEE BENEFIT: | E23: FRINGE RATE
B25: Social Security | E25: 0.062 | G25: =+$E25*$H21 -> 0
B26: Medicare | E26: 0.0145 | G26: =+$E26*$H21 -> 0
B27: SUTA | E27: 0 | G27: =+$E27*$H21 -> 0
B28: FUTA | E28: 0 | G28: =+$E28*$H21 -> 0 | H28: Sum of Payroll Taxes | I28: W/ Payroll Taxes
B29: Workman's Comp /General Liability Insurance | E29: 0 | G29: =+$E29*$H21 -> 0 | H29: =SUM(E25:E29) -> 0.0765 | I29: =+H29*I18+I18 -> #DIV/0!
A30: CBA | B30: Sick Leave (Full Time) | C30: 0 | D30: 0 | E30: =+D30*C30 -> 0 | G30: =+E30*I29 -> #DIV/0!
A31: CBA | B31: Sick Leave (Part Time) | C31: 0 | D31: 0 | E31: =+D31*C31 -> 0 | G31: =+E31*I29 -> #DIV/0!
A32: CBA | B32: Holiday (Based on 11 Days) | C32: 0 | D32: 0 | E32: =+C32*D32 -> 0 | G32: =+E32*I29 -> #DIV/0!
A33: CBA | B33: Vacation (Based on 10 Days) | C33: 0 | D33: 0 | E33: =+C33*D33 -> 0 | G33: =+E33*I29 -> #DIV/0!
A34: CBA | B34: Vacation (Based on 17.5 Days) | C34: 0 | D34: 0 | E34: =+D34*C34 -> 0 | G34: =+E34*I29 -> #DIV/0!
A35: CBA | B35: Vacation (Based on 22.5 Days) | C35: 0 | D35: 0 | E35: =+D35*C35 -> 0 | G35: =+E35*I29 -> #DIV/0!
B36: Health and Welfare for Sick/Holiday/Vacation Hours | E36: =SUM(E30:E35) -> 0 | F36: 0 | G36: =E36*F36 -> 0 | H36: =SUM(G25:G36) -> #DIV/0! | I36: =(H36+H20)/H18 -> #DIV/0! | K36: =K18*I36 -> #DIV/0!
H37: =+H36+H21 -> #DIV/0!
A41: OVERHEAD EXPENSE | D41: 0 | H41: =+H37*D41 -> #DIV/0! | I41: =+H41/H37 -> #DIV/0! | K41: =+(K18+K36)*I41 -> #DIV/0!
A43: OTHER DIRECT COSTS (ODC):
B44: Uniforms @ | C44: 0 | D44: 0 | E44: 0 | G44: =+(C44*D44*E44) -> 0
B45: Boot Allowance | C45: 0 | D45: 0 | E45: 0 | G45: =+(C45*D45*E45) -> 0
B46: Ammo | C46: 0 | D46: 0 | E46: 0 | G46: =+(C46*D46*E46) -> 0
B47: Duty Gear | C47: 0 | D47: 0 | E47: 0 | G47: =+(C47*D47*E47) -> 0
B48: Weapons | C48: 0 | D48: 0 | E48: 0 | G48: =+(C48*D48*E48) -> 0
B49: Medical /Drug Screening / Physicals | C49: 0 | D49: 0 | E49: 0 | G49: =+(C49*D49*E49) -> 0
B50: Professional Licenses | C50: 0 | D50: 0 | E50: 0 | G50: =+(C50*D50*E50) -> 0
B51: Training - Nonrecurring | C51: 0 | D51: 0 | E51: 0 | G51: =+(C51*D51*E51) -> 0
B52: Training - Recurring Annual | C52: 0 | D52: 0 | E52: 0 | G52: =+(C52*D52*E52) -> 0
B53: Shooting Range Qualification / Requal | C53: 0 | D53: 0 | E53: 0 | G53: =+(C53*D53*E53) -> 0
B54: Travel | C54: 0 | D54: 0 | E54: 0 | G54: =+(C54*D54*E54) -> 0 | H54: =SUM(G44:G54) -> 0 | K54: =SUM(K18:K53) -> #DIV/0!
C55: SUBTOTAL | H55: =SUM(H37:H54) -> #DIV/0!
A57: G&A EXPENSE | D57: 0 | H57: =+H55*D57 -> #DIV/0! | I57: =D57 -> 0 | K57: =+K54*I57 -> #DIV/0!
D58: SUBTOTAL G&A/WC/DL | K58: =SUM(K54:K57) -> #DIV/0!
A60: PROFIT | D60: 0 | H60: =(H55+H57)*D60 -> #DIV/0!
D61: SUBTOTAL COST AND PROFIT | H61: =SUM(H55:H60) -> #DIV/0! | I61: =D60 -> 0 | K61: =+K58*I61 -> #DIV/0!
A64: STATE TAXES | D64: 0 | H64: =+H61*D64 -> #DIV/0!
F66: ANNUAL TOTAL | H66: =SUM(H61:H64) -> #DIV/0!
F67: MONTHLY RATE | H67: =+H66/12 -> #DIV/0!
B68: TAS/OTHER SERVICES/TRAINING/RANDOM SCREENING/ROVING PATROL | F68: HOURLY PRICE | H68: =+H66/(E18) -> #DIV/0! | K68: =SUM(K58:K67) -> #DIV/0!
A70: =$A$2 -> ZMP Rate Build Up | F70: Option Period 1 | K70: ESS
F71: CBA
A72: =_OP1 -> 9/30/2027-9/29/2028
A73: DIRECT LABOR (DL): | E73: HOURS | F73: Rate | H73: TOTAL
A74: 1 | B74: Captain | E74: 0 | F74: 0 | H74: =+E74*F74 -> 0
A75: 2 | B75: Guard II | E75: 0 | F75: 0 | H75: =+E75*F75 -> 0
A76: 3 | B76: Guard II | E76: 0 | F76: 0 | H76: =+E76*F76 -> 0
A77: 4 | B77: Guard II | E77: 0 | F77: 0 | H77: =+E77*F77 -> 0
A78: 5 | B78: Guard II | E78: 0 | F78: 0 | H78: =+E78*F78 -> 0
A79: 6 | B79: Guard II | E79: 0 | F79: 0 | H79: =+E79*F79 -> 0
A80: 7 | B80: Guard II | E80: 0 | F80: 0 | H80: =+E80*F80 -> 0
A81: 8 | B81: Guard II | E81: 0 | F81: 0 | H81: =+E81*F81 -> 0
A82: 9 | B82: Guard II | E82: 0 | F82: 0 | H82: =+E82*F82 -> 0
A83: 10 | B83: Guard II | E83: 0 | F83: 0 | H83: =+E83*F83 -> 0
A84: 11 | B84: Guard II | E84: 0 | F84: 0 | H84: =+E84*F84 -> 0
A85: 12 | B85: Guard II | E85: 0 | F85: 0 | H85: =+E85*F85 -> 0
B86: Total | E86: =SUM(E74:E85) -> 0 | H86: =SUM(H74:H85) -> 0 | I86: =+H86/E86 -> #DIV/0! | K86: =+I86*1.5 -> #DIV/0!
B88: Health and Welfare | F88: 5 | H88: =+E86*F88 -> 0
H89: =+H86+H88 -> 0
A91: EMPLOYEE BENEFIT: | E91: FRINGE RATE
B93: Social Security | E93: 0.062 | G93: =+$E93*$H89 -> 0
B94: Medicare | E94: 0.0145 | G94: =+$E94*$H89 -> 0
B95: SUTA | E95: 0 | G95: =+$E95*$H89 -> 0
B96: FUTA | E96: 0 | G96: =+$E96*$H89 -> 0 | H96: Sum of Payroll Taxes | I96: W/ Payroll Taxes
B97: Workman's Comp /General Liability Insurance | E97: 0 | G97: =+$E97*$H89 -> 0 | H97: =SUM(E93:E97) -> 0.0765 | I97: =+H97*I86+I86 -> #DIV/0!
A98: CBA | B98: Sick Leave (Full Time) | C98: 0 | D98: 0 | E98: =+D98*C98 -> 0 | G98: =+E98*I97 -> #DIV/0!
A99: CBA | B99: Sick Leave (Part Time) | C99: 0 | D99: 0 | E99: =+D99*C99 -> 0 | G99: =+E99*I97 -> #DIV/0!
A100: CBA | B100: Holiday (Based on 11 Days) | C100: 0 | D100: 0 | E100: =+C100*D100 -> 0 | G100: =+E100*I97 -> #DIV/0!
A101: CBA | B101: Vacation (Based on 10 Days) | C101: 0 | D101: 0 | E101: =+C101*D101 -> 0 | G101: =+E101*I97 -> #DIV/0!
A102: CBA | B102: Vacation (Based on 17.5 Days) | C102: 0 | D102: 0 | E102: =+D102*C102 -> 0 | G102: =+E102*I97 -> #DIV/0!
A103: CBA | B103: Vacation (Based on 22.5 Days) | C103: 0 | D103: 0 | E103: =+D103*C103 -> 0 | G103: =+E103*I97 -> #DIV/0!
B104: Health and Welfare for Sick/Holiday/Vacation Hours | E104: =SUM(E98:E103) -> 0 | F104: 0 | G104: =E104*F104 -> 0 | H104: =SUM(G93:G104) -> #DIV/0! | I104: =(H104+H88)/H86 -> #DIV/0! | K104: =K86*I104 -> #DIV/0!
H105: =+H104+H89 -> #DIV/0!
A109: OVERHEAD EXPENSE | D109: 0 | H109: =+H105*D109 -> #DIV/0! | I109: =+H109/H105 -> #DIV/0! | K109: =+(K86+K104)*I109 -> #DIV/0!
A111: OTHER DIRECT COSTS (ODC):
B112: Uniforms @ | C112: 0 | D112: 0 | E112: 0 | G112: =+(C112*D112*E112) -> 0
B113: Boot Allowance | C113: 0 | D113: 0 | E113: 0 | G113: =+(C113*D113*E113) -> 0
B114: Ammo | C114: 0 | D114: 0 | E114: 0 | G114: =+(C114*D114*E114) -> 0
B115: Duty Gear | C115: 0 | D115: 0 | E115: 0 | G115: =+(C115*D115*E115) -> 0
B116: Weapons | C116: 0 | D116: 0 | E116: 0 | G116: =+(C116*D116*E116) -> 0
B117: Medical /Drug Screening / Physicals | C117: 0 | D117: 0 | E117: 0 | G117: =+(C117*D117*E117) -> 0
B118: Professional Licenses | C118: 0 | D118: 0 | E118: 0 | G118: =+(C118*D118*E118) -> 0
B119: Training - Nonrecurring | C119: 0 | D119: 0 | E119: 0 | G119: =+(C119*D119*E119) -> 0
B120: Training - Recurring Annual | C120: 0 | D120: 0 | E120: 0 | G120: =+(C120*D120*E120) -> 0
B121: Shooting Range Qualification / Requal | C121: 0 | D121: 0 | E121: 0 | G121: =+(C121*D121*E121) -> 0
...

Sheet ZOB Rate Build Up
A2: {=MID(CELL("filename", A1), FIND("]", CELL("filename", A1)) + 1, LEN(CELL("filename", A1)) - FIND("]", CELL("filename", A1)))} -> ZOB Rate Build Up | F2: Base Period | K2: ESS
F3: CBA
A4: =_BasePeriod -> 9/30/2026-9/29/2027
A5: DIRECT LABOR (DL): | E5: HOURS | F5: Rate | H5: TOTAL
A6: 1 | B6: Captain | E6: 0 | F6: 0 | H6: =+E6*F6 -> 0
A7: 2 | B7: Guard II | E7: 0 | F7: 0 | H7: =+E7*F7 -> 0
A8: 3 | B8: Guard II | E8: 0 | F8: 0 | H8: =+E8*F8 -> 0
A9: 4 | B9: Guard II | E9: 0 | F9: 0 | H9: =+E9*F9 -> 0
A10: 5 | B10: Guard II | E10: 0 | F10: 0 | H10: =+E10*F10 -> 0
A11: 6 | B11: Guard II | E11: 0 | F11: 0 | H11: =+E11*F11 -> 0
A12: 7 | B12: Guard II | E12: 0 | F12: 0 | H12: =+E12*F12 -> 0
A13: 8 | B13: Guard II | E13: 0 | F13: 0 | H13: =+E13*F13 -> 0
A14: 9 | B14: Guard II | E14: 0 | F14: 0 | H14: =+E14*F14 -> 0
A15: 10 | B15: Guard II | E15: 0 | F15: 0 | H15: =+E15*F15 -> 0
A16: 11 | B16: Guard II | E16: 0 | F16: 0 | H16: =+E16*F16 -> 0
A17: 12 | B17: Guard II | E17: 0 | F17: 0 | H17: =+E17*F17 -> 0
B18: Total | E18: =SUM(E6:E17) -> 0 | H18: =SUM(H6:H17) -> 0 | I18: =+H18/E18 -> #DIV/0! | K18: =+I18*1.5 -> #DIV/0!
B20: Health and Welfare | F20: 0 | H20: =+E18*F20 -> 0
H21: =+H18+H20 -> 0
A23: EMPLOYEE BENEFIT: | E23: FRINGE RATE
B25: Social Security | E25: 0.062 | G25: =+$E25*$H21 -> 0
B26: Medicare | E26: 0.0145 | G26: =+$E26*$H21 -> 0
B27: SUTA | E27: 0 | G27: =+$E27*$H21 -> 0
B28: FUTA | E28: 0 | G28: =+$E28*$H21 -> 0 | H28: Sum of Payroll Taxes | I28: W/ Payroll Taxes
B29: Workman's Comp /General Liability Insurance | E29: 0 | G29: =+$E29*$H21 -> 0 | H29: =SUM(E25:E29) -> 0.0765 | I29: =+H29*I18+I18 -> #DIV/0!
A30: CBA | B30: Sick Leave (Full Time) | C30: 0 | D30: 0 | E30: =+D30*C30 -> 0 | G30: =+E30*I29 -> #DIV/0!
A31: CBA | B31: Sick Leave (Part Time) | C31: 0 | D31: 0 | E31: =+D31*C31 -> 0 | G31: =+E31*I29 -> #DIV/0!
A32: CBA | B32: Holiday (Based on 11 Days) | C32: 0 | D32: 0 | E32: =+C32*D32 -> 0 | G32: =+E32*I29 -> #DIV/0!
A33: CBA | B33: Vacation (Based on 10 Days) | C33: 0 | D33: 0 | E33: =+C33*D33 -> 0 | G33: =+E33*I29 -> #DIV/0!
A34: CBA | B34: Vacation (Based on 17.5 Days) | C34: 0 | D34: 0 | E34: =+D34*C34 -> 0 | G34: =+E34*I29 -> #DIV/0!
A35: CBA | B35: Vacation (Based on 22.5 Days) | C35: 0 | D35: 0 | E35: =+D35*C35 -> 0 | G35: =+E35*I29 -> #DIV/0!
B36: Health and Welfare for Sick/Holiday/Vacation Hours | E36: =SUM(E30:E35) -> 0 | F36: 0 | G36: =E36*F36 -> 0 | H36: =SUM(G25:G36) -> #DIV/0! | I36: =(H36+H20)/H18 -> #DIV/0! | K36: =K18*I36 -> #DIV/0!
H37: =+H36+H21 -> #DIV/0!
A41: OVERHEAD EXPENSE | D41: 0 | H41: =+H37*D41 -> #DIV/0! | I41: =+H41/H37 -> #DIV/0! | K41: =+(K18+K36)*I41 -> #DIV/0!
A43: OTHER DIRECT COSTS (ODC):
B44: Uniforms @ | C44: 0 | D44: 0 | E44: 0 | G44: =+(C44*D44*E44) -> 0
B45: Boot Allowance | C45: 0 | D45: 0 | E45: 0 | G45: =+(C45*D45*E45) -> 0
B46: Ammo | C46: 0 | D46: 0 | E46: 0 | G46: =+(C46*D46*E46) -> 0
B47: Duty Gear | C47: 0 | D47: 0 | E47: 0 | G47: =+(C47*D47*E47) -> 0
B48: Weapons | C48: 0 | D48: 0 | E48: 0 | G48: =+(C48*D48*E48) -> 0
B49: Medical /Drug Screening / Physicals | C49: 0 | D49: 0 | E49: 0 | G49: =+(C49*D49*E49) -> 0
B50: Professional Licenses | C50: 0 | D50: 0 | E50: 0 | G50: =+(C50*D50*E50) -> 0
B51: Training - Nonrecurring | C51: 0 | D51: 0 | E51: 0 | G51: =+(C51*D51*E51) -> 0
B52: Training - Recurring Annual | C52: 0 | D52: 0 | E52: 0 | G52: =+(C52*D52*E52) -> 0
B53: Shooting Range Qualification / Requal | C53: 0 | D53: 0 | E53: 0 | G53: =+(C53*D53*E53) -> 0
B54: Travel | C54: 0 | D54: 0 | E54: 0 | G54: =+(C54*D54*E54) -> 0 | H54: =SUM(G44:G54) -> 0 | K54: =SUM(K18:K53) -> #DIV/0!
C55: SUBTOTAL | H55: =SUM(H37:H54) -> #DIV/0!
A57: G&A EXPENSE | D57: 0 | H57: =+H55*D57 -> #DIV/0! | I57: =D57 -> 0 | K57: =+K54*I57 -> #DIV/0!
D58: SUBTOTAL G&A/WC/DL | K58: =SUM(K54:K57) -> #DIV/0!
A60: PROFIT | D60: 0 | H60: =(H55+H57)*D60 -> #DIV/0!
D61: SUBTOTAL COST AND PROFIT | H61: =SUM(H55:H60) -> #DIV/0! | I61: =D60 -> 0 | K61: =+K58*I61 -> #DIV/0!
A64: STATE TAXES | D64: 0 | H64: =+H61*D64 -> #DIV/0!
F66: ANNUAL TOTAL | H66: =SUM(H61:H64) -> #DIV/0!
F67: MONTHLY RATE | H67: =+H66/12 -> #DIV/0!
B68: TAS/OTHER SERVICES/TRAINING/RANDOM SCREENING/ROVING PATROL | F68: HOURLY PRICE | H68: =+H66/(E18) -> #DIV/0! | K68: =SUM(K58:K67) -> #DIV/0!
A70: =$A$2 -> ZOB Rate Build Up | F70: Option Period 1 | K70: ESS
F71: CBA
A72: =_OP1 -> 9/30/2027-9/29/2028
A73: DIRECT LABOR (DL): | E73: HOURS | F73: Rate | H73: TOTAL
A74: 1 | B74: Captain | E74: 0 | F74: 0 | H74: =+E74*F74 -> 0
A75: 2 | B75: Guard II | E75: 0 | F75: 0 | H75: =+E75*F75 -> 0
A76: 3 | B76: Guard II | E76: 0 | F76: 0 | H76: =+E76*F76 -> 0
A77: 4 | B77: Guard II | E77: 0 | F77: 0 | H77: =+E77*F77 -> 0
A78: 5 | B78: Guard II | E78: 0 | F78: 0 | H78: =+E78*F78 -> 0
A79: 6 | B79: Guard II | E79: 0 | F79: 0 | H79: =+E79*F79 -> 0
A80: 7 | B80: Guard II | E80: 0 | F80: 0 | H80: =+E80*F80 -> 0
A81: 8 | B81: Guard II | E81: 0 | F81: 0 | H81: =+E81*F81 -> 0
A82: 9 | B82: Guard II | E82: 0 | F82: 0 | H82: =+E82*F82 -> 0
A83: 10 | B83: Guard II | E83: 0 | F83: 0 | H83: =+E83*F83 -> 0
A84: 11 | B84: Guard II | E84: 0 | F84: 0 | H84: =+E84*F84 -> 0
A85: 12 | B85: Guard II | E85: 0 | F85: 0 | H85: =+E85*F85 -> 0
B86: Total | E86: =SUM(E74:E85) -> 0 | H86: =SUM(H74:H85) -> 0 | I86: =+H86/E86 -> #DIV/0! | K86: =+I86*1.5 -> #DIV/0!
B88: Health and Welfare | F88: 5 | H88: =+E86*F88 -> 0
H89: =+H86+H88 -> 0
A91: EMPLOYEE BENEFIT: | E91: FRINGE RATE
B93: Social Security | E93: 0.062 | G93: =+$E93*$H89 -> 0
B94: Medicare | E94: 0.0145 | G94: =+$E94*$H89 -> 0
B95: SUTA | E95: 0 | G95: =+$E95*$H89 -> 0
B96: FUTA | E96: 0 | G96: =+$E96*$H89 -> 0 | H96: Sum of Payroll Taxes | I96: W/ Payroll Taxes
B97: Workman's Comp /General Liability Insurance | E97: 0 | G97: =+$E97*$H89 -> 0 | H97: =SUM(E93:E97) -> 0.0765 | I97: =+H97*I86+I86 -> #DIV/0!
A98: CBA | B98: Sick Leave (Full Time) | C98: 0 | D98: 0 | E98: =+D98*C98 -> 0 | G98: =+E98*I97 -> #DIV/0!
A99: CBA | B99: Sick Leave (Part Time) | C99: 0 | D99: 0 | E99: =+D99*C99 -> 0 | G99: =+E99*I97 -> #DIV/0!
A100: CBA | B100: Holiday (Based on 11 Days) | C100: 0 | D100: 0 | E100: =+C100*D100 -> 0 | G100: =+E100*I97 -> #DIV/0!
A101: CBA | B101: Vacation (Based on 10 Days) | C101: 0 | D101: 0 | E101: =+C101*D101 -> 0 | G101: =+E101*I97 -> #DIV/0!
A102: CBA | B102: Vacation (Based on 17.5 Days) | C102: 0 | D102: 0 | E102: =+D102*C102 -> 0 | G102: =+E102*I97 -> #DIV/0!
A103: CBA | B103: Vacation (Based on 22.5 Days) | C103: 0 | D103: 0 | E103: =+D103*C103 -> 0 | G103: =+E103*I97 -> #DIV/0!
B104: Health and Welfare for Sick/Holiday/Vacation Hours | E104: =SUM(E98:E103) -> 0 | F104: 0 | G104: =E104*F104 -> 0 | H104: =SUM(G93:G104) -> #DIV/0! | I104: =(H104+H88)/H86 -> #DIV/0! | K104: =K86*I104 -> #DIV/0!
H105: =+H104+H89 -> #DIV/0!
A109: OVERHEAD EXPENSE | D109: 0 | H109: =+H105*D109 -> #DIV/0! | I109: =+H109/H105 -> #DIV/0! | K109: =+(K86+K104)*I109 -> #DIV/0!
A111: OTHER DIRECT COSTS (ODC):
B112: Uniforms @ | C112: 0 | D112: 0 | E112: 0 | G112: =+(C112*D112*E112) -> 0
B113: Boot Allowance | C113: 0 | D113: 0 | E113: 0 | G113: =+(C113*D113*E113) -> 0
B114: Ammo | C114: 0 | D114: 0 | E114: 0 | G114: =+(C114*D114*E114) -> 0
B115: Duty Gear | C115: 0 | D115: 0 | E115: 0 | G115: =+(C115*D115*E115) -> 0
B116: Weapons | C116: 0 | D116: 0 | E116: 0 | G116: =+(C116*D116*E116) -> 0
B117: Medical /Drug Screening / Physicals | C117: 0 | D117: 0 | E117: 0 | G117: =+(C117*D117*E117) -> 0
B118: Professional Licenses | C118: 0 | D118: 0 | E118: 0 | G118: =+(C118*D118*E118) -> 0
B119: Training - Nonrecurring | C119: 0 | D119: 0 | E119: 0 | G119: =+(C119*D119*E119) -> 0
B120: Training - Recurring Annual | C120: 0 | D120: 0 | E120: 0 | G120: =+(C120*D120*E120) -> 0
B121: Shooting Range Qualification / Requal | C121: 0 | D121: 0 | E121: 0 | G121: =+(C121*D121*E121) -> 0
...
