Workbook
Name _Hlk8638798: SUMMARY!#REF!

Sheet SUMMARY
A1: Vendor Pricing: DOTS VIPR Procurement (IDIQ)
A4: Vendor:
A5: Title: | B5: Disaster Overseas Transportation Support (DOTS) - Virgin Islands/Puerto Rico (VIPR)
A6: FEMA Component: | B6: Logistics Management Directorate
A7: Contract Type: | B7: IDIQ - Firm Fixed Unit Prices
A8: Date Submitted:
A9: PoP: | B9: 2026 - 2029
A10: Total Contract Value: | B10: =D18 -> 0
A14: Contract Year | B14: Period of Performance | C14: CLIN (s) | D14: Total Cost
A15: Base | B15: 7/1/2026 - 6/30/2027 | C15: 0001 - 0036 | D15: =Base!G173 -> 0
A16: Option Year 1 | B16: 7/1/2027 - 6/30/2028 | C16: 1001 - 1035 | D16: ='OY1'!G173 -> 0
A17: Option Year 2 | B17: 7/1/2028 - 6/30/2029 | C17: 2001 - 2035 | D17: ='OY2'!G173 -> 0
A18: Total | D18: =SUM(D15:D17) -> 0

Sheet Base
A1: CLIN | B1: Description | C1: Quantities | D1: Unit | E1: Unit Price | F1: Days | G1: Total Price | H1: PWS REF
A2: Inclusive of container handling (CHE)/material handling (MHE) equipment usage, fees, taxes, diversions.
A3: GROUND TRANSPORTATION:
A4: 0001 | B4: Surface line haul/Drayage services of containerized commodities from Origin to Port of Embarkation. | H4: 2.2-2.2.1
A5: 0001AA | B5: Ground Transportation: Point of Origin to Port of Embarkation (Mid Atlantic Region) | C5: 250 | D5: EA Container/Trailer | F5: N/A | G5: =IF(ISNUMBER(E5),C5*E5,0) -> 0
A6: 0001AB | B6: Ground Transportation: Point of Origin to Port of Embarkation (South Atlantic Region) | C6: 500 | D6: EA Container/Trailer | F6: N/A | G6: =IF(ISNUMBER(E6),C6*E6,0) -> 0
A7: 0001AC | B7: Ground Transportation: Point of Origin to Port of Embarkation (Gulf Coast) | C7: 200 | D7: EA Container/Trailer | F7: N/A | G7: =IF(ISNUMBER(E7),C7*E7,0) -> 0
A8: 0001AD | B8: Ground Transportation: Point of Origin to Port of Embarkation (FEMA Distribution Center Caribbean, San Juan PR) | C8: 500 | D8: EA Container/Trailer | F8: N/A | G8: =IF(ISNUMBER(E8),C8*E8,0) -> 0
A9: 0002 | B9: Surface line haul services of containerized commodities from Port of Debarkation to FEMA designated Point of Need. | H9: 2.2.4-2.2.5
A10: 0002AA | B10: Ground Transportation: Destination - USVI locations | C10: 1000 | D10: EA Container/Trailer | F10: N/A | G10: =IF(ISNUMBER(E10),C10*E10,0) -> 0
A11: 0002AB | B11: Ground Transportation: Destination - Puerto Rico locations | C11: 2500 | D11: EA Container/Trailer | F11: N/A | G11: =IF(ISNUMBER(E11),C11*E11,0) -> 0
A12: 0003 | B12: Shuttle service of resources Intra-Island (containers/dry van trailers/box trucks/flat beds) | H12: 2.2.4-2.2.5
A13: 0003AA | B13: Ground Transportation: USVI locations | C13: 1000 | D13: EA Container/Trailer | F13: N/A | G13: =IF(ISNUMBER(E13),C13*E13,0) -> 0
A14: 0003AB | B14: Ground Transportation: Puerto Rico locations | C14: 2500 | D14: EA Container/Trailer | F14: N/A | G14: =IF(ISNUMBER(E14),C14*E14,0) -> 0
A15: 0004 | B15: Surface line haul services of containerized retrograde commodities from FEMA designated Point of Need to Port of embarkation. | H15: 2.2-2.2.6
A16: 0004AA | B16: Ground Transportation: Port of Embarkation - USVI | C16: 1000 | D16: EA Container/Trailer | F16: N/A | G16: =IF(ISNUMBER(E16),C16*E16,0) -> 0
A17: 0004AB | B17: Ground Transportation: Port of Embarkation - Puerto Rico | C17: 2500 | D17: EA Container/Trailer | F17: N/A | G17: =IF(ISNUMBER(E17),C17*E17,0) -> 0
A18: 0005 | B18: Surface line haul/Drayage services of Breakbulk Cargo. (Per Chassis) | H18: 2.2-2.2.1
A19: 0005AA | B19: Ground Transportation: Point of Origin to Port of Embarkation (Mid Atlantic Region) | C19: 100 | D19: EA Container/Trailer | F19: N/A | G19: =IF(ISNUMBER(E19),C19*E19,0) -> 0
A20: 0005AB | B20: Ground Transportation: Point of Origin to Port of Embarkation (South Atlantic Region) | C20: 100 | D20: EA Container/Trailer | F20: N/A | G20: =IF(ISNUMBER(E20),C20*E20,0) -> 0
A21: 0005AC | B21: Ground Transportation: Point of Origin to Port of Embarkation (Gulf Coast) | C21: 100 | D21: EA Container/Trailer | F21: N/A | G21: =IF(ISNUMBER(E21),C21*E21,0) -> 0
A22: 0005AD | B22: Ground Transportation: Point of Origin to Port of Embarkation (FEMA Distribution Center Caribbean, San Juan PR) | C22: 100 | D22: EA Container/Trailer | F22: N/A | G22: =IF(ISNUMBER(E22),C22*E22,0) -> 0
A23: 0006 | B23: Surface line haul services of Breakbulk Cargo. (Per Chassis) | H23: 2.2.4-2.2.5
A24: 0006AA | B24: Ground Transportation: Destination - USVI locations | C24: 10 | D24: EA Container/Trailer | F24: N/A | G24: =IF(ISNUMBER(E24),C24*E24,0) -> 0
A25: 0006AB | B25: Ground Transportation: Destination - Puerto Rico locations | C25: 10 | D25: EA Container/Trailer | F25: N/A | G25: =IF(ISNUMBER(E25),C25*E25,0) -> 0
A26: 0007 | B26: Surface line haul services of retrograde Breakbulk Cargo from FEMA designated Point of Need to port of embarkation. (Per Chassis) | H26: 2.2-2.2.6
A27: 0007AA | B27: Ground Transportation: Port of Embarkation - USVI | C27: 10 | D27: EA Container/Trailer | F27: N/A | G27: =IF(ISNUMBER(E27),C27*E27,0) -> 0
A28: 0007AB | B28: Ground Transportation: Port of Embarkation - Puerto Rico | C28: 10 | D28: EA Container/Trailer | F28: N/A | G28: =IF(ISNUMBER(E28),C28*E28,0) -> 0
G29: =SUM(G5:G28) -> 0
A30: OCEAN TRANSPORTATION
A31: 0008 | B31: Transport loaded containers, via ocean vessel from Port of Embarkation to assigned port in the USVI, FOB Destination. | H31: 2.2.2-2.2.6
A32: 0008AA | B32: Ocean Transportation: Mid Atlantic Region to assigned port in the USVI | C32: 250 | D32: EA Container/Trailer | F32: N/A | G32: =IF(ISNUMBER(E32),C32*E32,0) -> 0
A33: 0008AB | B33: Ocean Transportation: South Atlantic Region to assigned port in the USVI | C33: 1000 | D33: EA Container/Trailer | F33: N/A | G33: =IF(ISNUMBER(E33),C33*E33,0) -> 0
A34: 0008AC | B34: Ocean Transportation: Gulf Coast to assigned port in the USVI | C34: 200 | D34: EA Container/Trailer | F34: N/A | G34: =IF(ISNUMBER(E34),C34*E34,0) -> 0
A35: 0008AD | B35: Ocean Transportation: FEMA Distribution Center Caribbean, San Juan PR to assigned port in the USVI | C35: 50 | D35: EA Container/Trailer | F35: N/A | G35: =IF(ISNUMBER(E35),C35*E35,0) -> 0
A36: 0009 | B36: Transport loaded containers, via ocean vessel from Port of Embarkation to assigned port in Puerto Rico, FOB Destination. | H36: 2.2.2-2.2.6
A37: 0009AA | B37: Ocean Transportation: Mid Atlantic Region to assigned port in Puerto Rico | C37: 250 | D37: EA Container/Trailer | F37: N/A | G37: =IF(ISNUMBER(E37),C37*E37,0) -> 0
A38: 0009AB | B38: Ocean Transportation: South Atlantic Region to assigned port in Puerto Rico | C38: 1000 | D38: EA Container/Trailer | F38: N/A | G38: =IF(ISNUMBER(E38),C38*E38,0) -> 0
A39: 0009AC | B39: Ocean Transportation: Gulf Coast to assigned port in Puerto Rico | C39: 200 | D39: EA Container/Trailer | F39: N/A | G39: =IF(ISNUMBER(E39),C39*E39,0) -> 0
A40: 0009AD | B40: Ocean Transportation: FEMA Distribution Center Caribbean, San Juan PR to assigned port in Puerto Rico (i.e. Ponce, Vieques) | C40: 50 | D40: EA Container/Trailer | F40: N/A | G40: =IF(ISNUMBER(E40),C40*E40,0) -> 0
A41: 0010 | B41: Dedicated Vessel Voyage from Port of Embarkation to assigned port in USVI, FOB Destination (30 day minimum length of dedicated vessel) | H41: 2.2.2-2.26
A42: 0010AA | B42: Ocean Transportation: Mid Atlantic Region to assigned port in the USVI | C42: 1 | D42: Vessel/Barge per Day | F42: 30 | G42: =+C42*E42*F42 -> 0
A43: 0010AB | B43: Ocean Transportation: South Atlantic Region to assigned port in the USVI | C43: 1 | D43: Vessel/Barge per Day | F43: 30 | G43: =+C43*E43*F43 -> 0
A44: 0010AC | B44: Ocean Transportation: Gulf Coast to assigned port in the USVI | C44: 1 | D44: Vessel/Barge per Day | F44: 30 | G44: =+C44*E44*F44 -> 0
A45: 0010AD | B45: Ocean Transportation: FEMA Distribution Center Caribbean, San Juan PR to assigned port in the USVI | C45: 1 | D45: Vessel/Barge per Day | F45: 30 | G45: =+C45*E45*F45 -> 0
A46: 0011 | B46: Dedicated Vessel Voyage from Port of Embarkation to assigned port in Puerto Rico, FOB Destination (30 day minimum length of dedicated vessel) | H46: 2.2.2-2.26
A47: 0011AA | B47: Ocean Transportation: Mid Atlantic Region to assigned port in Puerto Rico | C47: 1 | D47: Vessel/Barge per Day | F47: 30 | G47: =+C47*E47*F47 -> 0
A48: 0011AB | B48: Ocean Transportation: South Atlantic Region to assigned port in Puerto Rico | C48: 1 | D48: Vessel/Barge per Day | F48: 30 | G48: =+C48*E48*F48 -> 0
A49: 0011AC | B49: Ocean Transportation: Gulf Coast to assigned port in Puerto Rico | C49: 1 | D49: Vessel/Barge per Day | F49: 30 | G49: =+C49*E49*F49 -> 0
A50: 0011AD | B50: Ocean Transportation: FEMA Distribution Center Caribbean, San Juan PR to assigned port in Puerto Rico | C50: 1 | D50: Vessel/Barge per Day | F50: 30 | G50: =+C50*E50*F50 -> 0
A51: 0012 | B51: Transport Breakbulk Cargo (up to 1200 cft) | H51: 2.2.2
A52: 0012AA | B52: Ocean Transportation: Mid Atlantic Region to Destination USVI | C52: 1000 | D52: Cubic Feet | F52: N/A | G52: =IF(ISNUMBER(E52),C52*E52,0) -> 0
A53: 0012AB | B53: Ocean Transportation: Mid Atlantic Region to Destination Puerto Rico | C53: 1000 | D53: Cubic Feet | F53: N/A | G53: =IF(ISNUMBER(E53),C53*E53,0) -> 0
A54: 0012AC | B54: Ocean Transportation: South Atlantic Region to Destination USVI | C54: 1000 | D54: Cubic Feet | F54: N/A | G54: =IF(ISNUMBER(E54),C54*E54,0) -> 0
A55: 0012AD | B55: Ocean Transportation: South Atlantic Region to Destination Puerto Rico | C55: 1000 | D55: Cubic Feet | F55: N/A | G55: =IF(ISNUMBER(E55),C55*E55,0) -> 0
A56: 0012AE | B56: Ocean Transportation: Gulf Coast to Destination USVI | C56: 1000 | D56: Cubic Feet | F56: N/A | G56: =IF(ISNUMBER(E56),C56*E56,0) -> 0
A57: 0012AF | B57: Ocean Transportation: Gulf Coast to Destination Puerto Rico | C57: 1000 | D57: Cubic Feet | F57: N/A | G57: =IF(ISNUMBER(E57),C57*E57,0) -> 0
A58: 0012AG | B58: Ocean Transportation: FEMA Distribution Center Caribbean to/from Destination USVI | C58: 1000 | D58: Cubic Feet | F58: N/A | G58: =IF(ISNUMBER(E58),C58*E58,0) -> 0
A59: 0013 | B59: Transport Breakbulk Cargo (over 1200 cft) | H59: 2.2.2
A60: 0013AA | B60: Ocean Transportation: Mid Atlantic Region to Destination USVI | C60: 2500 | D60: Cubic Feet | F60: N/A | G60: =IF(ISNUMBER(E60),C60*E60,0) -> 0
A61: 0013AB | B61: Ocean Transportation: Mid Atlantic Region to Destination Puerto Rico | C61: 2500 | D61: Cubic Feet | F61: N/A | G61: =IF(ISNUMBER(E61),C61*E61,0) -> 0
A62: 0013AC | B62: Ocean Transportation: South Atlantic Region to Destination USVI | C62: 2500 | D62: Cubic Feet | F62: N/A | G62: =IF(ISNUMBER(E62),C62*E62,0) -> 0
A63: 0013AD | B63: Ocean Transportation: South Atlantic Region to Destination Puerto Rico | C63: 2500 | D63: Cubic Feet | F63: N/A | G63: =IF(ISNUMBER(E63),C63*E63,0) -> 0
A64: 0013AE | B64: Ocean Transportation: Gulf Coast to Destination USVI | C64: 2500 | D64: Cubic Feet | F64: N/A | G64: =IF(ISNUMBER(E64),C64*E64,0) -> 0
A65: 0013AF | B65: Ocean Transportation: Gulf Coast to Destination Puerto Rico | C65: 2500 | D65: Cubic Feet | F65: N/A | G65: =IF(ISNUMBER(E65),C65*E65,0) -> 0
A66: 0013AG | B66: Ocean Transportation: FEMA Distribution Center Caribbean to/from Destination USVI | C66: 2500 | D66: Cubic Feet | F66: N/A | G66: =IF(ISNUMBER(E66),C66*E66,0) -> 0
A67: 0014 | B67: Retrograde fully loaded containerized commodities from USVI to origin loading facility. | H67: 2.2-2.2.6
A68: 0014AA | B68: Ocean Transportation: USVI to Mid Atlantic Region | C68: 125 | D68: EA Container/Trailer | F68: N/A | G68: =IF(ISNUMBER(E68),C68*E68,0) -> 0
A69: 0014AB | B69: Ocean Transportation: USVI to South Atlantic Region | C69: 1750 | D69: EA Container/Trailer | F69: N/A | G69: =IF(ISNUMBER(E69),C69*E69,0) -> 0
A70: 0014AC | B70: Ocean Transportation: USVI to Gulf Coast | C70: 100 | D70: EA Container/Trailer | F70: N/A | G70: =IF(ISNUMBER(E70),C70*E70,0) -> 0
A71: 0014AD | B71: Ocean Transportation: USVI to FEMA Distribution Center Caribbean, San Juan PR | C71: 25 | D71: EA Container/Trailer | F71: N/A | G71: =IF(ISNUMBER(E71),C71*E71,0) -> 0
A72: 0015 | B72: Retrograde fully loaded containerized commodities from Puerto Rico to origin loading facility. | H72: 2.2-2.2.6
A73: 0015AA | B73: Ocean Transportation: Puerto Rico to Mid Atlantic Region | C73: 125 | D73: EA Container/Trailer | F73: N/A | G73: =IF(ISNUMBER(E73),C73*E73,0) -> 0
A74: 0015AB | B74: Ocean Transportation: Puerto Rico to South Atlantic Region | C74: 1750 | D74: EA Container/Trailer | F74: N/A | G74: =IF(ISNUMBER(E74),C74*E74,0) -> 0
A75: 0015AC | B75: Ocean Transportation: Puerto Rico to Gulf Coast | C75: 100 | D75: EA Container/Trailer | F75: N/A | G75: =IF(ISNUMBER(E75),C75*E75,0) -> 0
A76: 0016 | B76: Retrograde Breakbulk Cargo (up to 1200 cft) | H76: 2.2-2.2.6
A77: 0016AA | B77: Ocean Transportation: USVI to Mid Atlantic Region | C77: 500 | D77: Cubic Feet | F77: N/A | G77: =IF(ISNUMBER(E77),C77*E77,0) -> 0
A78: 0016AB | B78: Ocean Transportation: USVI to South Atlantic Region | C78: 500 | D78: Cubic Feet | F78: N/A | G78: =IF(ISNUMBER(E78),C78*E78,0) -> 0
A79: 0016AC | B79: Ocean Transportation: USVI to Gulf Coast | C79: 500 | D79: Cubic Feet | F79: N/A | G79: =IF(ISNUMBER(E79),C79*E79,0) -> 0
A80: 0016AD | B80: Ocean Transportation: USVI to FEMA Distribution Center Caribbean | C80: 500 | D80: Cubic Feet | F80: N/A | G80: =IF(ISNUMBER(E80),C80*E80,0) -> 0
A81: 0016AE | B81: Ocean Transportation: Puerto Rico to Mid Atlantic Region | C81: 500 | D81: Cubic Feet | F81: N/A | G81: =IF(ISNUMBER(E81),C81*E81,0) -> 0
A82: 0016AF | B82: Ocean Transportation: Puerto Rico to South Atlantic Region | C82: 500 | D82: Cubic Feet | F82: N/A | G82: =IF(ISNUMBER(E82),C82*E82,0) -> 0
A83: 0016AG | B83: Ocean Transportation: Puerto Rico to Gulf Coast | C83: 500 | D83: Cubic Feet | F83: N/A | G83: =IF(ISNUMBER(E83),C83*E83,0) -> 0
A84: 0017 | B84: Retrograde Breakbulk Cargo (above 1200 cft) | H84: 2.2-2.2.6
A85: 0017AA | B85: Ocean Transportation: USVI to Mid Atlantic Region | C85: 1750 | D85: Cubic Feet | F85: N/A | G85: =IF(ISNUMBER(E85),C85*E85,0) -> 0
A86: 0017AB | B86: Ocean Transportation: USVI to South Atlantic Region | C86: 1750 | D86: Cubic Feet | F86: N/A | G86: =IF(ISNUMBER(E86),C86*E86,0) -> 0
A87: 0017AC | B87: Ocean Transportation: USVI to Gulf Coast | C87: 1750 | D87: Cubic Feet | F87: N/A | G87: =IF(ISNUMBER(E87),C87*E87,0) -> 0
A88: 0017AD | B88: Ocean Transportation: USVI to FEMA Distribution Center Caribbean | C88: 1750 | D88: Cubic Feet | F88: N/A | G88: =IF(ISNUMBER(E88),C88*E88,0) -> 0
A89: 0017AE | B89: Ocean Transportation: Puerto Rico to Mid Atlantic Region | C89: 1750 | D89: Cubic Feet | F89: N/A | G89: =IF(ISNUMBER(E89),C89*E89,0) -> 0
A90: 0017AF | B90: Ocean Transportation: Puerto Rico to South Atlantic Region | C90: 1750 | D90: Cubic Feet | F90: N/A | G90: =IF(ISNUMBER(E90),C90*E90,0) -> 0
A91: 0017AG | B91: Ocean Transportation: Puerto Rico to Gulf Coast | C91: 1750 | D91: Cubic Feet | F91: N/A | G91: =IF(ISNUMBER(E91),C91*E91,0) -> 0
G92: =SUM(G32:G91) -> 0
A93: AIR TRANSPORTATION
A94: 0018 | B94: Expedited Air Transportation Services. USVI, FOB Destination. Standard Pallet Size (48"L x 40"W x 48"H). Weight: Below 1650lbs. | H94: 2.3
A95: 0018AA | B95: Air Transportation: Mid Atlantic Region to Destination USVI | C95: 200 | D95: Pallet | F95: N/A | G95: =IF(ISNUMBER(E95),C95*E95,0) -> 0
A96: 0018AB | B96: Air Transportation: South Atlantic Region to Destination USVI | C96: 200 | D96: Pallet | F96: N/A | G96: =IF(ISNUMBER(E96),C96*E96,0) -> 0
A97: 0018AC | B97: Air Transportation: Gulf Coast to Destination USVI | C97: 200 | D97: Pallet | F97: N/A | G97: =IF(ISNUMBER(E97),C97*E97,0) -> 0
A98: 0018AD | B98: Air Transportation: FEMA Distribution Center Caribbean to Destination USVI | C98: 200 | D98: Pallet | F98: N/A | G98: =IF(ISNUMBER(E98),C98*E98,0) -> 0
A99: 0019 | B99: Expedited Air Transportation Services. Puerto Rico, FOB Destination. Standard Pallet Size (48"L x 40"W x 48"H). Weight: Below 1650lbs. | H99: 2.3
A100: 0019AA | B100: Air Transportation: Mid Atlantic Region to Destination Puerto Rico | C100: 200 | D100: Pallet | F100: N/A | G100: =IF(ISNUMBER(E100),C100*E100,0) -> 0
...

Sheet OY1
A1: CLIN | B1: Description | C1: Quantities | D1: Unit | E1: Unit Price | F1: Days | G1: Total Price | H1: PWS REF
A2: Inclusive of container handling (CHE)/material handling (MHE) equipment usage, fees, taxes, diversions.
A3: GROUND TRANSPORTATION:
A4: 1001 | B4: Surface line haul/Drayage services of containerized commodities from Origin to Port of Embarkation. | H4: 2.2-2.2.1
A5: 1001AA | B5: Ground Transportation: Point of Origin to Port of Embarkation (Mid Atlantic Region) | C5: 250 | D5: EA Container/Trailer | F5: N/A | G5: =IF(ISNUMBER(E5),C5*E5,0) -> 0
A6: 1001AB | B6: Ground Transportation: Point of Origin to Port of Embarkation (South Atlantic Region) | C6: 500 | D6: EA Container/Trailer | F6: N/A | G6: =IF(ISNUMBER(E6),C6*E6,0) -> 0
A7: 1001AC | B7: Ground Transportation: Point of Origin to Port of Embarkation (Gulf Coast) | C7: 200 | D7: EA Container/Trailer | F7: N/A | G7: =IF(ISNUMBER(E7),C7*E7,0) -> 0
A8: 1001AD | B8: Ground Transportation: Point of Origin to Port of Embarkation (FEMA Distribution Center Caribbean, San Juan PR) | C8: 500 | D8: EA Container/Trailer | F8: N/A | G8: =IF(ISNUMBER(E8),C8*E8,0) -> 0
A9: 1002 | B9: Surface line haul services of containerized commodities from Port of Debarkation to FEMA designated Point of Need. | H9: 2.2.4-2.2.5
A10: 1002AA | B10: Ground Transportation: Destination - USVI locations | C10: 1000 | D10: EA Container/Trailer | F10: N/A | G10: =IF(ISNUMBER(E10),C10*E10,0) -> 0
A11: 1002AB | B11: Ground Transportation: Destination - Puerto Rico locations | C11: 2500 | D11: EA Container/Trailer | F11: N/A | G11: =IF(ISNUMBER(E11),C11*E11,0) -> 0
A12: 1003 | B12: Shuttle service of resources Intra-Island (containers/dry van trailers/box trucks/flat beds) | H12: 2.2.4-2.2.5
A13: 1003AA | B13: Ground Transportation: USVI locations | C13: 1000 | D13: EA Container/Trailer | F13: N/A | G13: =IF(ISNUMBER(E13),C13*E13,0) -> 0
A14: 1003AB | B14: Ground Transportation: Puerto Rico locations | C14: 2500 | D14: EA Container/Trailer | F14: N/A | G14: =IF(ISNUMBER(E14),C14*E14,0) -> 0
A15: 1004 | B15: Surface line haul services of containerized retrograde commodities from FEMA designated Point of Need to Port of embarkation. | H15: 2.2-2.2.6
A16: 1004AA | B16: Ground Transportation: Port of Embarkation - USVI | C16: 1000 | D16: EA Container/Trailer | F16: N/A | G16: =IF(ISNUMBER(E16),C16*E16,0) -> 0
A17: 1004AB | B17: Ground Transportation: Port of Embarkation - Puerto Rico | C17: 2500 | D17: EA Container/Trailer | F17: N/A | G17: =IF(ISNUMBER(E17),C17*E17,0) -> 0
A18: 1005 | B18: Surface line haul/Drayage services of Breakbulk Cargo. (Per Chassis) | H18: 2.2-2.2.1
A19: 1005AA | B19: Ground Transportation: Point of Origin to Port of Embarkation (Mid Atlantic Region) | C19: 100 | D19: EA Container/Trailer | F19: N/A | G19: =IF(ISNUMBER(E19),C19*E19,0) -> 0
A20: 1005AB | B20: Ground Transportation: Point of Origin to Port of Embarkation (South Atlantic Region) | C20: 100 | D20: EA Container/Trailer | F20: N/A | G20: =IF(ISNUMBER(E20),C20*E20,0) -> 0
A21: 1005AC | B21: Ground Transportation: Point of Origin to Port of Embarkation (Gulf Coast) | C21: 100 | D21: EA Container/Trailer | F21: N/A | G21: =IF(ISNUMBER(E21),C21*E21,0) -> 0
A22: 1005AD | B22: Ground Transportation: Point of Origin to Port of Embarkation (FEMA Distribution Center Caribbean, San Juan PR) | C22: 100 | D22: EA Container/Trailer | F22: N/A | G22: =IF(ISNUMBER(E22),C22*E22,0) -> 0
A23: 1006 | B23: Surface line haul services of Breakbulk Cargo. (Per Chassis) | H23: 2.2.4-2.2.5
A24: 1006AA | B24: Ground Transportation: Destination - USVI locations | C24: 10 | D24: EA Container/Trailer | F24: N/A | G24: =IF(ISNUMBER(E24),C24*E24,0) -> 0
A25: 1006AB | B25: Ground Transportation: Destination - Puerto Rico locations | C25: 10 | D25: EA Container/Trailer | F25: N/A | G25: =IF(ISNUMBER(E25),C25*E25,0) -> 0
A26: 1007 | B26: Surface line haul services of retrograde Breakbulk Cargo from FEMA designated Point of Need to port of embarkation. (Per Chassis) | H26: 2.2-2.2.6
A27: 1007AA | B27: Ground Transportation: Port of Embarkation - USVI | C27: 10 | D27: EA Container/Trailer | F27: N/A | G27: =IF(ISNUMBER(E27),C27*E27,0) -> 0
A28: 1007AB | B28: Ground Transportation: Port of Embarkation - Puerto Rico | C28: 10 | D28: EA Container/Trailer | F28: N/A | G28: =IF(ISNUMBER(E28),C28*E28,0) -> 0
G29: =SUM(G5:G28) -> 0
A30: OCEAN TRANSPORTATION
A31: 1008 | B31: Transport loaded containers, via ocean vessel from Port of Embarkation to assigned port in the USVI, FOB Destination. | H31: 2.2.2-2.2.6
A32: 1008AA | B32: Ocean Transportation: Mid Atlantic Region to assigned port in the USVI | C32: 250 | D32: EA Container/Trailer | F32: N/A | G32: =IF(ISNUMBER(E32),C32*E32,0) -> 0
A33: 1008AB | B33: Ocean Transportation: South Atlantic Region to assigned port in the USVI | C33: 1000 | D33: EA Container/Trailer | F33: N/A | G33: =IF(ISNUMBER(E33),C33*E33,0) -> 0
A34: 1008AC | B34: Ocean Transportation: Gulf Coast to assigned port in the USVI | C34: 200 | D34: EA Container/Trailer | F34: N/A | G34: =IF(ISNUMBER(E34),C34*E34,0) -> 0
A35: 1008AD | B35: Ocean Transportation: FEMA Distribution Center Caribbean, San Juan PR to assigned port in the USVI | C35: 50 | D35: EA Container/Trailer | F35: N/A | G35: =IF(ISNUMBER(E35),C35*E35,0) -> 0
A36: 1009 | B36: Transport loaded containers, via ocean vessel from Port of Embarkation to assigned port in Puerto Rico, FOB Destination. | H36: 2.2.2-2.2.6
A37: 1009AA | B37: Ocean Transportation: Mid Atlantic Region to assigned port in Puerto Rico | C37: 250 | D37: EA Container/Trailer | F37: N/A | G37: =IF(ISNUMBER(E37),C37*E37,0) -> 0
A38: 1009AB | B38: Ocean Transportation: South Atlantic Region to assigned port in Puerto Rico | C38: 1000 | D38: EA Container/Trailer | F38: N/A | G38: =IF(ISNUMBER(E38),C38*E38,0) -> 0
A39: 1009AC | B39: Ocean Transportation: Gulf Coast to assigned port in Puerto Rico | C39: 200 | D39: EA Container/Trailer | F39: N/A | G39: =IF(ISNUMBER(E39),C39*E39,0) -> 0
A40: 1009AD | B40: Ocean Transportation: FEMA Distribution Center Caribbean, San Juan PR to assigned port in Puerto Rico (i.e. Ponce, Vieques) | C40: 50 | D40: EA Container/Trailer | F40: N/A | G40: =IF(ISNUMBER(E40),C40*E40,0) -> 0
A41: 1010 | B41: Dedicated Vessel Voyage from Port of Embarkation to assigned port in USVI, FOB Destination (30 day minimum length of dedicated vessel) | H41: 2.2.2-2.26
A42: 1010AA | B42: Ocean Transportation: Mid Atlantic Region to assigned port in the USVI | C42: 1 | D42: Vessel/Barge per Day | F42: 30 | G42: =+C42*E42*F42 -> 0
A43: 1010AB | B43: Ocean Transportation: South Atlantic Region to assigned port in the USVI | C43: 1 | D43: Vessel/Barge per Day | F43: 30 | G43: =+C43*E43*F43 -> 0
A44: 1010AC | B44: Ocean Transportation: Gulf Coast to assigned port in the USVI | C44: 1 | D44: Vessel/Barge per Day | F44: 30 | G44: =+C44*E44*F44 -> 0
A45: 1010AD | B45: Ocean Transportation: FEMA Distribution Center Caribbean, San Juan PR to assigned port in the USVI | C45: 1 | D45: Vessel/Barge per Day | F45: 30 | G45: =+C45*E45*F45 -> 0
A46: 1011 | B46: Dedicated Vessel Voyage from Port of Embarkation to assigned port in Puerto Rico, FOB Destination (30 day minimum length of dedicated vessel) | H46: 2.2.2-2.26
A47: 1011AA | B47: Ocean Transportation: Mid Atlantic Region to assigned port in Puerto Rico | C47: 1 | D47: Vessel/Barge per Day | F47: 30 | G47: =+C47*E47*F47 -> 0
A48: 1011AB | B48: Ocean Transportation: South Atlantic Region to assigned port in Puerto Rico | C48: 1 | D48: Vessel/Barge per Day | F48: 30 | G48: =+C48*E48*F48 -> 0
A49: 1011AC | B49: Ocean Transportation: Gulf Coast to assigned port in Puerto Rico | C49: 1 | D49: Vessel/Barge per Day | F49: 30 | G49: =+C49*E49*F49 -> 0
A50: 1011AD | B50: Ocean Transportation: FEMA Distribution Center Caribbean, San Juan PR to assigned port in Puerto Rico | C50: 1 | D50: Vessel/Barge per Day | F50: 30 | G50: =+C50*E50*F50 -> 0
A51: 1012 | B51: Transport Breakbulk Cargo (up to 1200 cft) | H51: 2.2.2
A52: 1012AA | B52: Ocean Transportation: Mid Atlantic Region to Destination USVI | C52: 1000 | D52: Cubic Feet | F52: N/A | G52: =IF(ISNUMBER(E52),C52*E52,0) -> 0
A53: 1012AB | B53: Ocean Transportation: Mid Atlantic Region to Destination Puerto Rico | C53: 1000 | D53: Cubic Feet | F53: N/A | G53: =IF(ISNUMBER(E53),C53*E53,0) -> 0
A54: 1012AC | B54: Ocean Transportation: South Atlantic Region to Destination USVI | C54: 1000 | D54: Cubic Feet | F54: N/A | G54: =IF(ISNUMBER(E54),C54*E54,0) -> 0
A55: 1012AD | B55: Ocean Transportation: South Atlantic Region to Destination Puerto Rico | C55: 1000 | D55: Cubic Feet | F55: N/A | G55: =IF(ISNUMBER(E55),C55*E55,0) -> 0
A56: 1012AE | B56: Ocean Transportation: Gulf Coast to Destination USVI | C56: 1000 | D56: Cubic Feet | F56: N/A | G56: =IF(ISNUMBER(E56),C56*E56,0) -> 0
A57: 1012AF | B57: Ocean Transportation: Gulf Coast to Destination Puerto Rico | C57: 1000 | D57: Cubic Feet | F57: N/A | G57: =IF(ISNUMBER(E57),C57*E57,0) -> 0
A58: 1012AG | B58: Ocean Transportation: FEMA Distribution Center Caribbean to/from Destination USVI | C58: 1000 | D58: Cubic Feet | F58: N/A | G58: =IF(ISNUMBER(E58),C58*E58,0) -> 0
A59: 1013 | B59: Transport Breakbulk Cargo (over 1200 cft) | H59: 2.2.2
A60: 1013AA | B60: Ocean Transportation: Mid Atlantic Region to Destination USVI | C60: 2500 | D60: Cubic Feet | F60: N/A | G60: =IF(ISNUMBER(E60),C60*E60,0) -> 0
A61: 1013AB | B61: Ocean Transportation: Mid Atlantic Region to Destination Puerto Rico | C61: 2500 | D61: Cubic Feet | F61: N/A | G61: =IF(ISNUMBER(E61),C61*E61,0) -> 0
A62: 1013AC | B62: Ocean Transportation: South Atlantic Region to Destination USVI | C62: 2500 | D62: Cubic Feet | F62: N/A | G62: =IF(ISNUMBER(E62),C62*E62,0) -> 0
A63: 1013AD | B63: Ocean Transportation: South Atlantic Region to Destination Puerto Rico | C63: 2500 | D63: Cubic Feet | F63: N/A | G63: =IF(ISNUMBER(E63),C63*E63,0) -> 0
A64: 1013AE | B64: Ocean Transportation: Gulf Coast to Destination USVI | C64: 2500 | D64: Cubic Feet | F64: N/A | G64: =IF(ISNUMBER(E64),C64*E64,0) -> 0
A65: 1013AF | B65: Ocean Transportation: Gulf Coast to Destination Puerto Rico | C65: 2500 | D65: Cubic Feet | F65: N/A | G65: =IF(ISNUMBER(E65),C65*E65,0) -> 0
A66: 1013AG | B66: Ocean Transportation: FEMA Distribution Center Caribbean to/from Destination USVI | C66: 2500 | D66: Cubic Feet | F66: N/A | G66: =IF(ISNUMBER(E66),C66*E66,0) -> 0
A67: 1014 | B67: Retrograde fully loaded containerized commodities from USVI to origin loading facility. | H67: 2.2-2.2.6
A68: 1014AA | B68: Ocean Transportation: USVI to Mid Atlantic Region | C68: 125 | D68: EA Container/Trailer | F68: N/A | G68: =IF(ISNUMBER(E68),C68*E68,0) -> 0
A69: 1014AB | B69: Ocean Transportation: USVI to South Atlantic Region | C69: 1750 | D69: EA Container/Trailer | F69: N/A | G69: =IF(ISNUMBER(E69),C69*E69,0) -> 0
A70: 1014AC | B70: Ocean Transportation: USVI to Gulf Coast | C70: 100 | D70: EA Container/Trailer | F70: N/A | G70: =IF(ISNUMBER(E70),C70*E70,0) -> 0
A71: 1014AD | B71: Ocean Transportation: USVI to FEMA Distribution Center Caribbean, San Juan PR | C71: 25 | D71: EA Container/Trailer | F71: N/A | G71: =IF(ISNUMBER(E71),C71*E71,0) -> 0
A72: 1015 | B72: Retrograde fully loaded containerized commodities from Puerto Rico to origin loading facility. | H72: 2.2-2.2.6
A73: 1015AA | B73: Ocean Transportation: Puerto Rico to Mid Atlantic Region | C73: 125 | D73: EA Container/Trailer | F73: N/A | G73: =IF(ISNUMBER(E73),C73*E73,0) -> 0
A74: 1015AB | B74: Ocean Transportation: Puerto Rico to South Atlantic Region | C74: 1750 | D74: EA Container/Trailer | F74: N/A | G74: =IF(ISNUMBER(E74),C74*E74,0) -> 0
A75: 1015AC | B75: Ocean Transportation: Puerto Rico to Gulf Coast | C75: 100 | D75: EA Container/Trailer | F75: N/A | G75: =IF(ISNUMBER(E75),C75*E75,0) -> 0
A76: 1016 | B76: Retrograde Breakbulk Cargo (up to 1200 cft) | H76: 2.2-2.2.6
A77: 1016AA | B77: Ocean Transportation: USVI to Mid Atlantic Region | C77: 500 | D77: Cubic Feet | F77: N/A | G77: =IF(ISNUMBER(E77),C77*E77,0) -> 0
A78: 1016AB | B78: Ocean Transportation: USVI to South Atlantic Region | C78: 500 | D78: Cubic Feet | F78: N/A | G78: =IF(ISNUMBER(E78),C78*E78,0) -> 0
A79: 1016AC | B79: Ocean Transportation: USVI to Gulf Coast | C79: 500 | D79: Cubic Feet | F79: N/A | G79: =IF(ISNUMBER(E79),C79*E79,0) -> 0
A80: 1016AD | B80: Ocean Transportation: USVI to FEMA Distribution Center Caribbean | C80: 500 | D80: Cubic Feet | F80: N/A | G80: =IF(ISNUMBER(E80),C80*E80,0) -> 0
A81: 1016AE | B81: Ocean Transportation: Puerto Rico to Mid Atlantic Region | C81: 500 | D81: Cubic Feet | F81: N/A | G81: =IF(ISNUMBER(E81),C81*E81,0) -> 0
A82: 1016AF | B82: Ocean Transportation: Puerto Rico to South Atlantic Region | C82: 500 | D82: Cubic Feet | F82: N/A | G82: =IF(ISNUMBER(E82),C82*E82,0) -> 0
A83: 1016AG | B83: Ocean Transportation: Puerto Rico to Gulf Coast | C83: 500 | D83: Cubic Feet | F83: N/A | G83: =IF(ISNUMBER(E83),C83*E83,0) -> 0
A84: 1017 | B84: Retrograde Breakbulk Cargo (above 1200 cft) | H84: 2.2-2.2.6
A85: 1017AA | B85: Ocean Transportation: USVI to Mid Atlantic Region | C85: 1750 | D85: Cubic Feet | F85: N/A | G85: =IF(ISNUMBER(E85),C85*E85,0) -> 0
A86: 1017AB | B86: Ocean Transportation: USVI to South Atlantic Region | C86: 1750 | D86: Cubic Feet | F86: N/A | G86: =IF(ISNUMBER(E86),C86*E86,0) -> 0
A87: 1017AC | B87: Ocean Transportation: USVI to Gulf Coast | C87: 1750 | D87: Cubic Feet | F87: N/A | G87: =IF(ISNUMBER(E87),C87*E87,0) -> 0
A88: 1017AD | B88: Ocean Transportation: USVI to FEMA Distribution Center Caribbean | C88: 1750 | D88: Cubic Feet | F88: N/A | G88: =IF(ISNUMBER(E88),C88*E88,0) -> 0
A89: 1017AE | B89: Ocean Transportation: Puerto Rico to Mid Atlantic Region | C89: 1750 | D89: Cubic Feet | F89: N/A | G89: =IF(ISNUMBER(E89),C89*E89,0) -> 0
A90: 1017AF | B90: Ocean Transportation: Puerto Rico to South Atlantic Region | C90: 1750 | D90: Cubic Feet | F90: N/A | G90: =IF(ISNUMBER(E90),C90*E90,0) -> 0
A91: 1017AG | B91: Ocean Transportation: Puerto Rico to Gulf Coast | C91: 1750 | D91: Cubic Feet | F91: N/A | G91: =IF(ISNUMBER(E91),C91*E91,0) -> 0
G92: =SUM(G32:G91) -> 0
A93: AIR TRANSPORTATION
A94: 1018 | B94: Expedited Air Transportation Services. USVI, FOB Destination. Standard Pallet Size (48"L x 40"W x 48"H). Weight: Below 1650lbs. | H94: 2.3
A95: 1018AA | B95: Air Transportation: Mid Atlantic Region to Destination USVI | C95: 200 | D95: Pallet | F95: N/A | G95: =IF(ISNUMBER(E95),C95*E95,0) -> 0
A96: 1018AB | B96: Air Transportation: South Atlantic Region to Destination USVI | C96: 200 | D96: Pallet | F96: N/A | G96: =IF(ISNUMBER(E96),C96*E96,0) -> 0
A97: 1018AC | B97: Air Transportation: Gulf Coast to Destination USVI | C97: 200 | D97: Pallet | F97: N/A | G97: =IF(ISNUMBER(E97),C97*E97,0) -> 0
A98: 1018AD | B98: Air Transportation: FEMA Distribution Center Caribbean to Destination USVI | C98: 200 | D98: Pallet | F98: N/A | G98: =IF(ISNUMBER(E98),C98*E98,0) -> 0
A99: 1019 | B99: Expedited Air Transportation Services. Puerto Rico, FOB Destination. Standard Pallet Size (48"L x 40"W x 48"H). Weight: Below 1650lbs. | H99: 2.3
A100: 1019AA | B100: Air Transportation: Mid Atlantic Region to Destination Puerto Rico | C100: 200 | D100: Pallet | F100: N/A | G100: =IF(ISNUMBER(E100),C100*E100,0) -> 0
...

Sheet OY2
A1: CLIN | B1: Description | C1: Quantities | D1: Unit | E1: Unit Price | F1: Days | G1: Total Price | H1: PWS REF
A2: Inclusive of container handling (CHE)/material handling (MHE) equipment usage, fees, taxes, diversions.
A3: GROUND TRANSPORTATION:
A4: 2001 | B4: Surface line haul/Drayage services of containerized commodities from Origin to Port of Embarkation. | H4: 2.2-2.2.1
A5: 2001AA | B5: Ground Transportation: Point of Origin to Port of Embarkation (Mid Atlantic Region) | C5: 250 | D5: EA Container/Trailer | F5: N/A | G5: =IF(ISNUMBER(E5),C5*E5,0) -> 0
A6: 2001AB | B6: Ground Transportation: Point of Origin to Port of Embarkation (South Atlantic Region) | C6: 500 | D6: EA Container/Trailer | F6: N/A | G6: =IF(ISNUMBER(E6),C6*E6,0) -> 0
A7: 2001AC | B7: Ground Transportation: Point of Origin to Port of Embarkation (Gulf Coast) | C7: 200 | D7: EA Container/Trailer | F7: N/A | G7: =IF(ISNUMBER(E7),C7*E7,0) -> 0
A8: 2001AD | B8: Ground Transportation: Point of Origin to Port of Embarkation (FEMA Distribution Center Caribbean, San Juan PR) | C8: 500 | D8: EA Container/Trailer | F8: N/A | G8: =IF(ISNUMBER(E8),C8*E8,0) -> 0
A9: 2002 | B9: Surface line haul services of containerized commodities from Port of Debarkation to FEMA designated Point of Need. | H9: 2.2.4-2.2.5
A10: 2002AA | B10: Ground Transportation: Destination - USVI locations | C10: 1000 | D10: EA Container/Trailer | F10: N/A | G10: =IF(ISNUMBER(E10),C10*E10,0) -> 0
A11: 2002AB | B11: Ground Transportation: Destination - Puerto Rico locations | C11: 2500 | D11: EA Container/Trailer | F11: N/A | G11: =IF(ISNUMBER(E11),C11*E11,0) -> 0
A12: 2003 | B12: Shuttle service of resources Intra-Island (containers/dry van trailers/box trucks/flat beds) | H12: 2.2.4-2.2.5
A13: 2003AA | B13: Ground Transportation: USVI locations | C13: 1000 | D13: EA Container/Trailer | F13: N/A | G13: =IF(ISNUMBER(E13),C13*E13,0) -> 0
A14: 2003AB | B14: Ground Transportation: Puerto Rico locations | C14: 2500 | D14: EA Container/Trailer | F14: N/A | G14: =IF(ISNUMBER(E14),C14*E14,0) -> 0
A15: 2004 | B15: Surface line haul services of containerized retrograde commodities from FEMA designated Point of Need to Port of embarkation. | H15: 2.2-2.2.6
A16: 2004AA | B16: Ground Transportation: Port of Embarkation - USVI | C16: 1000 | D16: EA Container/Trailer | F16: N/A | G16: =IF(ISNUMBER(E16),C16*E16,0) -> 0
A17: 2004AB | B17: Ground Transportation: Port of Embarkation - Puerto Rico | C17: 2500 | D17: EA Container/Trailer | F17: N/A | G17: =IF(ISNUMBER(E17),C17*E17,0) -> 0
A18: 2005 | B18: Surface line haul/Drayage services of Breakbulk Cargo. (Per Chassis) | H18: 2.2-2.2.1
A19: 2005AA | B19: Ground Transportation: Point of Origin to Port of Embarkation (Mid Atlantic Region) | C19: 100 | D19: EA Container/Trailer | F19: N/A | G19: =IF(ISNUMBER(E19),C19*E19,0) -> 0
A20: 2005AB | B20: Ground Transportation: Point of Origin to Port of Embarkation (South Atlantic Region) | C20: 100 | D20: EA Container/Trailer | F20: N/A | G20: =IF(ISNUMBER(E20),C20*E20,0) -> 0
A21: 2005AC | B21: Ground Transportation: Point of Origin to Port of Embarkation (Gulf Coast) | C21: 100 | D21: EA Container/Trailer | F21: N/A | G21: =IF(ISNUMBER(E21),C21*E21,0) -> 0
A22: 2005AD | B22: Ground Transportation: Point of Origin to Port of Embarkation (FEMA Distribution Center Caribbean, San Juan PR) | C22: 100 | D22: EA Container/Trailer | F22: N/A | G22: =IF(ISNUMBER(E22),C22*E22,0) -> 0
A23: 2006 | B23: Surface line haul services of Breakbulk Cargo. (Per Chassis) | H23: 2.2.4-2.2.5
A24: 2006AA | B24: Ground Transportation: Destination - USVI locations | C24: 10 | D24: EA Container/Trailer | F24: N/A | G24: =IF(ISNUMBER(E24),C24*E24,0) -> 0
A25: 2006AB | B25: Ground Transportation: Destination - Puerto Rico locations | C25: 10 | D25: EA Container/Trailer | F25: N/A | G25: =IF(ISNUMBER(E25),C25*E25,0) -> 0
A26: 2007 | B26: Surface line haul services of retrograde Breakbulk Cargo from FEMA designated Point of Need to port of embarkation. (Per Chassis) | H26: 2.2-2.2.6
A27: 2007AA | B27: Ground Transportation: Port of Embarkation - USVI | C27: 10 | D27: EA Container/Trailer | F27: N/A | G27: =IF(ISNUMBER(E27),C27*E27,0) -> 0
A28: 2007AB | B28: Ground Transportation: Port of Embarkation - Puerto Rico | C28: 10 | D28: EA Container/Trailer | F28: N/A | G28: =IF(ISNUMBER(E28),C28*E28,0) -> 0
G29: =SUM(G5:G28) -> 0
A30: OCEAN TRANSPORTATION
A31: 2008 | B31: Transport loaded containers, via ocean vessel from Port of Embarkation to assigned port in the USVI, FOB Destination. | H31: 2.2.2-2.2.6
A32: 2008AA | B32: Ocean Transportation: Mid Atlantic Region to assigned port in the USVI | C32: 250 | D32: EA Container/Trailer | F32: N/A | G32: =IF(ISNUMBER(E32),C32*E32,0) -> 0
A33: 2008AB | B33: Ocean Transportation: South Atlantic Region to assigned port in the USVI | C33: 1000 | D33: EA Container/Trailer | F33: N/A | G33: =IF(ISNUMBER(E33),C33*E33,0) -> 0
A34: 2008AC | B34: Ocean Transportation: Gulf Coast to assigned port in the USVI | C34: 200 | D34: EA Container/Trailer | F34: N/A | G34: =IF(ISNUMBER(E34),C34*E34,0) -> 0
A35: 2008AD | B35: Ocean Transportation: FEMA Distribution Center Caribbean, San Juan PR to assigned port in the USVI | C35: 50 | D35: EA Container/Trailer | F35: N/A | G35: =IF(ISNUMBER(E35),C35*E35,0) -> 0
A36: 2009 | B36: Transport loaded containers, via ocean vessel from Port of Embarkation to assigned port in Puerto Rico, FOB Destination. | H36: 2.2.2-2.2.6
A37: 2009AA | B37: Ocean Transportation: Mid Atlantic Region to assigned port in Puerto Rico | C37: 250 | D37: EA Container/Trailer | F37: N/A | G37: =IF(ISNUMBER(E37),C37*E37,0) -> 0
A38: 2009AB | B38: Ocean Transportation: South Atlantic Region to assigned port in Puerto Rico | C38: 1000 | D38: EA Container/Trailer | F38: N/A | G38: =IF(ISNUMBER(E38),C38*E38,0) -> 0
A39: 2009AC | B39: Ocean Transportation: Gulf Coast to assigned port in Puerto Rico | C39: 200 | D39: EA Container/Trailer | F39: N/A | G39: =IF(ISNUMBER(E39),C39*E39,0) -> 0
A40: 2009AD | B40: Ocean Transportation: FEMA Distribution Center Caribbean, San Juan PR to assigned port in Puerto Rico (i.e. Ponce, Vieques) | C40: 50 | D40: EA Container/Trailer | F40: N/A | G40: =IF(ISNUMBER(E40),C40*E40,0) -> 0
A41: 2010 | B41: Dedicated Vessel Voyage from Port of Embarkation to assigned port in USVI, FOB Destination (30 day minimum length of dedicated vessel) | H41: 2.2.2-2.26
A42: 2010AA | B42: Ocean Transportation: Mid Atlantic Region to assigned port in the USVI | C42: 1 | D42: Vessel/Barge per Day | F42: 30 | G42: =+C42*E42*F42 -> 0
A43: 2010AB | B43: Ocean Transportation: South Atlantic Region to assigned port in the USVI | C43: 1 | D43: Vessel/Barge per Day | F43: 30 | G43: =+C43*E43*F43 -> 0
A44: 2010AC | B44: Ocean Transportation: Gulf Coast to assigned port in the USVI | C44: 1 | D44: Vessel/Barge per Day | F44: 30 | G44: =+C44*E44*F44 -> 0
A45: 2010AD | B45: Ocean Transportation: FEMA Distribution Center Caribbean, San Juan PR to assigned port in the USVI | C45: 1 | D45: Vessel/Barge per Day | F45: 30 | G45: =+C45*E45*F45 -> 0
A46: 2011 | B46: Dedicated Vessel Voyage from Port of Embarkation to assigned port in Puerto Rico, FOB Destination (30 day minimum length of dedicated vessel) | H46: 2.2.2-2.26
A47: 2011AA | B47: Ocean Transportation: Mid Atlantic Region to assigned port in Puerto Rico | C47: 1 | D47: Vessel/Barge per Day | F47: 30 | G47: =+C47*E47*F47 -> 0
A48: 2011AB | B48: Ocean Transportation: South Atlantic Region to assigned port in Puerto Rico | C48: 1 | D48: Vessel/Barge per Day | F48: 30 | G48: =+C48*E48*F48 -> 0
A49: 2011AC | B49: Ocean Transportation: Gulf Coast to assigned port in Puerto Rico | C49: 1 | D49: Vessel/Barge per Day | F49: 30 | G49: =+C49*E49*F49 -> 0
A50: 2011AD | B50: Ocean Transportation: FEMA Distribution Center Caribbean, San Juan PR to assigned port in Puerto Rico | C50: 1 | D50: Vessel/Barge per Day | F50: 30 | G50: =+C50*E50*F50 -> 0
A51: 2012 | B51: Transport Breakbulk Cargo (up to 1200 cft) | H51: 2.2.2
A52: 2012AA | B52: Ocean Transportation: Mid Atlantic Region to Destination USVI | C52: 1000 | D52: Cubic Feet | F52: N/A | G52: =IF(ISNUMBER(E52),C52*E52,0) -> 0
A53: 2012AB | B53: Ocean Transportation: Mid Atlantic Region to Destination Puerto Rico | C53: 1000 | D53: Cubic Feet | F53: N/A | G53: =IF(ISNUMBER(E53),C53*E53,0) -> 0
A54: 2012AC | B54: Ocean Transportation: South Atlantic Region to Destination USVI | C54: 1000 | D54: Cubic Feet | F54: N/A | G54: =IF(ISNUMBER(E54),C54*E54,0) -> 0
A55: 2012AD | B55: Ocean Transportation: South Atlantic Region to Destination Puerto Rico | C55: 1000 | D55: Cubic Feet | F55: N/A | G55: =IF(ISNUMBER(E55),C55*E55,0) -> 0
A56: 2012AE | B56: Ocean Transportation: Gulf Coast to Destination USVI | C56: 1000 | D56: Cubic Feet | F56: N/A | G56: =IF(ISNUMBER(E56),C56*E56,0) -> 0
A57: 2012AF | B57: Ocean Transportation: Gulf Coast to Destination Puerto Rico | C57: 1000 | D57: Cubic Feet | F57: N/A | G57: =IF(ISNUMBER(E57),C57*E57,0) -> 0
A58: 2012AG | B58: Ocean Transportation: FEMA Distribution Center Caribbean to/from Destination USVI | C58: 1000 | D58: Cubic Feet | F58: N/A | G58: =IF(ISNUMBER(E58),C58*E58,0) -> 0
A59: 2013 | B59: Transport Breakbulk Cargo (over 1200 cft) | H59: 2.2.2
A60: 2013AA | B60: Ocean Transportation: Mid Atlantic Region to Destination USVI | C60: 2500 | D60: Cubic Feet | F60: N/A | G60: =IF(ISNUMBER(E60),C60*E60,0) -> 0
A61: 2013AB | B61: Ocean Transportation: Mid Atlantic Region to Destination Puerto Rico | C61: 2500 | D61: Cubic Feet | F61: N/A | G61: =IF(ISNUMBER(E61),C61*E61,0) -> 0
A62: 2013AC | B62: Ocean Transportation: South Atlantic Region to Destination USVI | C62: 2500 | D62: Cubic Feet | F62: N/A | G62: =IF(ISNUMBER(E62),C62*E62,0) -> 0
A63: 2013AD | B63: Ocean Transportation: South Atlantic Region to Destination Puerto Rico | C63: 2500 | D63: Cubic Feet | F63: N/A | G63: =IF(ISNUMBER(E63),C63*E63,0) -> 0
A64: 2013AE | B64: Ocean Transportation: Gulf Coast to Destination USVI | C64: 2500 | D64: Cubic Feet | F64: N/A | G64: =IF(ISNUMBER(E64),C64*E64,0) -> 0
A65: 2013AF | B65: Ocean Transportation: Gulf Coast to Destination Puerto Rico | C65: 2500 | D65: Cubic Feet | F65: N/A | G65: =IF(ISNUMBER(E65),C65*E65,0) -> 0
A66: 2013AG | B66: Ocean Transportation: FEMA Distribution Center Caribbean to/from Destination USVI | C66: 2500 | D66: Cubic Feet | F66: N/A | G66: =IF(ISNUMBER(E66),C66*E66,0) -> 0
A67: 2014 | B67: Retrograde fully loaded containerized commodities from USVI to origin loading facility. | H67: 2.2-2.2.6
A68: 2014AA | B68: Ocean Transportation: USVI to Mid Atlantic Region | C68: 125 | D68: EA Container/Trailer | F68: N/A | G68: =IF(ISNUMBER(E68),C68*E68,0) -> 0
A69: 2014AB | B69: Ocean Transportation: USVI to South Atlantic Region | C69: 1750 | D69: EA Container/Trailer | F69: N/A | G69: =IF(ISNUMBER(E69),C69*E69,0) -> 0
A70: 2014AC | B70: Ocean Transportation: USVI to Gulf Coast | C70: 100 | D70: EA Container/Trailer | F70: N/A | G70: =IF(ISNUMBER(E70),C70*E70,0) -> 0
A71: 2014AD | B71: Ocean Transportation: USVI to FEMA Distribution Center Caribbean, San Juan PR | C71: 25 | D71: EA Container/Trailer | F71: N/A | G71: =IF(ISNUMBER(E71),C71*E71,0) -> 0
A72: 2015 | B72: Retrograde fully loaded containerized commodities from Puerto Rico to origin loading facility. | H72: 2.2-2.2.6
A73: 2015AA | B73: Ocean Transportation: Puerto Rico to Mid Atlantic Region | C73: 125 | D73: EA Container/Trailer | F73: N/A | G73: =IF(ISNUMBER(E73),C73*E73,0) -> 0
A74: 2015AB | B74: Ocean Transportation: Puerto Rico to South Atlantic Region | C74: 1750 | D74: EA Container/Trailer | F74: N/A | G74: =IF(ISNUMBER(E74),C74*E74,0) -> 0
A75: 2015AC | B75: Ocean Transportation: Puerto Rico to Gulf Coast | C75: 100 | D75: EA Container/Trailer | F75: N/A | G75: =IF(ISNUMBER(E75),C75*E75,0) -> 0
A76: 2016 | B76: Retrograde Breakbulk Cargo (up to 1200 cft) | H76: 2.2-2.2.6
A77: 2016AA | B77: Ocean Transportation: USVI to Mid Atlantic Region | C77: 500 | D77: Cubic Feet | F77: N/A | G77: =IF(ISNUMBER(E77),C77*E77,0) -> 0
A78: 2016AB | B78: Ocean Transportation: USVI to South Atlantic Region | C78: 500 | D78: Cubic Feet | F78: N/A | G78: =IF(ISNUMBER(E78),C78*E78,0) -> 0
A79: 2016AC | B79: Ocean Transportation: USVI to Gulf Coast | C79: 500 | D79: Cubic Feet | F79: N/A | G79: =IF(ISNUMBER(E79),C79*E79,0) -> 0
A80: 2016AD | B80: Ocean Transportation: USVI to FEMA Distribution Center Caribbean | C80: 500 | D80: Cubic Feet | F80: N/A | G80: =IF(ISNUMBER(E80),C80*E80,0) -> 0
A81: 2016AE | B81: Ocean Transportation: Puerto Rico to Mid Atlantic Region | C81: 500 | D81: Cubic Feet | F81: N/A | G81: =IF(ISNUMBER(E81),C81*E81,0) -> 0
A82: 2016AF | B82: Ocean Transportation: Puerto Rico to South Atlantic Region | C82: 500 | D82: Cubic Feet | F82: N/A | G82: =IF(ISNUMBER(E82),C82*E82,0) -> 0
A83: 2016AG | B83: Ocean Transportation: Puerto Rico to Gulf Coast | C83: 500 | D83: Cubic Feet | F83: N/A | G83: =IF(ISNUMBER(E83),C83*E83,0) -> 0
A84: 2017 | B84: Retrograde Breakbulk Cargo (above 1200 cft) | H84: 2.2-2.2.6
A85: 2017AA | B85: Ocean Transportation: USVI to Mid Atlantic Region | C85: 1750 | D85: Cubic Feet | F85: N/A | G85: =IF(ISNUMBER(E85),C85*E85,0) -> 0
A86: 2017AB | B86: Ocean Transportation: USVI to South Atlantic Region | C86: 1750 | D86: Cubic Feet | F86: N/A | G86: =IF(ISNUMBER(E86),C86*E86,0) -> 0
A87: 2017AC | B87: Ocean Transportation: USVI to Gulf Coast | C87: 1750 | D87: Cubic Feet | F87: N/A | G87: =IF(ISNUMBER(E87),C87*E87,0) -> 0
A88: 2017AD | B88: Ocean Transportation: USVI to FEMA Distribution Center Caribbean | C88: 1750 | D88: Cubic Feet | F88: N/A | G88: =IF(ISNUMBER(E88),C88*E88,0) -> 0
A89: 2017AE | B89: Ocean Transportation: Puerto Rico to Mid Atlantic Region | C89: 1750 | D89: Cubic Feet | F89: N/A | G89: =IF(ISNUMBER(E89),C89*E89,0) -> 0
A90: 2017AF | B90: Ocean Transportation: Puerto Rico to South Atlantic Region | C90: 1750 | D90: Cubic Feet | F90: N/A | G90: =IF(ISNUMBER(E90),C90*E90,0) -> 0
A91: 2017AG | B91: Ocean Transportation: Puerto Rico to Gulf Coast | C91: 1750 | D91: Cubic Feet | F91: N/A | G91: =IF(ISNUMBER(E91),C91*E91,0) -> 0
G92: =SUM(G32:G91) -> 0
A93: AIR TRANSPORTATION
A94: 2018 | B94: Expedited Air Transportation Services. USVI, FOB Destination. Standard Pallet Size (48"L x 40"W x 48"H). Weight: Below 1650lbs. | H94: 2.3
A95: 2018AA | B95: Air Transportation: Mid Atlantic Region to Destination USVI | C95: 200 | D95: Pallet | F95: N/A | G95: =IF(ISNUMBER(E95),C95*E95,0) -> 0
A96: 2018AB | B96: Air Transportation: South Atlantic Region to Destination USVI | C96: 200 | D96: Pallet | F96: N/A | G96: =IF(ISNUMBER(E96),C96*E96,0) -> 0
A97: 2018AC | B97: Air Transportation: Gulf Coast to Destination USVI | C97: 200 | D97: Pallet | F97: N/A | G97: =IF(ISNUMBER(E97),C97*E97,0) -> 0
A98: 2018AD | B98: Air Transportation: FEMA Distribution Center Caribbean to Destination USVI | C98: 200 | D98: Pallet | F98: N/A | G98: =IF(ISNUMBER(E98),C98*E98,0) -> 0
A99: 2019 | B99: Expedited Air Transportation Services. Puerto Rico, FOB Destination. Standard Pallet Size (48"L x 40"W x 48"H). Weight: Below 1650lbs. | H99: 2.3
A100: 2019AA | B100: Air Transportation: Mid Atlantic Region to Destination Puerto Rico | C100: 200 | D100: Pallet | F100: N/A | G100: =IF(ISNUMBER(E100),C100*E100,0) -> 0
...

Sheet Opt YR 1
A1: RCTSD - Opt YR 1
A2: INSTRUCTIONS: Please note the quantites listed below are for evaluation purposes only. Quoters are not expected to have a minimum of the units used to evaluate. Unit Price will be fixed at time of award.
A3: CLIN | B3: Description | C3: Quantities | D3: Unit | E3: Unit Price | F3: Total Price
A4: 1001 | B4: Commodity Pre-Positioning. Task: Deliver Empty Shipping Containers to FEMA loading/discharging (receiving) locations. (Inclusive of container handling (CHE)/material handling (MHE) equipment) | C4: - | D4: - | E4: - | F4: -
A5: 1001AA | B5: Destination: Mid Atlantic Region | C5: =Base!C115 -> 250 | D5: EA | E5: =Base!E115*1.02 -> 0 | F5: =IF(ISNUMBER(E5),C5*E5,0) -> 0
A6: 1001AB | B6: Destination: South Atlantic Region | C6: =Base!C116 -> 500 | D6: EA | E6: =Base!E116*1.02 -> 0 | F6: =IF(ISNUMBER(E6),C6*E6,0) -> 0
A7: 1001AC | B7: Destination: Gulf Coast | C7: =Base!C117 -> 200 | D7: EA | E7: =Base!E117*1.02 -> 0 | F7: =IF(ISNUMBER(E7),C7*E7,0) -> 0
A8: 1001AD | B8: Destination: FEMA Distribution Center Caribbean, San Juan PR | C8: =Base!C118 -> 500 | D8: EA | E8: =Base!E118*1.02 -> 0 | F8: =IF(ISNUMBER(E8),C8*E8,0) -> 0
A9: 1002 | B9: Task: Surface line haul/Drayage services of containerized commodities from Origin to Port of Embarkation. (Inclusive of container handling (CHE)/material handling (MHE) equipment) | C9: =Base!C4 -> 0 | D9: - | E9: =Base!E4*1.02 -> 0
A10: 1002AA | B10: Ground Transportation: Point of Origin to Port of Embarkation (Mid Atlantic Region) | C10: =Base!C5 -> 250 | D10: EA | E10: =Base!E5*1.02 -> 0 | F10: =IF(ISNUMBER(E10),C10*E10,0) -> 0
A11: 1002AB | B11: Ground Transportation: Point of Origin to Port of Embarkation (South Atlantic Region) | C11: =Base!C6 -> 500 | D11: EA | E11: =Base!E6*1.02 -> 0 | F11: =IF(ISNUMBER(E11),C11*E11,0) -> 0
A12: 1002AC | B12: Ground Transportation: Point of Origin to Port of Embarkation (Gulf Coast) | C12: =Base!C7 -> 200 | D12: EA | E12: =Base!E7*1.02 -> 0 | F12: =IF(ISNUMBER(E12),C12*E12,0) -> 0
A13: 1002AD | B13: Ground Transportation: Point of Origin to Port of Embarkation (FEMA Distribution Center Caribbean, San Juan PR) | C13: =Base!C8 -> 500 | D13: EA | E13: =Base!E8*1.02 -> 0 | F13: =IF(ISNUMBER(E13),C13*E13,0) -> 0
A14: 1003 | B14: Task: Surface line haul/Drayage services of Breakbulk Cargo. (Per Chassis) (Inclusive of container handling (CHE)/material handling (MHE) equipment) | C14: =Base!C18 -> 0 | D14: - | E14: 0
A15: 1003AA | B15: Ground Transportation: Point of Origin to Port of Embarkation (Mid Atlantic Region) | C15: =Base!C19 -> 100 | D15: EA | E15: =Base!E19*1.02 -> 0 | F15: =IF(ISNUMBER(E15),C15*E15,0) -> 0
A16: 1003AB | B16: Ground Transportation: Point of Origin to Port of Embarkation (South Atlantic Region) | C16: =Base!C20 -> 100 | D16: EA | E16: =Base!E20*1.02 -> 0 | F16: =IF(ISNUMBER(E16),C16*E16,0) -> 0
A17: 1003AC | B17: Ground Transportation: Point of Origin to Port of Embarkation (Gulf Coast) | C17: =Base!C21 -> 100 | D17: EA | E17: =Base!E21*1.02 -> 0 | F17: =IF(ISNUMBER(E17),C17*E17,0) -> 0
A18: 1003AD | B18: Ground Transportation: Point of Origin to Port of Embarkation (FEMA Distribution Center Caribbean, San Juan PR) | C18: =Base!C22 -> 100 | D18: EA | E18: =Base!E22*1.02 -> 0 | F18: =IF(ISNUMBER(E18),C18*E18,0) -> 0
A19: 1004 | B19: Task: Transport loaded containers, via ocean vessel from Port of Embarkation to assigned port in the USVI, FOB Destination. (Inclusive of container handling (CHE)/material handling (MHE) equipment) | C19: =Base!C31 -> 0 | D19: - | E19: 0
A20: 1004AA | B20: Ocean Transportation: Mid Atlantic Region to assigned port in the USVI | C20: =Base!C32 -> 250 | D20: EA | E20: =Base!E32*1.02 -> 0 | F20: =IF(ISNUMBER(E20),C20*E20,0) -> 0
A21: 1004AB | B21: Ocean Transportation: South Atlantic Region to assigned port in the USVI | C21: =Base!C33 -> 1000 | D21: EA | E21: =Base!E33*1.02 -> 0 | F21: =IF(ISNUMBER(E21),C21*E21,0) -> 0
A22: 1004AC | B22: Ocean Transportation: Gulf Coast to assigned port in the USVI | C22: =Base!C34 -> 200 | D22: EA | E22: =Base!E34*1.02 -> 0 | F22: =IF(ISNUMBER(E22),C22*E22,0) -> 0
A23: 1004AD | B23: Ocean Transportation: FEMA Distribution Center Caribbean, San Juan PR to assigned port in the USVI | C23: =Base!C35 -> 50 | D23: EA | E23: =Base!E35*1.02 -> 0 | F23: =IF(ISNUMBER(E23),C23*E23,0) -> 0
A24: 1005 | B24: Task: Transport loaded containers, via ocean vessel from Port of Embarkation to assigned port in Puerto Rico, FOB Destination. (Inclusive of container handling (CHE)/material handling (MHE) equipment) | C24: =Base!C36 -> 0 | D24: - | E24: 0 | F24: 0
A25: 1005AA | B25: Ocean Transportation: Mid Atlantic Region to assigned port in Puerto Rico | C25: =Base!C37 -> 250 | D25: EA | E25: =Base!E37*1.02 -> 0 | F25: =IF(ISNUMBER(E25),C25*E25,0) -> 0
A26: 1005AB | B26: Ocean Transportation: South Atlantic Region to assigned port in Puerto Rico | C26: =Base!C38 -> 1000 | D26: EA | E26: =Base!E38*1.02 -> 0 | F26: =IF(ISNUMBER(E26),C26*E26,0) -> 0
A27: 1005AC | B27: Ocean Transportation: Gulf Coast to assigned port in Puerto Rico | C27: =Base!C39 -> 200 | D27: EA | E27: =Base!E39*1.02 -> 0 | F27: =IF(ISNUMBER(E27),C27*E27,0) -> 0
A28: 1005AD | B28: Ocean Transportation: FEMA Distribution Center Caribbean, San Juan PR to assigned port in Puerto Rico | C28: =Base!C40 -> 50 | D28: EA | E28: =Base!E40*1.02 -> 0 | F28: =IF(ISNUMBER(E28),C28*E28,0) -> 0
A29: 1006 | B29: Task: Dedicated Vessel Voyage from Port of Embarkation to assigned port in USVI, FOB Destination (Inclusive of container handling (CHE)/material handling (MHE) equipment and services) (30 day minimum length of dedicated vessel) | C29: =Base!C41 -> 0 | D29: - | E29: 0
A30: 1006AA | B30: Ocean Transportation: Mid Atlantic Region to assigned port in the USVI | C30: =Base!C42 -> 1 | D30: Vessel/Barge per Day | E30: =Base!E42*1.02 -> 0 | F30: =IF(ISNUMBER(E30),C30*E30,0) -> 0
A31: 1006AB | B31: Ocean Transportation: South Atlantic Region to assigned port in the USVI | C31: =Base!C43 -> 1 | D31: Vessel/Barge per Day | E31: =Base!E43*1.02 -> 0 | F31: =IF(ISNUMBER(E31),C31*E31,0) -> 0
A32: 1006AC | B32: Ocean Transportation: Gulf Coast to assigned port in the USVI | C32: =Base!C44 -> 1 | D32: Vessel/Barge per Day | E32: =Base!E44*1.02 -> 0 | F32: =IF(ISNUMBER(E32),C32*E32,0) -> 0
A33: 1006AD | B33: Ocean Transportation: FEMA Distribution Center Caribbean, San Juan PR to assigned port in the USVI | C33: =Base!C45 -> 1 | D33: Vessel/Barge per Day | E33: =Base!E45*1.02 -> 0 | F33: =IF(ISNUMBER(E33),C33*E33,0) -> 0
A34: 1007 | B34: Task: Dedicated Vessel Voyage from Port of Embarkation to assigned port in Puerto Rico, FOB Destination (Inclusive of container handling (CHE)/material handling (MHE) equipment and services) (30 day minimum length of dedicated vessel) | C34: =Base!C46 -> 0 | D34: - | E34: 0
A35: 1007AA | B35: Ocean Transportation: Mid Atlantic Region to assigned port in Puerto Rico | C35: =Base!C47 -> 1 | D35: Vessel/Barge per Day | E35: =Base!E47*1.02 -> 0 | F35: =IF(ISNUMBER(E35),C35*E35,0) -> 0
A36: 1007AB | B36: Ocean Transportation: South Atlantic Region to assigned port in Puerto Rico | C36: =Base!C48 -> 1 | D36: Vessel/Barge per Day | E36: =Base!E48*1.02 -> 0 | F36: =IF(ISNUMBER(E36),C36*E36,0) -> 0
A37: 1007AC | B37: Ocean Transportation: Gulf Coast to assigned port in Puerto Rico | C37: =Base!C49 -> 1 | D37: Vessel/Barge per Day | E37: =Base!E49*1.02 -> 0 | F37: =IF(ISNUMBER(E37),C37*E37,0) -> 0
A38: 1007AD | B38: Ocean Transportation: FEMA Distribution Center Caribbean, San Juan PR to assigned port in Puerto Rico | C38: =Base!C50 -> 1 | D38: Vessel/Barge per Day | E38: =Base!E50*1.02 -> 0 | F38: =IF(ISNUMBER(E38),C38*E38,0) -> 0
A39: 1008 | B39: Task: Expedited Air Transportation Services. USVI, FOB Destination. (Inclusive of container handling (CHE)/material handling (MHE) equipment). Standard Pallet Size (48"L x 40"W x 48"H). Weight: Up to 1650lbs. | C39: =Base!C94 -> 0 | D39: - | E39: 0
A40: 1008AA | B40: Air Transportation: Mid Atlantic Region to Destination USVI | C40: =Base!C95 -> 200 | D40: Warehouse Pallets | E40: =Base!E95*1.02 -> 0 | F40: =IF(ISNUMBER(E40),C40*E40,0) -> 0
A41: 1008AB | B41: Air Transportation: South Atlantic Region to Destination USVI | C41: =Base!C96 -> 200 | D41: Warehouse Pallets | E41: =Base!E96*1.02 -> 0 | F41: =IF(ISNUMBER(E41),C41*E41,0) -> 0
A42: 1008AC | B42: Air Transportation: Gulf Coast to Destination USVI | C42: =Base!C97 -> 200 | D42: Warehouse Pallets | E42: =Base!E97*1.02 -> 0 | F42: =IF(ISNUMBER(E42),C42*E42,0) -> 0
A43: 1008AD | B43: Air Transportation: FEMA Distribution Center Caribbean to Destination USVI | C43: =Base!C98 -> 200 | D43: Warehouse Pallets | E43: =Base!E98*1.02 -> 0 | F43: =IF(ISNUMBER(E43),C43*E43,0) -> 0
A44: 1009 | B44: Task: Expedited Air Transportation Services. Puerto Rico, FOB Destination. (Inclusive of container handling (CHE)/material handling (MHE) equipment). Standard Pallet Size (48"L x 40"W x 48"H). Weight: Up to 1650lbs. | C44: =Base!C99 -> 0 | D44: - | E44: 0 | F44: 0
A45: 1009AA | B45: Air Transportation: Mid Atlantic Region to Destination Puerto Rico | C45: =Base!C100 -> 200 | D45: Warehouse Pallets | E45: =Base!E100*1.02 -> 0 | F45: =IF(ISNUMBER(E45),C45*E45,0) -> 0
A46: 1009AB | B46: Air Transportation: South Atlantic Region to Destination Puerto Rico | C46: =Base!C101 -> 200 | D46: Warehouse Pallets | E46: =Base!E101*1.02 -> 0 | F46: =IF(ISNUMBER(E46),C46*E46,0) -> 0
A47: 1009AC | B47: Air Transportation: Gulf Coast to Destination Puerto Rico | C47: =Base!C102 -> 200 | D47: Warehouse Pallets | E47: =Base!E102*1.02 -> 0 | F47: =IF(ISNUMBER(E47),C47*E47,0) -> 0
A48: 1009AD | B48: Air Transportation: FEMA Distribution Center Caribbean to Destination Puerto Rico | C48: =Base!#REF! -> #REF! | D48: Warehouse Pallets | E48: =Base!#REF!*1.02 -> #REF! | F48: =IF(ISNUMBER(E48),C48*E48,0) -> 0
A49: 1010 | B49: Task: Expedited Air Transportation Services. USVI, FOB Destination. (Inclusive of container handling (CHE)/material handling (MHE) equipment). Standard Pallet Size (48"L x 40"W x 48"H). Weight: 1650lbs and above. | C49: =Base!C103 -> 0 | D49: - | E49: 0
A50: 1010AA | B50: Air Transportation: Mid Atlantic Region to Destination USVI | C50: =Base!C104 -> 200 | D50: Warehouse Pallets | E50: =Base!E104*1.02 -> 0 | F50: =IF(ISNUMBER(E50),C50*E50,0) -> 0
A51: 1010AB | B51: Air Transportation: South Atlantic Region to Destination USVI | C51: =Base!C105 -> 200 | D51: Warehouse Pallets | E51: =Base!E105*1.02 -> 0 | F51: =IF(ISNUMBER(E51),C51*E51,0) -> 0
A52: 1010AC | B52: Air Transportation: Gulf Coast to Destination USVI | C52: =Base!C106 -> 200 | D52: Warehouse Pallets | E52: =Base!E106*1.02 -> 0 | F52: =IF(ISNUMBER(E52),C52*E52,0) -> 0
A53: 1010AD | B53: Air Transportation: FEMA Distribution Center Caribbean to Destination USVI | C53: =Base!C107 -> 200 | D53: Warehouse Pallets | E53: =Base!E107*1.02 -> 0 | F53: =IF(ISNUMBER(E53),C53*E53,0) -> 0
A54: 1011 | B54: Task: Expedited Air Transportation Services. Puerto Rico, FOB Destination. (Inclusive of container handling (CHE)/material handling (MHE) equipment). Standard Pallet Size (48"L x 40"W x 48"H). Weight: 1650lbs and above. | C54: =Base!C108 -> 0 | D54: - | E54: 0
A55: 1011AA | B55: Air Transportation: Mid Atlantic Region to Destination Puerto Rico | C55: =Base!C109 -> 200 | D55: Warehouse Pallets | E55: =Base!E109*1.02 -> 0 | F55: =IF(ISNUMBER(E55),C55*E55,0) -> 0
A56: 1011AB | B56: Air Transportation: South Atlantic Region to Destination Puerto Rico | C56: =Base!C110 -> 200 | D56: Warehouse Pallets | E56: =Base!E110*1.02 -> 0 | F56: =IF(ISNUMBER(E56),C56*E56,0) -> 0
A57: 1011AC | B57: Air Transportation: Gulf Coast to Destination Puerto Rico | C57: =Base!C111 -> 200 | D57: Warehouse Pallets | E57: =Base!E111*1.02 -> 0 | F57: =IF(ISNUMBER(E57),C57*E57,0) -> 0
A58: 1011AD | B58: Air Transportation: FEMA Distribution Center Caribbean to Destination Puerto Rico | C58: =Base!#REF! -> #REF! | D58: Warehouse Pallets | E58: =Base!#REF!*1.02 -> #REF! | F58: =IF(ISNUMBER(E58),C58*E58,0) -> 0
A59: 1012 | B59: Task: Transport Breakbulk Cargo (up to 700 cft) (Inclusive of container handling (CHE)/material handling (MHE) equipment and services) | C59: =Base!C51 -> 0 | D59: - | E59: 0
A60: 1012AA | B60: Ocean Transportation: Mid Atlantic Region to Destination USVI | C60: =Base!C52 -> 1000 | D60: Cubic Feet | E60: =Base!E52*1.02 -> 0 | F60: =IF(ISNUMBER(E60),C60*E60,0) -> 0
A61: 1012AB | B61: Ocean Transportation: Mid Atlantic Region to Destination Puerto Rico | C61: =Base!C53 -> 1000 | D61: Cubic Feet | E61: =Base!E53*1.02 -> 0 | F61: =IF(ISNUMBER(E61),C61*E61,0) -> 0
A62: 1012AC | B62: Ocean Transportation: South Atlantic Region to Destination USVI | C62: =Base!C54 -> 1000 | D62: Cubic Feet | E62: =Base!E54*1.02 -> 0 | F62: =IF(ISNUMBER(E62),C62*E62,0) -> 0
A63: 1012AD | B63: Ocean Transportation: South Atlantic Region to Destination Puerto Rico | C63: =Base!C55 -> 1000 | D63: Cubic Feet | E63: =Base!E55*1.02 -> 0 | F63: =IF(ISNUMBER(E63),C63*E63,0) -> 0
A64: 1012AE | B64: Ocean Transportation: Gulf Coast to Destination USVI | C64: =Base!C56 -> 1000 | D64: Cubic Feet | E64: =Base!E56*1.02 -> 0 | F64: =IF(ISNUMBER(E64),C64*E64,0) -> 0
A65: 1012AF | B65: Ocean Transportation: Gulf Coast to Destination Puerto Rico | C65: =Base!C57 -> 1000 | D65: Cubic Feet | E65: =Base!E57*1.02 -> 0 | F65: =IF(ISNUMBER(E65),C65*E65,0) -> 0
A66: 1012AG | B66: Ocean Transportation: FEMA Distribution Center Caribbean to Destination USVI | C66: =Base!C58 -> 1000 | D66: Cubic Feet | E66: =Base!E58*1.02 -> 0 | F66: =IF(ISNUMBER(E66),C66*E66,0) -> 0
A67: 1012AH | B67: Ocean Transportation: FEMA Distribution Center Caribbean to Destination Puerto Rico | C67: =Base!#REF! -> #REF! | D67: Cubic Feet | E67: =Base!#REF!*1.02 -> #REF! | F67: =IF(ISNUMBER(E67),C67*E67,0) -> 0
A68: 1013 | B68: Task: Transport Breakbulk Cargo (from 701 to 1200 cft) (Inclusive of container handling (CHE)/material handling (MHE) equipment and services) | C68: =Base!#REF! -> #REF! | D68: - | E68: 0
A69: 1013AA | B69: Ocean Transportation: Mid Atlantic Region to Destination USVI | C69: =Base!#REF! -> #REF! | D69: Cubic Feet | E69: =Base!#REF!*1.02 -> #REF! | F69: =IF(ISNUMBER(E69),C69*E69,0) -> 0
A70: 1013AB | B70: Ocean Transportation: Mid Atlantic Region to Destination Puerto Rico | C70: =Base!#REF! -> #REF! | D70: Cubic Feet | E70: =Base!#REF!*1.02 -> #REF! | F70: =IF(ISNUMBER(E70),C70*E70,0) -> 0
A71: 1013AC | B71: Ocean Transportation: South Atlantic Region to Destination USVI | C71: =Base!#REF! -> #REF! | D71: Cubic Feet | E71: =Base!#REF!*1.02 -> #REF! | F71: =IF(ISNUMBER(E71),C71*E71,0) -> 0
A72: 1013AD | B72: Ocean Transportation: South Atlantic Region to Destination Puerto Rico | C72: =Base!#REF! -> #REF! | D72: Cubic Feet | E72: =Base!#REF!*1.02 -> #REF! | F72: =IF(ISNUMBER(E72),C72*E72,0) -> 0
A73: 1013AE | B73: Ocean Transportation: Gulf Coast to Destination USVI | C73: =Base!#REF! -> #REF! | D73: Cubic Feet | E73: =Base!#REF!*1.02 -> #REF! | F73: =IF(ISNUMBER(E73),C73*E73,0) -> 0
A74: 1013AF | B74: Ocean Transportation: Gulf Coast to Destination Puerto Rico | C74: =Base!#REF! -> #REF! | D74: Cubic Feet | E74: =Base!#REF!*1.02 -> #REF! | F74: =IF(ISNUMBER(E74),C74*E74,0) -> 0
A75: 1013AG | B75: Ocean Transportation: FEMA Distribution Center Caribbean to Destination USVI | C75: =Base!#REF! -> #REF! | D75: Cubic Feet | E75: =Base!#REF!*1.02 -> #REF! | F75: =IF(ISNUMBER(E75),C75*E75,0) -> 0
A76: 1013AH | B76: Ocean Transportation: FEMA Distribution Center Caribbean to Destination Puerto Rico | C76: =Base!#REF! -> #REF! | D76: Cubic Feet | E76: =Base!#REF!*1.02 -> #REF! | F76: =IF(ISNUMBER(E76),C76*E76,0) -> 0
A77: 1014 | B77: Task: Transport Breakbulk Cargo (over 1200 cft) (Inclusive of container handling (CHE)/material handling (MHE) equipment and services) | C77: =Base!C59 -> 0 | D77: - | E77: 0
A78: 1014AA | B78: Ocean Transportation: Mid Atlantic Region to Destination USVI | C78: =Base!C60 -> 2500 | D78: Cubic Feet | E78: =Base!E60*1.02 -> 0 | F78: =IF(ISNUMBER(E78),C78*E78,0) -> 0
A79: 1014AB | B79: Ocean Transportation: Mid Atlantic Region to Destination Puerto Rico | C79: =Base!C61 -> 2500 | D79: Cubic Feet | E79: =Base!E61*1.02 -> 0 | F79: =IF(ISNUMBER(E79),C79*E79,0) -> 0
A80: 1014AC | B80: Ocean Transportation: South Atlantic Region to Destination USVI | C80: =Base!C62 -> 2500 | D80: Cubic Feet | E80: =Base!E62*1.02 -> 0 | F80: =IF(ISNUMBER(E80),C80*E80,0) -> 0
A81: 1014AD | B81: Ocean Transportation: South Atlantic Region to Destination Puerto Rico | C81: =Base!C63 -> 2500 | D81: Cubic Feet | E81: =Base!E63*1.02 -> 0 | F81: =IF(ISNUMBER(E81),C81*E81,0) -> 0
A82: 1014AE | B82: Ocean Transportation: Gulf Coast to Destination USVI | C82: =Base!C64 -> 2500 | D82: Cubic Feet | E82: =Base!E64*1.02 -> 0 | F82: =IF(ISNUMBER(E82),C82*E82,0) -> 0
A83: 1014AF | B83: Ocean Transportation: Gulf Coast to Destination Puerto Rico | C83: =Base!C65 -> 2500 | D83: Cubic Feet | E83: =Base!E65*1.02 -> 0 | F83: =IF(ISNUMBER(E83),C83*E83,0) -> 0
A84: 1014AG | B84: Ocean Transportation: FEMA Distribution Center Caribbean to Destination USVI | C84: =Base!C66 -> 2500 | D84: Cubic Feet | E84: =Base!E66*1.02 -> 0 | F84: =IF(ISNUMBER(E84),C84*E84,0) -> 0
A85: 1014AH | B85: Ocean Transportation: FEMA Distribution Center Caribbean to Destination Puerto Rico | C85: =Base!#REF! -> #REF! | D85: Cubic Feet | E85: =Base!#REF!*1.02 -> #REF! | F85: =IF(ISNUMBER(E85),C85*E85,0) -> 0
A86: 1015 | B86: Task: Surface line haul services of containerized commodities from Port of Debarkation to FEMA designated Point of Need. (Inclusive of container handling (CHE)/material handling (MHE) equipment) | C86: =Base!C9 -> 0 | D86: - | E86: 0
A87: 1015AA | B87: Ground Transportation: Destination - USVI locations | C87: =Base!C10 -> 1000 | D87: EA | E87: =Base!E10*1.02 -> 0 | F87: =IF(ISNUMBER(E87),C87*E87,0) -> 0
A88: 1015AB | B88: Ground Transportation: Destination - Puerto Rico locations | C88: =Base!C11 -> 2500 | D88: EA | E88: =Base!E11*1.02 -> 0 | F88: =IF(ISNUMBER(E88),C88*E88,0) -> 0
A89: 1016 | B89: Task: Surface line haul services of Breakbulk Cargo. (Per Chassis) (Inclusive of container handling (CHE)/material handling (MHE) equipment) | C89: =Base!C23 -> 0 | D89: - | E89: 0
A90: 1016AA | B90: Ground Transportation: Destination - USVI locations | C90: =Base!C24 -> 10 | D90: EA | E90: =Base!E24*1.02 -> 0 | F90: =IF(ISNUMBER(E90),C90*E90,0) -> 0
A91: 1016AB | B91: Ground Transportation: Destination - Puerto Rico locations | C91: =Base!C25 -> 10 | D91: EA | E91: =Base!E25*1.02 -> 0 | F91: =IF(ISNUMBER(E91),C91*E91,0) -> 0
A92: 1017 | B92: Task: Surface line haul services of containerized commodities Intra-Island. (Inclusive of container handling (CHE)/material handling (MHE) equipment) | C92: =Base!C12 -> 0 | D92: - | E92: 0
A93: 1017AA | B93: Ground Transportation: USVI locations | C93: =Base!C13 -> 1000 | D93: EA | E93: =Base!E13*1.02 -> 0 | F93: =IF(ISNUMBER(E93),C93*E93,0) -> 0
A94: 1017AB | B94: Ground Transportation: Puerto Rico locations | C94: =Base!C14 -> 2500 | D94: EA | E94: =Base!E14*1.02 -> 0 | F94: =IF(ISNUMBER(E94),C94*E94,0) -> 0
A95: 1018 | B95: Task: Container Staging Services. (Inclusive of container handling (CHE)/material handling (MHE) equipment) | C95: =Base!C127 -> 0 | D95: -
A96: 1018AA | B96: Location: USVI | C96: =Base!C128 -> 1 | D96: EA | E96: =Base!E128*1.02 -> 0 | F96: =IF(ISNUMBER(E96),C96*E96,0) -> 0
A97: 1018AB | B97: Location: Puerto Rico | C97: =Base!C129 -> 1 | D97: EA | E97: =Base!E129*1.02 -> 0 | F97: =IF(ISNUMBER(E97),C97*E97,0) -> 0
A98: 1018AC | B98: Daily Container Retention Rate (20ft, 40ft, 53ft) (with [insert # of days] free of charge days) | C98: =Base!C130 -> 1000 | D98: EA/DAY | E98: =Base!E130*1.02 -> 0 | F98: =IF(ISNUMBER(E98),C98*E98,0) -> 0
A99: 1018AD | B99: Daily Container Detention Rate (20ft, 40ft, 53ft) (starting on the [Xth] day) | C99: =Base!C131 -> 1000 | D99: EA/DAY | E99: =Base!E131*1.02 -> 0 | F99: =IF(ISNUMBER(E99),C99*E99,0) -> 0
A100: 1018AE | B100: Daily Chassis Detention Rate (starting on the [Xth] day) | C100: =Base!C132 -> 1000 | D100: EA/DAY | E100: =Base!E132*1.02 -> 0 | F100: =IF(ISNUMBER(E100),C100*E100,0) -> 0
...

Sheet Opt YR 2
A1: RCTSD - Opt YR 2
A2: INSTRUCTIONS: Please note the quantites listed below are for evaluation purposes only. Quoters are not expected to have a minimum of the units used to evaluate. Unit Price will be fixed at time of award.
A3: CLIN | B3: Description | C3: Quantities | D3: Unit | E3: Unit Price | F3: Total Price
A4: 2001 | B4: Commodity Pre-Positioning. Task: Deliver Empty Shipping Containers to FEMA loading/discharging (receiving) locations. (Inclusive of container handling (CHE)/material handling (MHE) equipment) | C4: - | D4: - | E4: - | F4: -
A5: 2001AA | B5: Destination: Mid Atlantic Region | C5: =Base!C115 -> 250 | D5: EA | E5: =Base!E115*1.04 -> 0 | F5: =IF(ISNUMBER(E5),C5*E5,0) -> 0
A6: 2001AB | B6: Destination: South Atlantic Region | C6: =Base!C116 -> 500 | D6: EA | E6: =Base!E116*1.04 -> 0 | F6: =IF(ISNUMBER(E6),C6*E6,0) -> 0
A7: 2001AC | B7: Destination: Gulf Coast | C7: =Base!C117 -> 200 | D7: EA | E7: =Base!E117*1.04 -> 0 | F7: =IF(ISNUMBER(E7),C7*E7,0) -> 0
A8: 2001AD | B8: Destination: FEMA Distribution Center Caribbean, San Juan PR | C8: =Base!C118 -> 500 | D8: EA | E8: =Base!E118*1.04 -> 0 | F8: =IF(ISNUMBER(E8),C8*E8,0) -> 0
A9: 2002 | B9: Task: Surface line haul/Drayage services of containerized commodities from Origin to Port of Embarkation. (Inclusive of container handling (CHE)/material handling (MHE) equipment) | C9: =Base!C4 -> 0 | D9: - | E9: =Base!E4*1.04 -> 0
A10: 2002AA | B10: Ground Transportation: Point of Origin to Port of Embarkation (Mid Atlantic Region) | C10: =Base!C5 -> 250 | D10: EA | E10: =Base!E5*1.04 -> 0 | F10: =IF(ISNUMBER(E10),C10*E10,0) -> 0
A11: 2002AB | B11: Ground Transportation: Point of Origin to Port of Embarkation (South Atlantic Region) | C11: =Base!C6 -> 500 | D11: EA | E11: =Base!E6*1.04 -> 0 | F11: =IF(ISNUMBER(E11),C11*E11,0) -> 0
A12: 2002AC | B12: Ground Transportation: Point of Origin to Port of Embarkation (Gulf Coast) | C12: =Base!C7 -> 200 | D12: EA | E12: =Base!E7*1.04 -> 0 | F12: =IF(ISNUMBER(E12),C12*E12,0) -> 0
A13: 2002AD | B13: Ground Transportation: Point of Origin to Port of Embarkation (FEMA Distribution Center Caribbean, San Juan PR) | C13: =Base!C8 -> 500 | D13: EA | E13: =Base!E8*1.04 -> 0 | F13: =IF(ISNUMBER(E13),C13*E13,0) -> 0
A14: 2003 | B14: Task: Surface line haul/Drayage services of Breakbulk Cargo. (Per Chassis) (Inclusive of container handling (CHE)/material handling (MHE) equipment) | C14: =Base!C18 -> 0 | D14: - | E14: 0
A15: 2003AA | B15: Ground Transportation: Point of Origin to Port of Embarkation (Mid Atlantic Region) | C15: =Base!C19 -> 100 | D15: EA | E15: =Base!E19*1.04 -> 0 | F15: =IF(ISNUMBER(E15),C15*E15,0) -> 0
A16: 2003AB | B16: Ground Transportation: Point of Origin to Port of Embarkation (South Atlantic Region) | C16: =Base!C20 -> 100 | D16: EA | E16: =Base!E20*1.04 -> 0 | F16: =IF(ISNUMBER(E16),C16*E16,0) -> 0
A17: 2003AC | B17: Ground Transportation: Point of Origin to Port of Embarkation (Gulf Coast) | C17: =Base!C21 -> 100 | D17: EA | E17: =Base!E21*1.04 -> 0 | F17: =IF(ISNUMBER(E17),C17*E17,0) -> 0
A18: 2003AD | B18: Ground Transportation: Point of Origin to Port of Embarkation (FEMA Distribution Center Caribbean, San Juan PR) | C18: =Base!C22 -> 100 | D18: EA | E18: =Base!E22*1.04 -> 0 | F18: =IF(ISNUMBER(E18),C18*E18,0) -> 0
A19: 2004 | B19: Task: Transport loaded containers, via ocean vessel from Port of Embarkation to assigned port in the USVI, FOB Destination. (Inclusive of container handling (CHE)/material handling (MHE) equipment) | C19: =Base!C31 -> 0 | D19: - | E19: 0
A20: 2004AA | B20: Ocean Transportation: Mid Atlantic Region to assigned port in the USVI | C20: =Base!C32 -> 250 | D20: EA | E20: =Base!E32*1.04 -> 0 | F20: =IF(ISNUMBER(E20),C20*E20,0) -> 0
A21: 2004AB | B21: Ocean Transportation: South Atlantic Region to assigned port in the USVI | C21: =Base!C33 -> 1000 | D21: EA | E21: =Base!E33*1.04 -> 0 | F21: =IF(ISNUMBER(E21),C21*E21,0) -> 0
A22: 2004AC | B22: Ocean Transportation: Gulf Coast to assigned port in the USVI | C22: =Base!C34 -> 200 | D22: EA | E22: =Base!E34*1.04 -> 0 | F22: =IF(ISNUMBER(E22),C22*E22,0) -> 0
A23: 2004AD | B23: Ocean Transportation: FEMA Distribution Center Caribbean, San Juan PR to assigned port in the USVI | C23: =Base!C35 -> 50 | D23: EA | E23: =Base!E35*1.04 -> 0 | F23: =IF(ISNUMBER(E23),C23*E23,0) -> 0
A24: 2005 | B24: Task: Transport loaded containers, via ocean vessel from Port of Embarkation to assigned port in Puerto Rico, FOB Destination. (Inclusive of container handling (CHE)/material handling (MHE) equipment) | C24: =Base!C36 -> 0 | D24: - | E24: 0 | F24: 0
A25: 2005AA | B25: Ocean Transportation: Mid Atlantic Region to assigned port in Puerto Rico | C25: =Base!C37 -> 250 | D25: EA | E25: =Base!E37*1.04 -> 0 | F25: =IF(ISNUMBER(E25),C25*E25,0) -> 0
A26: 2005AB | B26: Ocean Transportation: South Atlantic Region to assigned port in Puerto Rico | C26: =Base!C38 -> 1000 | D26: EA | E26: =Base!E38*1.04 -> 0 | F26: =IF(ISNUMBER(E26),C26*E26,0) -> 0
A27: 2005AC | B27: Ocean Transportation: Gulf Coast to assigned port in Puerto Rico | C27: =Base!C39 -> 200 | D27: EA | E27: =Base!E39*1.04 -> 0 | F27: =IF(ISNUMBER(E27),C27*E27,0) -> 0
A28: 2005AD | B28: Ocean Transportation: FEMA Distribution Center Caribbean, San Juan PR to assigned port in Puerto Rico | C28: =Base!C40 -> 50 | D28: EA | E28: =Base!E40*1.04 -> 0 | F28: =IF(ISNUMBER(E28),C28*E28,0) -> 0
A29: 2006 | B29: Task: Dedicated Vessel Voyage from Port of Embarkation to assigned port in USVI, FOB Destination (Inclusive of container handling (CHE)/material handling (MHE) equipment and services) (30 day minimum length of dedicated vessel) | C29: =Base!C41 -> 0 | D29: - | E29: 0
A30: 2006AA | B30: Ocean Transportation: Mid Atlantic Region to assigned port in the USVI | C30: =Base!C42 -> 1 | D30: Vessel/Barge per Day | E30: =Base!E42*1.04 -> 0 | F30: =IF(ISNUMBER(E30),C30*E30,0) -> 0
A31: 2006AB | B31: Ocean Transportation: South Atlantic Region to assigned port in the USVI | C31: =Base!C43 -> 1 | D31: Vessel/Barge per Day | E31: =Base!E43*1.04 -> 0 | F31: =IF(ISNUMBER(E31),C31*E31,0) -> 0
A32: 2006AC | B32: Ocean Transportation: Gulf Coast to assigned port in the USVI | C32: =Base!C44 -> 1 | D32: Vessel/Barge per Day | E32: =Base!E44*1.04 -> 0 | F32: =IF(ISNUMBER(E32),C32*E32,0) -> 0
A33: 2006AD | B33: Ocean Transportation: FEMA Distribution Center Caribbean, San Juan PR to assigned port in the USVI | C33: =Base!C45 -> 1 | D33: Vessel/Barge per Day | E33: =Base!E45*1.04 -> 0 | F33: =IF(ISNUMBER(E33),C33*E33,0) -> 0
A34: 2007 | B34: Task: Dedicated Vessel Voyage from Port of Embarkation to assigned port in Puerto Rico, FOB Destination (Inclusive of container handling (CHE)/material handling (MHE) equipment and services) (30 day minimum length of dedicated vessel) | C34: =Base!C46 -> 0 | D34: - | E34: 0
A35: 2007AA | B35: Ocean Transportation: Mid Atlantic Region to assigned port in Puerto Rico | C35: =Base!C47 -> 1 | D35: Vessel/Barge per Day | E35: =Base!E47*1.04 -> 0 | F35: =IF(ISNUMBER(E35),C35*E35,0) -> 0
A36: 2007AB | B36: Ocean Transportation: South Atlantic Region to assigned port in Puerto Rico | C36: =Base!C48 -> 1 | D36: Vessel/Barge per Day | E36: =Base!E48*1.04 -> 0 | F36: =IF(ISNUMBER(E36),C36*E36,0) -> 0
A37: 2007AC | B37: Ocean Transportation: Gulf Coast to assigned port in Puerto Rico | C37: =Base!C49 -> 1 | D37: Vessel/Barge per Day | E37: =Base!E49*1.04 -> 0 | F37: =IF(ISNUMBER(E37),C37*E37,0) -> 0
A38: 2007AD | B38: Ocean Transportation: FEMA Distribution Center Caribbean, San Juan PR to assigned port in Puerto Rico | C38: =Base!C50 -> 1 | D38: Vessel/Barge per Day | E38: =Base!E50*1.04 -> 0 | F38: =IF(ISNUMBER(E38),C38*E38,0) -> 0
A39: 2008 | B39: Task: Expedited Air Transportation Services. USVI, FOB Destination. (Inclusive of container handling (CHE)/material handling (MHE) equipment). Standard Pallet Size (48"L x 40"W x 48"H). Weight: Up to 1650lbs. | C39: =Base!C94 -> 0 | D39: - | E39: 0
A40: 2008AA | B40: Air Transportation: Mid Atlantic Region to Destination USVI | C40: =Base!C95 -> 200 | D40: Warehouse Pallets | E40: =Base!E95*1.04 -> 0 | F40: =IF(ISNUMBER(E40),C40*E40,0) -> 0
A41: 2008AB | B41: Air Transportation: South Atlantic Region to Destination USVI | C41: =Base!C96 -> 200 | D41: Warehouse Pallets | E41: =Base!E96*1.04 -> 0 | F41: =IF(ISNUMBER(E41),C41*E41,0) -> 0
A42: 2008AC | B42: Air Transportation: Gulf Coast to Destination USVI | C42: =Base!C97 -> 200 | D42: Warehouse Pallets | E42: =Base!E97*1.04 -> 0 | F42: =IF(ISNUMBER(E42),C42*E42,0) -> 0
A43: 2008AD | B43: Air Transportation: FEMA Distribution Center Caribbean to Destination USVI | C43: =Base!C98 -> 200 | D43: Warehouse Pallets | E43: =Base!E98*1.04 -> 0 | F43: =IF(ISNUMBER(E43),C43*E43,0) -> 0
A44: 2009 | B44: Task: Expedited Air Transportation Services. Puerto Rico, FOB Destination. (Inclusive of container handling (CHE)/material handling (MHE) equipment). Standard Pallet Size (48"L x 40"W x 48"H). Weight: Up to 1650lbs. | C44: =Base!C99 -> 0 | D44: - | E44: 0 | F44: 0
A45: 2009AA | B45: Air Transportation: Mid Atlantic Region to Destination Puerto Rico | C45: =Base!C100 -> 200 | D45: Warehouse Pallets | E45: =Base!E100*1.04 -> 0 | F45: =IF(ISNUMBER(E45),C45*E45,0) -> 0
A46: 2009AB | B46: Air Transportation: South Atlantic Region to Destination Puerto Rico | C46: =Base!C101 -> 200 | D46: Warehouse Pallets | E46: =Base!E101*1.04 -> 0 | F46: =IF(ISNUMBER(E46),C46*E46,0) -> 0
A47: 2009AC | B47: Air Transportation: Gulf Coast to Destination Puerto Rico | C47: =Base!C102 -> 200 | D47: Warehouse Pallets | E47: =Base!E102*1.04 -> 0 | F47: =IF(ISNUMBER(E47),C47*E47,0) -> 0
A48: 2009AD | B48: Air Transportation: FEMA Distribution Center Caribbean to Destination Puerto Rico | C48: =Base!#REF! -> #REF! | D48: Warehouse Pallets | E48: =Base!#REF!*1.04 -> #REF! | F48: =IF(ISNUMBER(E48),C48*E48,0) -> 0
A49: 2010 | B49: Task: Expedited Air Transportation Services. USVI, FOB Destination. (Inclusive of container handling (CHE)/material handling (MHE) equipment). Standard Pallet Size (48"L x 40"W x 48"H). Weight: 1650lbs and above. | C49: =Base!C103 -> 0 | D49: - | E49: 0
A50: 2010AA | B50: Air Transportation: Mid Atlantic Region to Destination USVI | C50: =Base!C104 -> 200 | D50: Warehouse Pallets | E50: =Base!E104*1.04 -> 0 | F50: =IF(ISNUMBER(E50),C50*E50,0) -> 0
A51: 2010AB | B51: Air Transportation: South Atlantic Region to Destination USVI | C51: =Base!C105 -> 200 | D51: Warehouse Pallets | E51: =Base!E105*1.04 -> 0 | F51: =IF(ISNUMBER(E51),C51*E51,0) -> 0
A52: 2010AC | B52: Air Transportation: Gulf Coast to Destination USVI | C52: =Base!C106 -> 200 | D52: Warehouse Pallets | E52: =Base!E106*1.04 -> 0 | F52: =IF(ISNUMBER(E52),C52*E52,0) -> 0
A53: 2010AD | B53: Air Transportation: FEMA Distribution Center Caribbean to Destination USVI | C53: =Base!C107 -> 200 | D53: Warehouse Pallets | E53: =Base!E107*1.04 -> 0 | F53: =IF(ISNUMBER(E53),C53*E53,0) -> 0
A54: 2011 | B54: Task: Expedited Air Transportation Services. Puerto Rico, FOB Destination. (Inclusive of container handling (CHE)/material handling (MHE) equipment). Standard Pallet Size (48"L x 40"W x 48"H). Weight: 1650lbs and above. | C54: =Base!C108 -> 0 | D54: - | E54: 0
A55: 2011AA | B55: Air Transportation: Mid Atlantic Region to Destination Puerto Rico | C55: =Base!C109 -> 200 | D55: Warehouse Pallets | E55: =Base!E109*1.04 -> 0 | F55: =IF(ISNUMBER(E55),C55*E55,0) -> 0
A56: 2011AB | B56: Air Transportation: South Atlantic Region to Destination Puerto Rico | C56: =Base!C110 -> 200 | D56: Warehouse Pallets | E56: =Base!E110*1.04 -> 0 | F56: =IF(ISNUMBER(E56),C56*E56,0) -> 0
A57: 2011AC | B57: Air Transportation: Gulf Coast to Destination Puerto Rico | C57: =Base!C111 -> 200 | D57: Warehouse Pallets | E57: =Base!E111*1.04 -> 0 | F57: =IF(ISNUMBER(E57),C57*E57,0) -> 0
A58: 2011AD | B58: Air Transportation: FEMA Distribution Center Caribbean to Destination Puerto Rico | C58: =Base!#REF! -> #REF! | D58: Warehouse Pallets | E58: =Base!#REF!*1.04 -> #REF! | F58: =IF(ISNUMBER(E58),C58*E58,0) -> 0
A59: 2012 | B59: Task: Transport Breakbulk Cargo (up to 700 cft) (Inclusive of container handling (CHE)/material handling (MHE) equipment and services) | C59: =Base!C51 -> 0 | D59: - | E59: 0
A60: 2012AA | B60: Ocean Transportation: Mid Atlantic Region to Destination USVI | C60: =Base!C52 -> 1000 | D60: Cubic Feet | E60: =Base!E52*1.04 -> 0 | F60: =IF(ISNUMBER(E60),C60*E60,0) -> 0
A61: 2012AB | B61: Ocean Transportation: Mid Atlantic Region to Destination Puerto Rico | C61: =Base!C53 -> 1000 | D61: Cubic Feet | E61: =Base!E53*1.04 -> 0 | F61: =IF(ISNUMBER(E61),C61*E61,0) -> 0
A62: 2012AC | B62: Ocean Transportation: South Atlantic Region to Destination USVI | C62: =Base!C54 -> 1000 | D62: Cubic Feet | E62: =Base!E54*1.04 -> 0 | F62: =IF(ISNUMBER(E62),C62*E62,0) -> 0
A63: 2012AD | B63: Ocean Transportation: South Atlantic Region to Destination Puerto Rico | C63: =Base!C55 -> 1000 | D63: Cubic Feet | E63: =Base!E55*1.04 -> 0 | F63: =IF(ISNUMBER(E63),C63*E63,0) -> 0
A64: 2012AE | B64: Ocean Transportation: Gulf Coast to Destination USVI | C64: =Base!C56 -> 1000 | D64: Cubic Feet | E64: =Base!E56*1.04 -> 0 | F64: =IF(ISNUMBER(E64),C64*E64,0) -> 0
A65: 2012AF | B65: Ocean Transportation: Gulf Coast to Destination Puerto Rico | C65: =Base!C57 -> 1000 | D65: Cubic Feet | E65: =Base!E57*1.04 -> 0 | F65: =IF(ISNUMBER(E65),C65*E65,0) -> 0
A66: 2012AG | B66: Ocean Transportation: FEMA Distribution Center Caribbean to Destination USVI | C66: =Base!C58 -> 1000 | D66: Cubic Feet | E66: =Base!E58*1.04 -> 0 | F66: =IF(ISNUMBER(E66),C66*E66,0) -> 0
A67: 2012AH | B67: Ocean Transportation: FEMA Distribution Center Caribbean to Destination Puerto Rico | C67: =Base!#REF! -> #REF! | D67: Cubic Feet | E67: =Base!#REF!*1.04 -> #REF! | F67: =IF(ISNUMBER(E67),C67*E67,0) -> 0
A68: 2013 | B68: Task: Transport Breakbulk Cargo (from 701 to 1200 cft) (Inclusive of container handling (CHE)/material handling (MHE) equipment and services) | C68: =Base!#REF! -> #REF! | D68: - | E68: 0
A69: 2013AA | B69: Ocean Transportation: Mid Atlantic Region to Destination USVI | C69: =Base!#REF! -> #REF! | D69: Cubic Feet | E69: =Base!#REF!*1.04 -> #REF! | F69: =IF(ISNUMBER(E69),C69*E69,0) -> 0
A70: 2013AB | B70: Ocean Transportation: Mid Atlantic Region to Destination Puerto Rico | C70: =Base!#REF! -> #REF! | D70: Cubic Feet | E70: =Base!#REF!*1.04 -> #REF! | F70: =IF(ISNUMBER(E70),C70*E70,0) -> 0
A71: 2013AC | B71: Ocean Transportation: South Atlantic Region to Destination USVI | C71: =Base!#REF! -> #REF! | D71: Cubic Feet | E71: =Base!#REF!*1.04 -> #REF! | F71: =IF(ISNUMBER(E71),C71*E71,0) -> 0
A72: 2013AD | B72: Ocean Transportation: South Atlantic Region to Destination Puerto Rico | C72: =Base!#REF! -> #REF! | D72: Cubic Feet | E72: =Base!#REF!*1.04 -> #REF! | F72: =IF(ISNUMBER(E72),C72*E72,0) -> 0
A73: 2013AE | B73: Ocean Transportation: Gulf Coast to Destination USVI | C73: =Base!#REF! -> #REF! | D73: Cubic Feet | E73: =Base!#REF!*1.04 -> #REF! | F73: =IF(ISNUMBER(E73),C73*E73,0) -> 0
A74: 2013AF | B74: Ocean Transportation: Gulf Coast to Destination Puerto Rico | C74: =Base!#REF! -> #REF! | D74: Cubic Feet | E74: =Base!#REF!*1.04 -> #REF! | F74: =IF(ISNUMBER(E74),C74*E74,0) -> 0
A75: 2013AG | B75: Ocean Transportation: FEMA Distribution Center Caribbean to Destination USVI | C75: =Base!#REF! -> #REF! | D75: Cubic Feet | E75: =Base!#REF!*1.04 -> #REF! | F75: =IF(ISNUMBER(E75),C75*E75,0) -> 0
A76: 2013AH | B76: Ocean Transportation: FEMA Distribution Center Caribbean to Destination Puerto Rico | C76: =Base!#REF! -> #REF! | D76: Cubic Feet | E76: =Base!#REF!*1.04 -> #REF! | F76: =IF(ISNUMBER(E76),C76*E76,0) -> 0
A77: 2014 | B77: Task: Transport Breakbulk Cargo (over 1200 cft) (Inclusive of container handling (CHE)/material handling (MHE) equipment and services) | C77: =Base!C59 -> 0 | D77: - | E77: 0
A78: 2014AA | B78: Ocean Transportation: Mid Atlantic Region to Destination USVI | C78: =Base!C60 -> 2500 | D78: Cubic Feet | E78: =Base!E60*1.04 -> 0 | F78: =IF(ISNUMBER(E78),C78*E78,0) -> 0
A79: 2014AB | B79: Ocean Transportation: Mid Atlantic Region to Destination Puerto Rico | C79: =Base!C61 -> 2500 | D79: Cubic Feet | E79: =Base!E61*1.04 -> 0 | F79: =IF(ISNUMBER(E79),C79*E79,0) -> 0
A80: 2014AC | B80: Ocean Transportation: South Atlantic Region to Destination USVI | C80: =Base!C62 -> 2500 | D80: Cubic Feet | E80: =Base!E62*1.04 -> 0 | F80: =IF(ISNUMBER(E80),C80*E80,0) -> 0
A81: 2014AD | B81: Ocean Transportation: South Atlantic Region to Destination Puerto Rico | C81: =Base!C63 -> 2500 | D81: Cubic Feet | E81: =Base!E63*1.04 -> 0 | F81: =IF(ISNUMBER(E81),C81*E81,0) -> 0
A82: 2014AE | B82: Ocean Transportation: Gulf Coast to Destination USVI | C82: =Base!C64 -> 2500 | D82: Cubic Feet | E82: =Base!E64*1.04 -> 0 | F82: =IF(ISNUMBER(E82),C82*E82,0) -> 0
A83: 2014AF | B83: Ocean Transportation: Gulf Coast to Destination Puerto Rico | C83: =Base!C65 -> 2500 | D83: Cubic Feet | E83: =Base!E65*1.04 -> 0 | F83: =IF(ISNUMBER(E83),C83*E83,0) -> 0
A84: 2014AG | B84: Ocean Transportation: FEMA Distribution Center Caribbean to Destination USVI | C84: =Base!C66 -> 2500 | D84: Cubic Feet | E84: =Base!E66*1.04 -> 0 | F84: =IF(ISNUMBER(E84),C84*E84,0) -> 0
A85: 2014AH | B85: Ocean Transportation: FEMA Distribution Center Caribbean to Destination Puerto Rico | C85: =Base!#REF! -> #REF! | D85: Cubic Feet | E85: =Base!#REF!*1.04 -> #REF! | F85: =IF(ISNUMBER(E85),C85*E85,0) -> 0
A86: 2015 | B86: Task: Surface line haul services of containerized commodities from Port of Debarkation to FEMA designated Point of Need. (Inclusive of container handling (CHE)/material handling (MHE) equipment) | C86: =Base!C9 -> 0 | D86: - | E86: 0
A87: 2015AA | B87: Ground Transportation: Destination - USVI locations | C87: =Base!C10 -> 1000 | D87: EA | E87: =Base!E10*1.04 -> 0 | F87: =IF(ISNUMBER(E87),C87*E87,0) -> 0
A88: 2015AB | B88: Ground Transportation: Destination - Puerto Rico locations | C88: =Base!C11 -> 2500 | D88: EA | E88: =Base!E11*1.04 -> 0 | F88: =IF(ISNUMBER(E88),C88*E88,0) -> 0
A89: 2016 | B89: Task: Surface line haul services of Breakbulk Cargo. (Per Chassis) (Inclusive of container handling (CHE)/material handling (MHE) equipment) | C89: =Base!C23 -> 0 | D89: - | E89: 0
A90: 2016AA | B90: Ground Transportation: Destination - USVI locations | C90: =Base!C24 -> 10 | D90: EA | E90: =Base!E24*1.04 -> 0 | F90: =IF(ISNUMBER(E90),C90*E90,0) -> 0
A91: 2016AB | B91: Ground Transportation: Destination - Puerto Rico locations | C91: =Base!C25 -> 10 | D91: EA | E91: =Base!E25*1.04 -> 0 | F91: =IF(ISNUMBER(E91),C91*E91,0) -> 0
A92: 2017 | B92: Task: Surface line haul services of containerized commodities Intra-Island. (Inclusive of container handling (CHE)/material handling (MHE) equipment) | C92: =Base!C12 -> 0 | D92: - | E92: 0
A93: 2017AA | B93: Ground Transportation: USVI locations | C93: =Base!C13 -> 1000 | D93: EA | E93: =Base!E13*1.04 -> 0 | F93: =IF(ISNUMBER(E93),C93*E93,0) -> 0
A94: 2017AB | B94: Ground Transportation: Puerto Rico locations | C94: =Base!C14 -> 2500 | D94: EA | E94: =Base!E14*1.04 -> 0 | F94: =IF(ISNUMBER(E94),C94*E94,0) -> 0
A95: 2018 | B95: Task: Container Staging Services. (Inclusive of container handling (CHE)/material handling (MHE) equipment) | C95: =Base!C127 -> 0 | D95: - | E95: 0
A96: 2018AA | B96: Location: USVI | C96: =Base!C128 -> 1 | D96: EA | E96: =Base!E128*1.04 -> 0 | F96: =IF(ISNUMBER(E96),C96*E96,0) -> 0
A97: 2018AB | B97: Location: Puerto Rico | C97: =Base!C129 -> 1 | D97: EA | E97: =Base!E129*1.04 -> 0 | F97: =IF(ISNUMBER(E97),C97*E97,0) -> 0
A98: 2018AC | B98: Daily Container Retention Rate (20ft, 40ft, 53ft) (with [insert # of days] free of charge days) | C98: =Base!C130 -> 1000 | D98: EA/DAY | E98: =Base!E130*1.04 -> 0 | F98: =IF(ISNUMBER(E98),C98*E98,0) -> 0
A99: 2018AD | B99: Daily Container Detention Rate (20ft, 40ft, 53ft) (starting on the [Xth] day) | C99: =Base!C131 -> 1000 | D99: EA/DAY | E99: =Base!E131*1.04 -> 0 | F99: =IF(ISNUMBER(E99),C99*E99,0) -> 0
A100: 2018AE | B100: Daily Chassis Detention Rate (starting on the [Xth] day) | C100: =Base!C132 -> 1000 | D100: EA/DAY | E100: =Base!E132*1.04 -> 0 | F100: =IF(ISNUMBER(E100),C100*E100,0) -> 0
...

Sheet Opt YR 3
A1: RCTSD - Opt YR 3
A2: INSTRUCTIONS: Please note the quantites listed below are for evaluation purposes only. Quoters are not expected to have a minimum of the units used to evaluate. Unit Price will be fixed at time of award.
A3: CLIN | B3: Description | C3: Quantities | D3: Unit | E3: Unit Price | F3: Total Price
A4: 3001 | B4: Commodity Pre-Positioning. Task: Deliver Empty Shipping Containers to FEMA loading/discharging (receiving) locations. (Inclusive of container handling (CHE)/material handling (MHE) equipment) | C4: - | D4: - | E4: - | F4: -
A5: 3001AA | B5: Destination: Mid Atlantic Region | C5: =Base!C115 -> 250 | D5: EA | E5: =Base!E115*1.06 -> 0 | F5: =IF(ISNUMBER(E5),C5*E5,0) -> 0
A6: 3001AB | B6: Destination: South Atlantic Region | C6: =Base!C116 -> 500 | D6: EA | E6: =Base!E116*1.06 -> 0 | F6: =IF(ISNUMBER(E6),C6*E6,0) -> 0
A7: 3001AC | B7: Destination: Gulf Coast | C7: =Base!C117 -> 200 | D7: EA | E7: =Base!E117*1.06 -> 0 | F7: =IF(ISNUMBER(E7),C7*E7,0) -> 0
A8: 3001AD | B8: Destination: FEMA Distribution Center Caribbean, San Juan PR | C8: =Base!C118 -> 500 | D8: EA | E8: =Base!E118*1.06 -> 0 | F8: =IF(ISNUMBER(E8),C8*E8,0) -> 0
A9: 3002 | B9: Task: Surface line haul/Drayage services of containerized commodities from Origin to Port of Embarkation. (Inclusive of container handling (CHE)/material handling (MHE) equipment) | C9: =Base!C4 -> 0 | D9: - | E9: =Base!E4*1.06 -> 0
A10: 3002AA | B10: Ground Transportation: Point of Origin to Port of Embarkation (Mid Atlantic Region) | C10: =Base!C5 -> 250 | D10: EA | E10: =Base!E5*1.06 -> 0 | F10: =IF(ISNUMBER(E10),C10*E10,0) -> 0
A11: 3002AB | B11: Ground Transportation: Point of Origin to Port of Embarkation (South Atlantic Region) | C11: =Base!C6 -> 500 | D11: EA | E11: =Base!E6*1.06 -> 0 | F11: =IF(ISNUMBER(E11),C11*E11,0) -> 0
A12: 3002AC | B12: Ground Transportation: Point of Origin to Port of Embarkation (Gulf Coast) | C12: =Base!C7 -> 200 | D12: EA | E12: =Base!E7*1.06 -> 0 | F12: =IF(ISNUMBER(E12),C12*E12,0) -> 0
A13: 3002AD | B13: Ground Transportation: Point of Origin to Port of Embarkation (FEMA Distribution Center Caribbean, San Juan PR) | C13: =Base!C8 -> 500 | D13: EA | E13: =Base!E8*1.06 -> 0 | F13: =IF(ISNUMBER(E13),C13*E13,0) -> 0
A14: 3003 | B14: Task: Surface line haul/Drayage services of Breakbulk Cargo. (Per Chassis) (Inclusive of container handling (CHE)/material handling (MHE) equipment) | C14: =Base!C18 -> 0 | D14: - | E14: 0
A15: 3003AA | B15: Ground Transportation: Point of Origin to Port of Embarkation (Mid Atlantic Region) | C15: =Base!C19 -> 100 | D15: EA | E15: =Base!E19*1.06 -> 0 | F15: =IF(ISNUMBER(E15),C15*E15,0) -> 0
A16: 3003AB | B16: Ground Transportation: Point of Origin to Port of Embarkation (South Atlantic Region) | C16: =Base!C20 -> 100 | D16: EA | E16: =Base!E20*1.06 -> 0 | F16: =IF(ISNUMBER(E16),C16*E16,0) -> 0
A17: 3003AC | B17: Ground Transportation: Point of Origin to Port of Embarkation (Gulf Coast) | C17: =Base!C21 -> 100 | D17: EA | E17: =Base!E21*1.06 -> 0 | F17: =IF(ISNUMBER(E17),C17*E17,0) -> 0
A18: 3003AD | B18: Ground Transportation: Point of Origin to Port of Embarkation (FEMA Distribution Center Caribbean, San Juan PR) | C18: =Base!C22 -> 100 | D18: EA | E18: =Base!E22*1.06 -> 0 | F18: =IF(ISNUMBER(E18),C18*E18,0) -> 0
A19: 3004 | B19: Task: Transport loaded containers, via ocean vessel from Port of Embarkation to assigned port in the USVI, FOB Destination. (Inclusive of container handling (CHE)/material handling (MHE) equipment) | C19: =Base!C31 -> 0 | D19: - | E19: 0
A20: 3004AA | B20: Ocean Transportation: Mid Atlantic Region to assigned port in the USVI | C20: =Base!C32 -> 250 | D20: EA | E20: =Base!E32*1.06 -> 0 | F20: =IF(ISNUMBER(E20),C20*E20,0) -> 0
A21: 3004AB | B21: Ocean Transportation: South Atlantic Region to assigned port in the USVI | C21: =Base!C33 -> 1000 | D21: EA | E21: =Base!E33*1.06 -> 0 | F21: =IF(ISNUMBER(E21),C21*E21,0) -> 0
A22: 3004AC | B22: Ocean Transportation: Gulf Coast to assigned port in the USVI | C22: =Base!C34 -> 200 | D22: EA | E22: =Base!E34*1.06 -> 0 | F22: =IF(ISNUMBER(E22),C22*E22,0) -> 0
A23: 3004AD | B23: Ocean Transportation: FEMA Distribution Center Caribbean, San Juan PR to assigned port in the USVI | C23: =Base!C35 -> 50 | D23: EA | E23: =Base!E35*1.06 -> 0 | F23: =IF(ISNUMBER(E23),C23*E23,0) -> 0
A24: 3005 | B24: Task: Transport loaded containers, via ocean vessel from Port of Embarkation to assigned port in Puerto Rico, FOB Destination. (Inclusive of container handling (CHE)/material handling (MHE) equipment) | C24: =Base!C36 -> 0 | D24: - | E24: 0 | F24: 0
A25: 3005AA | B25: Ocean Transportation: Mid Atlantic Region to assigned port in Puerto Rico | C25: =Base!C37 -> 250 | D25: EA | E25: =Base!E37*1.06 -> 0 | F25: =IF(ISNUMBER(E25),C25*E25,0) -> 0
A26: 3005AB | B26: Ocean Transportation: South Atlantic Region to assigned port in Puerto Rico | C26: =Base!C38 -> 1000 | D26: EA | E26: =Base!E38*1.06 -> 0 | F26: =IF(ISNUMBER(E26),C26*E26,0) -> 0
A27: 3005AC | B27: Ocean Transportation: Gulf Coast to assigned port in Puerto Rico | C27: =Base!C39 -> 200 | D27: EA | E27: =Base!E39*1.06 -> 0 | F27: =IF(ISNUMBER(E27),C27*E27,0) -> 0
A28: 3005AD | B28: Ocean Transportation: FEMA Distribution Center Caribbean, San Juan PR to assigned port in Puerto Rico | C28: =Base!C40 -> 50 | D28: EA | E28: =Base!E40*1.06 -> 0 | F28: =IF(ISNUMBER(E28),C28*E28,0) -> 0
A29: 3006 | B29: Task: Dedicated Vessel Voyage from Port of Embarkation to assigned port in USVI, FOB Destination (Inclusive of container handling (CHE)/material handling (MHE) equipment and services) (30 day minimum length of dedicated vessel) | C29: =Base!C41 -> 0 | D29: - | E29: 0
A30: 3006AA | B30: Ocean Transportation: Mid Atlantic Region to assigned port in the USVI | C30: =Base!C42 -> 1 | D30: Vessel/Barge per Day | E30: =Base!E42*1.06 -> 0 | F30: =IF(ISNUMBER(E30),C30*E30,0) -> 0
A31: 3006AB | B31: Ocean Transportation: South Atlantic Region to assigned port in the USVI | C31: =Base!C43 -> 1 | D31: Vessel/Barge per Day | E31: =Base!E43*1.06 -> 0 | F31: =IF(ISNUMBER(E31),C31*E31,0) -> 0
A32: 3006AC | B32: Ocean Transportation: Gulf Coast to assigned port in the USVI | C32: =Base!C44 -> 1 | D32: Vessel/Barge per Day | E32: =Base!E44*1.06 -> 0 | F32: =IF(ISNUMBER(E32),C32*E32,0) -> 0
A33: 3006AD | B33: Ocean Transportation: FEMA Distribution Center Caribbean, San Juan PR to assigned port in the USVI | C33: =Base!C45 -> 1 | D33: Vessel/Barge per Day | E33: =Base!E45*1.06 -> 0 | F33: =IF(ISNUMBER(E33),C33*E33,0) -> 0
A34: 3007 | B34: Task: Dedicated Vessel Voyage from Port of Embarkation to assigned port in Puerto Rico, FOB Destination (Inclusive of container handling (CHE)/material handling (MHE) equipment and services) (30 day minimum length of dedicated vessel) | C34: =Base!C46 -> 0 | D34: - | E34: 0
A35: 3007AA | B35: Ocean Transportation: Mid Atlantic Region to assigned port in Puerto Rico | C35: =Base!C47 -> 1 | D35: Vessel/Barge per Day | E35: =Base!E47*1.06 -> 0 | F35: =IF(ISNUMBER(E35),C35*E35,0) -> 0
A36: 3007AB | B36: Ocean Transportation: South Atlantic Region to assigned port in Puerto Rico | C36: =Base!C48 -> 1 | D36: Vessel/Barge per Day | E36: =Base!E48*1.06 -> 0 | F36: =IF(ISNUMBER(E36),C36*E36,0) -> 0
A37: 3007AC | B37: Ocean Transportation: Gulf Coast to assigned port in Puerto Rico | C37: =Base!C49 -> 1 | D37: Vessel/Barge per Day | E37: =Base!E49*1.06 -> 0 | F37: =IF(ISNUMBER(E37),C37*E37,0) -> 0
A38: 3007AD | B38: Ocean Transportation: FEMA Distribution Center Caribbean, San Juan PR to assigned port in Puerto Rico | C38: =Base!C50 -> 1 | D38: Vessel/Barge per Day | E38: =Base!E50*1.06 -> 0 | F38: =IF(ISNUMBER(E38),C38*E38,0) -> 0
A39: 3008 | B39: Task: Expedited Air Transportation Services. USVI, FOB Destination. (Inclusive of container handling (CHE)/material handling (MHE) equipment). Standard Pallet Size (48"L x 40"W x 48"H). Weight: Up to 1650lbs. | C39: =Base!C94 -> 0 | D39: - | E39: 0
A40: 3008AA | B40: Air Transportation: Mid Atlantic Region to Destination USVI | C40: =Base!C95 -> 200 | D40: Warehouse Pallets | E40: =Base!E95*1.06 -> 0 | F40: =IF(ISNUMBER(E40),C40*E40,0) -> 0
A41: 3008AB | B41: Air Transportation: South Atlantic Region to Destination USVI | C41: =Base!C96 -> 200 | D41: Warehouse Pallets | E41: =Base!E96*1.06 -> 0 | F41: =IF(ISNUMBER(E41),C41*E41,0) -> 0
A42: 3008AC | B42: Air Transportation: Gulf Coast to Destination USVI | C42: =Base!C97 -> 200 | D42: Warehouse Pallets | E42: =Base!E97*1.06 -> 0 | F42: =IF(ISNUMBER(E42),C42*E42,0) -> 0
A43: 3008AD | B43: Air Transportation: FEMA Distribution Center Caribbean to Destination USVI | C43: =Base!C98 -> 200 | D43: Warehouse Pallets | E43: =Base!E98*1.06 -> 0 | F43: =IF(ISNUMBER(E43),C43*E43,0) -> 0
A44: 3009 | B44: Task: Expedited Air Transportation Services. Puerto Rico, FOB Destination. (Inclusive of container handling (CHE)/material handling (MHE) equipment). Standard Pallet Size (48"L x 40"W x 48"H). Weight: Up to 1650lbs. | C44: =Base!C99 -> 0 | D44: - | E44: 0 | F44: 0
A45: 3009AA | B45: Air Transportation: Mid Atlantic Region to Destination Puerto Rico | C45: =Base!C100 -> 200 | D45: Warehouse Pallets | E45: =Base!E100*1.06 -> 0 | F45: =IF(ISNUMBER(E45),C45*E45,0) -> 0
A46: 3009AB | B46: Air Transportation: South Atlantic Region to Destination Puerto Rico | C46: =Base!C101 -> 200 | D46: Warehouse Pallets | E46: =Base!E101*1.06 -> 0 | F46: =IF(ISNUMBER(E46),C46*E46,0) -> 0
A47: 3009AC | B47: Air Transportation: Gulf Coast to Destination Puerto Rico | C47: =Base!C102 -> 200 | D47: Warehouse Pallets | E47: =Base!E102*1.06 -> 0 | F47: =IF(ISNUMBER(E47),C47*E47,0) -> 0
A48: 3009AD | B48: Air Transportation: FEMA Distribution Center Caribbean to Destination Puerto Rico | C48: =Base!#REF! -> #REF! | D48: Warehouse Pallets | E48: =Base!#REF!*1.06 -> #REF! | F48: =IF(ISNUMBER(E48),C48*E48,0) -> 0
A49: 3010 | B49: Task: Expedited Air Transportation Services. USVI, FOB Destination. (Inclusive of container handling (CHE)/material handling (MHE) equipment). Standard Pallet Size (48"L x 40"W x 48"H). Weight: 1650lbs and above. | C49: =Base!C103 -> 0 | D49: - | E49: 0
A50: 3010AA | B50: Air Transportation: Mid Atlantic Region to Destination USVI | C50: =Base!C104 -> 200 | D50: Warehouse Pallets | E50: =Base!E104*1.06 -> 0 | F50: =IF(ISNUMBER(E50),C50*E50,0) -> 0
A51: 3010AB | B51: Air Transportation: South Atlantic Region to Destination USVI | C51: =Base!C105 -> 200 | D51: Warehouse Pallets | E51: =Base!E105*1.06 -> 0 | F51: =IF(ISNUMBER(E51),C51*E51,0) -> 0
A52: 3010AC | B52: Air Transportation: Gulf Coast to Destination USVI | C52: =Base!C106 -> 200 | D52: Warehouse Pallets | E52: =Base!E106*1.06 -> 0 | F52: =IF(ISNUMBER(E52),C52*E52,0) -> 0
A53: 3010AD | B53: Air Transportation: FEMA Distribution Center Caribbean to Destination USVI | C53: =Base!C107 -> 200 | D53: Warehouse Pallets | E53: =Base!E107*1.06 -> 0 | F53: =IF(ISNUMBER(E53),C53*E53,0) -> 0
A54: 3011 | B54: Task: Expedited Air Transportation Services. Puerto Rico, FOB Destination. (Inclusive of container handling (CHE)/material handling (MHE) equipment). Standard Pallet Size (48"L x 40"W x 48"H). Weight: 1650lbs and above. | C54: =Base!C108 -> 0 | D54: - | E54: 0
A55: 3011AA | B55: Air Transportation: Mid Atlantic Region to Destination Puerto Rico | C55: =Base!C109 -> 200 | D55: Warehouse Pallets | E55: =Base!E109*1.06 -> 0 | F55: =IF(ISNUMBER(E55),C55*E55,0) -> 0
A56: 3011AB | B56: Air Transportation: South Atlantic Region to Destination Puerto Rico | C56: =Base!C110 -> 200 | D56: Warehouse Pallets | E56: =Base!E110*1.06 -> 0 | F56: =IF(ISNUMBER(E56),C56*E56,0) -> 0
A57: 3011AC | B57: Air Transportation: Gulf Coast to Destination Puerto Rico | C57: =Base!C111 -> 200 | D57: Warehouse Pallets | E57: =Base!E111*1.06 -> 0 | F57: =IF(ISNUMBER(E57),C57*E57,0) -> 0
A58: 3011AD | B58: Air Transportation: FEMA Distribution Center Caribbean to Destination Puerto Rico | C58: =Base!#REF! -> #REF! | D58: Warehouse Pallets | E58: =Base!#REF!*1.06 -> #REF! | F58: =IF(ISNUMBER(E58),C58*E58,0) -> 0
A59: 3012 | B59: Task: Transport Breakbulk Cargo (up to 700 cft) (Inclusive of container handling (CHE)/material handling (MHE) equipment and services) | C59: =Base!C51 -> 0 | D59: - | E59: 0
A60: 3012AA | B60: Ocean Transportation: Mid Atlantic Region to Destination USVI | C60: =Base!C52 -> 1000 | D60: Cubic Feet | E60: =Base!E52*1.06 -> 0 | F60: =IF(ISNUMBER(E60),C60*E60,0) -> 0
A61: 3012AB | B61: Ocean Transportation: Mid Atlantic Region to Destination Puerto Rico | C61: =Base!C53 -> 1000 | D61: Cubic Feet | E61: =Base!E53*1.06 -> 0 | F61: =IF(ISNUMBER(E61),C61*E61,0) -> 0
A62: 3012AC | B62: Ocean Transportation: South Atlantic Region to Destination USVI | C62: =Base!C54 -> 1000 | D62: Cubic Feet | E62: =Base!E54*1.06 -> 0 | F62: =IF(ISNUMBER(E62),C62*E62,0) -> 0
A63: 3012AD | B63: Ocean Transportation: South Atlantic Region to Destination Puerto Rico | C63: =Base!C55 -> 1000 | D63: Cubic Feet | E63: =Base!E55*1.06 -> 0 | F63: =IF(ISNUMBER(E63),C63*E63,0) -> 0
A64: 3012AE | B64: Ocean Transportation: Gulf Coast to Destination USVI | C64: =Base!C56 -> 1000 | D64: Cubic Feet | E64: =Base!E56*1.06 -> 0 | F64: =IF(ISNUMBER(E64),C64*E64,0) -> 0
A65: 3012AF | B65: Ocean Transportation: Gulf Coast to Destination Puerto Rico | C65: =Base!C57 -> 1000 | D65: Cubic Feet | E65: =Base!E57*1.06 -> 0 | F65: =IF(ISNUMBER(E65),C65*E65,0) -> 0
A66: 3012AG | B66: Ocean Transportation: FEMA Distribution Center Caribbean to Destination USVI | C66: =Base!C58 -> 1000 | D66: Cubic Feet | E66: =Base!E58*1.06 -> 0 | F66: =IF(ISNUMBER(E66),C66*E66,0) -> 0
A67: 3012AH | B67: Ocean Transportation: FEMA Distribution Center Caribbean to Destination Puerto Rico | C67: =Base!#REF! -> #REF! | D67: Cubic Feet | E67: =Base!#REF!*1.06 -> #REF! | F67: =IF(ISNUMBER(E67),C67*E67,0) -> 0
A68: 3013 | B68: Task: Transport Breakbulk Cargo (from 701 to 1200 cft) (Inclusive of container handling (CHE)/material handling (MHE) equipment and services) | C68: =Base!#REF! -> #REF! | D68: - | E68: 0
A69: 3013AA | B69: Ocean Transportation: Mid Atlantic Region to Destination USVI | C69: =Base!#REF! -> #REF! | D69: Cubic Feet | E69: =Base!#REF!*1.06 -> #REF! | F69: =IF(ISNUMBER(E69),C69*E69,0) -> 0
A70: 3013AB | B70: Ocean Transportation: Mid Atlantic Region to Destination Puerto Rico | C70: =Base!#REF! -> #REF! | D70: Cubic Feet | E70: =Base!#REF!*1.06 -> #REF! | F70: =IF(ISNUMBER(E70),C70*E70,0) -> 0
A71: 3013AC | B71: Ocean Transportation: South Atlantic Region to Destination USVI | C71: =Base!#REF! -> #REF! | D71: Cubic Feet | E71: =Base!#REF!*1.06 -> #REF! | F71: =IF(ISNUMBER(E71),C71*E71,0) -> 0
A72: 3013AD | B72: Ocean Transportation: South Atlantic Region to Destination Puerto Rico | C72: =Base!#REF! -> #REF! | D72: Cubic Feet | E72: =Base!#REF!*1.06 -> #REF! | F72: =IF(ISNUMBER(E72),C72*E72,0) -> 0
A73: 3013AE | B73: Ocean Transportation: Gulf Coast to Destination USVI | C73: =Base!#REF! -> #REF! | D73: Cubic Feet | E73: =Base!#REF!*1.06 -> #REF! | F73: =IF(ISNUMBER(E73),C73*E73,0) -> 0
A74: 3013AF | B74: Ocean Transportation: Gulf Coast to Destination Puerto Rico | C74: =Base!#REF! -> #REF! | D74: Cubic Feet | E74: =Base!#REF!*1.06 -> #REF! | F74: =IF(ISNUMBER(E74),C74*E74,0) -> 0
A75: 3013AG | B75: Ocean Transportation: FEMA Distribution Center Caribbean to Destination USVI | C75: =Base!#REF! -> #REF! | D75: Cubic Feet | E75: =Base!#REF!*1.06 -> #REF! | F75: =IF(ISNUMBER(E75),C75*E75,0) -> 0
A76: 3013AH | B76: Ocean Transportation: FEMA Distribution Center Caribbean to Destination Puerto Rico | C76: =Base!#REF! -> #REF! | D76: Cubic Feet | E76: =Base!#REF!*1.06 -> #REF! | F76: =IF(ISNUMBER(E76),C76*E76,0) -> 0
A77: 3014 | B77: Task: Transport Breakbulk Cargo (over 1200 cft) (Inclusive of container handling (CHE)/material handling (MHE) equipment and services) | C77: =Base!C59 -> 0 | D77: - | E77: 0
A78: 3014AA | B78: Ocean Transportation: Mid Atlantic Region to Destination USVI | C78: =Base!C60 -> 2500 | D78: Cubic Feet | E78: =Base!E60*1.06 -> 0 | F78: =IF(ISNUMBER(E78),C78*E78,0) -> 0
A79: 3014AB | B79: Ocean Transportation: Mid Atlantic Region to Destination Puerto Rico | C79: =Base!C61 -> 2500 | D79: Cubic Feet | E79: =Base!E61*1.06 -> 0 | F79: =IF(ISNUMBER(E79),C79*E79,0) -> 0
A80: 3014AC | B80: Ocean Transportation: South Atlantic Region to Destination USVI | C80: =Base!C62 -> 2500 | D80: Cubic Feet | E80: =Base!E62*1.06 -> 0 | F80: =IF(ISNUMBER(E80),C80*E80,0) -> 0
A81: 3014AD | B81: Ocean Transportation: South Atlantic Region to Destination Puerto Rico | C81: =Base!C63 -> 2500 | D81: Cubic Feet | E81: =Base!E63*1.06 -> 0 | F81: =IF(ISNUMBER(E81),C81*E81,0) -> 0
A82: 3014AE | B82: Ocean Transportation: Gulf Coast to Destination USVI | C82: =Base!C64 -> 2500 | D82: Cubic Feet | E82: =Base!E64*1.06 -> 0 | F82: =IF(ISNUMBER(E82),C82*E82,0) -> 0
A83: 3014AF | B83: Ocean Transportation: Gulf Coast to Destination Puerto Rico | C83: =Base!C65 -> 2500 | D83: Cubic Feet | E83: =Base!E65*1.06 -> 0 | F83: =IF(ISNUMBER(E83),C83*E83,0) -> 0
A84: 3014AG | B84: Ocean Transportation: FEMA Distribution Center Caribbean to Destination USVI | C84: =Base!C66 -> 2500 | D84: Cubic Feet | E84: =Base!E66*1.06 -> 0 | F84: =IF(ISNUMBER(E84),C84*E84,0) -> 0
A85: 3014AH | B85: Ocean Transportation: FEMA Distribution Center Caribbean to Destination Puerto Rico | C85: =Base!#REF! -> #REF! | D85: Cubic Feet | E85: =Base!#REF!*1.06 -> #REF! | F85: =IF(ISNUMBER(E85),C85*E85,0) -> 0
A86: 3015 | B86: Task: Surface line haul services of containerized commodities from Port of Debarkation to FEMA designated Point of Need. (Inclusive of container handling (CHE)/material handling (MHE) equipment) | C86: =Base!C9 -> 0 | D86: - | E86: 0
A87: 3015AA | B87: Ground Transportation: Destination - USVI locations | C87: =Base!C10 -> 1000 | D87: EA | E87: =Base!E10*1.06 -> 0 | F87: =IF(ISNUMBER(E87),C87*E87,0) -> 0
A88: 3015AB | B88: Ground Transportation: Destination - Puerto Rico locations | C88: =Base!C11 -> 2500 | D88: EA | E88: =Base!E11*1.06 -> 0 | F88: =IF(ISNUMBER(E88),C88*E88,0) -> 0
A89: 3016 | B89: Task: Surface line haul services of Breakbulk Cargo. (Per Chassis) (Inclusive of container handling (CHE)/material handling (MHE) equipment) | C89: =Base!C23 -> 0 | D89: - | E89: 0
A90: 3016AA | B90: Ground Transportation: Destination - USVI locations | C90: =Base!C24 -> 10 | D90: EA | E90: =Base!E24*1.06 -> 0 | F90: =IF(ISNUMBER(E90),C90*E90,0) -> 0
A91: 3016AB | B91: Ground Transportation: Destination - Puerto Rico locations | C91: =Base!C25 -> 10 | D91: EA | E91: =Base!E25*1.06 -> 0 | F91: =IF(ISNUMBER(E91),C91*E91,0) -> 0
A92: 3017 | B92: Task: Surface line haul services of containerized commodities Intra-Island. (Inclusive of container handling (CHE)/material handling (MHE) equipment) | C92: =Base!C12 -> 0 | D92: - | E92: 0
A93: 3017AA | B93: Ground Transportation: USVI locations | C93: =Base!C13 -> 1000 | D93: EA | E93: =Base!E13*1.06 -> 0 | F93: =IF(ISNUMBER(E93),C93*E93,0) -> 0
A94: 3017AB | B94: Ground Transportation: Puerto Rico locations | C94: =Base!C14 -> 2500 | D94: EA | E94: =Base!E14*1.06 -> 0 | F94: =IF(ISNUMBER(E94),C94*E94,0) -> 0
A95: 3018 | B95: Task: Container Staging Services. (Inclusive of container handling (CHE)/material handling (MHE) equipment) | C95: =Base!C127 -> 0 | D95: - | E95: 0
A96: 3018AA | B96: Location: USVI | C96: =Base!C128 -> 1 | D96: EA | E96: =Base!E128*1.06 -> 0 | F96: =IF(ISNUMBER(E96),C96*E96,0) -> 0
A97: 3018AB | B97: Location: Puerto Rico | C97: =Base!C129 -> 1 | D97: EA | E97: =Base!E129*1.06 -> 0 | F97: =IF(ISNUMBER(E97),C97*E97,0) -> 0
A98: 3018AC | B98: Daily Container Retention Rate (20ft, 40ft, 53ft) (with [insert # of days] free of charge days) | C98: =Base!C130 -> 1000 | D98: EA/DAY | E98: =Base!E130*1.06 -> 0 | F98: =IF(ISNUMBER(E98),C98*E98,0) -> 0
A99: 3018AD | B99: Daily Container Detention Rate (20ft, 40ft, 53ft) (starting on the [Xth] day) | C99: =Base!C131 -> 1000 | D99: EA/DAY | E99: =Base!E131*1.06 -> 0 | F99: =IF(ISNUMBER(E99),C99*E99,0) -> 0
A100: 3018AE | B100: Daily Chassis Detention Rate (starting on the [Xth] day) | C100: =Base!C132 -> 1000 | D100: EA/DAY | E100: =Base!E132*1.06 -> 0 | F100: =IF(ISNUMBER(E100),C100*E100,0) -> 0
...

Sheet Opt YR 4
A1: RCTSD - Opt YR 4
A2: INSTRUCTIONS: Please note the quantites listed below are for evaluation purposes only. Quoters are not expected to have a minimum of the units used to evaluate. Unit Price will be fixed at time of award.
A3: CLIN | B3: Description | C3: Quantities | D3: Unit | E3: Unit Price | F3: Total Price
A4: 4001 | B4: Commodity Pre-Positioning. Task: Deliver Empty Shipping Containers to FEMA loading/discharging (receiving) locations. (Inclusive of container handling (CHE)/material handling (MHE) equipment) | C4: - | D4: - | E4: - | F4: -
A5: 4001AA | B5: Destination: Mid Atlantic Region | C5: =Base!C115 -> 250 | D5: EA | E5: =Base!E115*1.08 -> 0 | F5: =IF(ISNUMBER(E5),C5*E5,0) -> 0
A6: 4001AB | B6: Destination: South Atlantic Region | C6: =Base!C116 -> 500 | D6: EA | E6: =Base!E116*1.08 -> 0 | F6: =IF(ISNUMBER(E6),C6*E6,0) -> 0
A7: 4001AC | B7: Destination: Gulf Coast | C7: =Base!C117 -> 200 | D7: EA | E7: =Base!E117*1.08 -> 0 | F7: =IF(ISNUMBER(E7),C7*E7,0) -> 0
A8: 4001AD | B8: Destination: FEMA Distribution Center Caribbean, San Juan PR | C8: =Base!C118 -> 500 | D8: EA | E8: =Base!E118*1.08 -> 0 | F8: =IF(ISNUMBER(E8),C8*E8,0) -> 0
A9: 4002 | B9: Task: Surface line haul/Drayage services of containerized commodities from Origin to Port of Embarkation. (Inclusive of container handling (CHE)/material handling (MHE) equipment) | C9: =Base!C4 -> 0 | D9: - | E9: =Base!E4*1.08 -> 0
A10: 4002AA | B10: Ground Transportation: Point of Origin to Port of Embarkation (Mid Atlantic Region) | C10: =Base!C5 -> 250 | D10: EA | E10: =Base!E5*1.08 -> 0 | F10: =IF(ISNUMBER(E10),C10*E10,0) -> 0
A11: 4002AB | B11: Ground Transportation: Point of Origin to Port of Embarkation (South Atlantic Region) | C11: =Base!C6 -> 500 | D11: EA | E11: =Base!E6*1.08 -> 0 | F11: =IF(ISNUMBER(E11),C11*E11,0) -> 0
A12: 4002AC | B12: Ground Transportation: Point of Origin to Port of Embarkation (Gulf Coast) | C12: =Base!C7 -> 200 | D12: EA | E12: =Base!E7*1.08 -> 0 | F12: =IF(ISNUMBER(E12),C12*E12,0) -> 0
A13: 4002AD | B13: Ground Transportation: Point of Origin to Port of Embarkation (FEMA Distribution Center Caribbean, San Juan PR) | C13: =Base!C8 -> 500 | D13: EA | E13: =Base!E8*1.08 -> 0 | F13: =IF(ISNUMBER(E13),C13*E13,0) -> 0
A14: 4003 | B14: Task: Surface line haul/Drayage services of Breakbulk Cargo. (Per Chassis) (Inclusive of container handling (CHE)/material handling (MHE) equipment) | C14: =Base!C18 -> 0 | D14: - | E14: 0
A15: 4003AA | B15: Ground Transportation: Point of Origin to Port of Embarkation (Mid Atlantic Region) | C15: =Base!C19 -> 100 | D15: EA | E15: =Base!E19*1.08 -> 0 | F15: =IF(ISNUMBER(E15),C15*E15,0) -> 0
A16: 4003AB | B16: Ground Transportation: Point of Origin to Port of Embarkation (South Atlantic Region) | C16: =Base!C20 -> 100 | D16: EA | E16: =Base!E20*1.08 -> 0 | F16: =IF(ISNUMBER(E16),C16*E16,0) -> 0
A17: 4003AC | B17: Ground Transportation: Point of Origin to Port of Embarkation (Gulf Coast) | C17: =Base!C21 -> 100 | D17: EA | E17: =Base!E21*1.08 -> 0 | F17: =IF(ISNUMBER(E17),C17*E17,0) -> 0
A18: 4003AD | B18: Ground Transportation: Point of Origin to Port of Embarkation (FEMA Distribution Center Caribbean, San Juan PR) | C18: =Base!C22 -> 100 | D18: EA | E18: =Base!E22*1.08 -> 0 | F18: =IF(ISNUMBER(E18),C18*E18,0) -> 0
A19: 4004 | B19: Task: Transport loaded containers, via ocean vessel from Port of Embarkation to assigned port in the USVI, FOB Destination. (Inclusive of container handling (CHE)/material handling (MHE) equipment) | C19: =Base!C31 -> 0 | D19: - | E19: 0
A20: 4004AA | B20: Ocean Transportation: Mid Atlantic Region to assigned port in the USVI | C20: =Base!C32 -> 250 | D20: EA | E20: =Base!E32*1.08 -> 0 | F20: =IF(ISNUMBER(E20),C20*E20,0) -> 0
A21: 4004AB | B21: Ocean Transportation: South Atlantic Region to assigned port in the USVI | C21: =Base!C33 -> 1000 | D21: EA | E21: =Base!E33*1.08 -> 0 | F21: =IF(ISNUMBER(E21),C21*E21,0) -> 0
A22: 4004AC | B22: Ocean Transportation: Gulf Coast to assigned port in the USVI | C22: =Base!C34 -> 200 | D22: EA | E22: =Base!E34*1.08 -> 0 | F22: =IF(ISNUMBER(E22),C22*E22,0) -> 0
A23: 4004AD | B23: Ocean Transportation: FEMA Distribution Center Caribbean, San Juan PR to assigned port in the USVI | C23: =Base!C35 -> 50 | D23: EA | E23: =Base!E35*1.08 -> 0 | F23: =IF(ISNUMBER(E23),C23*E23,0) -> 0
A24: 4005 | B24: Task: Transport loaded containers, via ocean vessel from Port of Embarkation to assigned port in Puerto Rico, FOB Destination. (Inclusive of container handling (CHE)/material handling (MHE) equipment) | C24: =Base!C36 -> 0 | D24: - | E24: 0 | F24: 0
A25: 4005AA | B25: Ocean Transportation: Mid Atlantic Region to assigned port in Puerto Rico | C25: =Base!C37 -> 250 | D25: EA | E25: =Base!E37*1.08 -> 0 | F25: =IF(ISNUMBER(E25),C25*E25,0) -> 0
A26: 4005AB | B26: Ocean Transportation: South Atlantic Region to assigned port in Puerto Rico | C26: =Base!C38 -> 1000 | D26: EA | E26: =Base!E38*1.08 -> 0 | F26: =IF(ISNUMBER(E26),C26*E26,0) -> 0
A27: 4005AC | B27: Ocean Transportation: Gulf Coast to assigned port in Puerto Rico | C27: =Base!C39 -> 200 | D27: EA | E27: =Base!E39*1.08 -> 0 | F27: =IF(ISNUMBER(E27),C27*E27,0) -> 0
A28: 4005AD | B28: Ocean Transportation: FEMA Distribution Center Caribbean, San Juan PR to assigned port in Puerto Rico | C28: =Base!C40 -> 50 | D28: EA | E28: =Base!E40*1.08 -> 0 | F28: =IF(ISNUMBER(E28),C28*E28,0) -> 0
A29: 4006 | B29: Task: Dedicated Vessel Voyage from Port of Embarkation to assigned port in USVI, FOB Destination (Inclusive of container handling (CHE)/material handling (MHE) equipment and services) (30 day minimum length of dedicated vessel) | C29: =Base!C41 -> 0 | D29: - | E29: 0
A30: 4006AA | B30: Ocean Transportation: Mid Atlantic Region to assigned port in the USVI | C30: =Base!C42 -> 1 | D30: Vessel/Barge per Day | E30: =Base!E42*1.08 -> 0 | F30: =IF(ISNUMBER(E30),C30*E30,0) -> 0
A31: 4006AB | B31: Ocean Transportation: South Atlantic Region to assigned port in the USVI | C31: =Base!C43 -> 1 | D31: Vessel/Barge per Day | E31: =Base!E43*1.08 -> 0 | F31: =IF(ISNUMBER(E31),C31*E31,0) -> 0
A32: 4006AC | B32: Ocean Transportation: Gulf Coast to assigned port in the USVI | C32: =Base!C44 -> 1 | D32: Vessel/Barge per Day | E32: =Base!E44*1.08 -> 0 | F32: =IF(ISNUMBER(E32),C32*E32,0) -> 0
A33: 4006AD | B33: Ocean Transportation: FEMA Distribution Center Caribbean, San Juan PR to assigned port in the USVI | C33: =Base!C45 -> 1 | D33: Vessel/Barge per Day | E33: =Base!E45*1.08 -> 0 | F33: =IF(ISNUMBER(E33),C33*E33,0) -> 0
A34: 4007 | B34: Task: Dedicated Vessel Voyage from Port of Embarkation to assigned port in Puerto Rico, FOB Destination (Inclusive of container handling (CHE)/material handling (MHE) equipment and services) (30 day minimum length of dedicated vessel) | C34: =Base!C46 -> 0 | D34: - | E34: 0
A35: 4007AA | B35: Ocean Transportation: Mid Atlantic Region to assigned port in Puerto Rico | C35: =Base!C47 -> 1 | D35: Vessel/Barge per Day | E35: =Base!E47*1.08 -> 0 | F35: =IF(ISNUMBER(E35),C35*E35,0) -> 0
A36: 4007AB | B36: Ocean Transportation: South Atlantic Region to assigned port in Puerto Rico | C36: =Base!C48 -> 1 | D36: Vessel/Barge per Day | E36: =Base!E48*1.08 -> 0 | F36: =IF(ISNUMBER(E36),C36*E36,0) -> 0
A37: 4007AC | B37: Ocean Transportation: Gulf Coast to assigned port in Puerto Rico | C37: =Base!C49 -> 1 | D37: Vessel/Barge per Day | E37: =Base!E49*1.08 -> 0 | F37: =IF(ISNUMBER(E37),C37*E37,0) -> 0
A38: 4007AD | B38: Ocean Transportation: FEMA Distribution Center Caribbean, San Juan PR to assigned port in Puerto Rico | C38: =Base!C50 -> 1 | D38: Vessel/Barge per Day | E38: =Base!E50*1.08 -> 0 | F38: =IF(ISNUMBER(E38),C38*E38,0) -> 0
A39: 4008 | B39: Task: Expedited Air Transportation Services. USVI, FOB Destination. (Inclusive of container handling (CHE)/material handling (MHE) equipment). Standard Pallet Size (48"L x 40"W x 48"H). Weight: Up to 1650lbs. | C39: =Base!C94 -> 0 | D39: - | E39: 0
A40: 4008AA | B40: Air Transportation: Mid Atlantic Region to Destination USVI | C40: =Base!C95 -> 200 | D40: Warehouse Pallets | E40: =Base!E95*1.08 -> 0 | F40: =IF(ISNUMBER(E40),C40*E40,0) -> 0
A41: 4008AB | B41: Air Transportation: South Atlantic Region to Destination USVI | C41: =Base!C96 -> 200 | D41: Warehouse Pallets | E41: =Base!E96*1.08 -> 0 | F41: =IF(ISNUMBER(E41),C41*E41,0) -> 0
A42: 4008AC | B42: Air Transportation: Gulf Coast to Destination USVI | C42: =Base!C97 -> 200 | D42: Warehouse Pallets | E42: =Base!E97*1.08 -> 0 | F42: =IF(ISNUMBER(E42),C42*E42,0) -> 0
A43: 4008AD | B43: Air Transportation: FEMA Distribution Center Caribbean to Destination USVI | C43: =Base!C98 -> 200 | D43: Warehouse Pallets | E43: =Base!E98*1.08 -> 0 | F43: =IF(ISNUMBER(E43),C43*E43,0) -> 0
A44: 4009 | B44: Task: Expedited Air Transportation Services. Puerto Rico, FOB Destination. (Inclusive of container handling (CHE)/material handling (MHE) equipment). Standard Pallet Size (48"L x 40"W x 48"H). Weight: Up to 1650lbs. | C44: =Base!C99 -> 0 | D44: - | E44: 0 | F44: 0
A45: 4009AA | B45: Air Transportation: Mid Atlantic Region to Destination Puerto Rico | C45: =Base!C100 -> 200 | D45: Warehouse Pallets | E45: =Base!E100*1.08 -> 0 | F45: =IF(ISNUMBER(E45),C45*E45,0) -> 0
A46: 4009AB | B46: Air Transportation: South Atlantic Region to Destination Puerto Rico | C46: =Base!C101 -> 200 | D46: Warehouse Pallets | E46: =Base!E101*1.08 -> 0 | F46: =IF(ISNUMBER(E46),C46*E46,0) -> 0
A47: 4009AC | B47: Air Transportation: Gulf Coast to Destination Puerto Rico | C47: =Base!C102 -> 200 | D47: Warehouse Pallets | E47: =Base!E102*1.08 -> 0 | F47: =IF(ISNUMBER(E47),C47*E47,0) -> 0
A48: 4009AD | B48: Air Transportation: FEMA Distribution Center Caribbean to Destination Puerto Rico | C48: =Base!#REF! -> #REF! | D48: Warehouse Pallets | E48: =Base!#REF!*1.08 -> #REF! | F48: =IF(ISNUMBER(E48),C48*E48,0) -> 0
A49: 4040 | B49: Task: Expedited Air Transportation Services. USVI, FOB Destination. (Inclusive of container handling (CHE)/material handling (MHE) equipment). Standard Pallet Size (48"L x 40"W x 48"H). Weight: 1650lbs and above. | C49: =Base!C103 -> 0 | D49: - | E49: 0
A50: 4040AA | B50: Air Transportation: Mid Atlantic Region to Destination USVI | C50: =Base!C104 -> 200 | D50: Warehouse Pallets | E50: =Base!E104*1.08 -> 0 | F50: =IF(ISNUMBER(E50),C50*E50,0) -> 0
A51: 4040AB | B51: Air Transportation: South Atlantic Region to Destination USVI | C51: =Base!C105 -> 200 | D51: Warehouse Pallets | E51: =Base!E105*1.08 -> 0 | F51: =IF(ISNUMBER(E51),C51*E51,0) -> 0
A52: 4040AC | B52: Air Transportation: Gulf Coast to Destination USVI | C52: =Base!C106 -> 200 | D52: Warehouse Pallets | E52: =Base!E106*1.08 -> 0 | F52: =IF(ISNUMBER(E52),C52*E52,0) -> 0
A53: 4040AD | B53: Air Transportation: FEMA Distribution Center Caribbean to Destination USVI | C53: =Base!C107 -> 200 | D53: Warehouse Pallets | E53: =Base!E107*1.08 -> 0 | F53: =IF(ISNUMBER(E53),C53*E53,0) -> 0
A54: 4011 | B54: Task: Expedited Air Transportation Services. Puerto Rico, FOB Destination. (Inclusive of container handling (CHE)/material handling (MHE) equipment). Standard Pallet Size (48"L x 40"W x 48"H). Weight: 1650lbs and above. | C54: =Base!C108 -> 0 | D54: - | E54: =Base!E108*1.08 -> 0
A55: 4011AA | B55: Air Transportation: Mid Atlantic Region to Destination Puerto Rico | C55: =Base!C109 -> 200 | D55: Warehouse Pallets | E55: =Base!E109*1.08 -> 0 | F55: =IF(ISNUMBER(E55),C55*E55,0) -> 0
A56: 4011AB | B56: Air Transportation: South Atlantic Region to Destination Puerto Rico | C56: =Base!C110 -> 200 | D56: Warehouse Pallets | E56: =Base!E110*1.08 -> 0 | F56: =IF(ISNUMBER(E56),C56*E56,0) -> 0
A57: 4011AC | B57: Air Transportation: Gulf Coast to Destination Puerto Rico | C57: =Base!C111 -> 200 | D57: Warehouse Pallets | E57: =Base!E111*1.08 -> 0 | F57: =IF(ISNUMBER(E57),C57*E57,0) -> 0
A58: 4011AD | B58: Air Transportation: FEMA Distribution Center Caribbean to Destination Puerto Rico | C58: =Base!#REF! -> #REF! | D58: Warehouse Pallets | E58: =Base!#REF!*1.08 -> #REF! | F58: =IF(ISNUMBER(E58),C58*E58,0) -> 0
A59: 4012 | B59: Task: Transport Breakbulk Cargo (up to 700 cft) (Inclusive of container handling (CHE)/material handling (MHE) equipment and services) | C59: =Base!C51 -> 0 | D59: - | E59: 0
A60: 4012AA | B60: Ocean Transportation: Mid Atlantic Region to Destination USVI | C60: =Base!C52 -> 1000 | D60: Cubic Feet | E60: =Base!E52*1.08 -> 0 | F60: =IF(ISNUMBER(E60),C60*E60,0) -> 0
A61: 4012AB | B61: Ocean Transportation: Mid Atlantic Region to Destination Puerto Rico | C61: =Base!C53 -> 1000 | D61: Cubic Feet | E61: =Base!E53*1.08 -> 0 | F61: =IF(ISNUMBER(E61),C61*E61,0) -> 0
A62: 4012AC | B62: Ocean Transportation: South Atlantic Region to Destination USVI | C62: =Base!C54 -> 1000 | D62: Cubic Feet | E62: =Base!E54*1.08 -> 0 | F62: =IF(ISNUMBER(E62),C62*E62,0) -> 0
A63: 4012AD | B63: Ocean Transportation: South Atlantic Region to Destination Puerto Rico | C63: =Base!C55 -> 1000 | D63: Cubic Feet | E63: =Base!E55*1.08 -> 0 | F63: =IF(ISNUMBER(E63),C63*E63,0) -> 0
A64: 4012AE | B64: Ocean Transportation: Gulf Coast to Destination USVI | C64: =Base!C56 -> 1000 | D64: Cubic Feet | E64: =Base!E56*1.08 -> 0 | F64: =IF(ISNUMBER(E64),C64*E64,0) -> 0
A65: 4012AF | B65: Ocean Transportation: Gulf Coast to Destination Puerto Rico | C65: =Base!C57 -> 1000 | D65: Cubic Feet | E65: =Base!E57*1.08 -> 0 | F65: =IF(ISNUMBER(E65),C65*E65,0) -> 0
A66: 4012AG | B66: Ocean Transportation: FEMA Distribution Center Caribbean to Destination USVI | C66: =Base!C58 -> 1000 | D66: Cubic Feet | E66: =Base!E58*1.08 -> 0 | F66: =IF(ISNUMBER(E66),C66*E66,0) -> 0
A67: 4012AH | B67: Ocean Transportation: FEMA Distribution Center Caribbean to Destination Puerto Rico | C67: =Base!#REF! -> #REF! | D67: Cubic Feet | E67: =Base!#REF!*1.08 -> #REF! | F67: =IF(ISNUMBER(E67),C67*E67,0) -> 0
A68: 4013 | B68: Task: Transport Breakbulk Cargo (from 701 to 1200 cft) (Inclusive of container handling (CHE)/material handling (MHE) equipment and services) | C68: =Base!#REF! -> #REF! | D68: - | E68: 0
A69: 4013AA | B69: Ocean Transportation: Mid Atlantic Region to Destination USVI | C69: =Base!#REF! -> #REF! | D69: Cubic Feet | E69: =Base!#REF!*1.08 -> #REF! | F69: =IF(ISNUMBER(E69),C69*E69,0) -> 0
A70: 4013AB | B70: Ocean Transportation: Mid Atlantic Region to Destination Puerto Rico | C70: =Base!#REF! -> #REF! | D70: Cubic Feet | E70: =Base!#REF!*1.08 -> #REF! | F70: =IF(ISNUMBER(E70),C70*E70,0) -> 0
A71: 4013AC | B71: Ocean Transportation: South Atlantic Region to Destination USVI | C71: =Base!#REF! -> #REF! | D71: Cubic Feet | E71: =Base!#REF!*1.08 -> #REF! | F71: =IF(ISNUMBER(E71),C71*E71,0) -> 0
A72: 4013AD | B72: Ocean Transportation: South Atlantic Region to Destination Puerto Rico | C72: =Base!#REF! -> #REF! | D72: Cubic Feet | E72: =Base!#REF!*1.08 -> #REF! | F72: =IF(ISNUMBER(E72),C72*E72,0) -> 0
A73: 4013AE | B73: Ocean Transportation: Gulf Coast to Destination USVI | C73: =Base!#REF! -> #REF! | D73: Cubic Feet | E73: =Base!#REF!*1.08 -> #REF! | F73: =IF(ISNUMBER(E73),C73*E73,0) -> 0
A74: 4013AF | B74: Ocean Transportation: Gulf Coast to Destination Puerto Rico | C74: =Base!#REF! -> #REF! | D74: Cubic Feet | E74: =Base!#REF!*1.08 -> #REF! | F74: =IF(ISNUMBER(E74),C74*E74,0) -> 0
A75: 4013AG | B75: Ocean Transportation: FEMA Distribution Center Caribbean to Destination USVI | C75: =Base!#REF! -> #REF! | D75: Cubic Feet | E75: =Base!#REF!*1.08 -> #REF! | F75: =IF(ISNUMBER(E75),C75*E75,0) -> 0
A76: 4013AH | B76: Ocean Transportation: FEMA Distribution Center Caribbean to Destination Puerto Rico | C76: =Base!#REF! -> #REF! | D76: Cubic Feet | E76: =Base!#REF!*1.08 -> #REF! | F76: =IF(ISNUMBER(E76),C76*E76,0) -> 0
A77: 4014 | B77: Task: Transport Breakbulk Cargo (over 1200 cft) (Inclusive of container handling (CHE)/material handling (MHE) equipment and services) | C77: =Base!C59 -> 0 | D77: - | E77: 0
A78: 4014AA | B78: Ocean Transportation: Mid Atlantic Region to Destination USVI | C78: =Base!C60 -> 2500 | D78: Cubic Feet | E78: =Base!E60*1.08 -> 0 | F78: =IF(ISNUMBER(E78),C78*E78,0) -> 0
A79: 4014AB | B79: Ocean Transportation: Mid Atlantic Region to Destination Puerto Rico | C79: =Base!C61 -> 2500 | D79: Cubic Feet | E79: =Base!E61*1.08 -> 0 | F79: =IF(ISNUMBER(E79),C79*E79,0) -> 0
A80: 4014AC | B80: Ocean Transportation: South Atlantic Region to Destination USVI | C80: =Base!C62 -> 2500 | D80: Cubic Feet | E80: =Base!E62*1.08 -> 0 | F80: =IF(ISNUMBER(E80),C80*E80,0) -> 0
A81: 4014AD | B81: Ocean Transportation: South Atlantic Region to Destination Puerto Rico | C81: =Base!C63 -> 2500 | D81: Cubic Feet | E81: =Base!E63*1.08 -> 0 | F81: =IF(ISNUMBER(E81),C81*E81,0) -> 0
A82: 4014AE | B82: Ocean Transportation: Gulf Coast to Destination USVI | C82: =Base!C64 -> 2500 | D82: Cubic Feet | E82: =Base!E64*1.08 -> 0 | F82: =IF(ISNUMBER(E82),C82*E82,0) -> 0
A83: 4014AF | B83: Ocean Transportation: Gulf Coast to Destination Puerto Rico | C83: =Base!C65 -> 2500 | D83: Cubic Feet | E83: =Base!E65*1.08 -> 0 | F83: =IF(ISNUMBER(E83),C83*E83,0) -> 0
A84: 4014AG | B84: Ocean Transportation: FEMA Distribution Center Caribbean to Destination USVI | C84: =Base!C66 -> 2500 | D84: Cubic Feet | E84: =Base!E66*1.08 -> 0 | F84: =IF(ISNUMBER(E84),C84*E84,0) -> 0
A85: 4014AH | B85: Ocean Transportation: FEMA Distribution Center Caribbean to Destination Puerto Rico | C85: =Base!#REF! -> #REF! | D85: Cubic Feet | E85: =Base!#REF!*1.08 -> #REF! | F85: =IF(ISNUMBER(E85),C85*E85,0) -> 0
A86: 4015 | B86: Task: Surface line haul services of containerized commodities from Port of Debarkation to FEMA designated Point of Need. (Inclusive of container handling (CHE)/material handling (MHE) equipment) | C86: =Base!C9 -> 0 | D86: - | E86: 0
A87: 4015AA | B87: Ground Transportation: Destination - USVI locations | C87: =Base!C10 -> 1000 | D87: EA | E87: =Base!E10*1.08 -> 0 | F87: =IF(ISNUMBER(E87),C87*E87,0) -> 0
A88: 4015AB | B88: Ground Transportation: Destination - Puerto Rico locations | C88: =Base!C11 -> 2500 | D88: EA | E88: =Base!E11*1.08 -> 0 | F88: =IF(ISNUMBER(E88),C88*E88,0) -> 0
A89: 4016 | B89: Task: Surface line haul services of Breakbulk Cargo. (Per Chassis) (Inclusive of container handling (CHE)/material handling (MHE) equipment) | C89: =Base!C23 -> 0 | D89: - | E89: 0
A90: 4016AA | B90: Ground Transportation: Destination - USVI locations | C90: =Base!C24 -> 10 | D90: EA | E90: =Base!E24*1.08 -> 0 | F90: =IF(ISNUMBER(E90),C90*E90,0) -> 0
A91: 4016AB | B91: Ground Transportation: Destination - Puerto Rico locations | C91: =Base!C25 -> 10 | D91: EA | E91: =Base!E25*1.08 -> 0 | F91: =IF(ISNUMBER(E91),C91*E91,0) -> 0
A92: 4017 | B92: Task: Surface line haul services of containerized commodities Intra-Island. (Inclusive of container handling (CHE)/material handling (MHE) equipment) | C92: =Base!C12 -> 0 | D92: - | E92: 0
A93: 4017AA | B93: Ground Transportation: USVI locations | C93: =Base!C13 -> 1000 | D93: EA | E93: =Base!E13*1.08 -> 0 | F93: =IF(ISNUMBER(E93),C93*E93,0) -> 0
A94: 4017AB | B94: Ground Transportation: Puerto Rico locations | C94: =Base!C14 -> 2500 | D94: EA | E94: =Base!E14*1.08 -> 0 | F94: =IF(ISNUMBER(E94),C94*E94,0) -> 0
A95: 4018 | B95: Task: Container Staging Services. (Inclusive of container handling (CHE)/material handling (MHE) equipment) | C95: =Base!C127 -> 0 | D95: - | E95: 0
A96: 4018AA | B96: Location: USVI | C96: =Base!C128 -> 1 | D96: EA | E96: =Base!E128*1.08 -> 0 | F96: =IF(ISNUMBER(E96),C96*E96,0) -> 0
A97: 4018AB | B97: Location: Puerto Rico | C97: =Base!C129 -> 1 | D97: EA | E97: =Base!E129*1.08 -> 0 | F97: =IF(ISNUMBER(E97),C97*E97,0) -> 0
A98: 4018AC | B98: Daily Container Retention Rate (20ft, 40ft, 53ft) (with [insert # of days] free of charge days) | C98: =Base!C130 -> 1000 | D98: EA/DAY | E98: =Base!E130*1.08 -> 0 | F98: =IF(ISNUMBER(E98),C98*E98,0) -> 0
A99: 4018AD | B99: Daily Container Detention Rate (20ft, 40ft, 53ft) (starting on the [Xth] day) | C99: =Base!C131 -> 1000 | D99: EA/DAY | E99: =Base!E131*1.08 -> 0 | F99: =IF(ISNUMBER(E99),C99*E99,0) -> 0
A100: 4018AE | B100: Daily Chassis Detention Rate (starting on the [Xth] day) | C100: =Base!C132 -> 1000 | D100: EA/DAY | E100: =Base!E132*1.08 -> 0 | F100: =IF(ISNUMBER(E100),C100*E100,0) -> 0
...
